Workbook

Sheet Dashboard
A1: FPL 2026/27 Model — v0.2 Full Player Universe
A3: Snapshot | B3: 18 Aug 2026 | D3: Position | E3: Players | F3: Avg Price (£m) | G3: Avg Hist Mins
A4: Players | B4: 567 | D4: GK | E4: =COUNTIF(Players!$E$2:$E$568,D4) -> 63 | F4: =AVERAGEIF(Players!$E$2:$E$568,D4,Players!$G$2:$G$568) -> 4.531746 | G4: =AVERAGEIF(Players!$E$2:$E$568,D4,Players!$H$2:$H$568) -> 951.85714
A5: Teams | B5: 20 | D5: DEF | E5: =COUNTIF(Players!$E$2:$E$568,D5) -> 186 | F5: =AVERAGEIF(Players!$E$2:$E$568,D5,Players!$G$2:$G$568) -> 4.7043011 | G5: =AVERAGEIF(Players!$E$2:$E$568,D5,Players!$H$2:$H$568) -> 1196.9247
A6: Fixtures | B6: 380 | D6: MID | E6: =COUNTIF(Players!$E$2:$E$568,D6) -> 250 | F6: =AVERAGEIF(Players!$E$2:$E$568,D6,Players!$G$2:$G$568) -> 5.546 | G6: =AVERAGEIF(Players!$E$2:$E$568,D6,Players!$H$2:$H$568) -> 1054.728
A7: Player source | B7: FPL API snapshot via vaastav | D7: FWD | E7: =COUNTIF(Players!$E$2:$E$568,D7) -> 68 | F7: =AVERAGEIF(Players!$E$2:$E$568,D7,Players!$G$2:$G$568) -> 5.8088235 | G7: =AVERAGEIF(Players!$E$2:$E$568,D7,Players!$H$2:$H$568) -> 824.57353
A8: Stage | B8: Universe + historical priors
A10: Next modelling step: current expected minutes + bookmaker-implied fixture xG/clean-sheet probabilities.

Sheet Players
A1: Player ID | B1: Player | C1: Full Name | D1: Team | E1: Position | F1: Start Price (£m) | G1: Current Price (£m) | H1: Mins 25/26 | I1: xG 25/26 | J1: xA 25/26 | K1: xG90 Hist | L1: xA90 Hist | M1: Goals 25/26 | N1: Assists 25/26 | O1: FPL Pts 25/26 | P1: Pts/Game | Q1: Starts 25/26 | R1: DC90 | S1: Pens Order | T1: Direct FK Order | U1: Corners/IFK Order | V1: New Club? | W1: New Manager? | X1: Role Change | Y1: Start Prob | Z1: Exp Mins | AA1: Sample Weight | AB1: Pos xG90 Prior | AC1: Pos xA90 Prior | AD1: xG90 Prior | AE1: xA90 Prior | AF1: League Adj | AG1: Role Adj | AH1: Team Adj | AI1: Adj xG90 | AJ1: Adj xA90 | AK1: Status | AL1: Chance Play GW1 | AM1: News | AN1: Ownership % | AO1: Selectable? | AP1: Team Join Date | AQ1: Test Sample? | AR1: Notes | AS1: Source URL
A2: 1 | B2: Raya | C2: David Raya Martín | D2: Arsenal | E2: GK | F2: 6 | G2: 6 | H2: 3330 | I2: 0 | J2: 0.07 | K2: =IFERROR(I2*90/H2,0) -> 0 | L2: =IFERROR(J2*90/H2,0) -> 0.0018918919 | M2: 0 | N2: 0 | O2: 162 | P2: 4.4 | Q2: 37 | R2: 0 | V2: FALSE | W2: =IFERROR(VLOOKUP(D2,Teams!$B$2:$I$21,6,FALSE),"") -> 0 | X2: None | AA2: =IFERROR(H2/(H2+Priors!$G$3),0) -> 0.76905312 | AB2: =VLOOKUP(E2,Priors!$A$3:$C$6,2,FALSE) -> 0.00024013207 | AC2: =VLOOKUP(E2,Priors!$A$3:$C$6,3,FALSE) -> 0.0019810896 | AD2: =AA2*K2+(1-AA2)*AB2 -> 5.5457753e-05 | AE2: =AA2*L2+(1-AA2)*AC2 -> 0.0019124918 | AF2: 1 | AG2: 1 | AH2: =IFERROR(VLOOKUP(D2,Teams!$B$2:$I$21,7,FALSE),1) -> 1 | AI2: =AD2*AF2*AG2*AH2 -> 5.5457753e-05 | AJ2: =AE2*AF2*AG2*AH2 -> 0.0019124918 | AK2: Available | AN2: 0.307 | AO2: TRUE | AP2: 2024-07-04 | AQ2: TRUE | AS2: https://raw.githubusercontent.com/vaastav/Fantasy-Premier-League/master/data/2026-27/players_raw.csv
A3: 2 | B3: Arrizabalaga | C3: Kepa Arrizabalaga Revuelta | D3: Arsenal | E3: GK | F3: 5 | G3: 5 | H3: 90 | I3: 0 | J3: 0 | K3: =IFERROR(I3*90/H3,0) -> 0 | L3: =IFERROR(J3*90/H3,0) -> 0 | M3: 0 | N3: 0 | O3: 2 | P3: 2 | Q3: 1 | R3: 0 | V3: FALSE | W3: =IFERROR(VLOOKUP(D3,Teams!$B$2:$I$21,6,FALSE),"") -> 0 | X3: None | AA3: =IFERROR(H3/(H3+Priors!$G$3),0) -> 0.082568807 | AB3: =VLOOKUP(E3,Priors!$A$3:$C$6,2,FALSE) -> 0.00024013207 | AC3: =VLOOKUP(E3,Priors!$A$3:$C$6,3,FALSE) -> 0.0019810896 | AD3: =AA3*K3+(1-AA3)*AB3 -> 0.00022030465 | AE3: =AA3*L3+(1-AA3)*AC3 -> 0.0018175134 | AF3: 1 | AG3: 1 | AH3: =IFERROR(VLOOKUP(D3,Teams!$B$2:$I$21,7,FALSE),1) -> 1 | AI3: =AD3*AF3*AG3*AH3 -> 0.00022030465 | AJ3: =AE3*AF3*AG3*AH3 -> 0.0018175134 | AK3: Available | AN3: 0.002 | AO3: TRUE | AP3: 2025-07-01 | AQ3: FALSE | AS3: https://raw.githubusercontent.com/vaastav/Fantasy-Premier-League/master/data/2026-27/players_raw.csv
A4: 3 | B4: Meslier | C4: Illan Meslier | D4: Arsenal | E4: GK | F4: 5 | G4: 5 | H4: 0 | I4: 0 | J4: 0 | K4: =IFERROR(I4*90/H4,0) -> 0 | L4: =IFERROR(J4*90/H4,0) -> 0 | M4: 11 | N4: 0 | O4: 0 | P4: 0 | Q4: 0 | R4: 0 | V4: TRUE | W4: =IFERROR(VLOOKUP(D4,Teams!$B$2:$I$21,6,FALSE),"") -> 0 | X4: None | AA4: =IFERROR(H4/(H4+Priors!$G$3),0) -> 0 | AB4: =VLOOKUP(E4,Priors!$A$3:$C$6,2,FALSE) -> 0.00024013207 | AC4: =VLOOKUP(E4,Priors!$A$3:$C$6,3,FALSE) -> 0.0019810896 | AD4: =AA4*K4+(1-AA4)*AB4 -> 0.00024013207 | AE4: =AA4*L4+(1-AA4)*AC4 -> 0.0019810896 | AF4: 1 | AG4: 1 | AH4: =IFERROR(VLOOKUP(D4,Teams!$B$2:$I$21,7,FALSE),1) -> 1 | AI4: =AD4*AF4*AG4*AH4 -> 0.00024013207 | AJ4: =AE4*AF4*AG4*AH4 -> 0.0019810896 | AK4: Available | AN4: 0.001 | AO4: TRUE | AP4: 2026-07-09 | AQ4: FALSE | AS4: https://raw.githubusercontent.com/vaastav/Fantasy-Premier-League/master/data/2026-27/players_raw.csv
A5: 4 | B5: Gabriel | C5: Gabriel Magalhães | D5: Arsenal | E5: DEF | F5: 8 | G5: 8 | H5: 2750 | I5: 2.94 | J5: 1.75 | K5: =IFERROR(I5*90/H5,0) -> 0.096218182 | L5: =IFERROR(J5*90/H5,0) -> 0.057272727 | M5: 3 | N5: 5 | O5: 209 | P5: 6.5 | Q5: 30 | R5: 9.07 | V5: FALSE | W5: =IFERROR(VLOOKUP(D5,Teams!$B$2:$I$21,6,FALSE),"") -> 0 | X5: None | AA5: =IFERROR(H5/(H5+Priors!$G$3),0) -> 0.73333333 | AB5: =VLOOKUP(E5,Priors!$A$3:$C$6,2,FALSE) -> 0.060081391 | AC5: =VLOOKUP(E5,Priors!$A$3:$C$6,3,FALSE) -> 0.059588192 | AD5: =AA5*K5+(1-AA5)*AB5 -> 0.086581704 | AE5: =AA5*L5+(1-AA5)*AC5 -> 0.057890185 | AF5: 1 | AG5: 1 | AH5: =IFERROR(VLOOKUP(D5,Teams!$B$2:$I$21,7,FALSE),1) -> 1 | AI5: =AD5*AF5*AG5*AH5 -> 0.086581704 | AJ5: =AE5*AF5*AG5*AH5 -> 0.057890185 | AK5: Available | AN5: 0.259 | AO5: TRUE | AP5: 2020-09-01 | AQ5: TRUE | AS5: https://raw.githubusercontent.com/vaastav/Fantasy-Premier-League/master/data/2026-27/players_raw.csv
A6: 5 | B6: J.Timber | C6: Jurriën Timber | D6: Arsenal | E6: DEF | F6: 6.5 | G6: 6.5 | H6: 2452 | I6: 4.71 | J6: 1.53 | K6: =IFERROR(I6*90/H6,0) -> 0.17287928 | L6: =IFERROR(J6*90/H6,0) -> 0.056158238 | M6: 3 | N6: 6 | O6: 149 | P6: 5 | Q6: 28 | R6: 5.43 | V6: FALSE | W6: =IFERROR(VLOOKUP(D6,Teams!$B$2:$I$21,6,FALSE),"") -> 0 | X6: None | AA6: =IFERROR(H6/(H6+Priors!$G$3),0) -> 0.71031286 | AB6: =VLOOKUP(E6,Priors!$A$3:$C$6,2,FALSE) -> 0.060081391 | AC6: =VLOOKUP(E6,Priors!$A$3:$C$6,3,FALSE) -> 0.059588192 | AD6: =AA6*K6+(1-AA6)*AB6 -> 0.14020318 | AE6: =AA6*L6+(1-AA6)*AC6 -> 0.057151852 | AF6: 1 | AG6: 1 | AH6: =IFERROR(VLOOKUP(D6,Teams!$B$2:$I$21,7,FALSE),1) -> 1 | AI6: =AD6*AF6*AG6*AH6 -> 0.14020318 | AJ6: =AE6*AF6*AG6*AH6 -> 0.057151852 | AK6: Injured | AL6: 0 | AM6: Groin injury - Expected back 21 Aug | AN6: 0.005 | AO6: TRUE | AP6: 2023-07-14 | AQ6: FALSE | AS6: https://raw.githubusercontent.com/vaastav/Fantasy-Premier-League/master/data/2026-27/players_raw.csv
A7: 6 | B7: Saliba | C7: William Saliba | D7: Arsenal | E7: DEF | F7: 6 | G7: 6 | H7: 2614 | I7: 0.88 | J7: 1.21 | K7: =IFERROR(I7*90/H7,0) -> 0.030298393 | L7: =IFERROR(J7*90/H7,0) -> 0.041660291 | M7: 1 | N7: 0 | O7: 137 | P7: 4.4 | Q7: 30 | R7: 6.64 | V7: FALSE | W7: =IFERROR(VLOOKUP(D7,Teams!$B$2:$I$21,6,FALSE),"") -> 0 | X7: None | AA7: =IFERROR(H7/(H7+Priors!$G$3),0) -> 0.72329828 | AB7: =VLOOKUP(E7,Priors!$A$3:$C$6,2,FALSE) -> 0.060081391 | AC7: =VLOOKUP(E7,Priors!$A$3:$C$6,3,FALSE) -> 0.059588192 | AD7: =AA7*K7+(1-AA7)*AB7 -> 0.0385394 | AE7: =AA7*L7+(1-AA7)*AC7 -> 0.046620972 | AF7: 1 | AG7: 1 | AH7: =IFERROR(VLOOKUP(D7,Teams!$B$2:$I$21,7,FALSE),1) -> 1 | AI7: =AD7*AF7*AG7*AH7 -> 0.0385394 | AJ7: =AE7*AF7*AG7*AH7 -> 0.046620972 | AK7: Injured | AL7: 0 | AM7: Back injury - Unknown return date | AN7: 0.005 | AO7: TRUE | AP7: 2019-07-25 | AQ7: FALSE | AS7: https://raw.githubusercontent.com/vaastav/Fantasy-Premier-League/master/data/2026-27/players_raw.csv
A8: 7 | B8: Lewis-Skelly | C8: Myles Lewis-Skelly | D8: Arsenal | E8: MID | F8: 5.5 | G8: 5.5 | H8: 697 | I8: 0.1 | J8: 0.2 | K8: =IFERROR(I8*90/H8,0) -> 0.012912482 | L8: =IFERROR(J8*90/H8,0) -> 0.025824964 | M8: 0 | N8: 0 | O8: 29 | P8: 1.4 | Q8: 5 | R8: 3.23 | V8: FALSE | W8: =IFERROR(VLOOKUP(D8,Teams!$B$2:$I$21,6,FALSE),"") -> 0 | X8: None | AA8: =IFERROR(H8/(H8+Priors!$G$3),0) -> 0.41072481 | AB8: =VLOOKUP(E8,Priors!$A$3:$C$6,2,FALSE) -> 0.15714383 | AC8: =VLOOKUP(E8,Priors!$A$3:$C$6,3,FALSE) -> 0.13222063 | AD8: =AA8*K8+(1-AA8)*AB8 -> 0.097904439 | AE8: =AA8*L8+(1-AA8)*AC8 -> 0.08852129 | AF8: 1 | AG8: 1 | AH8: =IFERROR(VLOOKUP(D8,Teams!$B$2:$I$21,7,FALSE),1) -> 1 | AI8: =AD8*AF8*AG8*AH8 -> 0.097904439 | AJ8: =AE8*AF8*AG8*AH8 -> 0.08852129 | AK8: Available | AN8: 0.003 | AO8: TRUE | AP8: 2022-12-04 | AQ8: FALSE | AS8: https://raw.githubusercontent.com/vaastav/Fantasy-Premier-League/master/data/2026-27/players_raw.csv
A9: 8 | B9: Calafiori | C9: Riccardo Calafiori | D9: Arsenal | E9: DEF | F9: 5.5 | G9: 5.5 | H9: 1697 | I9: 3.36 | J9: 0.76 | K9: =IFERROR(I9*90/H9,0) -> 0.17819682 | L9: =IFERROR(J9*90/H9,0) -> 0.040306423 | M9: 1 | N9: 2 | O9: 109 | P9: 4.2 | Q9: 22 | R9: 5.41 | V9: FALSE | W9: =IFERROR(VLOOKUP(D9,Teams!$B$2:$I$21,6,FALSE),"") -> 0 | X9: None | AA9: =IFERROR(H9/(H9+Priors!$G$3),0) -> 0.62921765 | AB9: =VLOOKUP(E9,Priors!$A$3:$C$6,2,FALSE) -> 0.060081391 | AC9: =VLOOKUP(E9,Priors!$A$3:$C$6,3,FALSE) -> 0.059588192 | AD9: =AA9*K9+(1-AA9)*AB9 -> 0.1344017 | AE9: =AA9*L9+(1-AA9)*AC9 -> 0.047455763 | AF9: 1 | AG9: 1 | AH9: =IFERROR(VLOOKUP(D9,Teams!$B$2:$I$21,7,FALSE),1) -> 1 | AI9: =AD9*AF9*AG9*AH9 -> 0.1344017 | AJ9: =AE9*AF9*AG9*AH9 -> 0.047455763 | AK9: Available | AN9: 0.153 | AO9: TRUE | AP9: 2024-07-29 | AQ9: FALSE | AS9: https://raw.githubusercontent.com/vaastav/Fantasy-Premier-League/master/data/2026-27/players_raw.csv
A10: 9 | B10: Hincapie | C10: Piero Hincapié | D10: Arsenal | E10: DEF | F10: 5.5 | G10: 5.5 | H10: 1787 | I10: 0.36 | J10: 1.67 | K10: =IFERROR(I10*90/H10,0) -> 0.018130946 | L10: =IFERROR(J10*90/H10,0) -> 0.084107443 | M10: 1 | N10: 2 | O10: 87 | P10: 3.5 | Q10: 20 | R10: 8.61 | V10: TRUE | W10: =IFERROR(VLOOKUP(D10,Teams!$B$2:$I$21,6,FALSE),"") -> 0 | X10: None | AA10: =IFERROR(H10/(H10+Priors!$G$3),0) -> 0.64119125 | AB10: =VLOOKUP(E10,Priors!$A$3:$C$6,2,FALSE) -> 0.060081391 | AC10: =VLOOKUP(E10,Priors!$A$3:$C$6,3,FALSE) -> 0.059588192 | AD10: =AA10*K10+(1-AA10)*AB10 -> 0.033183133 | AE10: =AA10*L10+(1-AA10)*AC10 -> 0.075309721 | AF10: 1 | AG10: 1 | AH10: =IFERROR(VLOOKUP(D10,Teams!$B$2:$I$21,7,FALSE),1) -> 1 | AI10: =AD10*AF10*AG10*AH10 -> 0.033183133 | AJ10: =AE10*AF10*AG10*AH10 -> 0.075309721 | AK10: Available | AN10: 0.044 | AO10: TRUE | AP10: 2026-07-01 | AQ10: FALSE | AS10: https://raw.githubusercontent.com/vaastav/Fantasy-Premier-League/master/data/2026-27/players_raw.csv
A11: 10 | B11: White | C11: Benjamin White | D11: Arsenal | E11: DEF | F11: 5.5 | G11: 5.5 | H11: 699 | I11: 0.45 | J11: 0.69 | K11: =IFERROR(I11*90/H11,0) -> 0.057939914 | L11: =IFERROR(J11*90/H11,0) -> 0.088841202 | M11: 0 | N11: 1 | O11: 45 | P11: 3.8 | Q11: 9 | R11: 6.82 | V11: FALSE | W11: =IFERROR(VLOOKUP(D11,Teams!$B$2:$I$21,6,FALSE),"") -> 0 | X11: None | AA11: =IFERROR(H11/(H11+Priors!$G$3),0) -> 0.41141848 | AB11: =VLOOKUP(E11,Priors!$A$3:$C$6,2,FALSE) -> 0.060081391 | AC11: =VLOOKUP(E11,Priors!$A$3:$C$6,3,FALSE) -> 0.059588192 | AD11: =AA11*K11+(1-AA11)*AB11 -> 0.059200348 | AE11: =AA11*L11+(1-AA11)*AC11 -> 0.071623421 | AF11: 1 | AG11: 1 | AH11: =IFERROR(VLOOKUP(D11,Teams!$B$2:$I$21,7,FALSE),1) -> 1 | AI11: =AD11*AF11*AG11*AH11 -> 0.059200348 | AJ11: =AE11*AF11*AG11*AH11 -> 0.071623421 | AK11: Available | AL11: 100 | AN11: 0.002 | AO11: TRUE | AP11: 2021-07-30 | AQ11: FALSE | AS11: https://raw.githubusercontent.com/vaastav/Fantasy-Premier-League/master/data/2026-27/players_raw.csv
A12: 11 | B12: Mosquera | C12: Cristhian Mosquera | D12: Arsenal | E12: DEF | F12: 5.5 | G12: 5.5 | H12: 986 | I12: 0.1 | J12: 0.63 | K12: =IFERROR(I12*90/H12,0) -> 0.009127789 | L12: =IFERROR(J12*90/H12,0) -> 0.057505071 | M12: 0 | N12: 0 | O12: 40 | P12: 2 | Q12: 9 | R12: 8.67 | V12: FALSE | W12: =IFERROR(VLOOKUP(D12,Teams!$B$2:$I$21,6,FALSE),"") -> 0 | X12: None | AA12: =IFERROR(H12/(H12+Priors!$G$3),0) -> 0.49647533 | AB12: =VLOOKUP(E12,Priors!$A$3:$C$6,2,FALSE) -> 0.060081391 | AC12: =VLOOKUP(E12,Priors!$A$3:$C$6,3,FALSE) -> 0.059588192 | AD12: =AA12*K12+(1-AA12)*AB12 -> 0.034784185 | AE12: =AA12*L12+(1-AA12)*AC12 -> 0.058553974 | AF12: 1 | AG12: 1 | AH12: =IFERROR(VLOOKUP(D12,Teams!$B$2:$I$21,7,FALSE),1) -> 1 | AI12: =AD12*AF12*AG12*AH12 -> 0.034784185 | AJ12: =AE12*AF12*AG12*AH12 -> 0.058553974 | AK12: Available | AN12: 0.169 | AO12: TRUE | AP12: 2025-07-24 | AQ12: FALSE | AS12: https://raw.githubusercontent.com/vaastav/Fantasy-Premier-League/master/data/2026-27/players_raw.csv
A13: 12 | B13: Saka | C13: Bukayo Saka | D13: Arsenal | E13: MID | F13: 9.5 | G13: 9.5 | H13: 2218 | I13: 7.57 | J13: 7.16 | K13: =IFERROR(I13*90/H13,0) -> 0.30716862 | L13: =IFERROR(J13*90/H13,0) -> 0.29053201 | M13: 7 | N13: 10 | O13: 157 | P13: 5.1 | Q13: 25 | R13: 7.47 | S13: 1 | T13: 2 | U13: 6 | V13: FALSE | W13: =IFERROR(VLOOKUP(D13,Teams!$B$2:$I$21,6,FALSE),"") -> 0 | X13: None | AA13: =IFERROR(H13/(H13+Priors!$G$3),0) -> 0.68924798 | AB13: =VLOOKUP(E13,Priors!$A$3:$C$6,2,FALSE) -> 0.15714383 | AC13: =VLOOKUP(E13,Priors!$A$3:$C$6,3,FALSE) -> 0.13222063 | AD13: =AA13*K13+(1-AA13)*AB13 -> 0.26054811 | AE13: =AA13*L13+(1-AA13)*AC13 -> 0.24133643 | AF13: 1 | AG13: 1 | AH13: =IFERROR(VLOOKUP(D13,Teams!$B$2:$I$21,7,FALSE),1) -> 1 | AI13: =AD13*AF13*AG13*AH13 -> 0.26054811 | AJ13: =AE13*AF13*AG13*AH13 -> 0.24133643 | AK13: Available | AN13: 0.106 | AO13: TRUE | AP13: 2018-11-28 | AQ13: FALSE | AS13: https://raw.githubusercontent.com/vaastav/Fantasy-Premier-League/master/data/2026-27/players_raw.csv
A14: 13 | B14: Rice | C14: Declan Rice | D14: Arsenal | E14: MID | F14: 7.5 | G14: 7.5 | H14: 3093 | I14: 3.15 | J14: 7.32 | K14: =IFERROR(I14*90/H14,0) -> 0.091658584 | L14: =IFERROR(J14*90/H14,0) -> 0.21299709 | M14: 4 | N14: 9 | O14: 184 | P14: 5.1 | Q14: 35 | R14: 10.94 | T14: 1 | U14: 5 | V14: FALSE | W14: =IFERROR(VLOOKUP(D14,Teams!$B$2:$I$21,6,FALSE),"") -> 0 | X14: None | AA14: =IFERROR(H14/(H14+Priors!$G$3),0) -> 0.75568043 | AB14: =VLOOKUP(E14,Priors!$A$3:$C$6,2,FALSE) -> 0.15714383 | AC14: =VLOOKUP(E14,Priors!$A$3:$C$6,3,FALSE) -> 0.13222063 | AD14: =AA14*K14+(1-AA14)*AB14 -> 0.10765791 | AE14: =AA14*L14+(1-AA14)*AC14 -> 0.19326182 | AF14: 1 | AG14: 1 | AH14: =IFERROR(VLOOKUP(D14,Teams!$B$2:$I$21,7,FALSE),1) -> 1 | AI14: =AD14*AF14*AG14*AH14 -> 0.10765791 | AJ14: =AE14*AF14*AG14*AH14 -> 0.19326182 | AK14: Available | AN14: 0.223 | AO14: TRUE | AP14: 2023-07-15 | AQ14: FALSE | AS14: https://raw.githubusercontent.com/vaastav/Fantasy-Premier-League/master/data/2026-27/players_raw.csv
A15: 14 | B15: Eze | C15: Eberechi Eze | D15: Arsenal | E15: MID | F15: 6.5 | G15: 6.5 | H15: 1885 | I15: 5.18 | J15: 2.66 | K15: =IFERROR(I15*90/H15,0) -> 0.24732095 | L15: =IFERROR(J15*90/H15,0) -> 0.12700265 | M15: 7 | N15: 3 | O15: 113 | P15: 3.4 | Q15: 22 | R15: 5.73 | T15: 3 | V15: FALSE | W15: =IFERROR(VLOOKUP(D15,Teams!$B$2:$I$21,6,FALSE),"") -> 0 | X15: None | AA15: =IFERROR(H15/(H15+Priors!$G$3),0) -> 0.65337955 | AB15: =VLOOKUP(E15,Priors!$A$3:$C$6,2,FALSE) -> 0.15714383 | AC15: =VLOOKUP(E15,Priors!$A$3:$C$6,3,FALSE) -> 0.13222063 | AD15: =AA15*K15+(1-AA15)*AB15 -> 0.21606372 | AE15: =AA15*L15+(1-AA15)*AC15 -> 0.12881131 | AF15: 1 | AG15: 1 | AH15: =IFERROR(VLOOKUP(D15,Teams!$B$2:$I$21,7,FALSE),1) -> 1 | AI15: =AD15*AF15*AG15*AH15 -> 0.21606372 | AJ15: =AE15*AF15*AG15*AH15 -> 0.12881131 | AK15: Available | AN15: 0.033 | AO15: TRUE | AP15: 2025-08-23 | AQ15: FALSE | AS15: https://raw.githubusercontent.com/vaastav/Fantasy-Premier-League/master/data/2026-27/players_raw.csv
A16: 15 | B16: Ødegaard | C16: Martin Ødegaard | D16: Arsenal | E16: MID | F16: 6.5 | G16: 6.5 | H16: 1363 | I16: 1.25 | J16: 3.65 | K16: =IFERROR(I16*90/H16,0) -> 0.082538518 | L16: =IFERROR(J16*90/H16,0) -> 0.24101247 | M16: 1 | N16: 7 | O16: 74 | P16: 3.1 | Q16: 16 | R16: 6.74 | S16: 3 | U16: 8 | V16: FALSE | W16: =IFERROR(VLOOKUP(D16,Teams!$B$2:$I$21,6,FALSE),"") -> 0 | X16: None | AA16: =IFERROR(H16/(H16+Priors!$G$3),0) -> 0.57680914 | AB16: =VLOOKUP(E16,Priors!$A$3:$C$6,2,FALSE) -> 0.15714383 | AC16: =VLOOKUP(E16,Priors!$A$3:$C$6,3,FALSE) -> 0.13222063 | AD16: =AA16*K16+(1-AA16)*AB16 -> 0.11411081 | AE16: =AA16*L16+(1-AA16)*AC16 -> 0.19497276 | AF16: 1 | AG16: 1 | AH16: =IFERROR(VLOOKUP(D16,Teams!$B$2:$I$21,7,FALSE),1) -> 1 | AI16: =AD16*AF16*AG16*AH16 -> 0.11411081 | AJ16: =AE16*AF16*AG16*AH16 -> 0.19497276 | AK16: Available | AN16: 0.03 | AO16: TRUE | AP16: 2021-08-20 | AQ16: FALSE | AS16: https://raw.githubusercontent.com/vaastav/Fantasy-Premier-League/master/data/2026-27/players_raw.csv
A17: 16 | B17: Madueke | C17: Noni Madueke | D17: Arsenal | E17: MID | F17: 6.5 | G17: 6.5 | H17: 1205 | I17: 1.23 | J17: 2.86 | K17: =IFERROR(I17*90/H17,0) -> 0.09186722 | L17: =IFERROR(J17*90/H17,0) -> 0.21360996 | M17: 3 | N17: 1 | O17: 72 | P17: 2.8 | Q17: 16 | R17: 5.23 | U17: 7 | V17: FALSE | W17: =IFERROR(VLOOKUP(D17,Teams!$B$2:$I$21,6,FALSE),"") -> 0 | X17: None | AA17: =IFERROR(H17/(H17+Priors!$G$3),0) -> 0.54648526 | AB17: =VLOOKUP(E17,Priors!$A$3:$C$6,2,FALSE) -> 0.15714383 | AC17: =VLOOKUP(E17,Priors!$A$3:$C$6,3,FALSE) -> 0.13222063 | AD17: =AA17*K17+(1-AA17)*AB17 -> 0.12147113 | AE17: =AA17*L17+(1-AA17)*AC17 -> 0.1766987 | AF17: 1 | AG17: 1 | AH17: =IFERROR(VLOOKUP(D17,Teams!$B$2:$I$21,7,FALSE),1) -> 1 | AI17: =AD17*AF17*AG17*AH17 -> 0.12147113 | AJ17: =AE17*AF17*AG17*AH17 -> 0.1766987 | AK17: Available | AN17: 0.004 | AO17: TRUE | AP17: 2025-07-18 | AQ17: FALSE | AS17: https://raw.githubusercontent.com/vaastav/Fantasy-Premier-League/master/data/2026-27/players_raw.csv
A18: 17 | B18: Merino | C18: Mikel Merino Zazón | D18: Arsenal | E18: MID | F18: 6 | G18: 6 | H18: 1024 | I18: 3.36 | J18: 1.45 | K18: =IFERROR(I18*90/H18,0) -> 0.2953125 | L18: =IFERROR(J18*90/H18,0) -> 0.12744141 | M18: 4 | N18: 3 | O18: 67 | P18: 3 | Q18: 10 | R18: 9.93 | V18: FALSE | W18: =IFERROR(VLOOKUP(D18,Teams!$B$2:$I$21,6,FALSE),"") -> 0 | X18: None | AA18: =IFERROR(H18/(H18+Priors!$G$3),0) -> 0.50592885 | AB18: =VLOOKUP(E18,Priors!$A$3:$C$6,2,FALSE) -> 0.15714383 | AC18: =VLOOKUP(E18,Priors!$A$3:$C$6,3,FALSE) -> 0.13222063 | AD18: =AA18*K18+(1-AA18)*AB18 -> 0.22704735 | AE18: =AA18*L18+(1-AA18)*AC18 -> 0.12980268 | AF18: 1 | AG18: 1 | AH18: =IFERROR(VLOOKUP(D18,Teams!$B$2:$I$21,7,FALSE),1) -> 1 | AI18: =AD18*AF18*AG18*AH18 -> 0.22704735 | AJ18: =AE18*AF18*AG18*AH18 -> 0.12980268 | AK18: Available | AN18: 0.012 | AO18: TRUE | AP18: 2024-08-27 | AQ18: FALSE | AS18: https://raw.githubusercontent.com/vaastav/Fantasy-Premier-League/master/data/2026-27/players_raw.csv
A19: 18 | B19: Martinelli | C19: Gabriel Martinelli | D19: Arsenal | E19: MID | F19: 6.5 | G19: 6.5 | H19: 1065 | I19: 4.12 | J19: 1.27 | K19: =IFERROR(I19*90/H19,0) -> 0.34816901 | L19: =IFERROR(J19*90/H19,0) -> 0.10732394 | M19: 1 | N19: 5 | O19: 57 | P19: 1.9 | Q19: 11 | R19: 6.51 | V19: FALSE | W19: =IFERROR(VLOOKUP(D19,Teams!$B$2:$I$21,6,FALSE),"") -> 0 | X19: None | AA19: =IFERROR(H19/(H19+Priors!$G$3),0) -> 0.5157385 | AB19: =VLOOKUP(E19,Priors!$A$3:$C$6,2,FALSE) -> 0.15714383 | AC19: =VLOOKUP(E19,Priors!$A$3:$C$6,3,FALSE) -> 0.13222063 | AD19: =AA19*K19+(1-AA19)*AB19 -> 0.25566287 | AE19: =AA19*L19+(1-AA19)*AC19 -> 0.11938045 | AF19: 1 | AG19: 1 | AH19: =IFERROR(VLOOKUP(D19,Teams!$B$2:$I$21,7,FALSE),1) -> 1 | AI19: =AD19*AF19*AG19*AH19 -> 0.25566287 | AJ19: =AE19*AF19*AG19*AH19 -> 0.11938045 | AK19: Available | AN19: 0.003 | AO19: TRUE | AP19: 2019-07-15 | AQ19: FALSE | AS19: https://raw.githubusercontent.com/vaastav/Fantasy-Premier-League/master/data/2026-27/players_raw.csv
A20: 19 | B20: Zubimendi | C20: Martín Zubimendi Ibáñez | D20: Arsenal | E20: MID | F20: 5.5 | G20: 5.5 | H20: 2991 | I20: 2.84 | J20: 2.27 | K20: =IFERROR(I20*90/H20,0) -> 0.085456369 | L20: =IFERROR(J20*90/H20,0) -> 0.068304915 | M20: 5 | N20: 1 | O20: 133 | P20: 3.5 | Q20: 34 | R20: 9.24 | V20: FALSE | W20: =IFERROR(VLOOKUP(D20,Teams!$B$2:$I$21,6,FALSE),"") -> 0 | X20: None | AA20: =IFERROR(H20/(H20+Priors!$G$3),0) -> 0.74943623 | AB20: =VLOOKUP(E20,Priors!$A$3:$C$6,2,FALSE) -> 0.15714383 | AC20: =VLOOKUP(E20,Priors!$A$3:$C$6,3,FALSE) -> 0.13222063 | AD20: =AA20*K20+(1-AA20)*AB20 -> 0.10341865 | AE20: =AA20*L20+(1-AA20)*AC20 -> 0.084319877 | AF20: 1 | AG20: 1 | AH20: =IFERROR(VLOOKUP(D20,Teams!$B$2:$I$21,7,FALSE),1) -> 1 | AI20: =AD20*AF20*AG20*AH20 -> 0.10341865 | AJ20: =AE20*AF20*AG20*AH20 -> 0.084319877 | AK20: Available | AN20: 0.015 | AO20: TRUE | AP20: 2025-07-06 | AQ20: FALSE | AS20: https://raw.githubusercontent.com/vaastav/Fantasy-Premier-League/master/data/2026-27/players_raw.csv
A21: 20 | B21: Dowman | C21: Max Dowman | D21: Arsenal | E21: MID | F21: 5.5 | G21: 5.5 | H21: 152 | I21: 1.19 | J21: 0.3 | K21: =IFERROR(I21*90/H21,0) -> 0.70460526 | L21: =IFERROR(J21*90/H21,0) -> 0.17763158 | M21: 1 | N21: 1 | O21: 16 | P21: 2.7 | Q21: 1 | R21: 9.47 | V21: TRUE | W21: =IFERROR(VLOOKUP(D21,Teams!$B$2:$I$21,6,FALSE),"") -> 0 | X21: None | AA21: =IFERROR(H21/(H21+Priors!$G$3),0) -> 0.13194444 | AB21: =VLOOKUP(E21,Priors!$A$3:$C$6,2,FALSE) -> 0.15714383 | AC21: =VLOOKUP(E21,Priors!$A$3:$C$6,3,FALSE) -> 0.13222063 | AD21: =AA21*K21+(1-AA21)*AB21 -> 0.22937833 | AE21: =AA21*L21+(1-AA21)*AC21 -> 0.13821235 | AF21: 1 | AG21: 1 | AH21: =IFERROR(VLOOKUP(D21,Teams!$B$2:$I$21,7,FALSE),1) -> 1 | AI21: =AD21*AF21*AG21*AH21 -> 0.22937833 | AJ21: =AE21*AF21*AG21*AH21 -> 0.13821235 | AK21: Available | AN21: 0.002 | AO21: TRUE | AP21: None | AQ21: FALSE | AS21: https://raw.githubusercontent.com/vaastav/Fantasy-Premier-League/master/data/2026-27/players_raw.csv
A22: 21 | B22: Nørgaard | C22: Christian Nørgaard | D22: Arsenal | E22: MID | F22: 5 | G22: 5 | H22: 101 | I22: 0.08 | J22: 0.04 | K22: =IFERROR(I22*90/H22,0) -> 0.071287129 | L22: =IFERROR(J22*90/H22,0) -> 0.035643564 | M22: 0 | N22: 0 | O22: 7 | P22: 1 | Q22: 1 | R22: 14.26 | V22: FALSE | W22: =IFERROR(VLOOKUP(D22,Teams!$B$2:$I$21,6,FALSE),"") -> 0 | X22: None | AA22: =IFERROR(H22/(H22+Priors!$G$3),0) -> 0.091734787 | AB22: =VLOOKUP(E22,Priors!$A$3:$C$6,2,FALSE) -> 0.15714383 | AC22: =VLOOKUP(E22,Priors!$A$3:$C$6,3,FALSE) -> 0.13222063 | AD22: =AA22*K22+(1-AA22)*AB22 -> 0.14926779 | AE22: =AA22*L22+(1-AA22)*AC22 -> 0.12336115 | AF22: 1 | AG22: 1 | AH22: =IFERROR(VLOOKUP(D22,Teams!$B$2:$I$21,7,FALSE),1) -> 1 | AI22: =AD22*AF22*AG22*AH22 -> 0.14926779 | AJ22: =AE22*AF22*AG22*AH22 -> 0.12336115 | AK22: Available | AN22: 0.003 | AO22: TRUE | AP22: 2025-07-10 | AQ22: FALSE | AS22: https://raw.githubusercontent.com/vaastav/Fantasy-Premier-League/master/data/2026-27/players_raw.csv
A23: 22 | B23: Nwaneri | C23: Ethan Nwaneri | D23: Arsenal | E23: MID | F23: 5.5 | G23: 5.5 | H23: 165 | I23: 0.23 | J23: 0.08 | K23: =IFERROR(I23*90/H23,0) -> 0.12545455 | L23: =IFERROR(J23*90/H23,0) -> 0.043636364 | M23: 0 | N23: 0 | O23: 8 | P23: 1.3 | Q23: 0 | R23: 7.09 | V23: FALSE | W23: =IFERROR(VLOOKUP(D23,Teams!$B$2:$I$21,6,FALSE),"") -> 0 | X23: None | AA23: =IFERROR(H23/(H23+Priors!$G$3),0) -> 0.1416309 | AB23: =VLOOKUP(E23,Priors!$A$3:$C$6,2,FALSE) -> 0.15714383 | AC23: =VLOOKUP(E23,Priors!$A$3:$C$6,3,FALSE) -> 0.13222063 | AD23: =AA23*K23+(1-AA23)*AB23 -> 0.15265565 | AE23: =AA23*L23+(1-AA23)*AC23 -> 0.11967436 | AF23: 1 | AG23: 1 | AH23: =IFERROR(VLOOKUP(D23,Teams!$B$2:$I$21,7,FALSE),1) -> 1 | AI23: =AD23*AF23*AG23*AH23 -> 0.15265565 | AJ23: =AE23*AF23*AG23*AH23 -> 0.11967436 | AK23: Available | AN23: 0 | AO23: TRUE | AP23: 2022-09-17 | AQ23: FALSE | AS23: https://raw.githubusercontent.com/vaastav/Fantasy-Premier-League/master/data/2026-27/players_raw.csv
A24: 23 | B24: Fábio Vieira | C24: Fábio Vieira | D24: Arsenal | E24: MID | F24: 5.5 | G24: 5.5 | H24: 0 | I24: 0 | J24: 0 | K24: =IFERROR(I24*90/H24,0) -> 0 | L24: =IFERROR(J24*90/H24,0) -> 0 | M24: 0 | N24: 0 | O24: 0 | P24: 0 | Q24: 0 | R24: 0 | V24: FALSE | W24: =IFERROR(VLOOKUP(D24,Teams!$B$2:$I$21,6,FALSE),"") -> 0 | X24: None | AA24: =IFERROR(H24/(H24+Priors!$G$3),0) -> 0 | AB24: =VLOOKUP(E24,Priors!$A$3:$C$6,2,FALSE) -> 0.15714383 | AC24: =VLOOKUP(E24,Priors!$A$3:$C$6,3,FALSE) -> 0.13222063 | AD24: =AA24*K24+(1-AA24)*AB24 -> 0.15714383 | AE24: =AA24*L24+(1-AA24)*AC24 -> 0.13222063 | AF24: 1 | AG24: 1 | AH24: =IFERROR(VLOOKUP(D24,Teams!$B$2:$I$21,7,FALSE),1) -> 1 | AI24: =AD24*AF24*AG24*AH24 -> 0.15714383 | AJ24: =AE24*AF24*AG24*AH24 -> 0.13222063 | AK24: Available | AN24: 0 | AO24: TRUE | AP24: 2022-06-21 | AQ24: FALSE | AS24: https://raw.githubusercontent.com/vaastav/Fantasy-Premier-League/master/data/2026-27/players_raw.csv
A25: 24 | B25: Nelson | C25: Reiss Nelson | D25: Arsenal | E25: MID | F25: 5.5 | G25: 5.5 | H25: 118 | I25: 0.71 | J25: 0.11 | K25: =IFERROR(I25*90/H25,0) -> 0.54152542 | L25: =IFERROR(J25*90/H25,0) -> 0.083898305 | M25: 0 | N25: 1 | O25: 13 | P25: 1.3 | Q25: 0 | R25: 17.54 | V25: FALSE | W25: =IFERROR(VLOOKUP(D25,Teams!$B$2:$I$21,6,FALSE),"") -> 0 | X25: None | AA25: =IFERROR(H25/(H25+Priors!$G$3),0) -> 0.10554562 | AB25: =VLOOKUP(E25,Priors!$A$3:$C$6,2,FALSE) -> 0.15714383 | AC25: =VLOOKUP(E25,Priors!$A$3:$C$6,3,FALSE) -> 0.13222063 | AD25: =AA25*K25+(1-AA25)*AB25 -> 0.19771362 | AE25: =AA25*L25+(1-AA25)*AC25 -> 0.12712042 | AF25: 1 | AG25: 1 | AH25: =IFERROR(VLOOKUP(D25,Teams!$B$2:$I$21,7,FALSE),1) -> 1 | AI25: =AD25*AF25*AG25*AH25 -> 0.19771362 | AJ25: =AE25*AF25*AG25*AH25 -> 0.12712042 | AK25: Available | AN25: 0 | AO25: TRUE | AP25: 2017-07-12 | AQ25: FALSE | AS25: https://raw.githubusercontent.com/vaastav/Fantasy-Premier-League/master/data/2026-27/players_raw.csv
A26: 25 | B26: Gyökeres | C26: Viktor Gyökeres | D26: Arsenal | E26: FWD | F26: 7.5 | G26: 7.5 | H26: 2217 | I26: 12.26 | J26: 1.94 | K26: =IFERROR(I26*90/H26,0) -> 0.49769959 | L26: =IFERROR(J26*90/H26,0) -> 0.078755074 | M26: 14 | N26: 1 | O26: 128 | P26: 3.6 | Q26: 26 | R26: 3.45 | S26: 2 | V26: FALSE | W26: =IFERROR(VLOOKUP(D26,Teams!$B$2:$I$21,6,FALSE),"") -> 0 | X26: None | AA26: =IFERROR(H26/(H26+Priors!$G$3),0) -> 0.68915138 | AB26: =VLOOKUP(E26,Priors!$A$3:$C$6,2,FALSE) -> 0.44625207 | AC26: =VLOOKUP(E26,Priors!$A$3:$C$6,3,FALSE) -> 0.05821726 | AD26: =AA26*K26+(1-AA26)*AB26 -> 0.4817072 | AE26: =AA26*L26+(1-AA26)*AC26 -> 0.072370923 | AF26: 1 | AG26: 1 | AH26: =IFERROR(VLOOKUP(D26,Teams!$B$2:$I$21,7,FALSE),1) -> 1 | AI26: =AD26*AF26*AG26*AH26 -> 0.4817072 | AJ26: =AE26*AF26*AG26*AH26 -> 0.072370923 | AK26: Available | AN26: 0.13 | AO26: TRUE | AP26: 2025-07-26 | AQ26: FALSE | AS26: https://raw.githubusercontent.com/vaastav/Fantasy-Premier-League/master/data/2026-27/players_raw.csv
A27: 26 | B27: Havertz | C27: Kai Havertz | D27: Arsenal | E27: FWD | F27: 7.5 | G27: 7.5 | H27: 577 | I27: 3.31 | J27: 0.64 | K27: =IFERROR(I27*90/H27,0) -> 0.51629116 | L27: =IFERROR(J27*90/H27,0) -> 0.09982669 | M27: 2 | N27: 3 | O27: 36 | P27: 3 | Q27: 7 | R27: 4.99 | V27: FALSE | W27: =IFERROR(VLOOKUP(D27,Teams!$B$2:$I$21,6,FALSE),"") -> 0 | X27: None | AA27: =IFERROR(H27/(H27+Priors!$G$3),0) -> 0.36588459 | AB27: =VLOOKUP(E27,Priors!$A$3:$C$6,2,FALSE) -> 0.44625207 | AC27: =VLOOKUP(E27,Priors!$A$3:$C$6,3,FALSE) -> 0.05821726 | AD27: =AA27*K27+(1-AA27)*AB27 -> 0.4718783 | AE27: =AA27*L27+(1-AA27)*AC27 -> 0.073441509 | AF27: 1 | AG27: 1 | AH27: =IFERROR(VLOOKUP(D27,Teams!$B$2:$I$21,7,FALSE),1) -> 1 | AI27: =AD27*AF27*AG27*AH27 -> 0.4718783 | AJ27: =AE27*AF27*AG27*AH27 -> 0.073441509 | AK27: Available | AN27: 0.04 | AO27: TRUE | AP27: 2023-06-28 | AQ27: FALSE | AS27: https://raw.githubusercontent.com/vaastav/Fantasy-Premier-League/master/data/2026-27/players_raw.csv
A28: 27 | B28: G.Jesus | C28: Gabriel Jesus | D28: Arsenal | E28: FWD | F28: 6 | G28: 6 | H28: 418 | I28: 2.71 | J28: 0.26 | K28: =IFERROR(I28*90/H28,0) -> 0.58349282 | L28: =IFERROR(J28*90/H28,0) -> 0.055980861 | M28: 3 | N28: 0 | O28: 24 | P28: 1.7 | Q28: 3 | R28: 6.46 | V28: FALSE | W28: =IFERROR(VLOOKUP(D28,Teams!$B$2:$I$21,6,FALSE),"") -> 0 | X28: None | AA28: =IFERROR(H28/(H28+Priors!$G$3),0) -> 0.29478138 | AB28: =VLOOKUP(E28,Priors!$A$3:$C$6,2,FALSE) -> 0.44625207 | AC28: =VLOOKUP(E28,Priors!$A$3:$C$6,3,FALSE) -> 0.05821726 | AD28: =AA28*K28+(1-AA28)*AB28 -> 0.48670809 | AE28: =AA28*L28+(1-AA28)*AC28 -> 0.057558011 | AF28: 1 | AG28: 1 | AH28: =IFERROR(VLOOKUP(D28,Teams!$B$2:$I$21,7,FALSE),1) -> 1 | AI28: =AD28*AF28*AG28*AH28 -> 0.48670809 | AJ28: =AE28*AF28*AG28*AH28 -> 0.057558011 | AK28: Available | AN28: 0.004 | AO28: TRUE | AP28: 2022-07-04 | AQ28: FALSE | AS28: https://raw.githubusercontent.com/vaastav/Fantasy-Premier-League/master/data/2026-27/players_raw.csv
A29: 557 | B29: Tzolis | C29: Christos Tzolis | D29: Arsenal | E29: MID | F29: 6.5 | G29: 6.5 | H29: 0 | I29: 0 | J29: 0 | K29: =IFERROR(I29*90/H29,0) -> 0 | L29: =IFERROR(J29*90/H29,0) -> 0 | M29: 0 | N29: 0 | O29: 0 | P29: 0 | Q29: 0 | R29: 0 | V29: TRUE | W29: =IFERROR(VLOOKUP(D29,Teams!$B$2:$I$21,6,FALSE),"") -> 0 | X29: None | AA29: =IFERROR(H29/(H29+Priors!$G$3),0) -> 0 | AB29: =VLOOKUP(E29,Priors!$A$3:$C$6,2,FALSE) -> 0.15714383 | AC29: =VLOOKUP(E29,Priors!$A$3:$C$6,3,FALSE) -> 0.13222063 | AD29: =AA29*K29+(1-AA29)*AB29 -> 0.15714383 | AE29: =AA29*L29+(1-AA29)*AC29 -> 0.13222063 | AF29: 1 | AG29: 1 | AH29: =IFERROR(VLOOKUP(D29,Teams!$B$2:$I$21,7,FALSE),1) -> 1 | AI29: =AD29*AF29*AG29*AH29 -> 0.15714383 | AJ29: =AE29*AF29*AG29*AH29 -> 0.13222063 | AK29: Available | AN29: 0.017 | AO29: TRUE | AP29: 2026-07-23 | AQ29: TRUE | AS29: https://raw.githubusercontent.com/vaastav/Fantasy-Premier-League/master/data/2026-27/players_raw.csv
A30: 28 | B30: Martinez | C30: Emiliano Martínez | D30: Aston Villa | E30: GK | F30: 5 | G30: 5 | H30: 2835 | I30: 0 | J30: 0.08 | K30: =IFERROR(I30*90/H30,0) -> 0 | L30: =IFERROR(J30*90/H30,0) -> 0.0025396825 | M30: 0 | N30: 1 | O30: 120 | P30: 3.8 | Q30: 32 | R30: 0 | V30: FALSE | W30: =IFERROR(VLOOKUP(D30,Teams!$B$2:$I$21,6,FALSE),"") -> 0 | X30: None | AA30: =IFERROR(H30/(H30+Priors!$G$3),0) -> 0.73924381 | AB30: =VLOOKUP(E30,Priors!$A$3:$C$6,2,FALSE) -> 0.00024013207 | AC30: =VLOOKUP(E30,Priors!$A$3:$C$6,3,FALSE) -> 0.0019810896 | AD30: =AA30*K30+(1-AA30)*AB30 -> 6.2615925e-05 | AE30: =AA30*L30+(1-AA30)*AC30 -> 0.002394026 | AF30: 1 | AG30: 1 | AH30: =IFERROR(VLOOKUP(D30,Teams!$B$2:$I$21,7,FALSE),1) -> 1 | AI30: =AD30*AF30*AG30*AH30 -> 6.2615925e-05 | AJ30: =AE30*AF30*AG30*AH30 -> 0.002394026 | AK30: Available | AN30: 0.046 | AO30: TRUE | AP30: 2020-09-16 | AQ30: FALSE | AS30: https://raw.githubusercontent.com/vaastav/Fantasy-Premier-League/master/data/2026-27/players_raw.csv
A31: 29 | B31: M.Bizot | C31: Marco Bizot | D31: Aston Villa | E31: GK | F31: 4.5 | G31: 4.5 | H31: 585 | I31: 0 | J31: 0 | K31: =IFERROR(I31*90/H31,0) -> 0 | L31: =IFERROR(J31*90/H31,0) -> 0 | M31: 0 | N31: 0 | O31: 16 | P31: 2.3 | Q31: 6 | R31: 0 | V31: FALSE | W31: =IFERROR(VLOOKUP(D31,Teams!$B$2:$I$21,6,FALSE),"") -> 0 | X31: None | AA31: =IFERROR(H31/(H31+Priors!$G$3),0) -> 0.36908517 | AB31: =VLOOKUP(E31,Priors!$A$3:$C$6,2,FALSE) -> 0.00024013207 | AC31: =VLOOKUP(E31,Priors!$A$3:$C$6,3,FALSE) -> 0.0019810896 | AD31: =AA31*K31+(1-AA31)*AB31 -> 0.00015150288 | AE31: =AA31*L31+(1-AA31)*AC31 -> 0.0012498988 | AF31: 1 | AG31: 1 | AH31: =IFERROR(VLOOKUP(D31,Teams!$B$2:$I$21,7,FALSE),1) -> 1 | AI31: =AD31*AF31*AG31*AH31 -> 0.00015150288 | AJ31: =AE31*AF31*AG31*AH31 -> 0.0012498988 | AK31: Available | AN31: 0.001 | AO31: TRUE | AP31: 2025-07-15 | AQ31: FALSE | AS31: https://raw.githubusercontent.com/vaastav/Fantasy-Premier-League/master/data/2026-27/players_raw.csv
A32: 30 | B32: Digne | C32: Lucas Digne | D32: Aston Villa | E32: DEF | F32: 4.5 | G32: 4.5 | H32: 1842 | I32: 0.67 | J32: 3.28 | K32: =IFERROR(I32*90/H32,0) -> 0.032736156 | L32: =IFERROR(J32*90/H32,0) -> 0.16026059 | M32: 0 | N32: 7 | O32: 97 | P32: 3.1 | Q32: 21 | R32: 5.52 | U32: 4 | V32: FALSE | W32: =IFERROR(VLOOKUP(D32,Teams!$B$2:$I$21,6,FALSE),"") -> 0 | X32: None | AA32: =IFERROR(H32/(H32+Priors!$G$3),0) -> 0.64813512 | AB32: =VLOOKUP(E32,Priors!$A$3:$C$6,2,FALSE) -> 0.060081391 | AC32: =VLOOKUP(E32,Priors!$A$3:$C$6,3,FALSE) -> 0.059588192 | AD32: =AA32*K32+(1-AA32)*AB32 -> 0.042357984 | AE32: =AA32*L32+(1-AA32)*AC32 -> 0.12483751 | AF32: 1 | AG32: 1 | AH32: =IFERROR(VLOOKUP(D32,Teams!$B$2:$I$21,7,FALSE),1) -> 1 | AI32: =AD32*AF32*AG32*AH32 -> 0.042357984 | AJ32: =AE32*AF32*AG32*AH32 -> 0.12483751 | AK32: Available | AN32: 0.014 | AO32: TRUE | AP32: 2022-01-13 | AQ32: FALSE | AS32: https://raw.githubusercontent.com/vaastav/Fantasy-Premier-League/master/data/2026-27/players_raw.csv
A33: 31 | B33: Konsa | C33: Ezri Konsa Ngoyo | D33: Aston Villa | E33: DEF | F33: 4.5 | G33: 4.5 | H33: 3035 | I33: 1.27 | J33: 0.59 | K33: =IFERROR(I33*90/H33,0) -> 0.037660626 | L33: =IFERROR(J33*90/H33,0) -> 0.017495881 | M33: 0 | N33: 1 | O33: 100 | P33: 2.9 | Q33: 34 | R33: 5.81 | V33: FALSE | W33: =IFERROR(VLOOKUP(D33,Teams!$B$2:$I$21,6,FALSE),"") -> 0 | X33: None | AA33: =IFERROR(H33/(H33+Priors!$G$3),0) -> 0.75216853 | AB33: =VLOOKUP(E33,Priors!$A$3:$C$6,2,FALSE) -> 0.060081391 | AC33: =VLOOKUP(E33,Priors!$A$3:$C$6,3,FALSE) -> 0.059588192 | AD33: =AA33*K33+(1-AA33)*AB33 -> 0.043217197 | AE33: =AA33*L33+(1-AA33)*AC33 -> 0.027927681 | AF33: 1 | AG33: 1 | AH33: =IFERROR(VLOOKUP(D33,Teams!$B$2:$I$21,7,FALSE),1) -> 1 | AI33: =AD33*AF33*AG33*AH33 -> 0.043217197 | AJ33: =AE33*AF33*AG33*AH33 -> 0.027927681 | AK33: Available | AN33: 0.174 | AO33: TRUE | AP33: 2019-07-11 | AQ33: FALSE | AS33: https://raw.githubusercontent.com/vaastav/Fantasy-Premier-League/master/data/2026-27/players_raw.csv
A34: 32 | B34: Cash | C34: Matty Cash | D34: Aston Villa | E34: DEF | F34: 4.5 | G34: 4.5 | H34: 3016 | I34: 1.14 | J34: 2.94 | K34: =IFERROR(I34*90/H34,0) -> 0.034018568 | L34: =IFERROR(J34*90/H34,0) -> 0.087732095 | M34: 3 | N34: 3 | O34: 117 | P34: 3.3 | Q34: 34 | R34: 5.55 | U34: 5 | V34: FALSE | W34: =IFERROR(VLOOKUP(D34,Teams!$B$2:$I$21,6,FALSE),"") -> 0 | X34: None | AA34: =IFERROR(H34/(H34+Priors!$G$3),0) -> 0.75099602 | AB34: =VLOOKUP(E34,Priors!$A$3:$C$6,2,FALSE) -> 0.060081391 | AC34: =VLOOKUP(E34,Priors!$A$3:$C$6,3,FALSE) -> 0.059588192 | AD34: =AA34*K34+(1-AA34)*AB34 -> 0.040508315 | AE34: =AA34*L34+(1-AA34)*AC34 -> 0.080724151 | AF34: 1 | AG34: 1 | AH34: =IFERROR(VLOOKUP(D34,Teams!$B$2:$I$21,7,FALSE),1) -> 1 | AI34: =AD34*AF34*AG34*AH34 -> 0.040508315 | AJ34: =AE34*AF34*AG34*AH34 -> 0.080724151 | AK34: Available | AN34: 0.078 | AO34: TRUE | AP34: 2020-09-03 | AQ34: TRUE | AS34: https://raw.githubusercontent.com/vaastav/Fantasy-Premier-League/master/data/2026-27/players_raw.csv
A35: 33 | B35: Mings | C35: Tyrone Mings | D35: Aston Villa | E35: DEF | F35: 4.5 | G35: 4.5 | H35: 1322 | I35: 1.3 | J35: 0.42 | K35: =IFERROR(I35*90/H35,0) -> 0.088502269 | L35: =IFERROR(J35*90/H35,0) -> 0.028593041 | M35: 0 | N35: 1 | O35: 50 | P35: 2.9 | Q35: 15 | R35: 7.28 | V35: FALSE | W35: =IFERROR(VLOOKUP(D35,Teams!$B$2:$I$21,6,FALSE),"") -> 0 | X35: None | AA35: =IFERROR(H35/(H35+Priors!$G$3),0) -> 0.56933678 | AB35: =VLOOKUP(E35,Priors!$A$3:$C$6,2,FALSE) -> 0.060081391 | AC35: =VLOOKUP(E35,Priors!$A$3:$C$6,3,FALSE) -> 0.059588192 | AD35: =AA35*K35+(1-AA35)*AB35 -> 0.076262442 | AE35: =AA35*L35+(1-AA35)*AC35 -> 0.041941512 | AF35: 1 | AG35: 1 | AH35: =IFERROR(VLOOKUP(D35,Teams!$B$2:$I$21,7,FALSE),1) -> 1 | AI35: =AD35*AF35*AG35*AH35 -> 0.076262442 | AJ35: =AE35*AF35*AG35*AH35 -> 0.041941512 | AK35: Available | AN35: 0.002 | AO35: TRUE | AP35: 2019-07-08 | AQ35: FALSE | AS35: https://raw.githubusercontent.com/vaastav/Fantasy-Premier-League/master/data/2026-27/players_raw.csv
A36: 34 | B36: Pau | C36: Pau Torres | D36: Aston Villa | E36: DEF | F36: 4.5 | G36: 4.5 | H36: 1673 | I36: 1.33 | J36: 0.39 | K36: =IFERROR(I36*90/H36,0) -> 0.071548117 | L36: =IFERROR(J36*90/H36,0) -> 0.020980275 | M36: 0 | N36: 2 | O36: 64 | P36: 3 | Q36: 18 | R36: 6.03 | V36: FALSE | W36: =IFERROR(VLOOKUP(D36,Teams!$B$2:$I$21,6,FALSE),"") -> 0 | X36: None | AA36: =IFERROR(H36/(H36+Priors!$G$3),0) -> 0.62588851 | AB36: =VLOOKUP(E36,Priors!$A$3:$C$6,2,FALSE) -> 0.060081391 | AC36: =VLOOKUP(E36,Priors!$A$3:$C$6,3,FALSE) -> 0.059588192 | AD36: =AA36*K36+(1-AA36)*AB36 -> 0.067258283 | AE36: =AA36*L36+(1-AA36)*AC36 -> 0.03542394 | AF36: 1 | AG36: 1 | AH36: =IFERROR(VLOOKUP(D36,Teams!$B$2:$I$21,7,FALSE),1) -> 1 | AI36: =AD36*AF36*AG36*AH36 -> 0.067258283 | AJ36: =AE36*AF36*AG36*AH36 -> 0.03542394 | AK36: Available | AN36: 0.002 | AO36: TRUE | AP36: 2023-07-12 | AQ36: FALSE | AS36: https://raw.githubusercontent.com/vaastav/Fantasy-Premier-League/master/data/2026-27/players_raw.csv
A37: 35 | B37: Bogarde | C37: Lamare Bogarde | D37: Aston Villa | E37: MID | F37: 5 | G37: 5 | H37: 1042 | I37: 0 | J37: 0.2 | K37: =IFERROR(I37*90/H37,0) -> 0 | L37: =IFERROR(J37*90/H37,0) -> 0.017274472 | M37: 0 | N37: 0 | O37: 40 | P37: 1.4 | Q37: 11 | R37: 5.18 | V37: FALSE | W37: =IFERROR(VLOOKUP(D37,Teams!$B$2:$I$21,6,FALSE),"") -> 0 | X37: None | AA37: =IFERROR(H37/(H37+Priors!$G$3),0) -> 0.51028404 | AB37: =VLOOKUP(E37,Priors!$A$3:$C$6,2,FALSE) -> 0.15714383 | AC37: =VLOOKUP(E37,Priors!$A$3:$C$6,3,FALSE) -> 0.13222063 | AD37: =AA37*K37+(1-AA37)*AB37 -> 0.076955843 | AE37: =AA37*L37+(1-AA37)*AC37 -> 0.07356544 | AF37: 1 | AG37: 1 | AH37: =IFERROR(VLOOKUP(D37,Teams!$B$2:$I$21,7,FALSE),1) -> 1 | AI37: =AD37*AF37*AG37*AH37 -> 0.076955843 | AJ37: =AE37*AF37*AG37*AH37 -> 0.07356544 | AK37: Available | AN37: 0.001 | AO37: TRUE | AP37: 2021-01-07 | AQ37: FALSE | AS37: https://raw.githubusercontent.com/vaastav/Fantasy-Premier-League/master/data/2026-27/players_raw.csv
A38: 36 | B38: Maatsen | C38: Ian Maatsen | D38: Aston Villa | E38: DEF | F38: 4.5 | G38: 4.5 | H38: 1590 | I38: 1.26 | J38: 2.39 | K38: =IFERROR(I38*90/H38,0) -> 0.071320755 | L38: =IFERROR(J38*90/H38,0) -> 0.13528302 | M38: 0 | N38: 1 | O38: 54 | P38: 1.8 | Q38: 17 | R38: 7.25 | V38: FALSE | W38: =IFERROR(VLOOKUP(D38,Teams!$B$2:$I$21,6,FALSE),"") -> 0 | X38: None | AA38: =IFERROR(H38/(H38+Priors!$G$3),0) -> 0.61389961 | AB38: =VLOOKUP(E38,Priors!$A$3:$C$6,2,FALSE) -> 0.060081391 | AC38: =VLOOKUP(E38,Priors!$A$3:$C$6,3,FALSE) -> 0.059588192 | AD38: =AA38*K38+(1-AA38)*AB38 -> 0.066981232 | AE38: =AA38*L38+(1-AA38)*AC38 -> 0.10605722 | AF38: 1 | AG38: 1 | AH38: =IFERROR(VLOOKUP(D38,Teams!$B$2:$I$21,7,FALSE),1) -> 1 | AI38: =AD38*AF38*AG38*AH38 -> 0.066981232 | AJ38: =AE38*AF38*AG38*AH38 -> 0.10605722 | AK38: Available | AN38: 0.006 | AO38: TRUE | AP38: 2024-06-28 | AQ38: FALSE | AS38: https://raw.githubusercontent.com/vaastav/Fantasy-Premier-League/master/data/2026-27/players_raw.csv
A39: 37 | B39: Lindelöf | C39: Victor Lindelöf | D39: Aston Villa | E39: DEF | F39: 4.5 | G39: 4.5 | H39: 942 | I39: 0.28 | J39: 0.1 | K39: =IFERROR(I39*90/H39,0) -> 0.026751592 | L39: =IFERROR(J39*90/H39,0) -> 0.0095541401 | M39: 0 | N39: 1 | O39: 29 | P39: 1.7 | Q39: 11 | R39: 5.16 | V39: FALSE | W39: =IFERROR(VLOOKUP(D39,Teams!$B$2:$I$21,6,FALSE),"") -> 0 | X39: None | AA39: =IFERROR(H39/(H39+Priors!$G$3),0) -> 0.48506694 | AB39: =VLOOKUP(E39,Priors!$A$3:$C$6,2,FALSE) -> 0.060081391 | AC39: =VLOOKUP(E39,Priors!$A$3:$C$6,3,FALSE) -> 0.059588192 | AD39: =AA39*K39+(1-AA39)*AB39 -> 0.043914208 | AE39: =AA39*L39+(1-AA39)*AC39 -> 0.035318327 | AF39: 1 | AG39: 1 | AH39: =IFERROR(VLOOKUP(D39,Teams!$B$2:$I$21,7,FALSE),1) -> 1 | AI39: =AD39*AF39*AG39*AH39 -> 0.043914208 | AJ39: =AE39*AF39*AG39*AH39 -> 0.035318327 | AK39: Available | AN39: 0.002 | AO39: TRUE | AP39: 2025-09-01 | AQ39: FALSE | AS39: https://raw.githubusercontent.com/vaastav/Fantasy-Premier-League/master/data/2026-27/players_raw.csv
A40: 38 | B40: A.García | C40: Andrés García | D40: Aston Villa | E40: DEF | F40: 4 | G40: 4 | H40: 83 | I40: 0 | J40: 0.01 | K40: =IFERROR(I40*90/H40,0) -> 0 | L40: =IFERROR(J40*90/H40,0) -> 0.010843373 | M40: 0 | N40: 0 | O40: 5 | P40: 0.8 | Q40: 1 | R40: 10.84 | V40: TRUE | W40: =IFERROR(VLOOKUP(D40,Teams!$B$2:$I$21,6,FALSE),"") -> 0 | X40: None | AA40: =IFERROR(H40/(H40+Priors!$G$3),0) -> 0.076638966 | AB40: =VLOOKUP(E40,Priors!$A$3:$C$6,2,FALSE) -> 0.060081391 | AC40: =VLOOKUP(E40,Priors!$A$3:$C$6,3,FALSE) -> 0.059588192 | AD40: =AA40*K40+(1-AA40)*AB40 -> 0.055476816 | AE40: =AA40*L40+(1-AA40)*AC40 -> 0.055852439 | AF40: 1 | AG40: 1 | AH40: =IFERROR(VLOOKUP(D40,Teams!$B$2:$I$21,7,FALSE),1) -> 1 | AI40: =AD40*AF40*AG40*AH40 -> 0.055476816 | AJ40: =AE40*AF40*AG40*AH40 -> 0.055852439 | AK40: Available | AN40: 0.015 | AO40: TRUE | AP40: None | AQ40: FALSE | AS40: https://raw.githubusercontent.com/vaastav/Fantasy-Premier-League/master/data/2026-27/players_raw.csv
A41: 39 | B41: Nedeljkovic | C41: Kosta Nedeljkovic | D41: Aston Villa | E41: DEF | F41: 4 | G41: 4 | H41: 0 | I41: 0 | J41: 0 | K41: =IFERROR(I41*90/H41,0) -> 0 | L41: =IFERROR(J41*90/H41,0) -> 0 | M41: 0 | N41: 0 | O41: 0 | P41: 0 | Q41: 0 | R41: 0 | V41: FALSE | W41: =IFERROR(VLOOKUP(D41,Teams!$B$2:$I$21,6,FALSE),"") -> 0 | X41: None | AA41: =IFERROR(H41/(H41+Priors!$G$3),0) -> 0 | AB41: =VLOOKUP(E41,Priors!$A$3:$C$6,2,FALSE) -> 0.060081391 | AC41: =VLOOKUP(E41,Priors!$A$3:$C$6,3,FALSE) -> 0.059588192 | AD41: =AA41*K41+(1-AA41)*AB41 -> 0.060081391 | AE41: =AA41*L41+(1-AA41)*AC41 -> 0.059588192 | AF41: 1 | AG41: 1 | AH41: =IFERROR(VLOOKUP(D41,Teams!$B$2:$I$21,7,FALSE),1) -> 1 | AI41: =AD41*AF41*AG41*AH41 -> 0.060081391 | AJ41: =AE41*AF41*AG41*AH41 -> 0.059588192 | AK41: Available | AN41: 0.004 | AO41: TRUE | AP41: 2024-01-22 | AQ41: FALSE | AS41: https://raw.githubusercontent.com/vaastav/Fantasy-Premier-League/master/data/2026-27/players_raw.csv
A42: 41 | B42: Buendía | C42: Emiliano Buendía Stati | D42: Aston Villa | E42: MID | F42: 6 | G42: 6 | H42: 1753 | I42: 3.38 | J42: 2.23 | K42: =IFERROR(I42*90/H42,0) -> 0.17353109 | L42: =IFERROR(J42*90/H42,0) -> 0.11448945 | M42: 6 | N42: 2 | O42: 102 | P42: 2.8 | Q42: 21 | R42: 10.11 | S42: 1 | T42: 1 | V42: FALSE | W42: =IFERROR(VLOOKUP(D42,Teams!$B$2:$I$21,6,FALSE),"") -> 0 | X42: None | AA42: =IFERROR(H42/(H42+Priors!$G$3),0) -> 0.6367599 | AB42: =VLOOKUP(E42,Priors!$A$3:$C$6,2,FALSE) -> 0.15714383 | AC42: =VLOOKUP(E42,Priors!$A$3:$C$6,3,FALSE) -> 0.13222063 | AD42: =AA42*K42+(1-AA42)*AB42 -> 0.16757858 | AE42: =AA42*L42+(1-AA42)*AC42 -> 0.12093012 | AF42: 1 | AG42: 1 | AH42: =IFERROR(VLOOKUP(D42,Teams!$B$2:$I$21,7,FALSE),1) -> 1 | AI42: =AD42*AF42*AG42*AH42 -> 0.16757858 | AJ42: =AE42*AF42*AG42*AH42 -> 0.12093012 | AK42: Available | AN42: 0.008 | AO42: TRUE | AP42: 2021-06-10 | AQ42: FALSE | AS42: https://raw.githubusercontent.com/vaastav/Fantasy-Premier-League/master/data/2026-27/players_raw.csv
A43: 42 | B43: Guessand | C43: Evann Guessand | D43: Aston Villa | E43: MID | F43: 5.5 | G43: 5.5 | H43: 909 | I43: 1.56 | J43: 0.85 | K43: =IFERROR(I43*90/H43,0) -> 0.15445545 | L43: =IFERROR(J43*90/H43,0) -> 0.084158416 | M43: 1 | N43: 3 | O43: 44 | P43: 2.1 | Q43: 9 | R43: 8.22 | V43: FALSE | W43: =IFERROR(VLOOKUP(D43,Teams!$B$2:$I$21,6,FALSE),"") -> 0 | X43: None | AA43: =IFERROR(H43/(H43+Priors!$G$3),0) -> 0.47616553 | AB43: =VLOOKUP(E43,Priors!$A$3:$C$6,2,FALSE) -> 0.15714383 | AC43: =VLOOKUP(E43,Priors!$A$3:$C$6,3,FALSE) -> 0.13222063 | AD43: =AA43*K43+(1-AA43)*AB43 -> 0.15586372 | AE43: =AA43*L43+(1-AA43)*AC43 -> 0.10933506 | AF43: 1 | AG43: 1 | AH43: =IFERROR(VLOOKUP(D43,Teams!$B$2:$I$21,7,FALSE),1) -> 1 | AI43: =AD43*AF43*AG43*AH43 -> 0.15586372 | AJ43: =AE43*AF43*AG43*AH43 -> 0.10933506 | AK43: Available | AN43: 0 | AO43: TRUE | AP43: 2025-08-08 | AQ43: FALSE | AS43: https://raw.githubusercontent.com/vaastav/Fantasy-Premier-League/master/data/2026-27/players_raw.csv
A44: 44 | B44: Bailey | C44: Leon Bailey | D44: Aston Villa | E44: MID | F44: 5.5 | G44: 5.5 | H44: 450 | I44: 0.5 | J44: 1.46 | K44: =IFERROR(I44*90/H44,0) -> 0.1 | L44: =IFERROR(J44*90/H44,0) -> 0.292 | M44: 0 | N44: 2 | O44: 21 | P44: 1.6 | Q44: 3 | R44: 9.6 | V44: FALSE | W44: =IFERROR(VLOOKUP(D44,Teams!$B$2:$I$21,6,FALSE),"") -> 0 | X44: None | AA44: =IFERROR(H44/(H44+Priors!$G$3),0) -> 0.31034483 | AB44: =VLOOKUP(E44,Priors!$A$3:$C$6,2,FALSE) -> 0.15714383 | AC44: =VLOOKUP(E44,Priors!$A$3:$C$6,3,FALSE) -> 0.13222063 | AD44: =AA44*K44+(1-AA44)*AB44 -> 0.13940954 | AE44: =AA44*L44+(1-AA44)*AC44 -> 0.18180733 | AF44: 1 | AG44: 1 | AH44: =IFERROR(VLOOKUP(D44,Teams!$B$2:$I$21,7,FALSE),1) -> 1 | AI44: =AD44*AF44*AG44*AH44 -> 0.13940954 | AJ44: =AE44*AF44*AG44*AH44 -> 0.18180733 | AK44: Available | AN44: 0.001 | AO44: TRUE | AP44: 2021-08-04 | AQ44: FALSE | AS44: https://raw.githubusercontent.com/vaastav/Fantasy-Premier-League/master/data/2026-27/players_raw.csv
A45: 45 | B45: McGinn | C45: John McGinn | D45: Aston Villa | E45: MID | F45: 5.5 | G45: 5.5 | H45: 2136 | I45: 3 | J45: 4.11 | K45: =IFERROR(I45*90/H45,0) -> 0.12640449 | L45: =IFERROR(J45*90/H45,0) -> 0.17317416 | M45: 5 | N45: 4 | O45: 103 | P45: 3.4 | Q45: 28 | R45: 6.32 | U45: 6 | V45: FALSE | W45: =IFERROR(VLOOKUP(D45,Teams!$B$2:$I$21,6,FALSE),"") -> 0 | X45: None | AA45: =IFERROR(H45/(H45+Priors!$G$3),0) -> 0.68112245 | AB45: =VLOOKUP(E45,Priors!$A$3:$C$6,2,FALSE) -> 0.15714383 | AC45: =VLOOKUP(E45,Priors!$A$3:$C$6,3,FALSE) -> 0.13222063 | AD45: =AA45*K45+(1-AA45)*AB45 -> 0.13620658 | AE45: =AA45*L45+(1-AA45)*AC45 -> 0.160115 | AF45: 1 | AG45: 1 | AH45: =IFERROR(VLOOKUP(D45,Teams!$B$2:$I$21,7,FALSE),1) -> 1 | AI45: =AD45*AF45*AG45*AH45 -> 0.13620658 | AJ45: =AE45*AF45*AG45*AH45 -> 0.160115 | AK45: Available | AN45: 0.027 | AO45: TRUE | AP45: 2018-08-08 | AQ45: FALSE | AS45: https://raw.githubusercontent.com/vaastav/Fantasy-Premier-League/master/data/2026-27/players_raw.csv
A46: 46 | B46: Barkley | C46: Ross Barkley | D46: Aston Villa | E46: MID | F46: 5 | G46: 5 | H46: 844 | I46: 1.58 | J46: 1.26 | K46: =IFERROR(I46*90/H46,0) -> 0.16848341 | L46: =IFERROR(J46*90/H46,0) -> 0.13436019 | M46: 3 | N46: 2 | O46: 56 | P46: 2.7 | Q46: 7 | R46: 7.89 | V46: FALSE | W46: =IFERROR(VLOOKUP(D46,Teams!$B$2:$I$21,6,FALSE),"") -> 0 | X46: None | AA46: =IFERROR(H46/(H46+Priors!$G$3),0) -> 0.45770065 | AB46: =VLOOKUP(E46,Priors!$A$3:$C$6,2,FALSE) -> 0.15714383 | AC46: =VLOOKUP(E46,Priors!$A$3:$C$6,3,FALSE) -> 0.13222063 | AD46: =AA46*K46+(1-AA46)*AB46 -> 0.16233397 | AE46: =AA46*L46+(1-AA46)*AC46 -> 0.13319991 | AF46: 1 | AG46: 1 | AH46: =IFERROR(VLOOKUP(D46,Teams!$B$2:$I$21,7,FALSE),1) -> 1 | AI46: =AD46*AF46*AG46*AH46 -> 0.16233397 | AJ46: =AE46*AF46*AG46*AH46 -> 0.13319991 | AK46: Available | AN46: 0.002 | AO46: TRUE | AP46: 2024-07-01 | AQ46: FALSE | AS46: https://raw.githubusercontent.com/vaastav/Fantasy-Premier-League/master/data/2026-27/players_raw.csv
A47: 47 | B47: Kamara | C47: Boubacar Kamara | D47: Aston Villa | E47: MID | F47: 5 | G47: 5 | H47: 1410 | I47: 0.53 | J47: 0.84 | K47: =IFERROR(I47*90/H47,0) -> 0.033829787 | L47: =IFERROR(J47*90/H47,0) -> 0.053617021 | M47: 1 | N47: 3 | O47: 61 | P47: 3.4 | Q47: 17 | R47: 9.51 | V47: FALSE | W47: =IFERROR(VLOOKUP(D47,Teams!$B$2:$I$21,6,FALSE),"") -> 0 | X47: None | AA47: =IFERROR(H47/(H47+Priors!$G$3),0) -> 0.58506224 | AB47: =VLOOKUP(E47,Priors!$A$3:$C$6,2,FALSE) -> 0.15714383 | AC47: =VLOOKUP(E47,Priors!$A$3:$C$6,3,FALSE) -> 0.13222063 | AD47: =AA47*K47+(1-AA47)*AB47 -> 0.084997441 | AE47: =AA47*L47+(1-AA47)*AC47 -> 0.086232626 | AF47: 1 | AG47: 1 | AH47: =IFERROR(VLOOKUP(D47,Teams!$B$2:$I$21,7,FALSE),1) -> 1 | AI47: =AD47*AF47*AG47*AH47 -> 0.084997441 | AJ47: =AE47*AF47*AG47*AH47 -> 0.086232626 | AK47: Doubtful | AL47: 75 | AM47: Knee injury - 75% chance of playing | AN47: 0.001 | AO47: TRUE | AP47: 2022-06-11 | AQ47: FALSE | AS47: https://raw.githubusercontent.com/vaastav/Fantasy-Premier-League/master/data/2026-27/players_raw.csv
A48: 48 | B48: Onana | C48: Amadou Onana | D48: Aston Villa | E48: MID | F48: 5 | G48: 5 | H48: 1755 | I48: 1.68 | J48: 0.69 | K48: =IFERROR(I48*90/H48,0) -> 0.086153846 | L48: =IFERROR(J48*90/H48,0) -> 0.035384615 | M48: 2 | N48: 0 | O48: 76 | P48: 3 | Q48: 21 | R48: 11.23 | V48: FALSE | W48: =IFERROR(VLOOKUP(D48,Teams!$B$2:$I$21,6,FALSE),"") -> 0 | X48: None | AA48: =IFERROR(H48/(H48+Priors!$G$3),0) -> 0.63702359 | AB48: =VLOOKUP(E48,Priors!$A$3:$C$6,2,FALSE) -> 0.15714383 | AC48: =VLOOKUP(E48,Priors!$A$3:$C$6,3,FALSE) -> 0.13222063 | AD48: =AA48*K48+(1-AA48)*AB48 -> 0.11192154 | AE48: =AA48*L48+(1-AA48)*AC48 -> 0.070533804 | AF48: 1 | AG48: 1 | AH48: =IFERROR(VLOOKUP(D48,Teams!$B$2:$I$21,7,FALSE),1) -> 1 | AI48: =AD48*AF48*AG48*AH48 -> 0.11192154 | AJ48: =AE48*AF48*AG48*AH48 -> 0.070533804 | AK48: Injured | AL48: 0 | AM48: Knee injury - Unknown return date | AN48: 0 | AO48: TRUE | AP48: 2024-07-22 | AQ48: FALSE | AS48: https://raw.githubusercontent.com/vaastav/Fantasy-Premier-League/master/data/2026-27/players_raw.csv
A49: 49 | B49: Iling Jr | C49: Samuel Iling-Junior | D49: Aston Villa | E49: MID | F49: 5 | G49: 5 | H49: 0 | I49: 0 | J49: 0 | K49: =IFERROR(I49*90/H49,0) -> 0 | L49: =IFERROR(J49*90/H49,0) -> 0 | M49: 0 | N49: 0 | O49: 0 | P49: 0 | Q49: 0 | R49: 0 | V49: FALSE | W49: =IFERROR(VLOOKUP(D49,Teams!$B$2:$I$21,6,FALSE),"") -> 0 | X49: None | AA49: =IFERROR(H49/(H49+Priors!$G$3),0) -> 0 | AB49: =VLOOKUP(E49,Priors!$A$3:$C$6,2,FALSE) -> 0.15714383 | AC49: =VLOOKUP(E49,Priors!$A$3:$C$6,3,FALSE) -> 0.13222063 | AD49: =AA49*K49+(1-AA49)*AB49 -> 0.15714383 | AE49: =AA49*L49+(1-AA49)*AC49 -> 0.13222063 | AF49: 1 | AG49: 1 | AH49: =IFERROR(VLOOKUP(D49,Teams!$B$2:$I$21,7,FALSE),1) -> 1 | AI49: =AD49*AF49*AG49*AH49 -> 0.15714383 | AJ49: =AE49*AF49*AG49*AH49 -> 0.13222063 | AK49: Available | AN49: 0 | AO49: TRUE | AP49: 2024-07-01 | AQ49: FALSE | AS49: https://raw.githubusercontent.com/vaastav/Fantasy-Premier-League/master/data/2026-27/players_raw.csv
A50: 50 | B50: Burrowes | C50: Bradley Burrowes | D50: Aston Villa | E50: MID | F50: 4.5 | G50: 4.5 | H50: 16 | I50: 0 | J50: 0 | K50: =IFERROR(I50*90/H50,0) -> 0 | L50: =IFERROR(J50*90/H50,0) -> 0 | M50: 0 | N50: 0 | O50: 1 | P50: 1 | Q50: 0 | R50: 5.62 | V50: TRUE | W50: =IFERROR(VLOOKUP(D50,Teams!$B$2:$I$21,6,FALSE),"") -> 0 | X50: None | AA50: =IFERROR(H50/(H50+Priors!$G$3),0) -> 0.015748031 | AB50: =VLOOKUP(E50,Priors!$A$3:$C$6,2,FALSE) -> 0.15714383 | AC50: =VLOOKUP(E50,Priors!$A$3:$C$6,3,FALSE) -> 0.13222063 | AD50: =AA50*K50+(1-AA50)*AB50 -> 0.15466913 | AE50: =AA50*L50+(1-AA50)*AC50 -> 0.13013841 | AF50: 1 | AG50: 1 | AH50: =IFERROR(VLOOKUP(D50,Teams!$B$2:$I$21,7,FALSE),1) -> 1 | AI50: =AD50*AF50*AG50*AH50 -> 0.15466913 | AJ50: =AE50*AF50*AG50*AH50 -> 0.13013841 | AK50: Available | AN50: 0.009 | AO50: TRUE | AP50: None | AQ50: FALSE | AS50: https://raw.githubusercontent.com/vaastav/Fantasy-Premier-League/master/data/2026-27/players_raw.csv
A51: 51 | B51: George Hemmings | C51: George Hemmings | D51: Aston Villa | E51: MID | F51: 4.5 | G51: 4.5 | H51: 25 | I51: 0.04 | J51: 0.01 | K51: =IFERROR(I51*90/H51,0) -> 0.144 | L51: =IFERROR(J51*90/H51,0) -> 0.036 | M51: 0 | N51: 0 | O51: 2 | P51: 1 | Q51: 0 | R51: 3.6 | V51: TRUE | W51: =IFERROR(VLOOKUP(D51,Teams!$B$2:$I$21,6,FALSE),"") -> 0 | X51: None | AA51: =IFERROR(H51/(H51+Priors!$G$3),0) -> 0.024390244 | AB51: =VLOOKUP(E51,Priors!$A$3:$C$6,2,FALSE) -> 0.15714383 | AC51: =VLOOKUP(E51,Priors!$A$3:$C$6,3,FALSE) -> 0.13222063 | AD51: =AA51*K51+(1-AA51)*AB51 -> 0.15682325 | AE51: =AA51*L51+(1-AA51)*AC51 -> 0.12987378 | AF51: 1 | AG51: 1 | AH51: =IFERROR(VLOOKUP(D51,Teams!$B$2:$I$21,7,FALSE),1) -> 1 | AI51: =AD51*AF51*AG51*AH51 -> 0.15682325 | AJ51: =AE51*AF51*AG51*AH51 -> 0.12987378 | AK51: Available | AN51: 0.003 | AO51: TRUE | AP51: None | AQ51: FALSE | AS51: https://raw.githubusercontent.com/vaastav/Fantasy-Premier-League/master/data/2026-27/players_raw.csv
A52: 52 | B52: Alysson | C52: Alysson Edward | D52: Aston Villa | E52: MID | F52: 5 | G52: 5 | H52: 47 | I52: 0.05 | J52: 0.05 | K52: =IFERROR(I52*90/H52,0) -> 0.095744681 | L52: =IFERROR(J52*90/H52,0) -> 0.095744681 | M52: 0 | N52: 0 | O52: 3 | P52: 1 | Q52: 0 | R52: 7.66 | V52: FALSE | W52: =IFERROR(VLOOKUP(D52,Teams!$B$2:$I$21,6,FALSE),"") -> 0 | X52: None | AA52: =IFERROR(H52/(H52+Priors!$G$3),0) -> 0.044890162 | AB52: =VLOOKUP(E52,Priors!$A$3:$C$6,2,FALSE) -> 0.15714383 | AC52: =VLOOKUP(E52,Priors!$A$3:$C$6,3,FALSE) -> 0.13222063 | AD52: =AA52*K52+(1-AA52)*AB52 -> 0.15438761 | AE52: =AA52*L52+(1-AA52)*AC52 -> 0.13058322 | AF52: 1 | AG52: 1 | AH52: =IFERROR(VLOOKUP(D52,Teams!$B$2:$I$21,7,FALSE),1) -> 1 | AI52: =AD52*AF52*AG52*AH52 -> 0.15438761 | AJ52: =AE52*AF52*AG52*AH52 -> 0.13058322 | AK52: Available | AN52: 0 | AO52: TRUE | AP52: 2026-01-01 | AQ52: FALSE | AS52: https://raw.githubusercontent.com/vaastav/Fantasy-Premier-League/master/data/2026-27/players_raw.csv
A53: 53 | B53: Manzambi | C53: Johan Manzambi | D53: Aston Villa | E53: MID | F53: 6 | G53: 6 | H53: 0 | I53: 0 | J53: 0 | K53: =IFERROR(I53*90/H53,0) -> 0 | L53: =IFERROR(J53*90/H53,0) -> 0 | M53: 0 | N53: 0 | O53: 0 | P53: 0 | Q53: 0 | R53: 0 | V53: TRUE | W53: =IFERROR(VLOOKUP(D53,Teams!$B$2:$I$21,6,FALSE),"") -> 0 | X53: None | AA53: =IFERROR(H53/(H53+Priors!$G$3),0) -> 0 | AB53: =VLOOKUP(E53,Priors!$A$3:$C$6,2,FALSE) -> 0.15714383 | AC53: =VLOOKUP(E53,Priors!$A$3:$C$6,3,FALSE) -> 0.13222063 | AD53: =AA53*K53+(1-AA53)*AB53 -> 0.15714383 | AE53: =AA53*L53+(1-AA53)*AC53 -> 0.13222063 | AF53: 1 | AG53: 1 | AH53: =IFERROR(VLOOKUP(D53,Teams!$B$2:$I$21,7,FALSE),1) -> 1 | AI53: =AD53*AF53*AG53*AH53 -> 0.15714383 | AJ53: =AE53*AF53*AG53*AH53 -> 0.13222063 | AK53: Available | AN53: 0.025 | AO53: TRUE | AP53: 2026-07-17 | AQ53: FALSE | AS53: https://raw.githubusercontent.com/vaastav/Fantasy-Premier-League/master/data/2026-27/players_raw.csv
A54: 54 | B54: Gomes | C54: João Gomes | D54: Aston Villa | E54: MID | F54: 5.5 | G54: 5.5 | H54: 2207 | I54: 1.15 | J54: 1.34 | K54: =IFERROR(I54*90/H54,0) -> 0.046896239 | L54: =IFERROR(J54*90/H54,0) -> 0.054644314 | M54: 1 | N54: 1 | O54: 85 | P54: 3 | Q54: 25 | R54: 15.78 | V54: TRUE | W54: =IFERROR(VLOOKUP(D54,Teams!$B$2:$I$21,6,FALSE),"") -> 0 | X54: None | AA54: =IFERROR(H54/(H54+Priors!$G$3),0) -> 0.6881821 | AB54: =VLOOKUP(E54,Priors!$A$3:$C$6,2,FALSE) -> 0.15714383 | AC54: =VLOOKUP(E54,Priors!$A$3:$C$6,3,FALSE) -> 0.13222063 | AD54: =AA54*K54+(1-AA54)*AB54 -> 0.081273412 | AE54: =AA54*L54+(1-AA54)*AC54 -> 0.078833997 | AF54: 1 | AG54: 1 | AH54: =IFERROR(VLOOKUP(D54,Teams!$B$2:$I$21,7,FALSE),1) -> 1 | AI54: =AD54*AF54*AG54*AH54 -> 0.081273412 | AJ54: =AE54*AF54*AG54*AH54 -> 0.078833997 | AK54: Available | AN54: 0.003 | AO54: TRUE | AP54: 2026-07-20 | AQ54: FALSE | AS54: https://raw.githubusercontent.com/vaastav/Fantasy-Premier-League/master/data/2026-27/players_raw.csv
A55: 55 | B55: Watkins | C55: Ollie Watkins | D55: Aston Villa | E55: FWD | F55: 8 | G55: 8 | H55: 2833 | I55: 15.4 | J55: 1.18 | K55: =IFERROR(I55*90/H55,0) -> 0.48923403 | L55: =IFERROR(J55*90/H55,0) -> 0.037486763 | M55: 16 | N55: 4 | O55: 167 | P55: 4.5 | Q55: 33 | R55: 2.99 | S55: 2 | V55: FALSE | W55: =IFERROR(VLOOKUP(D55,Teams!$B$2:$I$21,6,FALSE),"") -> 0 | X55: None | AA55: =IFERROR(H55/(H55+Priors!$G$3),0) -> 0.73910775 | AB55: =VLOOKUP(E55,Priors!$A$3:$C$6,2,FALSE) -> 0.44625207 | AC55: =VLOOKUP(E55,Priors!$A$3:$C$6,3,FALSE) -> 0.05821726 | AD55: =AA55*K55+(1-AA55)*AB55 -> 0.47802037 | AE55: =AA55*L55+(1-AA55)*AC55 -> 0.042895189 | AF55: 1 | AG55: 1 | AH55: =IFERROR(VLOOKUP(D55,Teams!$B$2:$I$21,7,FALSE),1) -> 1 | AI55: =AD55*AF55*AG55*AH55 -> 0.47802037 | AJ55: =AE55*AF55*AG55*AH55 -> 0.042895189 | AK55: Available | AN55: 0.124 | AO55: TRUE | AP55: 2020-09-09 | AQ55: FALSE | AS55: https://raw.githubusercontent.com/vaastav/Fantasy-Premier-League/master/data/2026-27/players_raw.csv
A56: 56 | B56: Abraham | C56: Tammy Abraham | D56: Aston Villa | E56: FWD | F56: 5.5 | G56: 5.5 | H56: 278 | I56: 2.05 | J56: 0.36 | K56: =IFERROR(I56*90/H56,0) -> 0.66366906 | L56: =IFERROR(J56*90/H56,0) -> 0.11654676 | M56: 2 | N56: 0 | O56: 23 | P56: 1.9 | Q56: 2 | R56: 4.21 | V56: FALSE | W56: =IFERROR(VLOOKUP(D56,Teams!$B$2:$I$21,6,FALSE),"") -> 0 | X56: None | AA56: =IFERROR(H56/(H56+Priors!$G$3),0) -> 0.21752739 | AB56: =VLOOKUP(E56,Priors!$A$3:$C$6,2,FALSE) -> 0.44625207 | AC56: =VLOOKUP(E56,Priors!$A$3:$C$6,3,FALSE) -> 0.05821726 | AD56: =AA56*K56+(1-AA56)*AB56 -> 0.49354622 | AE56: =AA56*L56+(1-AA56)*AC56 -> 0.070905524 | AF56: 1 | AG56: 1 | AH56: =IFERROR(VLOOKUP(D56,Teams!$B$2:$I$21,7,FALSE),1) -> 1 | AI56: =AD56*AF56*AG56*AH56 -> 0.49354622 | AJ56: =AE56*AF56*AG56*AH56 -> 0.070905524 | AK56: Injured | AL56: 0 | AM56: Shoulder injury - Expected back 23 Aug | AN56: 0 | AO56: TRUE | AP56: 2026-01-27 | AQ56: FALSE | AS56: https://raw.githubusercontent.com/vaastav/Fantasy-Premier-League/master/data/2026-27/players_raw.csv
A57: 160 | B57: Garnacho | C57: Alejandro Garnacho Ferreyra | D57: Aston Villa | E57: MID | F57: 6 | G57: 6 | H57: 1261 | I57: 3.44 | J57: 3.68 | K57: =IFERROR(I57*90/H57,0) -> 0.24551943 | L57: =IFERROR(J57*90/H57,0) -> 0.26264869 | M57: 1 | N57: 4 | O57: 56 | P57: 2.3 | Q57: 14 | R57: 5.07 | V57: TRUE | W57: =IFERROR(VLOOKUP(D57,Teams!$B$2:$I$21,6,FALSE),"") -> 0 | X57: None | AA57: =IFERROR(H57/(H57+Priors!$G$3),0) -> 0.55771782 | AB57: =VLOOKUP(E57,Priors!$A$3:$C$6,2,FALSE) -> 0.15714383 | AC57: =VLOOKUP(E57,Priors!$A$3:$C$6,3,FALSE) -> 0.13222063 | AD57: =AA57*K57+(1-AA57)*AB57 -> 0.20643248 | AE57: =AA57*L57+(1-AA57)*AC57 -> 0.20496268 | AF57: 1 | AG57: 1 | AH57: =IFERROR(VLOOKUP(D57,Teams!$B$2:$I$21,7,FALSE),1) -> 1 | AI57: =AD57*AF57*AG57*AH57 -> 0.20643248 | AJ57: =AE57*AF57*AG57*AH57 -> 0.20496268 | AK57: Available | AN57: 0.011 | AO57: TRUE | AP57: 2026-07-23 | AQ57: FALSE | AS57: https://raw.githubusercontent.com/vaastav/Fantasy-Premier-League/master/data/2026-27/players_raw.csv
A58: 57 | B58: Petrović | C58: Đorđe Petrović | D58: Bournemouth | E58: GK | F58: 4.5 | G58: 4.5 | H58: 3420 | I58: 0 | J58: 0 | K58: =IFERROR(I58*90/H58,0) -> 0 | L58: =IFERROR(J58*90/H58,0) -> 0 | M58: 0 | N58: 0 | O58: 124 | P58: 3.3 | Q58: 38 | R58: 0 | V58: FALSE | W58: =IFERROR(VLOOKUP(D58,Teams!$B$2:$I$21,6,FALSE),"") -> 0 | X58: None | AA58: =IFERROR(H58/(H58+Priors!$G$3),0) -> 0.77375566 | AB58: =VLOOKUP(E58,Priors!$A$3:$C$6,2,FALSE) -> 0.00024013207 | AC58: =VLOOKUP(E58,Priors!$A$3:$C$6,3,FALSE) -> 0.0019810896 | AD58: =AA58*K58+(1-AA58)*AB58 -> 5.4328523e-05 | AE58: =AA58*L58+(1-AA58)*AC58 -> 0.00044821032 | AF58: 1 | AG58: 1 | AH58: =IFERROR(VLOOKUP(D58,Teams!$B$2:$I$21,7,FALSE),1) -> 1 | AI58: =AD58*AF58*AG58*AH58 -> 5.4328523e-05 | AJ58: =AE58*AF58*AG58*AH58 -> 0.00044821032 | AK58: Available | AN58: 0.036 | AO58: TRUE | AP58: 2025-07-16 | AQ58: FALSE | AS58: https://raw.githubusercontent.com/vaastav/Fantasy-Premier-League/master/data/2026-27/players_raw.csv
A59: 58 | B59: Forster | C59: Fraser Forster | D59: Bournemouth | E59: GK | F59: 4 | G59: 4 | H59: 0 | I59: 0 | J59: 0 | K59: =IFERROR(I59*90/H59,0) -> 0 | L59: =IFERROR(J59*90/H59,0) -> 0 | M59: 0 | N59: 0 | O59: 0 | P59: 0 | Q59: 0 | R59: 0 | V59: FALSE | W59: =IFERROR(VLOOKUP(D59,Teams!$B$2:$I$21,6,FALSE),"") -> 0 | X59: None | AA59: =IFERROR(H59/(H59+Priors!$G$3),0) -> 0 | AB59: =VLOOKUP(E59,Priors!$A$3:$C$6,2,FALSE) -> 0.00024013207 | AC59: =VLOOKUP(E59,Priors!$A$3:$C$6,3,FALSE) -> 0.0019810896 | AD59: =AA59*K59+(1-AA59)*AB59 -> 0.00024013207 | AE59: =AA59*L59+(1-AA59)*AC59 -> 0.0019810896 | AF59: 1 | AG59: 1 | AH59: =IFERROR(VLOOKUP(D59,Teams!$B$2:$I$21,7,FALSE),1) -> 1 | AI59: =AD59*AF59*AG59*AH59 -> 0.00024013207 | AJ59: =AE59*AF59*AG59*AH59 -> 0.0019810896 | AK59: Available | AN59: 0.031 | AO59: TRUE | AP59: 2026-01-02 | AQ59: FALSE | AS59: https://raw.githubusercontent.com/vaastav/Fantasy-Premier-League/master/data/2026-27/players_raw.csv
A60: 59 | B60: Dennis | C60: Will Dennis | D60: Bournemouth | E60: GK | F60: 4 | G60: 4 | H60: 0 | I60: 0 | J60: 0 | K60: =IFERROR(I60*90/H60,0) -> 0 | L60: =IFERROR(J60*90/H60,0) -> 0 | M60: 0 | N60: 0 | O60: 0 | P60: 0 | Q60: 0 | R60: 0 | V60: FALSE | W60: =IFERROR(VLOOKUP(D60,Teams!$B$2:$I$21,6,FALSE),"") -> 0 | X60: None | AA60: =IFERROR(H60/(H60+Priors!$G$3),0) -> 0 | AB60: =VLOOKUP(E60,Priors!$A$3:$C$6,2,FALSE) -> 0.00024013207 | AC60: =VLOOKUP(E60,Priors!$A$3:$C$6,3,FALSE) -> 0.0019810896 | AD60: =AA60*K60+(1-AA60)*AB60 -> 0.00024013207 | AE60: =AA60*L60+(1-AA60)*AC60 -> 0.0019810896 | AF60: 1 | AG60: 1 | AH60: =IFERROR(VLOOKUP(D60,Teams!$B$2:$I$21,7,FALSE),1) -> 1 | AI60: =AD60*AF60*AG60*AH60 -> 0.00024013207 | AJ60: =AE60*AF60*AG60*AH60 -> 0.0019810896 | AK60: Available | AN60: 0.002 | AO60: TRUE | AP60: 2019-08-01 | AQ60: FALSE | AS60: https://raw.githubusercontent.com/vaastav/Fantasy-Premier-League/master/data/2026-27/players_raw.csv
A61: 60 | B61: Hill | C61: James Hill | D61: Bournemouth | E61: DEF | F61: 5.5 | G61: 5.5 | H61: 2102 | I61: 0.89 | J61: 1.16 | K61: =IFERROR(I61*90/H61,0) -> 0.038106565 | L61: =IFERROR(J61*90/H61,0) -> 0.049666984 | M61: 0 | N61: 3 | O61: 110 | P61: 3.8 | Q61: 22 | R61: 11.13 | V61: FALSE | W61: =IFERROR(VLOOKUP(D61,Teams!$B$2:$I$21,6,FALSE),"") -> 0 | X61: None | AA61: =IFERROR(H61/(H61+Priors!$G$3),0) -> 0.67762734 | AB61: =VLOOKUP(E61,Priors!$A$3:$C$6,2,FALSE) -> 0.060081391 | AC61: =VLOOKUP(E61,Priors!$A$3:$C$6,3,FALSE) -> 0.059588192 | AD61: =AA61*K61+(1-AA61)*AB61 -> 0.045190648 | AE61: =AA61*L61+(1-AA61)*AC61 -> 0.05286531 | AF61: 1 | AG61: 1 | AH61: =IFERROR(VLOOKUP(D61,Teams!$B$2:$I$21,7,FALSE),1) -> 1 | AI61: =AD61*AF61*AG61*AH61 -> 0.045190648 | AJ61: =AE61*AF61*AG61*AH61 -> 0.05286531 | AK61: Available | AN61: 0.013 | AO61: TRUE | AP61: 2022-01-05 | AQ61: FALSE | AS61: https://raw.githubusercontent.com/vaastav/Fantasy-Premier-League/master/data/2026-27/players_raw.csv
A62: 61 | B62: Truffert | C62: Adrien Truffert | D62: Bournemouth | E62: DEF | F62: 5.5 | G62: 5.5 | H62: 3378 | I62: 1.35 | J62: 3.07 | K62: =IFERROR(I62*90/H62,0) -> 0.035968028 | L62: =IFERROR(J62*90/H62,0) -> 0.081793961 | M62: 1 | N62: 6 | O62: 165 | P62: 4.3 | Q62: 38 | R62: 8.02 | V62: FALSE | W62: =IFERROR(VLOOKUP(D62,Teams!$B$2:$I$21,6,FALSE),"") -> 0 | X62: None | AA62: =IFERROR(H62/(H62+Priors!$G$3),0) -> 0.7715852 | AB62: =VLOOKUP(E62,Priors!$A$3:$C$6,2,FALSE) -> 0.060081391 | AC62: =VLOOKUP(E62,Priors!$A$3:$C$6,3,FALSE) -> 0.059588192 | AD62: =AA62*K62+(1-AA62)*AB62 -> 0.041475877 | AE62: =AA62*L62+(1-AA62)*AC62 -> 0.076721835 | AF62: 1 | AG62: 1 | AH62: =IFERROR(VLOOKUP(D62,Teams!$B$2:$I$21,7,FALSE),1) -> 1 | AI62: =AD62*AF62*AG62*AH62 -> 0.041475877 | AJ62: =AE62*AF62*AG62*AH62 -> 0.076721835 | AK62: Available | AN62: 0.046 | AO62: TRUE | AP62: 2025-06-16 | AQ62: FALSE | AS62: https://raw.githubusercontent.com/vaastav/Fantasy-Premier-League/master/data/2026-27/players_raw.csv
A63: 62 | B63: Diakité | C63: Bafodé Diakité | D63: Bournemouth | E63: DEF | F63: 5 | G63: 5 | H63: 1275 | I63: 0.02 | J63: 0.19 | K63: =IFERROR(I63*90/H63,0) -> 0.0014117647 | L63: =IFERROR(J63*90/H63,0) -> 0.013411765 | M63: 0 | N63: 0 | O63: 46 | P63: 2.6 | Q63: 15 | R63: 8.26 | V63: FALSE | W63: =IFERROR(VLOOKUP(D63,Teams!$B$2:$I$21,6,FALSE),"") -> 0 | X63: None | AA63: =IFERROR(H63/(H63+Priors!$G$3),0) -> 0.56043956 | AB63: =VLOOKUP(E63,Priors!$A$3:$C$6,2,FALSE) -> 0.060081391 | AC63: =VLOOKUP(E63,Priors!$A$3:$C$6,3,FALSE) -> 0.059588192 | AD63: =AA63*K63+(1-AA63)*AB63 -> 0.027200612 | AE63: =AA63*L63+(1-AA63)*AC63 -> 0.033709095 | AF63: 1 | AG63: 1 | AH63: =IFERROR(VLOOKUP(D63,Teams!$B$2:$I$21,7,FALSE),1) -> 1 | AI63: =AD63*AF63*AG63*AH63 -> 0.027200612 | AJ63: =AE63*AF63*AG63*AH63 -> 0.033709095 | AK63: Available | AN63: 0.002 | AO63: TRUE | AP63: 2025-08-13 | AQ63: FALSE | AS63: https://raw.githubusercontent.com/vaastav/Fantasy-Premier-League/master/data/2026-27/players_raw.csv
A64: 63 | B64: Milosavljević | C64: Veljko Milosavljevic | D64: Bournemouth | E64: DEF | F64: 5 | G64: 5 | H64: 367 | I64: 0.15 | J64: 0.19 | K64: =IFERROR(I64*90/H64,0) -> 0.036784741 | L64: =IFERROR(J64*90/H64,0) -> 0.046594005 | M64: 0 | N64: 0 | O64: 19 | P64: 2.7 | Q64: 4 | R64: 9.56 | V64: FALSE | W64: =IFERROR(VLOOKUP(D64,Teams!$B$2:$I$21,6,FALSE),"") -> 0 | X64: None | AA64: =IFERROR(H64/(H64+Priors!$G$3),0) -> 0.2684711 | AB64: =VLOOKUP(E64,Priors!$A$3:$C$6,2,FALSE) -> 0.060081391 | AC64: =VLOOKUP(E64,Priors!$A$3:$C$6,3,FALSE) -> 0.059588192 | AD64: =AA64*K64+(1-AA64)*AB64 -> 0.053826914 | AE64: =AA64*L64+(1-AA64)*AC64 -> 0.056099628 | AF64: 1 | AG64: 1 | AH64: =IFERROR(VLOOKUP(D64,Teams!$B$2:$I$21,7,FALSE),1) -> 1 | AI64: =AD64*AF64*AG64*AH64 -> 0.053826914 | AJ64: =AE64*AF64*AG64*AH64 -> 0.056099628 | AK64: Available | AN64: 0.001 | AO64: TRUE | AP64: 2025-09-01 | AQ64: FALSE | AS64: https://raw.githubusercontent.com/vaastav/Fantasy-Premier-League/master/data/2026-27/players_raw.csv
A65: 64 | B65: Smith | C65: Adam Smith | D65: Bournemouth | E65: DEF | F65: 4.5 | G65: 4.5 | H65: 1073 | I65: 0 | J65: 0.23 | K65: =IFERROR(I65*90/H65,0) -> 0 | L65: =IFERROR(J65*90/H65,0) -> 0.019291705 | M65: 0 | N65: 2 | O65: 58 | P65: 2.6 | Q65: 14 | R65: 5.87 | V65: FALSE | W65: =IFERROR(VLOOKUP(D65,Teams!$B$2:$I$21,6,FALSE),"") -> 0 | X65: None | AA65: =IFERROR(H65/(H65+Priors!$G$3),0) -> 0.51760733 | AB65: =VLOOKUP(E65,Priors!$A$3:$C$6,2,FALSE) -> 0.060081391 | AC65: =VLOOKUP(E65,Priors!$A$3:$C$6,3,FALSE) -> 0.059588192 | AD65: =AA65*K65+(1-AA65)*AB65 -> 0.028982823 | AE65: =AA65*L65+(1-AA65)*AC65 -> 0.038730435 | AF65: 1 | AG65: 1 | AH65: =IFERROR(VLOOKUP(D65,Teams!$B$2:$I$21,7,FALSE),1) -> 1 | AI65: =AD65*AF65*AG65*AH65 -> 0.028982823 | AJ65: =AE65*AF65*AG65*AH65 -> 0.038730435 | AK65: Available | AN65: 0.001 | AO65: TRUE | AP65: 2014-01-28 | AQ65: FALSE | AS65: https://raw.githubusercontent.com/vaastav/Fantasy-Premier-League/master/data/2026-27/players_raw.csv
A66: 65 | B66: J.Araujo | C66: Julián Araujo Zúñiga | D66: Bournemouth | E66: DEF | F66: 4.5 | G66: 4.5 | H66: 0 | I66: 0 | J66: 0 | K66: =IFERROR(I66*90/H66,0) -> 0 | L66: =IFERROR(J66*90/H66,0) -> 0 | M66: 0 | N66: 0 | O66: 0 | P66: 0 | Q66: 0 | R66: 0 | V66: FALSE | W66: =IFERROR(VLOOKUP(D66,Teams!$B$2:$I$21,6,FALSE),"") -> 0 | X66: None | AA66: =IFERROR(H66/(H66+Priors!$G$3),0) -> 0 | AB66: =VLOOKUP(E66,Priors!$A$3:$C$6,2,FALSE) -> 0.060081391 | AC66: =VLOOKUP(E66,Priors!$A$3:$C$6,3,FALSE) -> 0.059588192 | AD66: =AA66*K66+(1-AA66)*AB66 -> 0.060081391 | AE66: =AA66*L66+(1-AA66)*AC66 -> 0.059588192 | AF66: 1 | AG66: 1 | AH66: =IFERROR(VLOOKUP(D66,Teams!$B$2:$I$21,7,FALSE),1) -> 1 | AI66: =AD66*AF66*AG66*AH66 -> 0.060081391 | AJ66: =AE66*AF66*AG66*AH66 -> 0.059588192 | AK66: Available | AN66: 0.001 | AO66: TRUE | AP66: 2024-08-13 | AQ66: FALSE | AS66: https://raw.githubusercontent.com/vaastav/Fantasy-Premier-League/master/data/2026-27/players_raw.csv
A67: 66 | B67: Soler | C67: Julio Soler Barreto | D67: Bournemouth | E67: DEF | F67: 4 | G67: 4 | H67: 34 | I67: 0 | J67: 0 | K67: =IFERROR(I67*90/H67,0) -> 0 | L67: =IFERROR(J67*90/H67,0) -> 0 | M67: 0 | N67: 0 | O67: 3 | P67: 1 | Q67: 0 | R67: 2.65 | V67: FALSE | W67: =IFERROR(VLOOKUP(D67,Teams!$B$2:$I$21,6,FALSE),"") -> 0 | X67: None | AA67: =IFERROR(H67/(H67+Priors!$G$3),0) -> 0.032882012 | AB67: =VLOOKUP(E67,Priors!$A$3:$C$6,2,FALSE) -> 0.060081391 | AC67: =VLOOKUP(E67,Priors!$A$3:$C$6,3,FALSE) -> 0.059588192 | AD67: =AA67*K67+(1-AA67)*AB67 -> 0.058105794 | AE67: =AA67*L67+(1-AA67)*AC67 -> 0.057628812 | AF67: 1 | AG67: 1 | AH67: =IFERROR(VLOOKUP(D67,Teams!$B$2:$I$21,7,FALSE),1) -> 1 | AI67: =AD67*AF67*AG67*AH67 -> 0.058105794 | AJ67: =AE67*AF67*AG67*AH67 -> 0.057628812 | AK67: Available | AN67: 0.006 | AO67: TRUE | AP67: 2025-01-07 | AQ67: FALSE | AS67: https://raw.githubusercontent.com/vaastav/Fantasy-Premier-League/master/data/2026-27/players_raw.csv
A68: 67 | B68: Rayan | C68: Rayan | D68: Bournemouth | E68: MID | F68: 6.5 | G68: 6.5 | H68: 1110 | I68: 2.67 | J68: 1.84 | K68: =IFERROR(I68*90/H68,0) -> 0.21648649 | L68: =IFERROR(J68*90/H68,0) -> 0.14918919 | M68: 5 | N68: 2 | O68: 67 | P68: 4.5 | Q68: 13 | R68: 6.65 | V68: FALSE | W68: =IFERROR(VLOOKUP(D68,Teams!$B$2:$I$21,6,FALSE),"") -> 0 | X68: None | AA68: =IFERROR(H68/(H68+Priors!$G$3),0) -> 0.52606635 | AB68: =VLOOKUP(E68,Priors!$A$3:$C$6,2,FALSE) -> 0.15714383 | AC68: =VLOOKUP(E68,Priors!$A$3:$C$6,3,FALSE) -> 0.13222063 | AD68: =AA68*K68+(1-AA68)*AB68 -> 0.18836201 | AE68: =AA68*L68+(1-AA68)*AC68 -> 0.14114722 | AF68: 1 | AG68: 1 | AH68: =IFERROR(VLOOKUP(D68,Teams!$B$2:$I$21,7,FALSE),1) -> 1 | AI68: =AD68*AF68*AG68*AH68 -> 0.18836201 | AJ68: =AE68*AF68*AG68*AH68 -> 0.14114722 | AK68: Available | AN68: 0.034 | AO68: TRUE | AP68: 2026-01-27 | AQ68: FALSE | AS68: https://raw.githubusercontent.com/vaastav/Fantasy-Premier-League/master/data/2026-27/players_raw.csv
A69: 68 | B69: Tavernier | C69: Marcus Tavernier | D69: Bournemouth | E69: MID | F69: 6 | G69: 6 | H69: 2732 | I69: 9.06 | J69: 4.6 | K69: =IFERROR(I69*90/H69,0) -> 0.29846266 | L69: =IFERROR(J69*90/H69,0) -> 0.15153734 | M69: 7 | N69: 4 | O69: 137 | P69: 4 | Q69: 31 | R69: 8.27 | S69: 3 | T69: 1 | U69: 6 | V69: FALSE | W69: =IFERROR(VLOOKUP(D69,Teams!$B$2:$I$21,6,FALSE),"") -> 0 | X69: None | AA69: =IFERROR(H69/(H69+Priors!$G$3),0) -> 0.73204716 | AB69: =VLOOKUP(E69,Priors!$A$3:$C$6,2,FALSE) -> 0.15714383 | AC69: =VLOOKUP(E69,Priors!$A$3:$C$6,3,FALSE) -> 0.13222063 | AD69: =AA69*K69+(1-AA69)*AB69 -> 0.26059588 | AE69: =AA69*L69+(1-AA69)*AC69 -> 0.14636137 | AF69: 1 | AG69: 1 | AH69: =IFERROR(VLOOKUP(D69,Teams!$B$2:$I$21,7,FALSE),1) -> 1 | AI69: =AD69*AF69*AG69*AH69 -> 0.26059588 | AJ69: =AE69*AF69*AG69*AH69 -> 0.14636137 | AK69: Available | AN69: 0.019 | AO69: TRUE | AP69: 2022-08-01 | AQ69: FALSE | AS69: https://raw.githubusercontent.com/vaastav/Fantasy-Premier-League/master/data/2026-27/players_raw.csv
A70: 69 | B70: Scott | C70: Alex Scott | D70: Bournemouth | E70: MID | F70: 6 | G70: 6 | H70: 2848 | I70: 3.8 | J70: 2.94 | K70: =IFERROR(I70*90/H70,0) -> 0.12008427 | L70: =IFERROR(J70*90/H70,0) -> 0.092907303 | M70: 3 | N70: 2 | O70: 136 | P70: 3.7 | Q70: 34 | R70: 12.2 | T70: 4 | U70: 7 | V70: FALSE | W70: =IFERROR(VLOOKUP(D70,Teams!$B$2:$I$21,6,FALSE),"") -> 0 | X70: None | AA70: =IFERROR(H70/(H70+Priors!$G$3),0) -> 0.74012474 | AB70: =VLOOKUP(E70,Priors!$A$3:$C$6,2,FALSE) -> 0.15714383 | AC70: =VLOOKUP(E70,Priors!$A$3:$C$6,3,FALSE) -> 0.13222063 | AD70: =AA70*K70+(1-AA70)*AB70 -> 0.12971513 | AE70: =AA70*L70+(1-AA70)*AC70 -> 0.10312386 | AF70: 1 | AG70: 1 | AH70: =IFERROR(VLOOKUP(D70,Teams!$B$2:$I$21,7,FALSE),1) -> 1 | AI70: =AD70*AF70*AG70*AH70 -> 0.12971513 | AJ70: =AE70*AF70*AG70*AH70 -> 0.10312386 | AK70: Available | AN70: 0.016 | AO70: TRUE | AP70: 2023-08-10 | AQ70: FALSE | AS70: https://raw.githubusercontent.com/vaastav/Fantasy-Premier-League/master/data/2026-27/players_raw.csv
A71: 70 | B71: Kluivert | C71: Justin Kluivert | D71: Bournemouth | E71: MID | F71: 6 | G71: 6 | H71: 945 | I71: 2.31 | J71: 1.55 | K71: =IFERROR(I71*90/H71,0) -> 0.22 | L71: =IFERROR(J71*90/H71,0) -> 0.14761905 | M71: 2 | N71: 0 | O71: 41 | P71: 2 | Q71: 10 | R71: 6.19 | S71: 2 | T71: 2 | V71: FALSE | W71: =IFERROR(VLOOKUP(D71,Teams!$B$2:$I$21,6,FALSE),"") -> 0 | X71: None | AA71: =IFERROR(H71/(H71+Priors!$G$3),0) -> 0.48586118 | AB71: =VLOOKUP(E71,Priors!$A$3:$C$6,2,FALSE) -> 0.15714383 | AC71: =VLOOKUP(E71,Priors!$A$3:$C$6,3,FALSE) -> 0.13222063 | AD71: =AA71*K71+(1-AA71)*AB71 -> 0.1876832 | AE71: =AA71*L71+(1-AA71)*AC71 -> 0.13970212 | AF71: 1 | AG71: 1 | AH71: =IFERROR(VLOOKUP(D71,Teams!$B$2:$I$21,7,FALSE),1) -> 1 | AI71: =AD71*AF71*AG71*AH71 -> 0.1876832 | AJ71: =AE71*AF71*AG71*AH71 -> 0.13970212 | AK71: Available | AN71: 0.009 | AO71: TRUE | AP71: 2023-07-01 | AQ71: FALSE | AS71: https://raw.githubusercontent.com/vaastav/Fantasy-Premier-League/master/data/2026-27/players_raw.csv
A72: 71 | B72: Cook | C72: Lewis Cook | D72: Bournemouth | E72: MID | F72: 5 | G72: 5 | H72: 872 | I72: 0.07 | J72: 0.52 | K72: =IFERROR(I72*90/H72,0) -> 0.0072247706 | L72: =IFERROR(J72*90/H72,0) -> 0.053669725 | M72: 0 | N72: 1 | O72: 40 | P72: 2.2 | Q72: 8 | R72: 14.76 | U72: 8 | V72: FALSE | W72: =IFERROR(VLOOKUP(D72,Teams!$B$2:$I$21,6,FALSE),"") -> 0 | X72: None | AA72: =IFERROR(H72/(H72+Priors!$G$3),0) -> 0.46581197 | AB72: =VLOOKUP(E72,Priors!$A$3:$C$6,2,FALSE) -> 0.15714383 | AC72: =VLOOKUP(E72,Priors!$A$3:$C$6,3,FALSE) -> 0.13222063 | AD72: =AA72*K72+(1-AA72)*AB72 -> 0.087309739 | AE72: =AA72*L72+(1-AA72)*AC72 -> 0.095630678 | AF72: 1 | AG72: 1 | AH72: =IFERROR(VLOOKUP(D72,Teams!$B$2:$I$21,7,FALSE),1) -> 1 | AI72: =AD72*AF72*AG72*AH72 -> 0.087309739 | AJ72: =AE72*AF72*AG72*AH72 -> 0.095630678 | AK72: Available | AN72: 0.001 | AO72: TRUE | AP72: 2016-07-08 | AQ72: FALSE | AS72: https://raw.githubusercontent.com/vaastav/Fantasy-Premier-League/master/data/2026-27/players_raw.csv
A73: 72 | B73: Gannon-Doak | C73: Ben Gannon-Doak | D73: Bournemouth | E73: MID | F73: 5 | G73: 5 | H73: 105 | I73: 0.26 | J73: 0.13 | K73: =IFERROR(I73*90/H73,0) -> 0.22285714 | L73: =IFERROR(J73*90/H73,0) -> 0.11142857 | M73: 0 | N73: 1 | O73: 11 | P73: 1.4 | Q73: 0 | R73: 11.14 | V73: FALSE | W73: =IFERROR(VLOOKUP(D73,Teams!$B$2:$I$21,6,FALSE),"") -> 0 | X73: None | AA73: =IFERROR(H73/(H73+Priors!$G$3),0) -> 0.095022624 | AB73: =VLOOKUP(E73,Priors!$A$3:$C$6,2,FALSE) -> 0.15714383 | AC73: =VLOOKUP(E73,Priors!$A$3:$C$6,3,FALSE) -> 0.13222063 | AD73: =AA73*K73+(1-AA73)*AB73 -> 0.16338808 | AE73: =AA73*L73+(1-AA73)*AC73 -> 0.13024491 | AF73: 1 | AG73: 1 | AH73: =IFERROR(VLOOKUP(D73,Teams!$B$2:$I$21,7,FALSE),1) -> 1 | AI73: =AD73*AF73*AG73*AH73 -> 0.16338808 | AJ73: =AE73*AF73*AG73*AH73 -> 0.13024491 | AK73: Available | AN73: 0.001 | AO73: TRUE | AP73: 2025-08-18 | AQ73: FALSE | AS73: https://raw.githubusercontent.com/vaastav/Fantasy-Premier-League/master/data/2026-27/players_raw.csv
A74: 73 | B74: Adams | C74: Tyler Adams | D74: Bournemouth | E74: MID | F74: 5 | G74: 5 | H74: 1769 | I74: 0.63 | J74: 0.63 | K74: =IFERROR(I74*90/H74,0) -> 0.032052007 | L74: =IFERROR(J74*90/H74,0) -> 0.032052007 | M74: 2 | N74: 2 | O74: 77 | P74: 3.1 | Q74: 21 | R74: 11.8 | V74: FALSE | W74: =IFERROR(VLOOKUP(D74,Teams!$B$2:$I$21,6,FALSE),"") -> 0 | X74: None | AA74: =IFERROR(H74/(H74+Priors!$G$3),0) -> 0.63885879 | AB74: =VLOOKUP(E74,Priors!$A$3:$C$6,2,FALSE) -> 0.15714383 | AC74: =VLOOKUP(E74,Priors!$A$3:$C$6,3,FALSE) -> 0.13222063 | AD74: =AA74*K74+(1-AA74)*AB74 -> 0.07722782 | AE74: =AA74*L74+(1-AA74)*AC74 -> 0.068227024 | AF74: 1 | AG74: 1 | AH74: =IFERROR(VLOOKUP(D74,Teams!$B$2:$I$21,7,FALSE),1) -> 1 | AI74: =AD74*AF74*AG74*AH74 -> 0.07722782 | AJ74: =AE74*AF74*AG74*AH74 -> 0.068227024 | AK74: Available | AN74: 0.007 | AO74: TRUE | AP74: 2023-08-20 | AQ74: FALSE | AS74: https://raw.githubusercontent.com/vaastav/Fantasy-Premier-League/master/data/2026-27/players_raw.csv
A75: 74 | B75: Brooks | C75: David Brooks | D75: Bournemouth | E75: MID | F75: 5 | G75: 5 | H75: 1188 | I75: 5.81 | J75: 3.4 | K75: =IFERROR(I75*90/H75,0) -> 0.44015152 | L75: =IFERROR(J75*90/H75,0) -> 0.25757576 | M75: 1 | N75: 3 | O75: 59 | P75: 1.9 | Q75: 13 | R75: 7.12 | T75: 3 | U75: 9 | V75: FALSE | W75: =IFERROR(VLOOKUP(D75,Teams!$B$2:$I$21,6,FALSE),"") -> 0 | X75: None | AA75: =IFERROR(H75/(H75+Priors!$G$3),0) -> 0.54296161 | AB75: =VLOOKUP(E75,Priors!$A$3:$C$6,2,FALSE) -> 0.15714383 | AC75: =VLOOKUP(E75,Priors!$A$3:$C$6,3,FALSE) -> 0.13222063 | AD75: =AA75*K75+(1-AA75)*AB75 -> 0.31080614 | AE75: =AA75*L75+(1-AA75)*AC75 -> 0.20028365 | AF75: 1 | AG75: 1 | AH75: =IFERROR(VLOOKUP(D75,Teams!$B$2:$I$21,7,FALSE),1) -> 1 | AI75: =AD75*AF75*AG75*AH75 -> 0.31080614 | AJ75: =AE75*AF75*AG75*AH75 -> 0.20028365 | AK75: Available | AN75: 0.002 | AO75: TRUE | AP75: 2018-07-01 | AQ75: FALSE | AS75: https://raw.githubusercontent.com/vaastav/Fantasy-Premier-League/master/data/2026-27/players_raw.csv
A76: 75 | B76: Christie | C76: Ryan Christie | D76: Bournemouth | E76: MID | F76: 5 | G76: 5 | H76: 978 | I76: 1.81 | J76: 0.79 | K76: =IFERROR(I76*90/H76,0) -> 0.16656442 | L76: =IFERROR(J76*90/H76,0) -> 0.072699387 | M76: 2 | N76: 1 | O76: 47 | P76: 1.8 | Q76: 9 | R76: 11.32 | U76: 10 | V76: FALSE | W76: =IFERROR(VLOOKUP(D76,Teams!$B$2:$I$21,6,FALSE),"") -> 0 | X76: None | AA76: =IFERROR(H76/(H76+Priors!$G$3),0) -> 0.49443883 | AB76: =VLOOKUP(E76,Priors!$A$3:$C$6,2,FALSE) -> 0.15714383 | AC76: =VLOOKUP(E76,Priors!$A$3:$C$6,3,FALSE) -> 0.13222063 | AD76: =AA76*K76+(1-AA76)*AB76 -> 0.16180174 | AE76: =AA76*L76+(1-AA76)*AC76 -> 0.10279102 | AF76: 1 | AG76: 1 | AH76: =IFERROR(VLOOKUP(D76,Teams!$B$2:$I$21,7,FALSE),1) -> 1 | AI76: =AD76*AF76*AG76*AH76 -> 0.16180174 | AJ76: =AE76*AF76*AG76*AH76 -> 0.10279102 | AK76: Suspended | AL76: 0 | AM76: Suspended until 29 Aug | AN76: 0 | AO76: TRUE | AP76: 2021-08-31 | AQ76: FALSE | AS76: https://raw.githubusercontent.com/vaastav/Fantasy-Premier-League/master/data/2026-27/players_raw.csv
A77: 76 | B77: Tóth.A | C77: Alex Tóth | D77: Bournemouth | E77: MID | F77: 5 | G77: 5 | H77: 135 | I77: 0.11 | J77: 0.33 | K77: =IFERROR(I77*90/H77,0) -> 0.073333333 | L77: =IFERROR(J77*90/H77,0) -> 0.22 | M77: 0 | N77: 0 | O77: 8 | P77: 0.9 | Q77: 2 | R77: 11.33 | V77: FALSE | W77: =IFERROR(VLOOKUP(D77,Teams!$B$2:$I$21,6,FALSE),"") -> 0 | X77: None | AA77: =IFERROR(H77/(H77+Priors!$G$3),0) -> 0.11894273 | AB77: =VLOOKUP(E77,Priors!$A$3:$C$6,2,FALSE) -> 0.15714383 | AC77: =VLOOKUP(E77,Priors!$A$3:$C$6,3,FALSE) -> 0.13222063 | AD77: =AA77*K77+(1-AA77)*AB77 -> 0.14717518 | AE77: =AA77*L77+(1-AA77)*AC77 -> 0.14266135 | AF77: 1 | AG77: 1 | AH77: =IFERROR(VLOOKUP(D77,Teams!$B$2:$I$21,7,FALSE),1) -> 1 | AI77: =AD77*AF77*AG77*AH77 -> 0.14717518 | AJ77: =AE77*AF77*AG77*AH77 -> 0.14266135 | AK77: Available | AN77: 0 | AO77: TRUE | AP77: 2026-01-20 | AQ77: FALSE | AS77: https://raw.githubusercontent.com/vaastav/Fantasy-Premier-League/master/data/2026-27/players_raw.csv
A78: 77 | B78: Adli | C78: Amine Adli | D78: Bournemouth | E78: MID | F78: 5 | G78: 5 | H78: 1074 | I78: 2.6 | J78: 1.62 | K78: =IFERROR(I78*90/H78,0) -> 0.21787709 | L78: =IFERROR(J78*90/H78,0) -> 0.13575419 | M78: 3 | N78: 2 | O78: 67 | P78: 2.2 | Q78: 10 | R78: 10.31 | V78: FALSE | W78: =IFERROR(VLOOKUP(D78,Teams!$B$2:$I$21,6,FALSE),"") -> 0 | X78: None | AA78: =IFERROR(H78/(H78+Priors!$G$3),0) -> 0.51783992 | AB78: =VLOOKUP(E78,Priors!$A$3:$C$6,2,FALSE) -> 0.15714383 | AC78: =VLOOKUP(E78,Priors!$A$3:$C$6,3,FALSE) -> 0.13222063 | AD78: =AA78*K78+(1-AA78)*AB78 -> 0.18859394 | AE78: =AA78*L78+(1-AA78)*AC78 -> 0.13405045 | AF78: 1 | AG78: 1 | AH78: =IFERROR(VLOOKUP(D78,Teams!$B$2:$I$21,7,FALSE),1) -> 1 | AI78: =AD78*AF78*AG78*AH78 -> 0.18859394 | AJ78: =AE78*AF78*AG78*AH78 -> 0.13405045 | AK78: Available | AN78: 0.002 | AO78: TRUE | AP78: 2025-08-21 | AQ78: FALSE | AS78: https://raw.githubusercontent.com/vaastav/Fantasy-Premier-League/master/data/2026-27/players_raw.csv
A79: 78 | B79: Kroupi.Jr | C79: Junior Kroupi | D79: Bournemouth | E79: MID | F79: 7.5 | G79: 7.5 | H79: 1663 | I79: 8.31 | J79: 1.51 | K79: =IFERROR(I79*90/H79,0) -> 0.4497294 | L79: =IFERROR(J79*90/H79,0) -> 0.081719784 | M79: 13 | N79: 0 | O79: 113 | P79: 3.4 | Q79: 21 | R79: 6.06 | S79: 1 | V79: FALSE | W79: =IFERROR(VLOOKUP(D79,Teams!$B$2:$I$21,6,FALSE),"") -> 0 | X79: None | AA79: =IFERROR(H79/(H79+Priors!$G$3),0) -> 0.62448367 | AB79: =VLOOKUP(E79,Priors!$A$3:$C$6,2,FALSE) -> 0.15714383 | AC79: =VLOOKUP(E79,Priors!$A$3:$C$6,3,FALSE) -> 0.13222063 | AD79: =AA79*K79+(1-AA79)*AB79 -> 0.33985874 | AE79: =AA79*L79+(1-AA79)*AC79 -> 0.10068368 | AF79: 1 | AG79: 1 | AH79: =IFERROR(VLOOKUP(D79,Teams!$B$2:$I$21,7,FALSE),1) -> 1 | AI79: =AD79*AF79*AG79*AH79 -> 0.33985874 | AJ79: =AE79*AF79*AG79*AH79 -> 0.10068368 | AK79: Injured | AL79: 0 | AM79: Foot injury - Unknown return date | AN79: 0.062 | AO79: TRUE | AP79: 2025-02-02 | AQ79: FALSE | AS79: https://raw.githubusercontent.com/vaastav/Fantasy-Premier-League/master/data/2026-27/players_raw.csv
A80: 79 | B80: Evanilson | C80: Evanilson | D80: Bournemouth | E80: FWD | F80: 6 | G80: 6 | H80: 2741 | I80: 10.64 | J80: 1.48 | K80: =IFERROR(I80*90/H80,0) -> 0.34936155 | L80: =IFERROR(J80*90/H80,0) -> 0.048595403 | M80: 6 | N80: 7 | O80: 115 | P80: 3.2 | Q80: 32 | R80: 4.43 | V80: FALSE | W80: =IFERROR(VLOOKUP(D80,Teams!$B$2:$I$21,6,FALSE),"") -> 0 | X80: None | AA80: =IFERROR(H80/(H80+Priors!$G$3),0) -> 0.73269179 | AB80: =VLOOKUP(E80,Priors!$A$3:$C$6,2,FALSE) -> 0.44625207 | AC80: =VLOOKUP(E80,Priors!$A$3:$C$6,3,FALSE) -> 0.05821726 | AD80: =AA80*K80+(1-AA80)*AB80 -> 0.37526118 | AE80: =AA80*L80+(1-AA80)*AC80 -> 0.051167405 | AF80: 1 | AG80: 1 | AH80: =IFERROR(VLOOKUP(D80,Teams!$B$2:$I$21,7,FALSE),1) -> 1 | AI80: =AD80*AF80*AG80*AH80 -> 0.37526118 | AJ80: =AE80*AF80*AG80*AH80 -> 0.051167405 | AK80: Available | AN80: 0.02 | AO80: TRUE | AP80: 2024-08-16 | AQ80: FALSE | AS80: https://raw.githubusercontent.com/vaastav/Fantasy-Premier-League/master/data/2026-27/players_raw.csv
A81: 80 | B81: Enes Ünal | C81: Enes Ünal | D81: Bournemouth | E81: FWD | F81: 5.5 | G81: 5.5 | H81: 214 | I81: 2 | J81: 0.07 | K81: =IFERROR(I81*90/H81,0) -> 0.8411215 | L81: =IFERROR(J81*90/H81,0) -> 0.029439252 | M81: 1 | N81: 0 | O81: 27 | P81: 1.2 | Q81: 0 | R81: 9.67 | T81: 5 | V81: FALSE | W81: =IFERROR(VLOOKUP(D81,Teams!$B$2:$I$21,6,FALSE),"") -> 0 | X81: None | AA81: =IFERROR(H81/(H81+Priors!$G$3),0) -> 0.17627677 | AB81: =VLOOKUP(E81,Priors!$A$3:$C$6,2,FALSE) -> 0.44625207 | AC81: =VLOOKUP(E81,Priors!$A$3:$C$6,3,FALSE) -> 0.05821726 | AD81: =AA81*K81+(1-AA81)*AB81 -> 0.51585838 | AE81: =AA81*L81+(1-AA81)*AC81 -> 0.053144366 | AF81: 1 | AG81: 1 | AH81: =IFERROR(VLOOKUP(D81,Teams!$B$2:$I$21,7,FALSE),1) -> 1 | AI81: =AD81*AF81*AG81*AH81 -> 0.51585838 | AJ81: =AE81*AF81*AG81*AH81 -> 0.053144366 | AK81: Available | AN81: 0.002 | AO81: TRUE | AP81: 2024-07-01 | AQ81: FALSE | AS81: https://raw.githubusercontent.com/vaastav/Fantasy-Premier-League/master/data/2026-27/players_raw.csv
A82: 81 | B82: Rodríguez | C82: Álvaro Rodríguez | D82: Bournemouth | E82: FWD | F82: 6 | G82: 6 | H82: 0 | I82: 0 | J82: 0 | K82: =IFERROR(I82*90/H82,0) -> 0 | L82: =IFERROR(J82*90/H82,0) -> 0 | M82: 0 | N82: 0 | O82: 0 | P82: 0 | Q82: 0 | R82: 0 | V82: TRUE | W82: =IFERROR(VLOOKUP(D82,Teams!$B$2:$I$21,6,FALSE),"") -> 0 | X82: None | AA82: =IFERROR(H82/(H82+Priors!$G$3),0) -> 0 | AB82: =VLOOKUP(E82,Priors!$A$3:$C$6,2,FALSE) -> 0.44625207 | AC82: =VLOOKUP(E82,Priors!$A$3:$C$6,3,FALSE) -> 0.05821726 | AD82: =AA82*K82+(1-AA82)*AB82 -> 0.44625207 | AE82: =AA82*L82+(1-AA82)*AC82 -> 0.05821726 | AF82: 1 | AG82: 1 | AH82: =IFERROR(VLOOKUP(D82,Teams!$B$2:$I$21,7,FALSE),1) -> 1 | AI82: =AD82*AF82*AG82*AH82 -> 0.44625207 | AJ82: =AE82*AF82*AG82*AH82 -> 0.05821726 | AK82: Available | AN82: 0.003 | AO82: TRUE | AP82: 2026-07-14 | AQ82: FALSE | AS82: https://raw.githubusercontent.com/vaastav/Fantasy-Premier-League/master/data/2026-27/players_raw.csv
A83: 566 | B83: Silva | C83: António Silva | D83: Bournemouth | E83: DEF | F83: 5 | G83: 5 | H83: 0 | I83: 0 | J83: 0 | K83: =IFERROR(I83*90/H83,0) -> 0 | L83: =IFERROR(J83*90/H83,0) -> 0 | M83: 0 | N83: 0 | O83: 0 | P83: 0 | Q83: 0 | R83: 0 | V83: TRUE | W83: =IFERROR(VLOOKUP(D83,Teams!$B$2:$I$21,6,FALSE),"") -> 0 | X83: None | AA83: =IFERROR(H83/(H83+Priors!$G$3),0) -> 0 | AB83: =VLOOKUP(E83,Priors!$A$3:$C$6,2,FALSE) -> 0.060081391 | AC83: =VLOOKUP(E83,Priors!$A$3:$C$6,3,FALSE) -> 0.059588192 | AD83: =AA83*K83+(1-AA83)*AB83 -> 0.060081391 | AE83: =AA83*L83+(1-AA83)*AC83 -> 0.059588192 | AF83: 1 | AG83: 1 | AH83: =IFERROR(VLOOKUP(D83,Teams!$B$2:$I$21,7,FALSE),1) -> 1 | AI83: =AD83*AF83*AG83*AH83 -> 0.060081391 | AJ83: =AE83*AF83*AG83*AH83 -> 0.059588192 | AK83: Available | AN83: 0 | AO83: TRUE | AP83: 2026-08-01 | AQ83: FALSE | AS83: https://raw.githubusercontent.com/vaastav/Fantasy-Premier-League/master/data/2026-27/players_raw.csv
A84: 82 | B84: Kelleher | C84: Caoimhín Kelleher | D84: Brentford | E84: GK | F84: 5 | G84: 5 | H84: 3330 | I84: 0 | J84: 0.22 | K84: =IFERROR(I84*90/H84,0) -> 0 | L84: =IFERROR(J84*90/H84,0) -> 0.0059459459 | M84: 0 | N84: 0 | O84: 143 | P84: 3.9 | Q84: 37 | R84: 0 | V84: FALSE | W84: =IFERROR(VLOOKUP(D84,Teams!$B$2:$I$21,6,FALSE),"") -> 0 | X84: None | AA84: =IFERROR(H84/(H84+Priors!$G$3),0) -> 0.76905312 | AB84: =VLOOKUP(E84,Priors!$A$3:$C$6,2,FALSE) -> 0.00024013207 | AC84: =VLOOKUP(E84,Priors!$A$3:$C$6,3,FALSE) -> 0.0019810896 | AD84: =AA84*K84+(1-AA84)*AB84 -> 5.5457753e-05 | AE84: =AA84*L84+(1-AA84)*AC84 -> 0.0050302747 | AF84: 1 | AG84: 1 | AH84: =IFERROR(VLOOKUP(D84,Teams!$B$2:$I$21,7,FALSE),1) -> 1 | AI84: =AD84*AF84*AG84*AH84 -> 5.5457753e-05 | AJ84: =AE84*AF84*AG84*AH84 -> 0.0050302747 | AK84: Available | AN84: 0.056 | AO84: TRUE | AP84: 2025-06-03 | AQ84: FALSE | AS84: https://raw.githubusercontent.com/vaastav/Fantasy-Premier-League/master/data/2026-27/players_raw.csv
A85: 83 | B85: Valdimarsson | C85: Hákon Rafn Valdimarsson | D85: Brentford | E85: GK | F85: 4.5 | G85: 4.5 | H85: 90 | I85: 0 | J85: 0 | K85: =IFERROR(I85*90/H85,0) -> 0 | L85: =IFERROR(J85*90/H85,0) -> 0 | M85: 0 | N85: 0 | O85: 1 | P85: 1 | Q85: 1 | R85: 0 | V85: FALSE | W85: =IFERROR(VLOOKUP(D85,Teams!$B$2:$I$21,6,FALSE),"") -> 0 | X85: None | AA85: =IFERROR(H85/(H85+Priors!$G$3),0) -> 0.082568807 | AB85: =VLOOKUP(E85,Priors!$A$3:$C$6,2,FALSE) -> 0.00024013207 | AC85: =VLOOKUP(E85,Priors!$A$3:$C$6,3,FALSE) -> 0.0019810896 | AD85: =AA85*K85+(1-AA85)*AB85 -> 0.00022030465 | AE85: =AA85*L85+(1-AA85)*AC85 -> 0.0018175134 | AF85: 1 | AG85: 1 | AH85: =IFERROR(VLOOKUP(D85,Teams!$B$2:$I$21,7,FALSE),1) -> 1 | AI85: =AD85*AF85*AG85*AH85 -> 0.00022030465 | AJ85: =AE85*AF85*AG85*AH85 -> 0.0018175134 | AK85: Available | AN85: 0.001 | AO85: TRUE | AP85: 2024-01-26 | AQ85: FALSE | AS85: https://raw.githubusercontent.com/vaastav/Fantasy-Premier-League/master/data/2026-27/players_raw.csv
A86: 84 | B86: Collins | C86: Nathan Collins | D86: Brentford | E86: DEF | F86: 5.5 | G86: 5.5 | H86: 2971 | I86: 2.24 | J86: 1.71 | K86: =IFERROR(I86*90/H86,0) -> 0.067855941 | L86: =IFERROR(J86*90/H86,0) -> 0.05180074 | M86: 1 | N86: 2 | O86: 129 | P86: 3.7 | Q86: 32 | R86: 9.66 | V86: FALSE | W86: =IFERROR(VLOOKUP(D86,Teams!$B$2:$I$21,6,FALSE),"") -> 0 | X86: None | AA86: =IFERROR(H86/(H86+Priors!$G$3),0) -> 0.74817426 | AB86: =VLOOKUP(E86,Priors!$A$3:$C$6,2,FALSE) -> 0.060081391 | AC86: =VLOOKUP(E86,Priors!$A$3:$C$6,3,FALSE) -> 0.059588192 | AD86: =AA86*K86+(1-AA86)*AB86 -> 0.065898109 | AE86: =AA86*L86+(1-AA86)*AC86 -> 0.053761821 | AF86: 1 | AG86: 1 | AH86: =IFERROR(VLOOKUP(D86,Teams!$B$2:$I$21,7,FALSE),1) -> 1 | AI86: =AD86*AF86*AG86*AH86 -> 0.065898109 | AJ86: =AE86*AF86*AG86*AH86 -> 0.053761821 | AK86: Available | AN86: 0.02 | AO86: TRUE | AP86: 2023-07-04 | AQ86: FALSE | AS86: https://raw.githubusercontent.com/vaastav/Fantasy-Premier-League/master/data/2026-27/players_raw.csv
A87: 85 | B87: Van den Berg | C87: Sepp van den Berg | D87: Brentford | E87: DEF | F87: 5 | G87: 5 | H87: 2761 | I87: 3.36 | J87: 1.45 | K87: =IFERROR(I87*90/H87,0) -> 0.10952553 | L87: =IFERROR(J87*90/H87,0) -> 0.047265484 | M87: 0 | N87: 3 | O87: 113 | P87: 3.5 | Q87: 30 | R87: 8.87 | V87: FALSE | W87: =IFERROR(VLOOKUP(D87,Teams!$B$2:$I$21,6,FALSE),"") -> 0 | X87: None | AA87: =IFERROR(H87/(H87+Priors!$G$3),0) -> 0.73411327 | AB87: =VLOOKUP(E87,Priors!$A$3:$C$6,2,FALSE) -> 0.060081391 | AC87: =VLOOKUP(E87,Priors!$A$3:$C$6,3,FALSE) -> 0.059588192 | AD87: =AA87*K87+(1-AA87)*AB87 -> 0.096378993 | AE87: =AA87*L87+(1-AA87)*AC87 -> 0.050541928 | AF87: 1 | AG87: 1 | AH87: =IFERROR(VLOOKUP(D87,Teams!$B$2:$I$21,7,FALSE),1) -> 1 | AI87: =AD87*AF87*AG87*AH87 -> 0.096378993 | AJ87: =AE87*AF87*AG87*AH87 -> 0.050541928 | AK87: Available | AN87: 0.007 | AO87: TRUE | AP87: 2024-08-22 | AQ87: FALSE | AS87: https://raw.githubusercontent.com/vaastav/Fantasy-Premier-League/master/data/2026-27/players_raw.csv
A88: 86 | B88: Lewis-Potter | C88: Keane Lewis-Potter | D88: Brentford | E88: MID | F88: 5.5 | G88: 5.5 | H88: 1960 | I88: 3.01 | J88: 2.51 | K88: =IFERROR(I88*90/H88,0) -> 0.13821429 | L88: =IFERROR(J88*90/H88,0) -> 0.1152551 | M88: 3 | N88: 4 | O88: 115 | P88: 3.2 | Q88: 22 | R88: 3.4 | T88: 1 | V88: FALSE | W88: =IFERROR(VLOOKUP(D88,Teams!$B$2:$I$21,6,FALSE),"") -> 0 | X88: None | AA88: =IFERROR(H88/(H88+Priors!$G$3),0) -> 0.66216216 | AB88: =VLOOKUP(E88,Priors!$A$3:$C$6,2,FALSE) -> 0.15714383 | AC88: =VLOOKUP(E88,Priors!$A$3:$C$6,3,FALSE) -> 0.13222063 | AD88: =AA88*K88+(1-AA88)*AB88 -> 0.1446094 | AE88: =AA88*L88+(1-AA88)*AC88 -> 0.1209867 | AF88: 1 | AG88: 1 | AH88: =IFERROR(VLOOKUP(D88,Teams!$B$2:$I$21,7,FALSE),1) -> 1 | AI88: =AD88*AF88*AG88*AH88 -> 0.1446094 | AJ88: =AE88*AF88*AG88*AH88 -> 0.1209867 | AK88: Available | AN88: 0.005 | AO88: TRUE | AP88: 2022-07-12 | AQ88: FALSE | AS88: https://raw.githubusercontent.com/vaastav/Fantasy-Premier-League/master/data/2026-27/players_raw.csv
A89: 87 | B89: Ajer | C89: Kristoffer Ajer | D89: Brentford | E89: DEF | F89: 4.5 | G89: 4.5 | H89: 1805 | I89: 0.69 | J89: 0.73 | K89: =IFERROR(I89*90/H89,0) -> 0.034404432 | L89: =IFERROR(J89*90/H89,0) -> 0.036398892 | M89: 0 | N89: 2 | O89: 76 | P89: 2.8 | Q89: 20 | R89: 9.57 | V89: FALSE | W89: =IFERROR(VLOOKUP(D89,Teams!$B$2:$I$21,6,FALSE),"") -> 0 | X89: None | AA89: =IFERROR(H89/(H89+Priors!$G$3),0) -> 0.64349376 | AB89: =VLOOKUP(E89,Priors!$A$3:$C$6,2,FALSE) -> 0.060081391 | AC89: =VLOOKUP(E89,Priors!$A$3:$C$6,3,FALSE) -> 0.059588192 | AD89: =AA89*K89+(1-AA89)*AB89 -> 0.043558428 | AE89: =AA89*L89+(1-AA89)*AC89 -> 0.044666022 | AF89: 1 | AG89: 1 | AH89: =IFERROR(VLOOKUP(D89,Teams!$B$2:$I$21,7,FALSE),1) -> 1 | AI89: =AD89*AF89*AG89*AH89 -> 0.043558428 | AJ89: =AE89*AF89*AG89*AH89 -> 0.044666022 | AK89: Available | AN89: 0.012 | AO89: TRUE | AP89: 2021-07-21 | AQ89: FALSE | AS89: https://raw.githubusercontent.com/vaastav/Fantasy-Premier-League/master/data/2026-27/players_raw.csv
A90: 88 | B90: Kayode | C90: Michael Kayode | D90: Brentford | E90: DEF | F90: 4.5 | G90: 4.5 | H90: 3258 | I90: 1.28 | J90: 2.89 | K90: =IFERROR(I90*90/H90,0) -> 0.035359116 | L90: =IFERROR(J90*90/H90,0) -> 0.079834254 | M90: 1 | N90: 2 | O90: 113 | P90: 3.1 | Q90: 37 | R90: 6.05 | V90: FALSE | W90: =IFERROR(VLOOKUP(D90,Teams!$B$2:$I$21,6,FALSE),"") -> 0 | X90: None | AA90: =IFERROR(H90/(H90+Priors!$G$3),0) -> 0.76514796 | AB90: =VLOOKUP(E90,Priors!$A$3:$C$6,2,FALSE) -> 0.060081391 | AC90: =VLOOKUP(E90,Priors!$A$3:$C$6,3,FALSE) -> 0.059588192 | AD90: =AA90*K90+(1-AA90)*AB90 -> 0.041165193 | AE90: =AA90*L90+(1-AA90)*AC90 -> 0.075079425 | AF90: 1 | AG90: 1 | AH90: =IFERROR(VLOOKUP(D90,Teams!$B$2:$I$21,7,FALSE),1) -> 1 | AI90: =AD90*AF90*AG90*AH90 -> 0.041165193 | AJ90: =AE90*AF90*AG90*AH90 -> 0.075079425 | AK90: Available | AN90: 0.041 | AO90: TRUE | AP90: 2025-07-01 | AQ90: FALSE | AS90: https://raw.githubusercontent.com/vaastav/Fantasy-Premier-League/master/data/2026-27/players_raw.csv
A91: 89 | B91: Henry | C91: Rico Henry | D91: Brentford | E91: DEF | F91: 4.5 | G91: 4.5 | H91: 1322 | I91: 0.18 | J91: 0.54 | K91: =IFERROR(I91*90/H91,0) -> 0.01225416 | L91: =IFERROR(J91*90/H91,0) -> 0.036762481 | M91: 0 | N91: 2 | O91: 52 | P91: 2.1 | Q91: 14 | R91: 4.63 | V91: FALSE | W91: =IFERROR(VLOOKUP(D91,Teams!$B$2:$I$21,6,FALSE),"") -> 0 | X91: None | AA91: =IFERROR(H91/(H91+Priors!$G$3),0) -> 0.56933678 | AB91: =VLOOKUP(E91,Priors!$A$3:$C$6,2,FALSE) -> 0.060081391 | AC91: =VLOOKUP(E91,Priors!$A$3:$C$6,3,FALSE) -> 0.059588192 | AD91: =AA91*K91+(1-AA91)*AB91 -> 0.03285159 | AE91: =AA91*L91+(1-AA91)*AC91 -> 0.046592675 | AF91: 1 | AG91: 1 | AH91: =IFERROR(VLOOKUP(D91,Teams!$B$2:$I$21,7,FALSE),1) -> 1 | AI91: =AD91*AF91*AG91*AH91 -> 0.03285159 | AJ91: =AE91*AF91*AG91*AH91 -> 0.046592675 | AK91: Available | AN91: 0.002 | AO91: TRUE | AP91: 2016-08-31 | AQ91: FALSE | AS91: https://raw.githubusercontent.com/vaastav/Fantasy-Premier-League/master/data/2026-27/players_raw.csv
A92: 90 | B92: Hickey | C92: Aaron Hickey | D92: Brentford | E92: DEF | F92: 4.5 | G92: 4.5 | H92: 679 | I92: 0.44 | J92: 0.17 | K92: =IFERROR(I92*90/H92,0) -> 0.05832106 | L92: =IFERROR(J92*90/H92,0) -> 0.022533137 | M92: 0 | N92: 0 | O92: 37 | P92: 1.8 | Q92: 8 | R92: 6.76 | V92: FALSE | W92: =IFERROR(VLOOKUP(D92,Teams!$B$2:$I$21,6,FALSE),"") -> 0 | X92: None | AA92: =IFERROR(H92/(H92+Priors!$G$3),0) -> 0.40440739 | AB92: =VLOOKUP(E92,Priors!$A$3:$C$6,2,FALSE) -> 0.060081391 | AC92: =VLOOKUP(E92,Priors!$A$3:$C$6,3,FALSE) -> 0.059588192 | AD92: =AA92*K92+(1-AA92)*AB92 -> 0.059369501 | AE92: =AA92*L92+(1-AA92)*AC92 -> 0.044602854 | AF92: 1 | AG92: 1 | AH92: =IFERROR(VLOOKUP(D92,Teams!$B$2:$I$21,7,FALSE),1) -> 1 | AI92: =AD92*AF92*AG92*AH92 -> 0.059369501 | AJ92: =AE92*AF92*AG92*AH92 -> 0.044602854 | AK92: Available | AN92: 0.001 | AO92: TRUE | AP92: 2022-07-09 | AQ92: FALSE | AS92: https://raw.githubusercontent.com/vaastav/Fantasy-Premier-League/master/data/2026-27/players_raw.csv
A93: 91 | B93: Pinnock | C93: Ethan Pinnock | D93: Brentford | E93: DEF | F93: 4.5 | G93: 4.5 | H93: 318 | I93: 0.01 | J93: 0.06 | K93: =IFERROR(I93*90/H93,0) -> 0.0028301887 | L93: =IFERROR(J93*90/H93,0) -> 0.016981132 | M93: 0 | N93: 0 | O93: 14 | P93: 3.5 | Q93: 4 | R93: 11.89 | V93: FALSE | W93: =IFERROR(VLOOKUP(D93,Teams!$B$2:$I$21,6,FALSE),"") -> 0 | X93: None | AA93: =IFERROR(H93/(H93+Priors!$G$3),0) -> 0.24127466 | AB93: =VLOOKUP(E93,Priors!$A$3:$C$6,2,FALSE) -> 0.060081391 | AC93: =VLOOKUP(E93,Priors!$A$3:$C$6,3,FALSE) -> 0.059588192 | AD93: =AA93*K93+(1-AA93)*AB93 -> 0.046268127 | AE93: =AA93*L93+(1-AA93)*AC93 -> 0.049308188 | AF93: 1 | AG93: 1 | AH93: =IFERROR(VLOOKUP(D93,Teams!$B$2:$I$21,7,FALSE),1) -> 1 | AI93: =AD93*AF93*AG93*AH93 -> 0.046268127 | AJ93: =AE93*AF93*AG93*AH93 -> 0.049308188 | AK93: Available | AN93: 0.001 | AO93: TRUE | AP93: 2019-07-02 | AQ93: FALSE | AS93: https://raw.githubusercontent.com/vaastav/Fantasy-Premier-League/master/data/2026-27/players_raw.csv
A94: 92 | B94: Ji-soo | C94: Kim Ji-Soo | D94: Brentford | E94: DEF | F94: 4.5 | G94: 4.5 | H94: 0 | I94: 0 | J94: 0 | K94: =IFERROR(I94*90/H94,0) -> 0 | L94: =IFERROR(J94*90/H94,0) -> 0 | M94: 0 | N94: 0 | O94: 0 | P94: 0 | Q94: 0 | R94: 0 | V94: FALSE | W94: =IFERROR(VLOOKUP(D94,Teams!$B$2:$I$21,6,FALSE),"") -> 0 | X94: None | AA94: =IFERROR(H94/(H94+Priors!$G$3),0) -> 0 | AB94: =VLOOKUP(E94,Priors!$A$3:$C$6,2,FALSE) -> 0.060081391 | AC94: =VLOOKUP(E94,Priors!$A$3:$C$6,3,FALSE) -> 0.059588192 | AD94: =AA94*K94+(1-AA94)*AB94 -> 0.060081391 | AE94: =AA94*L94+(1-AA94)*AC94 -> 0.059588192 | AF94: 1 | AG94: 1 | AH94: =IFERROR(VLOOKUP(D94,Teams!$B$2:$I$21,7,FALSE),1) -> 1 | AI94: =AD94*AF94*AG94*AH94 -> 0.060081391 | AJ94: =AE94*AF94*AG94*AH94 -> 0.059588192 | AK94: Available | AN94: 0 | AO94: TRUE | AP94: 2023-07-20 | AQ94: FALSE | AS94: https://raw.githubusercontent.com/vaastav/Fantasy-Premier-League/master/data/2026-27/players_raw.csv
A95: 93 | B95: Schuster | C95: Jannik Schuster | D95: Brentford | E95: DEF | F95: 4.5 | G95: 4.5 | H95: 0 | I95: 0 | J95: 0 | K95: =IFERROR(I95*90/H95,0) -> 0 | L95: =IFERROR(J95*90/H95,0) -> 0 | M95: 0 | N95: 0 | O95: 0 | P95: 0 | Q95: 0 | R95: 0 | V95: TRUE | W95: =IFERROR(VLOOKUP(D95,Teams!$B$2:$I$21,6,FALSE),"") -> 0 | X95: None | AA95: =IFERROR(H95/(H95+Priors!$G$3),0) -> 0 | AB95: =VLOOKUP(E95,Priors!$A$3:$C$6,2,FALSE) -> 0.060081391 | AC95: =VLOOKUP(E95,Priors!$A$3:$C$6,3,FALSE) -> 0.059588192 | AD95: =AA95*K95+(1-AA95)*AB95 -> 0.060081391 | AE95: =AA95*L95+(1-AA95)*AC95 -> 0.059588192 | AF95: 1 | AG95: 1 | AH95: =IFERROR(VLOOKUP(D95,Teams!$B$2:$I$21,7,FALSE),1) -> 1 | AI95: =AD95*AF95*AG95*AH95 -> 0.060081391 | AJ95: =AE95*AF95*AG95*AH95 -> 0.059588192 | AK95: Available | AN95: 0.001 | AO95: TRUE | AP95: 2026-06-15 | AQ95: FALSE | AS95: https://raw.githubusercontent.com/vaastav/Fantasy-Premier-League/master/data/2026-27/players_raw.csv
A96: 94 | B96: Schade | C96: Kevin Schade | D96: Brentford | E96: MID | F96: 6 | G96: 6 | H96: 2744 | I96: 12.08 | J96: 2.05 | K96: =IFERROR(I96*90/H96,0) -> 0.39620991 | L96: =IFERROR(J96*90/H96,0) -> 0.067237609 | M96: 8 | N96: 5 | O96: 125 | P96: 3.6 | Q96: 32 | R96: 6.23 | S96: 2 | V96: FALSE | W96: =IFERROR(VLOOKUP(D96,Teams!$B$2:$I$21,6,FALSE),"") -> 0 | X96: None | AA96: =IFERROR(H96/(H96+Priors!$G$3),0) -> 0.73290598 | AB96: =VLOOKUP(E96,Priors!$A$3:$C$6,2,FALSE) -> 0.15714383 | AC96: =VLOOKUP(E96,Priors!$A$3:$C$6,3,FALSE) -> 0.13222063 | AD96: =AA96*K96+(1-AA96)*AB96 -> 0.33235679 | AE96: =AA96*L96+(1-AA96)*AC96 -> 0.084594185 | AF96: 1 | AG96: 1 | AH96: =IFERROR(VLOOKUP(D96,Teams!$B$2:$I$21,7,FALSE),1) -> 1 | AI96: =AD96*AF96*AG96*AH96 -> 0.33235679 | AJ96: =AE96*AF96*AG96*AH96 -> 0.084594185 | AK96: Available | AN96: 0.023 | AO96: TRUE | AP96: 2023-07-01 | AQ96: FALSE | AS96: https://raw.githubusercontent.com/vaastav/Fantasy-Premier-League/master/data/2026-27/players_raw.csv
A97: 95 | B97: O.Dango | C97: Dango Ouattara | D97: Brentford | E97: MID | F97: 6.5 | G97: 6.5 | H97: 2271 | I97: 7.94 | J97: 4.12 | K97: =IFERROR(I97*90/H97,0) -> 0.31466314 | L97: =IFERROR(J97*90/H97,0) -> 0.16327609 | M97: 7 | N97: 8 | O97: 136 | P97: 4.2 | Q97: 25 | R97: 7.33 | U97: 8 | V97: FALSE | W97: =IFERROR(VLOOKUP(D97,Teams!$B$2:$I$21,6,FALSE),"") -> 0 | X97: None | AA97: =IFERROR(H97/(H97+Priors!$G$3),0) -> 0.69428309 | AB97: =VLOOKUP(E97,Priors!$A$3:$C$6,2,FALSE) -> 0.15714383 | AC97: =VLOOKUP(E97,Priors!$A$3:$C$6,3,FALSE) -> 0.13222063 | AD97: =AA97*K97+(1-AA97)*AB97 -> 0.26650683 | AE97: =AA97*L97+(1-AA97)*AC97 -> 0.15378191 | AF97: 1 | AG97: 1 | AH97: =IFERROR(VLOOKUP(D97,Teams!$B$2:$I$21,7,FALSE),1) -> 1 | AI97: =AD97*AF97*AG97*AH97 -> 0.26650683 | AJ97: =AE97*AF97*AG97*AH97 -> 0.15378191 | AK97: Available | AN97: 0.013 | AO97: TRUE | AP97: 2025-08-16 | AQ97: FALSE | AS97: https://raw.githubusercontent.com/vaastav/Fantasy-Premier-League/master/data/2026-27/players_raw.csv
A98: 96 | B98: Damsgaard | C98: Mikkel Damsgaard | D98: Brentford | E98: MID | F98: 5.5 | G98: 5.5 | H98: 2046 | I98: 2.61 | J98: 5.43 | K98: =IFERROR(I98*90/H98,0) -> 0.11480938 | L98: =IFERROR(J98*90/H98,0) -> 0.2388563 | M98: 4 | N98: 4 | O98: 113 | P98: 3.4 | Q98: 24 | R98: 10.6 | T98: 3 | U98: 6 | V98: FALSE | W98: =IFERROR(VLOOKUP(D98,Teams!$B$2:$I$21,6,FALSE),"") -> 0 | X98: None | AA98: =IFERROR(H98/(H98+Priors!$G$3),0) -> 0.67170059 | AB98: =VLOOKUP(E98,Priors!$A$3:$C$6,2,FALSE) -> 0.15714383 | AC98: =VLOOKUP(E98,Priors!$A$3:$C$6,3,FALSE) -> 0.13222063 | AD98: =AA98*K98+(1-AA98)*AB98 -> 0.12870776 | AE98: =AA98*L98+(1-AA98)*AC98 -> 0.20384788 | AF98: 1 | AG98: 1 | AH98: =IFERROR(VLOOKUP(D98,Teams!$B$2:$I$21,7,FALSE),1) -> 1 | AI98: =AD98*AF98*AG98*AH98 -> 0.12870776 | AJ98: =AE98*AF98*AG98*AH98 -> 0.20384788 | AK98: Available | AN98: 0.007 | AO98: TRUE | AP98: 2022-08-10 | AQ98: FALSE | AS98: https://raw.githubusercontent.com/vaastav/Fantasy-Premier-League/master/data/2026-27/players_raw.csv
A99: 97 | B99: Jensen | C99: Mathias Jensen | D99: Brentford | E99: MID | F99: 5.5 | G99: 5.5 | H99: 2239 | I99: 2.21 | J99: 6.06 | K99: =IFERROR(I99*90/H99,0) -> 0.088834301 | L99: =IFERROR(J99*90/H99,0) -> 0.24359089 | M99: 3 | N99: 2 | O99: 98 | P99: 2.7 | Q99: 26 | R99: 8.84 | S99: 3 | T99: 2 | U99: 5 | V99: FALSE | W99: =IFERROR(VLOOKUP(D99,Teams!$B$2:$I$21,6,FALSE),"") -> 0 | X99: None | AA99: =IFERROR(H99/(H99+Priors!$G$3),0) -> 0.69126274 | AB99: =VLOOKUP(E99,Priors!$A$3:$C$6,2,FALSE) -> 0.15714383 | AC99: =VLOOKUP(E99,Priors!$A$3:$C$6,3,FALSE) -> 0.13222063 | AD99: =AA99*K99+(1-AA99)*AB99 -> 0.109924 | AE99: =AA99*L99+(1-AA99)*AC99 -> 0.20920674 | AF99: 1 | AG99: 1 | AH99: =IFERROR(VLOOKUP(D99,Teams!$B$2:$I$21,7,FALSE),1) -> 1 | AI99: =AD99*AF99*AG99*AH99 -> 0.109924 | AJ99: =AE99*AF99*AG99*AH99 -> 0.20920674 | AK99: Available | AN99: 0.001 | AO99: TRUE | AP99: 2019-07-10 | AQ99: FALSE | AS99: https://raw.githubusercontent.com/vaastav/Fantasy-Premier-League/master/data/2026-27/players_raw.csv
A100: 98 | B100: Janelt | C100: Vitaly Janelt | D100: Brentford | E100: MID | F100: 5 | G100: 5 | H100: 1434 | I100: 0.82 | J100: 2.27 | K100: =IFERROR(I100*90/H100,0) -> 0.051464435 | L100: =IFERROR(J100*90/H100,0) -> 0.14246862 | M100: 1 | N100: 4 | O100: 74 | P100: 3 | Q100: 15 | R100: 11.49 | U100: 7 | V100: FALSE | W100: =IFERROR(VLOOKUP(D100,Teams!$B$2:$I$21,6,FALSE),"") -> 0 | X100: None | AA100: =IFERROR(H100/(H100+Priors!$G$3),0) -> 0.58915366 | AB100: =VLOOKUP(E100,Priors!$A$3:$C$6,2,FALSE) -> 0.15714383 | AC100: =VLOOKUP(E100,Priors!$A$3:$C$6,3,FALSE) -> 0.13222063 | AD100: =AA100*K100+(1-AA100)*AB100 -> 0.094882429 | AE100: =AA100*L100+(1-AA100)*AC100 -> 0.13825827 | AF100: 1 | AG100: 1 | AH100: =IFERROR(VLOOKUP(D100,Teams!$B$2:$I$21,7,FALSE),1) -> 1 | AI100: =AD100*AF100*AG100*AH100 -> 0.094882429 | AJ100: =AE100*AF100*AG100*AH100 -> 0.13825827 | AK100: Available | AN100: 0.001 | AO100: TRUE | AP100: 2020-10-03 | AQ100: FALSE | AS100: https://raw.githubusercontent.com/vaastav/Fantasy-Premier-League/master/data/2026-27/players_raw.csv
...

Sheet Teams
A1: Team ID | B1: Team | C1: Short | D1: FPL Strength Home | E1: FPL Strength Away | F1: Promoted 26/27? | G1: New Manager? | H1: Team Attack Adj | I1: Team Defence Adj | J1: Notes | K1: Source URL
A2: 1 | B2: Arsenal | C2: ARS | D2: 4 | E2: 5 | F2: FALSE | H2: 1 | I2: 1 | K2: https://raw.githubusercontent.com/vaastav/Fantasy-Premier-League/master/data/2026-27/teams.csv
A3: 2 | B3: Aston Villa | C3: AVL | D3: 3 | E3: 4 | F3: FALSE | H3: 1 | I3: 1 | K3: https://raw.githubusercontent.com/vaastav/Fantasy-Premier-League/master/data/2026-27/teams.csv
A4: 3 | B4: Bournemouth | C4: BOU | D4: 3 | E4: 3 | F4: FALSE | H4: 1 | I4: 1 | K4: https://raw.githubusercontent.com/vaastav/Fantasy-Premier-League/master/data/2026-27/teams.csv
A5: 4 | B5: Brentford | C5: BRE | D5: 3 | E5: 3 | F5: FALSE | H5: 1 | I5: 1 | K5: https://raw.githubusercontent.com/vaastav/Fantasy-Premier-League/master/data/2026-27/teams.csv
A6: 5 | B6: Brighton | C6: BHA | D6: 2 | E6: 3 | F6: FALSE | H6: 1 | I6: 1 | K6: https://raw.githubusercontent.com/vaastav/Fantasy-Premier-League/master/data/2026-27/teams.csv
A7: 6 | B7: Chelsea | C7: CHE | D7: 4 | E7: 4 | F7: FALSE | H7: 1 | I7: 1 | K7: https://raw.githubusercontent.com/vaastav/Fantasy-Premier-League/master/data/2026-27/teams.csv
A8: 7 | B8: Coventry City | C8: COV | D8: 2 | E8: 2 | F8: TRUE | H8: 1 | I8: 1 | K8: https://raw.githubusercontent.com/vaastav/Fantasy-Premier-League/master/data/2026-27/teams.csv
A9: 8 | B9: Crystal Palace | C9: CRY | D9: 3 | E9: 3 | F9: FALSE | H9: 1 | I9: 1 | K9: https://raw.githubusercontent.com/vaastav/Fantasy-Premier-League/master/data/2026-27/teams.csv
A10: 9 | B10: Everton | C10: EVE | D10: 3 | E10: 3 | F10: FALSE | H10: 1 | I10: 1 | K10: https://raw.githubusercontent.com/vaastav/Fantasy-Premier-League/master/data/2026-27/teams.csv
A11: 10 | B11: Fulham | C11: FUL | D11: 2 | E11: 3 | F11: FALSE | H11: 1 | I11: 1 | K11: https://raw.githubusercontent.com/vaastav/Fantasy-Premier-League/master/data/2026-27/teams.csv
A12: 11 | B12: Hull City | C12: HUL | D12: 2 | E12: 2 | F12: TRUE | H12: 1 | I12: 1 | K12: https://raw.githubusercontent.com/vaastav/Fantasy-Premier-League/master/data/2026-27/teams.csv
A13: 12 | B13: Ipswich Town | C13: IPS | D13: 2 | E13: 2 | F13: TRUE | H13: 1 | I13: 1 | K13: https://raw.githubusercontent.com/vaastav/Fantasy-Premier-League/master/data/2026-27/teams.csv
... A21: 20 | B21: Sunderland | C21: SUN | D21: 2 | E21: 3 | F21: FALSE | H21: 1 | I21: 1 | K21: https://raw.githubusercontent.com/vaastav/Fantasy-Premier-League/master/data/2026-27/teams.csv

Sheet Priors
A1: POSITIONAL PRIORS | F1: MODEL ASSUMPTIONS | I1: MODEL NOTES
A2: Position | B2: xG90 prior | C2: xA90 prior | D2: Method | F2: Assumption | G2: Value | I2: Raw current-season FPL universe: 567 players
A3: GK | B3: =IFERROR(SUMIFS(Players!$I$2:$I$568,Players!$E$2:$E$568,A3)*90/SUMIFS(Players!$H$2:$H$568,Players!$E$2:$E$568,A3),0) -> 0.00024013207 | C3: =IFERROR(SUMIFS(Players!$J$2:$J$568,Players!$E$2:$E$568,A3)*90/SUMIFS(Players!$H$2:$H$568,Players!$E$2:$E$568,A3),0) -> 0.0019810896 | D3: Minute-weighted 25/26 history | F3: Shrinkage minutes (k) | G3: 1000 | I3: Historical 25/26 fields are the preseason FPL snapshot values.
A4: DEF | B4: =IFERROR(SUMIFS(Players!$I$2:$I$568,Players!$E$2:$E$568,A4)*90/SUMIFS(Players!$H$2:$H$568,Players!$E$2:$E$568,A4),0) -> 0.060081391 | C4: =IFERROR(SUMIFS(Players!$J$2:$J$568,Players!$E$2:$E$568,A4)*90/SUMIFS(Players!$H$2:$H$568,Players!$E$2:$E$568,A4),0) -> 0.059588192 | D4: Minute-weighted 25/26 history | F4: Projection horizon (GWs) | G4: 6 | I4: Players with no PL history shrink fully toward the positional prior.
A5: MID | B5: =IFERROR(SUMIFS(Players!$I$2:$I$568,Players!$E$2:$E$568,A5)*90/SUMIFS(Players!$H$2:$H$568,Players!$E$2:$E$568,A5),0) -> 0.15714383 | C5: =IFERROR(SUMIFS(Players!$J$2:$J$568,Players!$E$2:$E$568,A5)*90/SUMIFS(Players!$H$2:$H$568,Players!$E$2:$E$568,A5),0) -> 0.13222063 | D5: Minute-weighted 25/26 history | F5: Default league adj | G5: 1 | I5: Sample Weight = minutes / (minutes + k).
A6: FWD | B6: =IFERROR(SUMIFS(Players!$I$2:$I$568,Players!$E$2:$E$568,A6)*90/SUMIFS(Players!$H$2:$H$568,Players!$E$2:$E$568,A6),0) -> 0.44625207 | C6: =IFERROR(SUMIFS(Players!$J$2:$J$568,Players!$E$2:$E$568,A6)*90/SUMIFS(Players!$H$2:$H$568,Players!$E$2:$E$568,A6),0) -> 0.05821726 | D6: Minute-weighted 25/26 history | F6: Default role adj | G6: 1 | I6: League/role adjustments are explicit judgement inputs, default 1.00.
F7: Snapshot date | G7: 2026-08-18 | I7: Team adjustment links to the Teams sheet, default 1.00.
I8: Yellow = assumption/input; blue text = hardcoded data.
I9: Green text = links to another worksheet; black = formulas.
I10: Fixture market xG fields are intentionally blank for later bookmaker work.

Sheet Fixtures
A1: GW | B1: Fixture ID | C1: Kickoff UTC | D1: Team | E1: Opponent | F1: H/A | G1: Official FDR | H1: Team ID | I1: Opponent ID | J1: Market Team xG | K1: Market Opp xG | L1: CS Prob | M1: Attack Fixture Adj | N1: Def Fixture Adj | O1: Notes | P1: Source URL
A2: 1 | B2: 1 | C2: 46255.792 | D2: Coventry City | E2: Arsenal | F2: A | G2: 5 | H2: 7 | I2: 1 | L2: =IF(K2="","",EXP(-K2)) | M2: 1 | N2: 1 | P2: https://raw.githubusercontent.com/vaastav/Fantasy-Premier-League/master/data/2026-27/fixtures.csv
A3: 1 | B3: 1 | C3: 46255.792 | D3: Arsenal | E3: Coventry City | F3: H | G3: 2 | H3: 1 | I3: 7 | L3: =IF(K3="","",EXP(-K3)) | M3: 1 | N3: 1 | P3: https://raw.githubusercontent.com/vaastav/Fantasy-Premier-League/master/data/2026-27/fixtures.csv
A4: 1 | B4: 2 | C4: 46256.688 | D4: Spurs | E4: Brentford | F4: A | G4: 3 | H4: 19 | I4: 4 | L4: =IF(K4="","",EXP(-K4)) | M4: 1 | N4: 1 | P4: https://raw.githubusercontent.com/vaastav/Fantasy-Premier-League/master/data/2026-27/fixtures.csv
A5: 1 | B5: 2 | C5: 46256.688 | D5: Brentford | E5: Spurs | F5: H | G5: 3 | H5: 4 | I5: 19 | L5: =IF(K5="","",EXP(-K5)) | M5: 1 | N5: 1 | P5: https://raw.githubusercontent.com/vaastav/Fantasy-Premier-League/master/data/2026-27/fixtures.csv
A6: 1 | B6: 3 | C6: 46256.583 | D6: Crystal Palace | E6: Everton | F6: A | G6: 3 | H6: 8 | I6: 9 | L6: =IF(K6="","",EXP(-K6)) | M6: 1 | N6: 1 | P6: https://raw.githubusercontent.com/vaastav/Fantasy-Premier-League/master/data/2026-27/fixtures.csv
A7: 1 | B7: 3 | C7: 46256.583 | D7: Everton | E7: Crystal Palace | F7: H | G7: 3 | H7: 9 | I7: 8 | L7: =IF(K7="","",EXP(-K7)) | M7: 1 | N7: 1 | P7: https://raw.githubusercontent.com/vaastav/Fantasy-Premier-League/master/data/2026-27/fixtures.csv
A8: 1 | B8: 4 | C8: 46256.479 | D8: Man Utd | E8: Hull City | F8: A | G8: 2 | H8: 16 | I8: 11 | L8: =IF(K8="","",EXP(-K8)) | M8: 1 | N8: 1 | P8: https://raw.githubusercontent.com/vaastav/Fantasy-Premier-League/master/data/2026-27/fixtures.csv
A9: 1 | B9: 4 | C9: 46256.479 | D9: Hull City | E9: Man Utd | F9: H | G9: 4 | H9: 11 | I9: 16 | L9: =IF(K9="","",EXP(-K9)) | M9: 1 | N9: 1 | P9: https://raw.githubusercontent.com/vaastav/Fantasy-Premier-League/master/data/2026-27/fixtures.csv
A10: 1 | B10: 5 | C10: 46256.583 | D10: Sunderland | E10: Ipswich Town | F10: A | G10: 2 | H10: 20 | I10: 12 | L10: =IF(K10="","",EXP(-K10)) | M10: 1 | N10: 1 | P10: https://raw.githubusercontent.com/vaastav/Fantasy-Premier-League/master/data/2026-27/fixtures.csv
A11: 1 | B11: 5 | C11: 46256.583 | D11: Ipswich Town | E11: Sunderland | F11: H | G11: 2 | H11: 12 | I11: 20 | L11: =IF(K11="","",EXP(-K11)) | M11: 1 | N11: 1 | P11: https://raw.githubusercontent.com/vaastav/Fantasy-Premier-League/master/data/2026-27/fixtures.csv
A12: 1 | B12: 6 | C12: 46256.583 | D12: Leeds | E12: Nott'm Forest | F12: A | G12: 3 | H12: 13 | I12: 18 | L12: =IF(K12="","",EXP(-K12)) | M12: 1 | N12: 1 | P12: https://raw.githubusercontent.com/vaastav/Fantasy-Premier-League/master/data/2026-27/fixtures.csv
A13: 1 | B13: 6 | C13: 46256.583 | D13: Nott'm Forest | E13: Leeds | F13: H | G13: 2 | H13: 18 | I13: 13 | L13: =IF(K13="","",EXP(-K13)) | M13: 1 | N13: 1 | P13: https://raw.githubusercontent.com/vaastav/Fantasy-Premier-League/master/data/2026-27/fixtures.csv
... A761: 38 | B761: 380 | C761: 46537.625 | D761: Sunderland | E761: Man City | F761: H | G761: 4 | H761: 20 | I761: 15 | L761: =IF(K761="","",EXP(-K761)) | M761: 1 | N761: 1 | P761: https://raw.githubusercontent.com/vaastav/Fantasy-Premier-League/master/data/2026-27/fixtures.csv

Sheet Projections
A1: GW | B1: Player ID | C1: Player | D1: Team | E1: Position | F1: Current Price (£m) | G1: Expected Mins | H1: Adj xG90 | I1: Adj xA90 | J1: Fixture Att Adj | K1: Fixture CS Prob | L1: Fixture xG | M1: Fixture xA | N1: Appearance Pts | O1: Goal Pts | P1: Assist Pts | Q1: CS Pts | R1: DC Pts | S1: Bonus Pts | T1: Total xPts
A3: Intentionally left as the next modelling layer: populate once minutes + point-conversion logic are agreed.

Sheet Squad
A1: Player | B1: Team | C1: Position | D1: Current Price (£m) | E1: Starter? | F1: Captain? | G1: Start Prob | H1: Exp Mins | I1: Adj xG90 | J1: Adj xA90 | K1: 6GW xPts | L1: Notes
B2: =IFERROR(VLOOKUP($A2,Players!$C$2:$AJ$568,2,FALSE),"") | C2: =IFERROR(VLOOKUP($A2,Players!$C$2:$AJ$568,3,FALSE),"") | D2: =IFERROR(VLOOKUP($A2,Players!$C$2:$AJ$568,5,FALSE),"") | G2: =IFERROR(VLOOKUP($A2,Players!$C$2:$AJ$568,23,FALSE),"") | H2: =IFERROR(VLOOKUP($A2,Players!$C$2:$AJ$568,24,FALSE),"") | I2: =IFERROR(VLOOKUP($A2,Players!$C$2:$AJ$568,33,FALSE),"") | J2: =IFERROR(VLOOKUP($A2,Players!$C$2:$AJ$568,34,FALSE),"")
B3: =IFERROR(VLOOKUP($A3,Players!$C$2:$AJ$568,2,FALSE),"") | C3: =IFERROR(VLOOKUP($A3,Players!$C$2:$AJ$568,3,FALSE),"") | D3: =IFERROR(VLOOKUP($A3,Players!$C$2:$AJ$568,5,FALSE),"") | G3: =IFERROR(VLOOKUP($A3,Players!$C$2:$AJ$568,23,FALSE),"") | H3: =IFERROR(VLOOKUP($A3,Players!$C$2:$AJ$568,24,FALSE),"") | I3: =IFERROR(VLOOKUP($A3,Players!$C$2:$AJ$568,33,FALSE),"") | J3: =IFERROR(VLOOKUP($A3,Players!$C$2:$AJ$568,34,FALSE),"")
B4: =IFERROR(VLOOKUP($A4,Players!$C$2:$AJ$568,2,FALSE),"") | C4: =IFERROR(VLOOKUP($A4,Players!$C$2:$AJ$568,3,FALSE),"") | D4: =IFERROR(VLOOKUP($A4,Players!$C$2:$AJ$568,5,FALSE),"") | G4: =IFERROR(VLOOKUP($A4,Players!$C$2:$AJ$568,23,FALSE),"") | H4: =IFERROR(VLOOKUP($A4,Players!$C$2:$AJ$568,24,FALSE),"") | I4: =IFERROR(VLOOKUP($A4,Players!$C$2:$AJ$568,33,FALSE),"") | J4: =IFERROR(VLOOKUP($A4,Players!$C$2:$AJ$568,34,FALSE),"")
B5: =IFERROR(VLOOKUP($A5,Players!$C$2:$AJ$568,2,FALSE),"") | C5: =IFERROR(VLOOKUP($A5,Players!$C$2:$AJ$568,3,FALSE),"") | D5: =IFERROR(VLOOKUP($A5,Players!$C$2:$AJ$568,5,FALSE),"") | G5: =IFERROR(VLOOKUP($A5,Players!$C$2:$AJ$568,23,FALSE),"") | H5: =IFERROR(VLOOKUP($A5,Players!$C$2:$AJ$568,24,FALSE),"") | I5: =IFERROR(VLOOKUP($A5,Players!$C$2:$AJ$568,33,FALSE),"") | J5: =IFERROR(VLOOKUP($A5,Players!$C$2:$AJ$568,34,FALSE),"")
B6: =IFERROR(VLOOKUP($A6,Players!$C$2:$AJ$568,2,FALSE),"") | C6: =IFERROR(VLOOKUP($A6,Players!$C$2:$AJ$568,3,FALSE),"") | D6: =IFERROR(VLOOKUP($A6,Players!$C$2:$AJ$568,5,FALSE),"") | G6: =IFERROR(VLOOKUP($A6,Players!$C$2:$AJ$568,23,FALSE),"") | H6: =IFERROR(VLOOKUP($A6,Players!$C$2:$AJ$568,24,FALSE),"") | I6: =IFERROR(VLOOKUP($A6,Players!$C$2:$AJ$568,33,FALSE),"") | J6: =IFERROR(VLOOKUP($A6,Players!$C$2:$AJ$568,34,FALSE),"")
B7: =IFERROR(VLOOKUP($A7,Players!$C$2:$AJ$568,2,FALSE),"") | C7: =IFERROR(VLOOKUP($A7,Players!$C$2:$AJ$568,3,FALSE),"") | D7: =IFERROR(VLOOKUP($A7,Players!$C$2:$AJ$568,5,FALSE),"") | G7: =IFERROR(VLOOKUP($A7,Players!$C$2:$AJ$568,23,FALSE),"") | H7: =IFERROR(VLOOKUP($A7,Players!$C$2:$AJ$568,24,FALSE),"") | I7: =IFERROR(VLOOKUP($A7,Players!$C$2:$AJ$568,33,FALSE),"") | J7: =IFERROR(VLOOKUP($A7,Players!$C$2:$AJ$568,34,FALSE),"")
B8: =IFERROR(VLOOKUP($A8,Players!$C$2:$AJ$568,2,FALSE),"") | C8: =IFERROR(VLOOKUP($A8,Players!$C$2:$AJ$568,3,FALSE),"") | D8: =IFERROR(VLOOKUP($A8,Players!$C$2:$AJ$568,5,FALSE),"") | G8: =IFERROR(VLOOKUP($A8,Players!$C$2:$AJ$568,23,FALSE),"") | H8: =IFERROR(VLOOKUP($A8,Players!$C$2:$AJ$568,24,FALSE),"") | I8: =IFERROR(VLOOKUP($A8,Players!$C$2:$AJ$568,33,FALSE),"") | J8: =IFERROR(VLOOKUP($A8,Players!$C$2:$AJ$568,34,FALSE),"")
B9: =IFERROR(VLOOKUP($A9,Players!$C$2:$AJ$568,2,FALSE),"") | C9: =IFERROR(VLOOKUP($A9,Players!$C$2:$AJ$568,3,FALSE),"") | D9: =IFERROR(VLOOKUP($A9,Players!$C$2:$AJ$568,5,FALSE),"") | G9: =IFERROR(VLOOKUP($A9,Players!$C$2:$AJ$568,23,FALSE),"") | H9: =IFERROR(VLOOKUP($A9,Players!$C$2:$AJ$568,24,FALSE),"") | I9: =IFERROR(VLOOKUP($A9,Players!$C$2:$AJ$568,33,FALSE),"") | J9: =IFERROR(VLOOKUP($A9,Players!$C$2:$AJ$568,34,FALSE),"")
B10: =IFERROR(VLOOKUP($A10,Players!$C$2:$AJ$568,2,FALSE),"") | C10: =IFERROR(VLOOKUP($A10,Players!$C$2:$AJ$568,3,FALSE),"") | D10: =IFERROR(VLOOKUP($A10,Players!$C$2:$AJ$568,5,FALSE),"") | G10: =IFERROR(VLOOKUP($A10,Players!$C$2:$AJ$568,23,FALSE),"") | H10: =IFERROR(VLOOKUP($A10,Players!$C$2:$AJ$568,24,FALSE),"") | I10: =IFERROR(VLOOKUP($A10,Players!$C$2:$AJ$568,33,FALSE),"") | J10: =IFERROR(VLOOKUP($A10,Players!$C$2:$AJ$568,34,FALSE),"")
B11: =IFERROR(VLOOKUP($A11,Players!$C$2:$AJ$568,2,FALSE),"") | C11: =IFERROR(VLOOKUP($A11,Players!$C$2:$AJ$568,3,FALSE),"") | D11: =IFERROR(VLOOKUP($A11,Players!$C$2:$AJ$568,5,FALSE),"") | G11: =IFERROR(VLOOKUP($A11,Players!$C$2:$AJ$568,23,FALSE),"") | H11: =IFERROR(VLOOKUP($A11,Players!$C$2:$AJ$568,24,FALSE),"") | I11: =IFERROR(VLOOKUP($A11,Players!$C$2:$AJ$568,33,FALSE),"") | J11: =IFERROR(VLOOKUP($A11,Players!$C$2:$AJ$568,34,FALSE),"")
B12: =IFERROR(VLOOKUP($A12,Players!$C$2:$AJ$568,2,FALSE),"") | C12: =IFERROR(VLOOKUP($A12,Players!$C$2:$AJ$568,3,FALSE),"") | D12: =IFERROR(VLOOKUP($A12,Players!$C$2:$AJ$568,5,FALSE),"") | G12: =IFERROR(VLOOKUP($A12,Players!$C$2:$AJ$568,23,FALSE),"") | H12: =IFERROR(VLOOKUP($A12,Players!$C$2:$AJ$568,24,FALSE),"") | I12: =IFERROR(VLOOKUP($A12,Players!$C$2:$AJ$568,33,FALSE),"") | J12: =IFERROR(VLOOKUP($A12,Players!$C$2:$AJ$568,34,FALSE),"")
B13: =IFERROR(VLOOKUP($A13,Players!$C$2:$AJ$568,2,FALSE),"") | C13: =IFERROR(VLOOKUP($A13,Players!$C$2:$AJ$568,3,FALSE),"") | D13: =IFERROR(VLOOKUP($A13,Players!$C$2:$AJ$568,5,FALSE),"") | G13: =IFERROR(VLOOKUP($A13,Players!$C$2:$AJ$568,23,FALSE),"") | H13: =IFERROR(VLOOKUP($A13,Players!$C$2:$AJ$568,24,FALSE),"") | I13: =IFERROR(VLOOKUP($A13,Players!$C$2:$AJ$568,33,FALSE),"") | J13: =IFERROR(VLOOKUP($A13,Players!$C$2:$AJ$568,34,FALSE),"")
... B16: =IFERROR(VLOOKUP($A16,Players!$C$2:$AJ$568,2,FALSE),"") | C16: =IFERROR(VLOOKUP($A16,Players!$C$2:$AJ$568,3,FALSE),"") | D16: =IFERROR(VLOOKUP($A16,Players!$C$2:$AJ$568,5,FALSE),"") | G16: =IFERROR(VLOOKUP($A16,Players!$C$2:$AJ$568,23,FALSE),"") | H16: =IFERROR(VLOOKUP($A16,Players!$C$2:$AJ$568,24,FALSE),"") | I16: =IFERROR(VLOOKUP($A16,Players!$C$2:$AJ$568,33,FALSE),"") | J16: =IFERROR(VLOOKUP($A16,Players!$C$2:$AJ$568,34,FALSE),"")

Sheet Lists
A1: Teams | B1: Positions | C1: Boolean | D1: Role Change | E1: Status Code
A2: Arsenal | B2: GK | C2: FALSE | D2: None | E2: a
A3: Aston Villa | B3: DEF | C3: TRUE | D3: More advanced | E3: d
A4: Bournemouth | B4: MID | D4: Deeper | E4: i
A5: Brentford | B5: FWD | D5: Rotation risk | E5: s
A6: Brighton | D6: Unknown | E6: u
A7: Chelsea
A8: Coventry City
A9: Crystal Palace
A10: Everton
A11: Fulham
A12: Hull City
A13: Ipswich Town
A14: Leeds
A15: Liverpool
A16: Man City
A17: Man Utd
A18: Newcastle
... A21: Sunderland
