Workbook

Sheet Dashboard
A1: FPL 2026/27 Model — v0.5 Team + Fixture Engine
A3: Snapshot | B3: 19 Aug 2026 | D3: Fixture | E3: Fair H | F3: Fair D | G3: Fair A | H3: Home xG | I3: Away xG
A4: GW1 market coverage | B4: 10 / 10 fixtures | D4: Arsenal v Coventry City | E4: 0.82429501 | F4: 0.12364425 | G4: 0.052060738 | H4: 2.6529358 | I4: 0.52865869
A5: Market anchor | B5: Oddschecker 1X2 best-price consensus | D5: Hull City v Man Utd | E5: 0.10324484 | F5: 0.19616519 | G5: 0.70058997 | H5: 0.60545883 | I5: 1.9843124
A6: De-vig | B6: Yes — normalize implied probs to 100% | D6: Ipswich Town v Sunderland | E6: 0.34958111 | F6: 0.28789033 | G6: 0.36252856 | H6: 1.1088257 | I6: 1.1347602
A7: Market xG method | B7: Independent Poisson fit to fair 1X2 | D7: Everton v Crystal Palace | E7: 0.43391067 | F7: 0.27894257 | G7: 0.28714676 | H7: 1.3042478 | I7: 1.0054212
A8: Default market weight | B8: 100% where market exists | D8: Nott'm Forest v Leeds | E8: 0.41309359 | F8: 0.28031351 | G8: 0.3065929 | H8: 1.266981 | I8: 1.0502507
A9: Structural model | B9: Parallel diagnostic / future fallback | D9: Brentford v Spurs | E9: 0.39069767 | F9: 0.26046512 | G9: 0.34883721 | H9: 1.3720338 | I9: 1.28186
A10: Final FPL xPts | B10: Not yet — v0.6 | D10: Man City v Bournemouth | E10: 0.65326633 | F10: 0.1959799 | G10: 0.15075377 | H10: 2.1387928 | I10: 0.91917821
D11: Brighton v Aston Villa | E11: 0.42603978 | F11: 0.25786618 | G11: 0.31609403 | H11: 1.4525482 | I11: 1.2147039
D12: Newcastle v Liverpool | E12: 0.26324671 | F12: 0.24974688 | G12: 0.48700641 | H12: 1.1006915 | I12: 1.5903535
D13: Fulham v Chelsea | E13: 0.25641026 | F13: 0.25641026 | G13: 0.48717949 | H13: 1.034539 | I13: 1.5291909
A14: Team | B14: Struct Attack | C14: Struct Def Weak | D14: GW1 Market xG | E14: GW1 Struct xG | F14: Gap
A15: Arsenal | B15: =VLOOKUP(A15,Team_26_27!$A$2:$U$21,20,FALSE) -> 1.1646206 | C15: =VLOOKUP(A15,Team_26_27!$A$2:$U$21,21,FALSE) -> 0.67296432 | D15: =IFERROR(VLOOKUP(A15,Fixture_Engine!$D$2:$J$21,7,FALSE),"") -> 2.6529358 | E15: =IFERROR(VLOOKUP(A15,Fixture_Engine!$D$2:$H$21,5,FALSE),"") -> 2.249456 | F15: =IF(OR(D15="",E15=""),"",D15-E15) -> 0.40347987
A16: Aston Villa | B16: =VLOOKUP(A16,Team_26_27!$A$2:$U$21,20,FALSE) -> 0.93528526 | C16: =VLOOKUP(A16,Team_26_27!$A$2:$U$21,21,FALSE) -> 1.0103455 | D16: =IFERROR(VLOOKUP(A16,Fixture_Engine!$D$2:$J$21,7,FALSE),"") -> 1.2147039 | E16: =IFERROR(VLOOKUP(A16,Fixture_Engine!$D$2:$H$21,5,FALSE),"") -> 1.1142149 | F16: =IF(OR(D16="",E16=""),"",D16-E16) -> 0.10048904
A17: Bournemouth | B17: =VLOOKUP(A17,Team_26_27!$A$2:$U$21,20,FALSE) -> 1.0910281 | C17: =VLOOKUP(A17,Team_26_27!$A$2:$U$21,21,FALSE) -> 1.0381578 | D17: =IFERROR(VLOOKUP(A17,Fixture_Engine!$D$2:$J$21,7,FALSE),"") -> 0.91917821 | E17: =IFERROR(VLOOKUP(A17,Fixture_Engine!$D$2:$H$21,5,FALSE),"") -> 1.245681 | F17: =IF(OR(D17="",E17=""),"",D17-E17) -> -0.3265028
A18: Brentford | B18: =VLOOKUP(A18,Team_26_27!$A$2:$U$21,20,FALSE) -> 1.0947656 | C18: =VLOOKUP(A18,Team_26_27!$A$2:$U$21,21,FALSE) -> 1.016935 | D18: =IFERROR(VLOOKUP(A18,Fixture_Engine!$D$2:$J$21,7,FALSE),"") -> 1.3720338 | E18: =IFERROR(VLOOKUP(A18,Fixture_Engine!$D$2:$H$21,5,FALSE),"") -> 1.6650091 | F18: =IF(OR(D18="",E18=""),"",D18-E18) -> -0.29297524
A19: Brighton | B19: =VLOOKUP(A19,Team_26_27!$A$2:$U$21,20,FALSE) -> 1.0631331 | C19: =VLOOKUP(A19,Team_26_27!$A$2:$U$21,21,FALSE) -> 0.94708651 | D19: =IFERROR(VLOOKUP(A19,Fixture_Engine!$D$2:$J$21,7,FALSE),"") -> 1.4525482 | E19: =IFERROR(VLOOKUP(A19,Fixture_Engine!$D$2:$H$21,5,FALSE),"") -> 1.6513645 | F19: =IF(OR(D19="",E19=""),"",D19-E19) -> -0.19881629
A20: Chelsea | B20: =VLOOKUP(A20,Team_26_27!$A$2:$U$21,20,FALSE) -> 1.138665 | C20: =VLOOKUP(A20,Team_26_27!$A$2:$U$21,21,FALSE) -> 0.99156076 | D20: =IFERROR(VLOOKUP(A20,Fixture_Engine!$D$2:$J$21,7,FALSE),"") -> 1.5291909 | E20: =IFERROR(VLOOKUP(A20,Fixture_Engine!$D$2:$H$21,5,FALSE),"") -> 1.4365177 | F20: =IF(OR(D20="",E20=""),"",D20-E20) -> 0.092673252
A21: Coventry City | B21: =VLOOKUP(A21,Team_26_27!$A$2:$U$21,20,FALSE) -> 0.78945623 | C21: =VLOOKUP(A21,Team_26_27!$A$2:$U$21,21,FALSE) -> 1.2563413 | D21: =IFERROR(VLOOKUP(A21,Fixture_Engine!$D$2:$J$21,7,FALSE),"") -> 0.52865869 | E21: =IFERROR(VLOOKUP(A21,Fixture_Engine!$D$2:$H$21,5,FALSE),"") -> 0.66827515 | F21: =IF(OR(D21="",E21=""),"",D21-E21) -> -0.13961646
A22: Crystal Palace | B22: =VLOOKUP(A22,Team_26_27!$A$2:$U$21,20,FALSE) -> 1.0527114 | C22: =VLOOKUP(A22,Team_26_27!$A$2:$U$21,21,FALSE) -> 0.98741881 | D22: =IFERROR(VLOOKUP(A22,Fixture_Engine!$D$2:$J$21,7,FALSE),"") -> 1.0054212 | E22: =IFERROR(VLOOKUP(A22,Fixture_Engine!$D$2:$H$21,5,FALSE),"") -> 1.3832447 | F22: =IF(OR(D22="",E22=""),"",D22-E22) -> -0.37782347
A23: Everton | B23: =VLOOKUP(A23,Team_26_27!$A$2:$U$21,20,FALSE) -> 0.91551497 | C23: =VLOOKUP(A23,Team_26_27!$A$2:$U$21,21,FALSE) -> 1.0446108 | D23: =IFERROR(VLOOKUP(A23,Fixture_Engine!$D$2:$J$21,7,FALSE),"") -> 1.3042478 | E23: =IFERROR(VLOOKUP(A23,Fixture_Engine!$D$2:$H$21,5,FALSE),"") -> 1.3897998 | F23: =IF(OR(D23="",E23=""),"",D23-E23) -> -0.085551999
A24: Fulham | B24: =VLOOKUP(A24,Team_26_27!$A$2:$U$21,20,FALSE) -> 0.95122387 | C24: =VLOOKUP(A24,Team_26_27!$A$2:$U$21,21,FALSE) -> 1.0029511 | D24: =IFERROR(VLOOKUP(A24,Fixture_Engine!$D$2:$J$21,7,FALSE),"") -> 1.034539 | E24: =IFERROR(VLOOKUP(A24,Fixture_Engine!$D$2:$H$21,5,FALSE),"") -> 1.450065 | F24: =IF(OR(D24="",E24=""),"",D24-E24) -> -0.41552599
A25: Hull City | B25: =VLOOKUP(A25,Team_26_27!$A$2:$U$21,20,FALSE) -> 0.6979443 | C25: =VLOOKUP(A25,Team_26_27!$A$2:$U$21,21,FALSE) -> 1.3659592 | D25: =IFERROR(VLOOKUP(A25,Fixture_Engine!$D$2:$J$21,7,FALSE),"") -> 0.60545883 | E25: =IFERROR(VLOOKUP(A25,Fixture_Engine!$D$2:$H$21,5,FALSE),"") -> 1.0091683 | F25: =IF(OR(D25="",E25=""),"",D25-E25) -> -0.40370943
A26: Ipswich Town | B26: =VLOOKUP(A26,Team_26_27!$A$2:$U$21,20,FALSE) -> 0.76259947 | C26: =VLOOKUP(A26,Team_26_27!$A$2:$U$21,21,FALSE) -> 1.2336552 | D26: =IFERROR(VLOOKUP(A26,Fixture_Engine!$D$2:$J$21,7,FALSE),"") -> 1.1088257 | E26: =IFERROR(VLOOKUP(A26,Fixture_Engine!$D$2:$H$21,5,FALSE),"") -> 1.1922712 | F26: =IF(OR(D26="",E26=""),"",D26-E26) -> -0.083445563
... A34: Sunderland | B34: =VLOOKUP(A34,Team_26_27!$A$2:$U$21,20,FALSE) -> 0.81270947 | C34: =VLOOKUP(A34,Team_26_27!$A$2:$U$21,21,FALSE) -> 1.016935 | D34: =IFERROR(VLOOKUP(A34,Fixture_Engine!$D$2:$J$21,7,FALSE),"") -> 1.1347602 | E34: =IFERROR(VLOOKUP(A34,Fixture_Engine!$D$2:$H$21,5,FALSE),"") -> 1.261143 | F34: =IF(OR(D34="",E34=""),"",D34-E34) -> -0.12638283
A37: Override architecture: Team_26_27 changes structural channels; Fixture_Engine can override a specific match; GW1_Player can later override minutes.

Sheet Players
A1: Player ID | B1: Code | C1: Player | D1: Full Name | E1: Team | F1: FPL Pos | G1: Start £m | H1: Current £m | I1: Pens Order | J1: Direct FK Order | K1: Corners/IFK Order | L1: Team Join Date | M1: New Club Summer? | N1: Promoted Club? | O1: Manager | P1: Manager Start | Q1: New Manager Summer? | R1: Manager Shift Since Aug-25? | S1: Status | T1: Chance Play GW1 | U1: News | V1: Ownership % | W1: Selectable? | X1: Current Source
A2: 1 | B2: 154561 | C2: Raya | D2: David Raya Martín | E2: Arsenal | F2: GK | G2: 6 | H2: 6 | L2: 2024-07-04 | M2: FALSE | N2: FALSE | O2: Mikel Arteta | P2: 2019-12-22 | Q2: FALSE | R2: FALSE | S2: Available | V2: 0.307 | W2: TRUE | X2: https://fantasy.premierleague.com/
A3: 2 | B3: 109745 | C3: Arrizabalaga | D3: Kepa Arrizabalaga Revuelta | E3: Arsenal | F3: GK | G3: 5 | H3: 5 | L3: 2025-07-01 | M3: FALSE | N3: FALSE | O3: Mikel Arteta | P3: 2019-12-22 | Q3: FALSE | R3: FALSE | S3: Available | V3: 0.002 | W3: TRUE | X3: https://fantasy.premierleague.com/
A4: 3 | B4: 437495 | C4: Meslier | D4: Illan Meslier | E4: Arsenal | F4: GK | G4: 5 | H4: 5 | L4: 2026-07-09 | M4: TRUE | N4: FALSE | O4: Mikel Arteta | P4: 2019-12-22 | Q4: FALSE | R4: FALSE | S4: Available | V4: 0.001 | W4: TRUE | X4: https://fantasy.premierleague.com/
A5: 4 | B5: 226597 | C5: Gabriel | D5: Gabriel dos Santos Magalhães | E5: Arsenal | F5: DEF | G5: 8 | H5: 8 | L5: 2020-09-01 | M5: FALSE | N5: FALSE | O5: Mikel Arteta | P5: 2019-12-22 | Q5: FALSE | R5: FALSE | S5: Available | V5: 0.259 | W5: TRUE | X5: https://fantasy.premierleague.com/
A6: 5 | B6: 445122 | C6: J.Timber | D6: Jurriën Timber | E6: Arsenal | F6: DEF | G6: 6.5 | H6: 6.5 | L6: 2023-07-14 | M6: FALSE | N6: FALSE | O6: Mikel Arteta | P6: 2019-12-22 | Q6: FALSE | R6: FALSE | S6: Injured | T6: 0 | U6: Groin injury - Expected back 21 Aug | V6: 0.005 | W6: TRUE | X6: https://fantasy.premierleague.com/
A7: 6 | B7: 462424 | C7: Saliba | D7: William Saliba | E7: Arsenal | F7: DEF | G7: 6 | H7: 6 | L7: 2019-07-25 | M7: FALSE | N7: FALSE | O7: Mikel Arteta | P7: 2019-12-22 | Q7: FALSE | R7: FALSE | S7: Injured | T7: 0 | U7: Back injury - Unknown return date | V7: 0.005 | W7: TRUE | X7: https://fantasy.premierleague.com/
A8: 7 | B8: 499169 | C8: Lewis-Skelly | D8: Myles Lewis-Skelly | E8: Arsenal | F8: MID | G8: 5.5 | H8: 5.5 | L8: 2022-12-04 | M8: FALSE | N8: FALSE | O8: Mikel Arteta | P8: 2019-12-22 | Q8: FALSE | R8: FALSE | S8: Available | V8: 0.003 | W8: TRUE | X8: https://fantasy.premierleague.com/
A9: 8 | B9: 466075 | C9: Calafiori | D9: Riccardo Calafiori | E9: Arsenal | F9: DEF | G9: 5.5 | H9: 5.5 | L9: 2024-07-29 | M9: FALSE | N9: FALSE | O9: Mikel Arteta | P9: 2019-12-22 | Q9: FALSE | R9: FALSE | S9: Available | V9: 0.153 | W9: TRUE | X9: https://fantasy.premierleague.com/
A10: 9 | B10: 448104 | C10: Hincapie | D10: Piero Hincapié | E10: Arsenal | F10: DEF | G10: 5.5 | H10: 5.5 | L10: 2026-07-01 | M10: TRUE | N10: FALSE | O10: Mikel Arteta | P10: 2019-12-22 | Q10: FALSE | R10: FALSE | S10: Available | V10: 0.044 | W10: TRUE | X10: https://fantasy.premierleague.com/
A11: 10 | B11: 198869 | C11: White | D11: Benjamin White | E11: Arsenal | F11: DEF | G11: 5.5 | H11: 5.5 | L11: 2021-07-30 | M11: FALSE | N11: FALSE | O11: Mikel Arteta | P11: 2019-12-22 | Q11: FALSE | R11: FALSE | S11: Available | T11: 100 | V11: 0.002 | W11: TRUE | X11: https://fantasy.premierleague.com/
A12: 11 | B12: 500040 | C12: Mosquera | D12: Cristhian Mosquera | E12: Arsenal | F12: DEF | G12: 5.5 | H12: 5.5 | L12: 2025-07-24 | M12: FALSE | N12: FALSE | O12: Mikel Arteta | P12: 2019-12-22 | Q12: FALSE | R12: FALSE | S12: Available | V12: 0.169 | W12: TRUE | X12: https://fantasy.premierleague.com/
A13: 12 | B13: 223340 | C13: Saka | D13: Bukayo Saka | E13: Arsenal | F13: MID | G13: 9.5 | H13: 9.5 | I13: 1 | J13: 2 | K13: 6 | L13: 2018-11-28 | M13: FALSE | N13: FALSE | O13: Mikel Arteta | P13: 2019-12-22 | Q13: FALSE | R13: FALSE | S13: Available | V13: 0.106 | W13: TRUE | X13: https://fantasy.premierleague.com/
A14: 13 | B14: 204480 | C14: Rice | D14: Declan Rice | E14: Arsenal | F14: MID | G14: 7.5 | H14: 7.5 | J14: 1 | K14: 5 | L14: 2023-07-15 | M14: FALSE | N14: FALSE | O14: Mikel Arteta | P14: 2019-12-22 | Q14: FALSE | R14: FALSE | S14: Available | V14: 0.223 | W14: TRUE | X14: https://fantasy.premierleague.com/
A15: 14 | B15: 232413 | C15: Eze | D15: Eberechi Eze | E15: Arsenal | F15: MID | G15: 6.5 | H15: 6.5 | J15: 3 | L15: 2025-08-23 | M15: FALSE | N15: FALSE | O15: Mikel Arteta | P15: 2019-12-22 | Q15: FALSE | R15: FALSE | S15: Available | V15: 0.033 | W15: TRUE | X15: https://fantasy.premierleague.com/
A16: 15 | B16: 184029 | C16: Ødegaard | D16: Martin Ødegaard | E16: Arsenal | F16: MID | G16: 6.5 | H16: 6.5 | I16: 3 | K16: 8 | L16: 2021-08-20 | M16: FALSE | N16: FALSE | O16: Mikel Arteta | P16: 2019-12-22 | Q16: FALSE | R16: FALSE | S16: Available | V16: 0.03 | W16: TRUE | X16: https://fantasy.premierleague.com/
A17: 16 | B17: 248857 | C17: Madueke | D17: Noni Madueke | E17: Arsenal | F17: MID | G17: 6.5 | H17: 6.5 | K17: 7 | L17: 2025-07-18 | M17: FALSE | N17: FALSE | O17: Mikel Arteta | P17: 2019-12-22 | Q17: FALSE | R17: FALSE | S17: Available | V17: 0.004 | W17: TRUE | X17: https://fantasy.premierleague.com/
A18: 17 | B18: 195384 | C18: Merino | D18: Mikel Merino Zazón | E18: Arsenal | F18: MID | G18: 6 | H18: 6 | L18: 2024-08-27 | M18: FALSE | N18: FALSE | O18: Mikel Arteta | P18: 2019-12-22 | Q18: FALSE | R18: FALSE | S18: Available | V18: 0.012 | W18: TRUE | X18: https://fantasy.premierleague.com/
A19: 18 | B19: 444145 | C19: Martinelli | D19: Gabriel Martinelli Silva | E19: Arsenal | F19: MID | G19: 6.5 | H19: 6.5 | L19: 2019-07-15 | M19: FALSE | N19: FALSE | O19: Mikel Arteta | P19: 2019-12-22 | Q19: FALSE | R19: FALSE | S19: Available | V19: 0.003 | W19: TRUE | X19: https://fantasy.premierleague.com/
A20: 19 | B20: 481655 | C20: Zubimendi | D20: Martín Zubimendi Ibáñez | E20: Arsenal | F20: MID | G20: 5.5 | H20: 5.5 | L20: 2025-07-06 | M20: FALSE | N20: FALSE | O20: Mikel Arteta | P20: 2019-12-22 | Q20: FALSE | R20: FALSE | S20: Available | V20: 0.015 | W20: TRUE | X20: https://fantasy.premierleague.com/
A21: 20 | B21: 616077 | C21: Dowman | D21: Max Dowman | E21: Arsenal | F21: MID | G21: 5.5 | H21: 5.5 | L21: None | M21: TRUE | N21: FALSE | O21: Mikel Arteta | P21: 2019-12-22 | Q21: FALSE | R21: FALSE | S21: Available | V21: 0.002 | W21: TRUE | X21: https://fantasy.premierleague.com/
A22: 21 | B22: 128295 | C22: Nørgaard | D22: Christian Nørgaard | E22: Arsenal | F22: MID | G22: 5 | H22: 5 | L22: 2025-07-10 | M22: FALSE | N22: FALSE | O22: Mikel Arteta | P22: 2019-12-22 | Q22: FALSE | R22: FALSE | S22: Available | V22: 0.003 | W22: TRUE | X22: https://fantasy.premierleague.com/
A23: 22 | B23: 499175 | C23: Nwaneri | D23: Ethan Nwaneri | E23: Arsenal | F23: MID | G23: 5.5 | H23: 5.5 | L23: 2022-09-17 | M23: FALSE | N23: FALSE | O23: Mikel Arteta | P23: 2019-12-22 | Q23: FALSE | R23: FALSE | S23: Available | V23: 0 | W23: TRUE | X23: https://fantasy.premierleague.com/
A24: 23 | B24: 438098 | C24: Fábio Vieira | D24: Fábio Ferreira Vieira | E24: Arsenal | F24: MID | G24: 5.5 | H24: 5.5 | L24: 2022-06-21 | M24: FALSE | N24: FALSE | O24: Mikel Arteta | P24: 2019-12-22 | Q24: FALSE | R24: FALSE | S24: Available | V24: 0 | W24: TRUE | X24: https://fantasy.premierleague.com/
A25: 24 | B25: 200641 | C25: Nelson | D25: Reiss Nelson | E25: Arsenal | F25: MID | G25: 5.5 | H25: 5.5 | L25: 2017-07-12 | M25: FALSE | N25: FALSE | O25: Mikel Arteta | P25: 2019-12-22 | Q25: FALSE | R25: FALSE | S25: Available | V25: 0 | W25: TRUE | X25: https://fantasy.premierleague.com/
A26: 25 | B26: 224117 | C26: Gyökeres | D26: Viktor Gyökeres | E26: Arsenal | F26: FWD | G26: 7.5 | H26: 7.5 | I26: 2 | L26: 2025-07-26 | M26: FALSE | N26: FALSE | O26: Mikel Arteta | P26: 2019-12-22 | Q26: FALSE | R26: FALSE | S26: Available | V26: 0.13 | W26: TRUE | X26: https://fantasy.premierleague.com/
A27: 26 | B27: 219847 | C27: Havertz | D27: Kai Havertz | E27: Arsenal | F27: FWD | G27: 7.5 | H27: 7.5 | L27: 2023-06-28 | M27: FALSE | N27: FALSE | O27: Mikel Arteta | P27: 2019-12-22 | Q27: FALSE | R27: FALSE | S27: Available | V27: 0.04 | W27: TRUE | X27: https://fantasy.premierleague.com/
A28: 27 | B28: 205651 | C28: G.Jesus | D28: Gabriel Fernando de Jesus | E28: Arsenal | F28: FWD | G28: 6 | H28: 6 | L28: 2022-07-04 | M28: FALSE | N28: FALSE | O28: Mikel Arteta | P28: 2019-12-22 | Q28: FALSE | R28: FALSE | S28: Available | V28: 0.004 | W28: TRUE | X28: https://fantasy.premierleague.com/
A29: 557 | B29: 439509 | C29: Tzolis | D29: Christos Tzolis | E29: Arsenal | F29: MID | G29: 6.5 | H29: 6.5 | L29: 2026-07-23 | M29: TRUE | N29: FALSE | O29: Mikel Arteta | P29: 2019-12-22 | Q29: FALSE | R29: FALSE | S29: Available | V29: 0.017 | W29: TRUE | X29: https://fantasy.premierleague.com/
A30: 28 | B30: 98980 | C30: Martinez | D30: Emiliano Martínez Romero | E30: Aston Villa | F30: GK | G30: 5 | H30: 5 | L30: 2020-09-16 | M30: FALSE | N30: FALSE | O30: Unai Emery | P30: 2022-11-01 | Q30: FALSE | R30: FALSE | S30: Available | V30: 0.046 | W30: TRUE | X30: https://fantasy.premierleague.com/
A31: 29 | B31: 72147 | C31: M.Bizot | D31: Marco Bizot | E31: Aston Villa | F31: GK | G31: 4.5 | H31: 4.5 | L31: 2025-07-15 | M31: FALSE | N31: FALSE | O31: Unai Emery | P31: 2022-11-01 | Q31: FALSE | R31: FALSE | S31: Available | V31: 0.001 | W31: TRUE | X31: https://fantasy.premierleague.com/
A32: 30 | B32: 101188 | C32: Digne | D32: Lucas Digne | E32: Aston Villa | F32: DEF | G32: 4.5 | H32: 4.5 | K32: 4 | L32: 2022-01-13 | M32: FALSE | N32: FALSE | O32: Unai Emery | P32: 2022-11-01 | Q32: FALSE | R32: FALSE | S32: Available | V32: 0.014 | W32: TRUE | X32: https://fantasy.premierleague.com/
A33: 31 | B33: 199798 | C33: Konsa | D33: Ezri Konsa Ngoyo | E33: Aston Villa | F33: DEF | G33: 4.5 | H33: 4.5 | L33: 2019-07-11 | M33: FALSE | N33: FALSE | O33: Unai Emery | P33: 2022-11-01 | Q33: FALSE | R33: FALSE | S33: Available | V33: 0.174 | W33: TRUE | X33: https://fantasy.premierleague.com/
A34: 32 | B34: 199796 | C34: Cash | D34: Matty Cash | E34: Aston Villa | F34: DEF | G34: 4.5 | H34: 4.5 | K34: 5 | L34: 2020-09-03 | M34: FALSE | N34: FALSE | O34: Unai Emery | P34: 2022-11-01 | Q34: FALSE | R34: FALSE | S34: Available | V34: 0.078 | W34: TRUE | X34: https://fantasy.premierleague.com/
A35: 33 | B35: 149484 | C35: Mings | D35: Tyrone Mings | E35: Aston Villa | F35: DEF | G35: 4.5 | H35: 4.5 | L35: 2019-07-08 | M35: FALSE | N35: FALSE | O35: Unai Emery | P35: 2022-11-01 | Q35: FALSE | R35: FALSE | S35: Available | V35: 0.002 | W35: TRUE | X35: https://fantasy.premierleague.com/
A36: 34 | B36: 244954 | C36: Pau | D36: Pau Torres | E36: Aston Villa | F36: DEF | G36: 4.5 | H36: 4.5 | L36: 2023-07-12 | M36: FALSE | N36: FALSE | O36: Unai Emery | P36: 2022-11-01 | Q36: FALSE | R36: FALSE | S36: Available | V36: 0.002 | W36: TRUE | X36: https://fantasy.premierleague.com/
A37: 35 | B37: 515597 | C37: Bogarde | D37: Lamare Bogarde | E37: Aston Villa | F37: MID | G37: 5 | H37: 5 | L37: 2021-01-07 | M37: FALSE | N37: FALSE | O37: Unai Emery | P37: 2022-11-01 | Q37: FALSE | R37: FALSE | S37: Available | V37: 0.001 | W37: TRUE | X37: https://fantasy.premierleague.com/
A38: 36 | B38: 441302 | C38: Maatsen | D38: Ian Maatsen | E38: Aston Villa | F38: DEF | G38: 4.5 | H38: 4.5 | L38: 2024-06-28 | M38: FALSE | N38: FALSE | O38: Unai Emery | P38: 2022-11-01 | Q38: FALSE | R38: FALSE | S38: Available | V38: 0.006 | W38: TRUE | X38: https://fantasy.premierleague.com/
A39: 37 | B39: 184667 | C39: Lindelöf | D39: Victor Lindelöf | E39: Aston Villa | F39: DEF | G39: 4.5 | H39: 4.5 | L39: 2025-09-01 | M39: FALSE | N39: FALSE | O39: Unai Emery | P39: 2022-11-01 | Q39: FALSE | R39: FALSE | S39: Available | V39: 0.002 | W39: TRUE | X39: https://fantasy.premierleague.com/
A40: 38 | B40: 606798 | C40: A.García | D40: Andrés García | E40: Aston Villa | F40: DEF | G40: 4 | H40: 4 | L40: None | M40: TRUE | N40: FALSE | O40: Unai Emery | P40: 2022-11-01 | Q40: FALSE | R40: FALSE | S40: Available | V40: 0.015 | W40: TRUE | X40: https://fantasy.premierleague.com/
A41: 39 | B41: 578545 | C41: Nedeljkovic | D41: Kosta Nedeljkovic | E41: Aston Villa | F41: DEF | G41: 4 | H41: 4 | L41: 2024-01-22 | M41: FALSE | N41: FALSE | O41: Unai Emery | P41: 2022-11-01 | Q41: FALSE | R41: FALSE | S41: Available | V41: 0.004 | W41: TRUE | X41: https://fantasy.premierleague.com/
A42: 41 | B42: 195546 | C42: Buendía | D42: Emiliano Buendía Stati | E42: Aston Villa | F42: MID | G42: 6 | H42: 6 | I42: 1 | J42: 1 | L42: 2021-06-10 | M42: FALSE | N42: FALSE | O42: Unai Emery | P42: 2022-11-01 | Q42: FALSE | R42: FALSE | S42: Available | V42: 0.008 | W42: TRUE | X42: https://fantasy.premierleague.com/
A43: 42 | B43: 485337 | C43: Guessand | D43: Evann Guessand | E43: Aston Villa | F43: MID | G43: 5.5 | H43: 5.5 | L43: 2025-08-08 | M43: FALSE | N43: FALSE | O43: Unai Emery | P43: 2022-11-01 | Q43: FALSE | R43: FALSE | S43: Available | V43: 0 | W43: TRUE | X43: https://fantasy.premierleague.com/
A44: 44 | B44: 215711 | C44: Bailey | D44: Leon Bailey | E44: Aston Villa | F44: MID | G44: 5.5 | H44: 5.5 | L44: 2021-08-04 | M44: FALSE | N44: FALSE | O44: Unai Emery | P44: 2022-11-01 | Q44: FALSE | R44: FALSE | S44: Available | V44: 0.001 | W44: TRUE | X44: https://fantasy.premierleague.com/
A45: 45 | B45: 122806 | C45: McGinn | D45: John McGinn | E45: Aston Villa | F45: MID | G45: 5.5 | H45: 5.5 | K45: 6 | L45: 2018-08-08 | M45: FALSE | N45: FALSE | O45: Unai Emery | P45: 2022-11-01 | Q45: FALSE | R45: FALSE | S45: Available | V45: 0.027 | W45: TRUE | X45: https://fantasy.premierleague.com/
A46: 46 | B46: 88894 | C46: Barkley | D46: Ross Barkley | E46: Aston Villa | F46: MID | G46: 5 | H46: 5 | L46: 2024-07-01 | M46: FALSE | N46: FALSE | O46: Unai Emery | P46: 2022-11-01 | Q46: FALSE | R46: FALSE | S46: Available | V46: 0.002 | W46: TRUE | X46: https://fantasy.premierleague.com/
A47: 47 | B47: 226944 | C47: Kamara | D47: Boubacar Kamara | E47: Aston Villa | F47: MID | G47: 5 | H47: 5 | L47: 2022-06-11 | M47: FALSE | N47: FALSE | O47: Unai Emery | P47: 2022-11-01 | Q47: FALSE | R47: FALSE | S47: Doubtful | T47: 75 | U47: Knee injury - 75% chance of playing | V47: 0.001 | W47: TRUE | X47: https://fantasy.premierleague.com/
A48: 48 | B48: 449871 | C48: Onana | D48: Amadou Onana | E48: Aston Villa | F48: MID | G48: 5 | H48: 5 | L48: 2024-07-22 | M48: FALSE | N48: FALSE | O48: Unai Emery | P48: 2022-11-01 | Q48: FALSE | R48: FALSE | S48: Injured | T48: 0 | U48: Knee injury - Unknown return date | V48: 0 | W48: TRUE | X48: https://fantasy.premierleague.com/
A49: 49 | B49: 469247 | C49: Iling Jr | D49: Samuel Iling-Junior | E49: Aston Villa | F49: MID | G49: 5 | H49: 5 | L49: 2024-07-01 | M49: FALSE | N49: FALSE | O49: Unai Emery | P49: 2022-11-01 | Q49: FALSE | R49: FALSE | S49: Available | V49: 0 | W49: TRUE | X49: https://fantasy.premierleague.com/
A50: 50 | B50: 645618 | C50: Burrowes | D50: Bradley Burrowes | E50: Aston Villa | F50: MID | G50: 4.5 | H50: 4.5 | L50: None | M50: TRUE | N50: FALSE | O50: Unai Emery | P50: 2022-11-01 | Q50: FALSE | R50: FALSE | S50: Available | V50: 0.009 | W50: TRUE | X50: https://fantasy.premierleague.com/
A51: 51 | B51: 577285 | C51: George Hemmings | D51: George Hemmings | E51: Aston Villa | F51: MID | G51: 4.5 | H51: 4.5 | L51: None | M51: TRUE | N51: FALSE | O51: Unai Emery | P51: 2022-11-01 | Q51: FALSE | R51: FALSE | S51: Available | V51: 0.003 | W51: TRUE | X51: https://fantasy.premierleague.com/
A52: 52 | B52: 653481 | C52: Alysson | D52: Alysson Edward Franco da Rocha dos Santos | E52: Aston Villa | F52: MID | G52: 5 | H52: 5 | L52: 2026-01-01 | M52: FALSE | N52: FALSE | O52: Unai Emery | P52: 2022-11-01 | Q52: FALSE | R52: FALSE | S52: Available | V52: 0 | W52: TRUE | X52: https://fantasy.premierleague.com/
A53: 53 | B53: 614071 | C53: Manzambi | D53: Johan Manzambi | E53: Aston Villa | F53: MID | G53: 6 | H53: 6 | L53: 2026-07-17 | M53: TRUE | N53: FALSE | O53: Unai Emery | P53: 2022-11-01 | Q53: FALSE | R53: FALSE | S53: Available | V53: 0.025 | W53: TRUE | X53: https://fantasy.premierleague.com/
A54: 54 | B54: 448089 | C54: Gomes | D54: Joao Gomes | E54: Aston Villa | F54: MID | G54: 5.5 | H54: 5.5 | L54: 2026-07-20 | M54: TRUE | N54: FALSE | O54: Unai Emery | P54: 2022-11-01 | Q54: FALSE | R54: FALSE | S54: Available | V54: 0.003 | W54: TRUE | X54: https://fantasy.premierleague.com/
A55: 55 | B55: 178301 | C55: Watkins | D55: Ollie Watkins | E55: Aston Villa | F55: FWD | G55: 8 | H55: 8 | I55: 2 | L55: 2020-09-09 | M55: FALSE | N55: FALSE | O55: Unai Emery | P55: 2022-11-01 | Q55: FALSE | R55: FALSE | S55: Available | V55: 0.124 | W55: TRUE | X55: https://fantasy.premierleague.com/
A56: 56 | B56: 173879 | C56: Abraham | D56: Tammy Abraham | E56: Aston Villa | F56: FWD | G56: 5.5 | H56: 5.5 | L56: 2026-01-27 | M56: FALSE | N56: FALSE | O56: Unai Emery | P56: 2022-11-01 | Q56: FALSE | R56: FALSE | S56: Injured | T56: 0 | U56: Shoulder injury - Expected back 23 Aug | V56: 0 | W56: TRUE | X56: https://fantasy.premierleague.com/
A57: 160 | B57: 493105 | C57: Garnacho | D57: Alejandro Garnacho Ferreyra | E57: Aston Villa | F57: MID | G57: 6 | H57: 6 | L57: 2026-07-23 | M57: TRUE | N57: FALSE | O57: Unai Emery | P57: 2022-11-01 | Q57: FALSE | R57: FALSE | S57: Available | V57: 0.011 | W57: TRUE | X57: https://fantasy.premierleague.com/
A58: 57 | B58: 457569 | C58: Petrović | D58: Đorđe Petrović | E58: Bournemouth | F58: GK | G58: 4.5 | H58: 4.5 | L58: 2025-07-16 | M58: FALSE | N58: FALSE | O58: Marco Rose | P58: 2026-06-01 | Q58: TRUE | R58: TRUE | S58: Available | V58: 0.036 | W58: TRUE | X58: https://fantasy.premierleague.com/
A59: 58 | B59: 40383 | C59: Forster | D59: Fraser Forster | E59: Bournemouth | F59: GK | G59: 4 | H59: 4 | L59: 2026-01-02 | M59: FALSE | N59: FALSE | O59: Marco Rose | P59: 2026-06-01 | Q59: TRUE | R59: TRUE | S59: Available | V59: 0.031 | W59: TRUE | X59: https://fantasy.premierleague.com/
A60: 59 | B60: 444172 | C60: Dennis | D60: Will Dennis | E60: Bournemouth | F60: GK | G60: 4 | H60: 4 | L60: 2019-08-01 | M60: FALSE | N60: FALSE | O60: Marco Rose | P60: 2026-06-01 | Q60: TRUE | R60: TRUE | S60: Available | V60: 0.002 | W60: TRUE | X60: https://fantasy.premierleague.com/
A61: 60 | B61: 463981 | C61: Hill | D61: James Hill | E61: Bournemouth | F61: DEF | G61: 5.5 | H61: 5.5 | L61: 2022-01-05 | M61: FALSE | N61: FALSE | O61: Marco Rose | P61: 2026-06-01 | Q61: TRUE | R61: TRUE | S61: Available | V61: 0.013 | W61: TRUE | X61: https://fantasy.premierleague.com/
A62: 61 | B62: 494521 | C62: Truffert | D62: Adrien Truffert | E62: Bournemouth | F62: DEF | G62: 5.5 | H62: 5.5 | L62: 2025-06-16 | M62: FALSE | N62: FALSE | O62: Marco Rose | P62: 2026-06-01 | Q62: TRUE | R62: TRUE | S62: Available | V62: 0.046 | W62: TRUE | X62: https://fantasy.premierleague.com/
A63: 62 | B63: 242882 | C63: Diakité | D63: Bafodé Diakité | E63: Bournemouth | F63: DEF | G63: 5 | H63: 5 | L63: 2025-08-13 | M63: FALSE | N63: FALSE | O63: Marco Rose | P63: 2026-06-01 | Q63: TRUE | R63: TRUE | S63: Available | V63: 0.002 | W63: TRUE | X63: https://fantasy.premierleague.com/
A64: 63 | B64: 620487 | C64: Milosavljević | D64: Veljko Milosavljevic | E64: Bournemouth | F64: DEF | G64: 5 | H64: 5 | L64: 2025-09-01 | M64: FALSE | N64: FALSE | O64: Marco Rose | P64: 2026-06-01 | Q64: TRUE | R64: TRUE | S64: Available | V64: 0.001 | W64: TRUE | X64: https://fantasy.premierleague.com/
A65: 64 | B65: 54469 | C65: Smith | D65: Adam Smith | E65: Bournemouth | F65: DEF | G65: 4.5 | H65: 4.5 | L65: 2014-01-28 | M65: FALSE | N65: FALSE | O65: Marco Rose | P65: 2026-06-01 | Q65: TRUE | R65: TRUE | S65: Available | V65: 0.001 | W65: TRUE | X65: https://fantasy.premierleague.com/
A66: 65 | B66: 436893 | C66: J.Araujo | D66: Julián Araujo Zúñiga | E66: Bournemouth | F66: DEF | G66: 4.5 | H66: 4.5 | L66: 2024-08-13 | M66: FALSE | N66: FALSE | O66: Marco Rose | P66: 2026-06-01 | Q66: TRUE | R66: TRUE | S66: Available | V66: 0.001 | W66: TRUE | X66: https://fantasy.premierleague.com/
A67: 66 | B67: 575901 | C67: Soler | D67: Julio Soler Barreto | E67: Bournemouth | F67: DEF | G67: 4 | H67: 4 | L67: 2025-01-07 | M67: FALSE | N67: FALSE | O67: Marco Rose | P67: 2026-06-01 | Q67: TRUE | R67: TRUE | S67: Available | V67: 0.006 | W67: TRUE | X67: https://fantasy.premierleague.com/
A68: 67 | B68: 499604 | C68: Rayan | D68: Rayan Vitor Simplício Rocha | E68: Bournemouth | F68: MID | G68: 6.5 | H68: 6.5 | L68: 2026-01-27 | M68: FALSE | N68: FALSE | O68: Marco Rose | P68: 2026-06-01 | Q68: TRUE | R68: TRUE | S68: Available | V68: 0.034 | W68: TRUE | X68: https://fantasy.premierleague.com/
A69: 68 | B69: 201658 | C69: Tavernier | D69: Marcus Tavernier | E69: Bournemouth | F69: MID | G69: 6 | H69: 6 | I69: 3 | J69: 1 | K69: 6 | L69: 2022-08-01 | M69: FALSE | N69: FALSE | O69: Marco Rose | P69: 2026-06-01 | Q69: TRUE | R69: TRUE | S69: Available | V69: 0.019 | W69: TRUE | X69: https://fantasy.premierleague.com/
A70: 69 | B70: 503139 | C70: Scott | D70: Alex Scott | E70: Bournemouth | F70: MID | G70: 6 | H70: 6 | J70: 4 | K70: 7 | L70: 2023-08-10 | M70: FALSE | N70: FALSE | O70: Marco Rose | P70: 2026-06-01 | Q70: TRUE | R70: TRUE | S70: Available | V70: 0.016 | W70: TRUE | X70: https://fantasy.premierleague.com/
A71: 70 | B71: 222683 | C71: Kluivert | D71: Justin Kluivert | E71: Bournemouth | F71: MID | G71: 6 | H71: 6 | I71: 2 | J71: 2 | L71: 2023-07-01 | M71: FALSE | N71: FALSE | O71: Marco Rose | P71: 2026-06-01 | Q71: TRUE | R71: TRUE | S71: Available | V71: 0.009 | W71: TRUE | X71: https://fantasy.premierleague.com/
A72: 71 | B72: 155408 | C72: Cook | D72: Lewis Cook | E72: Bournemouth | F72: MID | G72: 5 | H72: 5 | K72: 8 | L72: 2016-07-08 | M72: FALSE | N72: FALSE | O72: Marco Rose | P72: 2026-06-01 | Q72: TRUE | R72: TRUE | S72: Available | V72: 0.001 | W72: TRUE | X72: https://fantasy.premierleague.com/
A73: 72 | B73: 496208 | C73: Gannon-Doak | D73: Ben Gannon-Doak | E73: Bournemouth | F73: MID | G73: 5 | H73: 5 | L73: 2025-08-18 | M73: FALSE | N73: FALSE | O73: Marco Rose | P73: 2026-06-01 | Q73: TRUE | R73: TRUE | S73: Available | V73: 0.001 | W73: TRUE | X73: https://fantasy.premierleague.com/
A74: 73 | B74: 200785 | C74: Adams | D74: Tyler Adams | E74: Bournemouth | F74: MID | G74: 5 | H74: 5 | L74: 2023-08-20 | M74: FALSE | N74: FALSE | O74: Marco Rose | P74: 2026-06-01 | Q74: TRUE | R74: TRUE | S74: Available | V74: 0.007 | W74: TRUE | X74: https://fantasy.premierleague.com/
A75: 74 | B75: 111317 | C75: Brooks | D75: David Brooks | E75: Bournemouth | F75: MID | G75: 5 | H75: 5 | J75: 3 | K75: 9 | L75: 2018-07-01 | M75: FALSE | N75: FALSE | O75: Marco Rose | P75: 2026-06-01 | Q75: TRUE | R75: TRUE | S75: Available | V75: 0.002 | W75: TRUE | X75: https://fantasy.premierleague.com/
A76: 75 | B76: 158499 | C76: Christie | D76: Ryan Christie | E76: Bournemouth | F76: MID | G76: 5 | H76: 5 | K76: 10 | L76: 2021-08-31 | M76: FALSE | N76: FALSE | O76: Marco Rose | P76: 2026-06-01 | Q76: TRUE | R76: TRUE | S76: Suspended | T76: 0 | U76: Suspended until 29 Aug | V76: 0 | W76: TRUE | X76: https://fantasy.premierleague.com/
A77: 76 | B77: 614574 | C77: Tóth.A | D77: Alex Tóth | E77: Bournemouth | F77: MID | G77: 5 | H77: 5 | L77: 2026-01-20 | M77: FALSE | N77: FALSE | O77: Marco Rose | P77: 2026-06-01 | Q77: TRUE | R77: TRUE | S77: Available | V77: 0 | W77: TRUE | X77: https://fantasy.premierleague.com/
A78: 77 | B78: 489888 | C78: Adli | D78: Amine Adli | E78: Bournemouth | F78: MID | G78: 5 | H78: 5 | L78: 2025-08-21 | M78: FALSE | N78: FALSE | O78: Marco Rose | P78: 2026-06-01 | Q78: TRUE | R78: TRUE | S78: Available | V78: 0.002 | W78: TRUE | X78: https://fantasy.premierleague.com/
A79: 78 | B79: 560262 | C79: Kroupi.Jr | D79: Junior Kroupi | E79: Bournemouth | F79: MID | G79: 7.5 | H79: 7.5 | I79: 1 | L79: 2025-02-02 | M79: FALSE | N79: FALSE | O79: Marco Rose | P79: 2026-06-01 | Q79: TRUE | R79: TRUE | S79: Injured | T79: 0 | U79: Foot injury - Unknown return date | V79: 0.062 | W79: TRUE | X79: https://fantasy.premierleague.com/
A80: 79 | B80: 444102 | C80: Evanilson | D80: Francisco Evanilson de Lima Barbosa | E80: Bournemouth | F80: FWD | G80: 6 | H80: 6 | L80: 2024-08-16 | M80: FALSE | N80: FALSE | O80: Marco Rose | P80: 2026-06-01 | Q80: TRUE | R80: TRUE | S80: Available | V80: 0.02 | W80: TRUE | X80: https://fantasy.premierleague.com/
A81: 80 | B81: 168636 | C81: Enes Ünal | D81: Enes Ünal | E81: Bournemouth | F81: FWD | G81: 5.5 | H81: 5.5 | J81: 5 | L81: 2024-07-01 | M81: FALSE | N81: FALSE | O81: Marco Rose | P81: 2026-06-01 | Q81: TRUE | R81: TRUE | S81: Available | V81: 0.002 | W81: TRUE | X81: https://fantasy.premierleague.com/
A82: 81 | B82: 561245 | C82: Rodríguez | D82: Álvaro Rodríguez | E82: Bournemouth | F82: FWD | G82: 6 | H82: 6 | L82: 2026-07-14 | M82: TRUE | N82: FALSE | O82: Marco Rose | P82: 2026-06-01 | Q82: TRUE | R82: TRUE | S82: Available | V82: 0.003 | W82: TRUE | X82: https://fantasy.premierleague.com/
A83: 566 | B83: 483067 | C83: Silva | D83: António João Pereira de Albuquerque Tavares da Silva | E83: Bournemouth | F83: DEF | G83: 5 | H83: 5 | L83: 2026-08-01 | M83: TRUE | N83: FALSE | O83: Marco Rose | P83: 2026-06-01 | Q83: TRUE | R83: TRUE | S83: Available | V83: 0 | W83: TRUE | X83: https://fantasy.premierleague.com/
A84: 82 | B84: 200720 | C84: Kelleher | D84: Caoimhín Kelleher | E84: Brentford | F84: GK | G84: 5 | H84: 5 | L84: 2025-06-03 | M84: FALSE | N84: FALSE | O84: Keith Andrews | P84: 2025-06-27 | Q84: FALSE | R84: FALSE | S84: Available | V84: 0.056 | W84: TRUE | X84: https://fantasy.premierleague.com/
A85: 83 | B85: 507433 | C85: Valdimarsson | D85: Hákon Rafn Valdimarsson | E85: Brentford | F85: GK | G85: 4.5 | H85: 4.5 | L85: 2024-01-26 | M85: FALSE | N85: FALSE | O85: Keith Andrews | P85: 2025-06-27 | Q85: FALSE | R85: FALSE | S85: Available | V85: 0.001 | W85: TRUE | X85: https://fantasy.premierleague.com/
A86: 84 | B86: 432830 | C86: Collins | D86: Nathan Collins | E86: Brentford | F86: DEF | G86: 5.5 | H86: 5.5 | L86: 2023-07-04 | M86: FALSE | N86: FALSE | O86: Keith Andrews | P86: 2025-06-27 | Q86: FALSE | R86: FALSE | S86: Available | V86: 0.02 | W86: TRUE | X86: https://fantasy.premierleague.com/
A87: 85 | B87: 444765 | C87: Van den Berg | D87: Sepp van den Berg | E87: Brentford | F87: DEF | G87: 5 | H87: 5 | L87: 2024-08-22 | M87: FALSE | N87: FALSE | O87: Keith Andrews | P87: 2025-06-27 | Q87: FALSE | R87: FALSE | S87: Available | V87: 0.007 | W87: TRUE | X87: https://fantasy.premierleague.com/
A88: 86 | B88: 249231 | C88: Lewis-Potter | D88: Keane Lewis-Potter | E88: Brentford | F88: MID | G88: 5.5 | H88: 5.5 | J88: 1 | L88: 2022-07-12 | M88: FALSE | N88: FALSE | O88: Keith Andrews | P88: 2025-06-27 | Q88: FALSE | R88: FALSE | S88: Available | V88: 0.005 | W88: TRUE | X88: https://fantasy.premierleague.com/
A89: 87 | B89: 191866 | C89: Ajer | D89: Kristoffer Ajer | E89: Brentford | F89: DEF | G89: 4.5 | H89: 4.5 | L89: 2021-07-21 | M89: FALSE | N89: FALSE | O89: Keith Andrews | P89: 2025-06-27 | Q89: FALSE | R89: FALSE | S89: Available | V89: 0.012 | W89: TRUE | X89: https://fantasy.premierleague.com/
A90: 88 | B90: 607464 | C90: Kayode | D90: Michael Kayode | E90: Brentford | F90: DEF | G90: 4.5 | H90: 4.5 | L90: 2025-07-01 | M90: FALSE | N90: FALSE | O90: Keith Andrews | P90: 2025-06-27 | Q90: FALSE | R90: FALSE | S90: Available | V90: 0.041 | W90: TRUE | X90: https://fantasy.premierleague.com/
A91: 89 | B91: 194010 | C91: Henry | D91: Rico Henry | E91: Brentford | F91: DEF | G91: 4.5 | H91: 4.5 | L91: 2016-08-31 | M91: FALSE | N91: FALSE | O91: Keith Andrews | P91: 2025-06-27 | Q91: FALSE | R91: FALSE | S91: Available | V91: 0.002 | W91: TRUE | X91: https://fantasy.premierleague.com/
A92: 90 | B92: 472713 | C92: Hickey | D92: Aaron Hickey | E92: Brentford | F92: DEF | G92: 4.5 | H92: 4.5 | L92: 2022-07-09 | M92: FALSE | N92: FALSE | O92: Keith Andrews | P92: 2025-06-27 | Q92: FALSE | R92: FALSE | S92: Available | V92: 0.001 | W92: TRUE | X92: https://fantasy.premierleague.com/
A93: 91 | B93: 231065 | C93: Pinnock | D93: Ethan Pinnock | E93: Brentford | F93: DEF | G93: 4.5 | H93: 4.5 | L93: 2019-07-02 | M93: FALSE | N93: FALSE | O93: Keith Andrews | P93: 2025-06-27 | Q93: FALSE | R93: FALSE | S93: Available | V93: 0.001 | W93: TRUE | X93: https://fantasy.premierleague.com/
A94: 92 | B94: 570241 | C94: Ji-soo | D94: Kim Ji-soo | E94: Brentford | F94: DEF | G94: 4.5 | H94: 4.5 | L94: 2023-07-20 | M94: FALSE | N94: FALSE | O94: Keith Andrews | P94: 2025-06-27 | Q94: FALSE | R94: FALSE | S94: Available | V94: 0 | W94: TRUE | X94: https://fantasy.premierleague.com/
A95: 93 | B95: 513086 | C95: Schuster | D95: Jannik Schuster | E95: Brentford | F95: DEF | G95: 4.5 | H95: 4.5 | L95: 2026-06-15 | M95: TRUE | N95: FALSE | O95: Keith Andrews | P95: 2025-06-27 | Q95: FALSE | R95: FALSE | S95: Available | V95: 0.001 | W95: TRUE | X95: https://fantasy.premierleague.com/
A96: 94 | B96: 513418 | C96: Schade | D96: Kevin Schade | E96: Brentford | F96: MID | G96: 6 | H96: 6 | I96: 2 | L96: 2023-07-01 | M96: FALSE | N96: FALSE | O96: Keith Andrews | P96: 2025-06-27 | Q96: FALSE | R96: FALSE | S96: Available | V96: 0.023 | W96: TRUE | X96: https://fantasy.premierleague.com/
A97: 95 | B97: 533463 | C97: O.Dango | D97: Dango Ouattara | E97: Brentford | F97: MID | G97: 6.5 | H97: 6.5 | K97: 8 | L97: 2025-08-16 | M97: FALSE | N97: FALSE | O97: Keith Andrews | P97: 2025-06-27 | Q97: FALSE | R97: FALSE | S97: Available | V97: 0.013 | W97: TRUE | X97: https://fantasy.premierleague.com/
A98: 96 | B98: 440089 | C98: Damsgaard | D98: Mikkel Damsgaard | E98: Brentford | F98: MID | G98: 5.5 | H98: 5.5 | J98: 3 | K98: 6 | L98: 2022-08-10 | M98: FALSE | N98: FALSE | O98: Keith Andrews | P98: 2025-06-27 | Q98: FALSE | R98: FALSE | S98: Available | V98: 0.007 | W98: TRUE | X98: https://fantasy.premierleague.com/
A99: 97 | B99: 207283 | C99: Jensen | D99: Mathias Jensen | E99: Brentford | F99: MID | G99: 5.5 | H99: 5.5 | I99: 3 | J99: 2 | K99: 5 | L99: 2019-07-10 | M99: FALSE | N99: FALSE | O99: Keith Andrews | P99: 2025-06-27 | Q99: FALSE | R99: FALSE | S99: Available | V99: 0.001 | W99: TRUE | X99: https://fantasy.premierleague.com/
A100: 98 | B100: 204580 | C100: Janelt | D100: Vitaly Janelt | E100: Brentford | F100: MID | G100: 5 | H100: 5 | K100: 7 | L100: 2020-10-03 | M100: FALSE | N100: FALSE | O100: Keith Andrews | P100: 2025-06-27 | Q100: FALSE | R100: FALSE | S100: Available | V100: 0.001 | W100: TRUE | X100: https://fantasy.premierleague.com/
...

Sheet Attack_Priors
A1: Player ID | B1: Player | C1: Team | D1: FPL Pos | E1: Hist League | F1: Hist Team | G1: Hist Mins | H1: Hist xG | I1: Hist xA | J1: Hist xG90 | K1: Hist xA90 | L1: Hist Team xG | M1: Hist Team xG/Match | N1: Hist xG Share | O1: Hist xA Share | P1: Base Min Weight | Q1: League Reliability | R1: Team Changed? | S1: Transport Reliability | T1: New Manager Summer? | U1: Manager Reliability | V1: Effective Weight | W1: Pos xG Share Prior | X1: Pos xA Share Prior | Y1: xG Share Prior | Z1: xA Share Prior | AA1: Role xG Share Adj | AB1: Role xA Share Adj | AC1: Current xG Share Prior | AD1: Current xA Share Prior | AE1: Uncertainty | AF1: History Quality | AG1: Pens Order | AH1: Direct FK Order | AI1: Corners/IFK Order | AJ1: Manual Review? | AK1: History Source | AL1: Source URL | AM1: Notes | AN1: Hist Pens Order | AO1: Hist Pens Missed | AP1: Penalty Contamination? | AQ1: npxG Status
A2: 1 | B2: Raya | C2: Arsenal | D2: GK | E2: Premier League | F2: Arsenal | G2: 3330 | H2: 0 | I2: 0.07 | J2: 0 | K2: 0.0018918919 | L2: 65.6 | M2: 1.7263158 | N2: 0 | O2: 0.001095913 | P2: =IFERROR(G2/(G2+Priors!$H$3),0) -> 0.76905312 | Q2: =IF(E2="Premier League",Priors!$H$4,IF(E2="Championship",Priors!$H$5,Priors!$H$8)) -> 1 | R2: FALSE | S2: =IF(R2=TRUE,Priors!$H$6,1) -> 1 | T2: FALSE | U2: =IF(T2=TRUE,Priors!$H$7,1) -> 1 | V2: =P2*Q2*S2*U2 -> 0.76905312 | W2: =VLOOKUP(D2,Priors!$A$3:$C$6,2,FALSE) -> 0.00016719535 | X2: =VLOOKUP(D2,Priors!$A$3:$C$6,3,FALSE) -> 0.0013793616 | Y2: =IF(N2="",W2,V2*N2+(1-V2)*W2) -> 3.8613245e-05 | Z2: =IF(O2="",X2,V2*O2+(1-V2)*X2) -> 0.0011613746 | AA2: 1 | AB2: 1 | AC2: =Y2*AA2 -> 3.8613245e-05 | AD2: =Z2*AB2 -> 0.0011613746 | AE2: =1-V2 -> 0.23094688 | AF2: PL history | AJ2: FALSE | AK2: FPL Core Insights / official FPL historical feed | AL2: https://github.com/olbauday/FPL-Core-Insights/tree/main/data/2025-2026 | AO2: 0 | AP2: FALSE | AQ2: Total xG retained; low penalty contamination
A3: 2 | B3: Arrizabalaga | C3: Arsenal | D3: GK | E3: Premier League | F3: Arsenal | G3: 90 | H3: 0 | I3: 0 | J3: 0 | K3: 0 | L3: 65.6 | M3: 1.7263158 | N3: 0 | O3: 0 | P3: =IFERROR(G3/(G3+Priors!$H$3),0) -> 0.082568807 | Q3: =IF(E3="Premier League",Priors!$H$4,IF(E3="Championship",Priors!$H$5,Priors!$H$8)) -> 1 | R3: FALSE | S3: =IF(R3=TRUE,Priors!$H$6,1) -> 1 | T3: FALSE | U3: =IF(T3=TRUE,Priors!$H$7,1) -> 1 | V3: =P3*Q3*S3*U3 -> 0.082568807 | W3: =VLOOKUP(D3,Priors!$A$3:$C$6,2,FALSE) -> 0.00016719535 | X3: =VLOOKUP(D3,Priors!$A$3:$C$6,3,FALSE) -> 0.0013793616 | Y3: =IF(N3="",W3,V3*N3+(1-V3)*W3) -> 0.00015339023 | Z3: =IF(O3="",X3,V3*O3+(1-V3)*X3) -> 0.0012654694 | AA3: 1 | AB3: 1 | AC3: =Y3*AA3 -> 0.00015339023 | AD3: =Z3*AB3 -> 0.0012654694 | AE3: =1-V3 -> 0.91743119 | AF3: PL history | AJ3: TRUE | AK3: FPL Core Insights / official FPL historical feed | AL3: https://github.com/olbauday/FPL-Core-Insights/tree/main/data/2025-2026 | AO3: 0 | AP3: FALSE | AQ3: Total xG retained; low penalty contamination
A4: 3 | B4: Meslier | C4: Arsenal | D4: GK | E4: Missing/non-PL | P4: =IFERROR(G4/(G4+Priors!$H$3),0) -> 0 | Q4: =IF(E4="Premier League",Priors!$H$4,IF(E4="Championship",Priors!$H$5,Priors!$H$8)) -> 0 | R4: FALSE | S4: =IF(R4=TRUE,Priors!$H$6,1) -> 1 | T4: FALSE | U4: =IF(T4=TRUE,Priors!$H$7,1) -> 1 | V4: =P4*Q4*S4*U4 -> 0 | W4: =VLOOKUP(D4,Priors!$A$3:$C$6,2,FALSE) -> 0.00016719535 | X4: =VLOOKUP(D4,Priors!$A$3:$C$6,3,FALSE) -> 0.0013793616 | Y4: =IF(N4="",W4,V4*N4+(1-V4)*W4) -> 0.00016719535 | Z4: =IF(O4="",X4,V4*O4+(1-V4)*X4) -> 0.0013793616 | AA4: 1 | AB4: 1 | AC4: =Y4*AA4 -> 0.00016719535 | AD4: =Z4*AB4 -> 0.0013793616 | AE4: =1-V4 -> 1 | AF4: Missing/non-PL | AJ4: TRUE | AK4: No reliable 25/26 history loaded | AO4: 0 | AP4: FALSE | AQ4: Total xG retained; low penalty contamination
A5: 4 | B5: Gabriel | C5: Arsenal | D5: DEF | E5: Premier League | F5: Arsenal | G5: 2750 | H5: 2.94 | I5: 1.75 | J5: 0.096218182 | K5: 0.057272727 | L5: 65.6 | M5: 1.7263158 | N5: 0.055736142 | O5: 0.033176275 | P5: =IFERROR(G5/(G5+Priors!$H$3),0) -> 0.73333333 | Q5: =IF(E5="Premier League",Priors!$H$4,IF(E5="Championship",Priors!$H$5,Priors!$H$8)) -> 1 | R5: FALSE | S5: =IF(R5=TRUE,Priors!$H$6,1) -> 1 | T5: FALSE | U5: =IF(T5=TRUE,Priors!$H$7,1) -> 1 | V5: =P5*Q5*S5*U5 -> 0.73333333 | W5: =VLOOKUP(D5,Priors!$A$3:$C$6,2,FALSE) -> 0.041142361 | X5: =VLOOKUP(D5,Priors!$A$3:$C$6,3,FALSE) -> 0.04051308 | Y5: =IF(N5="",W5,V5*N5+(1-V5)*W5) -> 0.051844467 | Z5: =IF(O5="",X5,V5*O5+(1-V5)*X5) -> 0.035132756 | AA5: 1 | AB5: 1 | AC5: =Y5*AA5 -> 0.051844467 | AD5: =Z5*AB5 -> 0.035132756 | AE5: =1-V5 -> 0.26666667 | AF5: PL history | AJ5: FALSE | AK5: FPL Core Insights / official FPL historical feed | AL5: https://github.com/olbauday/FPL-Core-Insights/tree/main/data/2025-2026 | AO5: 0 | AP5: FALSE | AQ5: Total xG retained; low penalty contamination
A6: 5 | B6: J.Timber | C6: Arsenal | D6: DEF | E6: Premier League | F6: Arsenal | G6: 2452 | H6: 4.71 | I6: 1.53 | J6: 0.17287928 | K6: 0.056158238 | L6: 65.6 | M6: 1.7263158 | N6: 0.10014349 | O6: 0.032530687 | P6: =IFERROR(G6/(G6+Priors!$H$3),0) -> 0.71031286 | Q6: =IF(E6="Premier League",Priors!$H$4,IF(E6="Championship",Priors!$H$5,Priors!$H$8)) -> 1 | R6: FALSE | S6: =IF(R6=TRUE,Priors!$H$6,1) -> 1 | T6: FALSE | U6: =IF(T6=TRUE,Priors!$H$7,1) -> 1 | V6: =P6*Q6*S6*U6 -> 0.71031286 | W6: =VLOOKUP(D6,Priors!$A$3:$C$6,2,FALSE) -> 0.041142361 | X6: =VLOOKUP(D6,Priors!$A$3:$C$6,3,FALSE) -> 0.04051308 | Y6: =IF(N6="",W6,V6*N6+(1-V6)*W6) -> 0.08305162 | Z6: =IF(O6="",X6,V6*O6+(1-V6)*X6) -> 0.034843083 | AA6: 1 | AB6: 1 | AC6: =Y6*AA6 -> 0.08305162 | AD6: =Z6*AB6 -> 0.034843083 | AE6: =1-V6 -> 0.28968714 | AF6: PL history | AJ6: FALSE | AK6: FPL Core Insights / official FPL historical feed | AL6: https://github.com/olbauday/FPL-Core-Insights/tree/main/data/2025-2026 | AO6: 0 | AP6: FALSE | AQ6: Total xG retained; low penalty contamination
A7: 6 | B7: Saliba | C7: Arsenal | D7: DEF | E7: Premier League | F7: Arsenal | G7: 2614 | H7: 0.88 | I7: 1.21 | J7: 0.030298393 | K7: 0.041660291 | L7: 65.6 | M7: 1.7263158 | N7: 0.017550899 | O7: 0.024132485 | P7: =IFERROR(G7/(G7+Priors!$H$3),0) -> 0.72329828 | Q7: =IF(E7="Premier League",Priors!$H$4,IF(E7="Championship",Priors!$H$5,Priors!$H$8)) -> 1 | R7: FALSE | S7: =IF(R7=TRUE,Priors!$H$6,1) -> 1 | T7: FALSE | U7: =IF(T7=TRUE,Priors!$H$7,1) -> 1 | V7: =P7*Q7*S7*U7 -> 0.72329828 | W7: =VLOOKUP(D7,Priors!$A$3:$C$6,2,FALSE) -> 0.041142361 | X7: =VLOOKUP(D7,Priors!$A$3:$C$6,3,FALSE) -> 0.04051308 | Y7: =IF(N7="",W7,V7*N7+(1-V7)*W7) -> 0.024078697 | Z7: =IF(O7="",X7,V7*O7+(1-V7)*X7) -> 0.028665024 | AA7: 1 | AB7: 1 | AC7: =Y7*AA7 -> 0.024078697 | AD7: =Z7*AB7 -> 0.028665024 | AE7: =1-V7 -> 0.27670172 | AF7: PL history | AJ7: FALSE | AK7: FPL Core Insights / official FPL historical feed | AL7: https://github.com/olbauday/FPL-Core-Insights/tree/main/data/2025-2026 | AO7: 0 | AP7: FALSE | AQ7: Total xG retained; low penalty contamination
A8: 7 | B8: Lewis-Skelly | C8: Arsenal | D8: MID | E8: Premier League | F8: Arsenal | G8: 697 | H8: 0.1 | I8: 0.2 | J8: 0.012912482 | K8: 0.025824964 | L8: 65.6 | M8: 1.7263158 | N8: 0.0074797914 | O8: 0.014959583 | P8: =IFERROR(G8/(G8+Priors!$H$3),0) -> 0.41072481 | Q8: =IF(E8="Premier League",Priors!$H$4,IF(E8="Championship",Priors!$H$5,Priors!$H$8)) -> 1 | R8: FALSE | S8: =IF(R8=TRUE,Priors!$H$6,1) -> 1 | T8: FALSE | U8: =IF(T8=TRUE,Priors!$H$7,1) -> 1 | V8: =P8*Q8*S8*U8 -> 0.41072481 | W8: =VLOOKUP(D8,Priors!$A$3:$C$6,2,FALSE) -> 0.10751786 | X8: =VLOOKUP(D8,Priors!$A$3:$C$6,3,FALSE) -> 0.090240672 | Y8: =IF(N8="",W8,V8*N8+(1-V8)*W8) -> 0.066429744 | Z8: =IF(O8="",X8,V8*O8+(1-V8)*X8) -> 0.059320861 | AA8: 1 | AB8: 1 | AC8: =Y8*AA8 -> 0.066429744 | AD8: =Z8*AB8 -> 0.059320861 | AE8: =1-V8 -> 0.58927519 | AF8: PL history | AJ8: TRUE | AK8: FPL Core Insights / official FPL historical feed | AL8: https://github.com/olbauday/FPL-Core-Insights/tree/main/data/2025-2026 | AO8: 0 | AP8: FALSE | AQ8: Total xG retained; low penalty contamination
A9: 8 | B9: Calafiori | C9: Arsenal | D9: DEF | E9: Premier League | F9: Arsenal | G9: 1697 | H9: 3.36 | I9: 0.76 | J9: 0.17819682 | K9: 0.040306423 | L9: 65.6 | M9: 1.7263158 | N9: 0.10322377 | O9: 0.023348233 | P9: =IFERROR(G9/(G9+Priors!$H$3),0) -> 0.62921765 | Q9: =IF(E9="Premier League",Priors!$H$4,IF(E9="Championship",Priors!$H$5,Priors!$H$8)) -> 1 | R9: FALSE | S9: =IF(R9=TRUE,Priors!$H$6,1) -> 1 | T9: FALSE | U9: =IF(T9=TRUE,Priors!$H$7,1) -> 1 | V9: =P9*Q9*S9*U9 -> 0.62921765 | W9: =VLOOKUP(D9,Priors!$A$3:$C$6,2,FALSE) -> 0.041142361 | X9: =VLOOKUP(D9,Priors!$A$3:$C$6,3,FALSE) -> 0.04051308 | Y9: =IF(N9="",W9,V9*N9+(1-V9)*W9) -> 0.080205077 | Z9: =IF(O9="",X9,V9*O9+(1-V9)*X9) -> 0.029712655 | AA9: 1 | AB9: 1 | AC9: =Y9*AA9 -> 0.080205077 | AD9: =Z9*AB9 -> 0.029712655 | AE9: =1-V9 -> 0.37078235 | AF9: PL history | AJ9: FALSE | AK9: FPL Core Insights / official FPL historical feed | AL9: https://github.com/olbauday/FPL-Core-Insights/tree/main/data/2025-2026 | AO9: 0 | AP9: FALSE | AQ9: Total xG retained; low penalty contamination
A10: 9 | B10: Hincapie | C10: Arsenal | D10: DEF | E10: Premier League | F10: Arsenal | G10: 1787 | H10: 0.36 | I10: 1.67 | J10: 0.018130946 | K10: 0.084107443 | L10: 65.6 | M10: 1.7263158 | N10: 0.010502682 | O10: 0.048720775 | P10: =IFERROR(G10/(G10+Priors!$H$3),0) -> 0.64119125 | Q10: =IF(E10="Premier League",Priors!$H$4,IF(E10="Championship",Priors!$H$5,Priors!$H$8)) -> 1 | R10: FALSE | S10: =IF(R10=TRUE,Priors!$H$6,1) -> 1 | T10: FALSE | U10: =IF(T10=TRUE,Priors!$H$7,1) -> 1 | V10: =P10*Q10*S10*U10 -> 0.64119125 | W10: =VLOOKUP(D10,Priors!$A$3:$C$6,2,FALSE) -> 0.041142361 | X10: =VLOOKUP(D10,Priors!$A$3:$C$6,3,FALSE) -> 0.04051308 | Y10: =IF(N10="",W10,V10*N10+(1-V10)*W10) -> 0.021496467 | Z10: =IF(O10="",X10,V10*O10+(1-V10)*X10) -> 0.045775782 | AA10: 1 | AB10: 1 | AC10: =Y10*AA10 -> 0.021496467 | AD10: =Z10*AB10 -> 0.045775782 | AE10: =1-V10 -> 0.35880875 | AF10: PL history | AJ10: FALSE | AK10: FPL Core Insights / official FPL historical feed | AL10: https://github.com/olbauday/FPL-Core-Insights/tree/main/data/2025-2026 | AO10: 0 | AP10: FALSE | AQ10: Total xG retained; low penalty contamination
A11: 10 | B11: White | C11: Arsenal | D11: DEF | E11: Premier League | F11: Arsenal | G11: 699 | H11: 0.45 | I11: 0.69 | J11: 0.057939914 | K11: 0.088841202 | L11: 65.6 | M11: 1.7263158 | N11: 0.033562755 | O11: 0.051462891 | P11: =IFERROR(G11/(G11+Priors!$H$3),0) -> 0.41141848 | Q11: =IF(E11="Premier League",Priors!$H$4,IF(E11="Championship",Priors!$H$5,Priors!$H$8)) -> 1 | R11: FALSE | S11: =IF(R11=TRUE,Priors!$H$6,1) -> 1 | T11: FALSE | U11: =IF(T11=TRUE,Priors!$H$7,1) -> 1 | V11: =P11*Q11*S11*U11 -> 0.41141848 | W11: =VLOOKUP(D11,Priors!$A$3:$C$6,2,FALSE) -> 0.041142361 | X11: =VLOOKUP(D11,Priors!$A$3:$C$6,3,FALSE) -> 0.04051308 | Y11: =IF(N11="",W11,V11*N11+(1-V11)*W11) -> 0.038023971 | Z11: =IF(O11="",X11,V11*O11+(1-V11)*X11) -> 0.045018035 | AA11: 1 | AB11: 1 | AC11: =Y11*AA11 -> 0.038023971 | AD11: =Z11*AB11 -> 0.045018035 | AE11: =1-V11 -> 0.58858152 | AF11: PL history | AJ11: TRUE | AK11: FPL Core Insights / official FPL historical feed | AL11: https://github.com/olbauday/FPL-Core-Insights/tree/main/data/2025-2026 | AO11: 0 | AP11: FALSE | AQ11: Total xG retained; low penalty contamination
A12: 11 | B12: Mosquera | C12: Arsenal | D12: DEF | E12: Premier League | F12: Arsenal | G12: 986 | H12: 0.1 | I12: 0.63 | J12: 0.009127789 | K12: 0.057505071 | L12: 65.6 | M12: 1.7263158 | N12: 0.0052874388 | O12: 0.033310864 | P12: =IFERROR(G12/(G12+Priors!$H$3),0) -> 0.49647533 | Q12: =IF(E12="Premier League",Priors!$H$4,IF(E12="Championship",Priors!$H$5,Priors!$H$8)) -> 1 | R12: FALSE | S12: =IF(R12=TRUE,Priors!$H$6,1) -> 1 | T12: FALSE | U12: =IF(T12=TRUE,Priors!$H$7,1) -> 1 | V12: =P12*Q12*S12*U12 -> 0.49647533 | W12: =VLOOKUP(D12,Priors!$A$3:$C$6,2,FALSE) -> 0.041142361 | X12: =VLOOKUP(D12,Priors!$A$3:$C$6,3,FALSE) -> 0.04051308 | Y12: =IF(N12="",W12,V12*N12+(1-V12)*W12) -> 0.023341277 | Z12: =IF(O12="",X12,V12*O12+(1-V12)*X12) -> 0.036937358 | AA12: 1 | AB12: 1 | AC12: =Y12*AA12 -> 0.023341277 | AD12: =Z12*AB12 -> 0.036937358 | AE12: =1-V12 -> 0.50352467 | AF12: PL history | AJ12: FALSE | AK12: FPL Core Insights / official FPL historical feed | AL12: https://github.com/olbauday/FPL-Core-Insights/tree/main/data/2025-2026 | AO12: 0 | AP12: FALSE | AQ12: Total xG retained; low penalty contamination
A13: 12 | B13: Saka | C13: Arsenal | D13: MID | E13: Premier League | F13: Arsenal | G13: 2218 | H13: 7.57 | I13: 7.16 | J13: 0.30716862 | K13: 0.29053201 | L13: 65.6 | M13: 1.7263158 | N13: 0.17793304 | O13: 0.16829598 | P13: =IFERROR(G13/(G13+Priors!$H$3),0) -> 0.68924798 | Q13: =IF(E13="Premier League",Priors!$H$4,IF(E13="Championship",Priors!$H$5,Priors!$H$8)) -> 1 | R13: FALSE | S13: =IF(R13=TRUE,Priors!$H$6,1) -> 1 | T13: FALSE | U13: =IF(T13=TRUE,Priors!$H$7,1) -> 1 | V13: =P13*Q13*S13*U13 -> 0.68924798 | W13: =VLOOKUP(D13,Priors!$A$3:$C$6,2,FALSE) -> 0.10751786 | X13: =VLOOKUP(D13,Priors!$A$3:$C$6,3,FALSE) -> 0.090240672 | Y13: =IF(N13="",W13,V13*N13+(1-V13)*W13) -> 0.15605138 | Z13: =IF(O13="",X13,V13*O13+(1-V13)*X13) -> 0.14404014 | AA13: 1 | AB13: 1 | AC13: =Y13*AA13 -> 0.15605138 | AD13: =Z13*AB13 -> 0.14404014 | AE13: =1-V13 -> 0.31075202 | AF13: PL history | AG13: 1 | AH13: 2 | AI13: 6 | AJ13: FALSE | AK13: FPL Core Insights / official FPL historical feed | AL13: https://github.com/olbauday/FPL-Core-Insights/tree/main/data/2025-2026 | AN13: 1 | AO13: 0 | AP13: TRUE | AQ13: Total xG retained; penalty channel not decomposed
A14: 13 | B14: Rice | C14: Arsenal | D14: MID | E14: Premier League | F14: Arsenal | G14: 3093 | H14: 3.15 | I14: 7.32 | J14: 0.091658584 | K14: 0.21299709 | L14: 65.6 | M14: 1.7263158 | N14: 0.053094911 | O14: 0.12338246 | P14: =IFERROR(G14/(G14+Priors!$H$3),0) -> 0.75568043 | Q14: =IF(E14="Premier League",Priors!$H$4,IF(E14="Championship",Priors!$H$5,Priors!$H$8)) -> 1 | R14: FALSE | S14: =IF(R14=TRUE,Priors!$H$6,1) -> 1 | T14: FALSE | U14: =IF(T14=TRUE,Priors!$H$7,1) -> 1 | V14: =P14*Q14*S14*U14 -> 0.75568043 | W14: =VLOOKUP(D14,Priors!$A$3:$C$6,2,FALSE) -> 0.10751786 | X14: =VLOOKUP(D14,Priors!$A$3:$C$6,3,FALSE) -> 0.090240672 | Y14: =IF(N14="",W14,V14*N14+(1-V14)*W14) -> 0.066391503 | Z14: =IF(O14="",X14,V14*O14+(1-V14)*X14) -> 0.11528527 | AA14: 1 | AB14: 1 | AC14: =Y14*AA14 -> 0.066391503 | AD14: =Z14*AB14 -> 0.11528527 | AE14: =1-V14 -> 0.24431957 | AF14: PL history | AH14: 1 | AI14: 5 | AJ14: FALSE | AK14: FPL Core Insights / official FPL historical feed | AL14: https://github.com/olbauday/FPL-Core-Insights/tree/main/data/2025-2026 | AO14: 0 | AP14: FALSE | AQ14: Total xG retained; low penalty contamination
A15: 14 | B15: Eze | C15: Arsenal | D15: MID | E15: Premier League | F15: Arsenal | G15: 1885 | H15: 5.18 | I15: 2.66 | J15: 0.24732095 | K15: 0.12700265 | L15: 65.6 | M15: 1.7263158 | N15: 0.14326519 | O15: 0.07356861 | P15: =IFERROR(G15/(G15+Priors!$H$3),0) -> 0.65337955 | Q15: =IF(E15="Premier League",Priors!$H$4,IF(E15="Championship",Priors!$H$5,Priors!$H$8)) -> 1 | R15: FALSE | S15: =IF(R15=TRUE,Priors!$H$6,1) -> 1 | T15: FALSE | U15: =IF(T15=TRUE,Priors!$H$7,1) -> 1 | V15: =P15*Q15*S15*U15 -> 0.65337955 | W15: =VLOOKUP(D15,Priors!$A$3:$C$6,2,FALSE) -> 0.10751786 | X15: =VLOOKUP(D15,Priors!$A$3:$C$6,3,FALSE) -> 0.090240672 | Y15: =IF(N15="",W15,V15*N15+(1-V15)*W15) -> 0.13087443 | Z15: =IF(O15="",X15,V15*O15+(1-V15)*X15) -> 0.079347487 | AA15: 1 | AB15: 1 | AC15: =Y15*AA15 -> 0.13087443 | AD15: =Z15*AB15 -> 0.079347487 | AE15: =1-V15 -> 0.34662045 | AF15: PL history | AH15: 3 | AJ15: FALSE | AK15: FPL Core Insights / official FPL historical feed | AL15: https://github.com/olbauday/FPL-Core-Insights/tree/main/data/2025-2026 | AO15: 0 | AP15: FALSE | AQ15: Total xG retained; low penalty contamination
A16: 15 | B16: Ødegaard | C16: Arsenal | D16: MID | E16: Premier League | F16: Arsenal | G16: 1363 | H16: 1.25 | I16: 3.65 | J16: 0.082538518 | K16: 0.24101247 | L16: 65.6 | M16: 1.7263158 | N16: 0.047811946 | O16: 0.13961088 | P16: =IFERROR(G16/(G16+Priors!$H$3),0) -> 0.57680914 | Q16: =IF(E16="Premier League",Priors!$H$4,IF(E16="Championship",Priors!$H$5,Priors!$H$8)) -> 1 | R16: FALSE | S16: =IF(R16=TRUE,Priors!$H$6,1) -> 1 | T16: FALSE | U16: =IF(T16=TRUE,Priors!$H$7,1) -> 1 | V16: =P16*Q16*S16*U16 -> 0.57680914 | W16: =VLOOKUP(D16,Priors!$A$3:$C$6,2,FALSE) -> 0.10751786 | X16: =VLOOKUP(D16,Priors!$A$3:$C$6,3,FALSE) -> 0.090240672 | Y16: =IF(N16="",W16,V16*N16+(1-V16)*W16) -> 0.073078944 | Z16: =IF(O16="",X16,V16*O16+(1-V16)*X16) -> 0.11871786 | AA16: 1 | AB16: 1 | AC16: =Y16*AA16 -> 0.073078944 | AD16: =Z16*AB16 -> 0.11871786 | AE16: =1-V16 -> 0.42319086 | AF16: PL history | AG16: 3 | AI16: 8 | AJ16: FALSE | AK16: FPL Core Insights / official FPL historical feed | AL16: https://github.com/olbauday/FPL-Core-Insights/tree/main/data/2025-2026 | AN16: 3 | AO16: 0 | AP16: FALSE | AQ16: Total xG retained; low penalty contamination
A17: 16 | B17: Madueke | C17: Arsenal | D17: MID | E17: Premier League | F17: Arsenal | G17: 1205 | H17: 1.23 | I17: 2.86 | J17: 0.09186722 | K17: 0.21360996 | L17: 65.6 | M17: 1.7263158 | N17: 0.053215768 | O17: 0.12373748 | P17: =IFERROR(G17/(G17+Priors!$H$3),0) -> 0.54648526 | Q17: =IF(E17="Premier League",Priors!$H$4,IF(E17="Championship",Priors!$H$5,Priors!$H$8)) -> 1 | R17: FALSE | S17: =IF(R17=TRUE,Priors!$H$6,1) -> 1 | T17: FALSE | U17: =IF(T17=TRUE,Priors!$H$7,1) -> 1 | V17: =P17*Q17*S17*U17 -> 0.54648526 | W17: =VLOOKUP(D17,Priors!$A$3:$C$6,2,FALSE) -> 0.10751786 | X17: =VLOOKUP(D17,Priors!$A$3:$C$6,3,FALSE) -> 0.090240672 | Y17: =IF(N17="",W17,V17*N17+(1-V17)*W17) -> 0.077842567 | Z17: =IF(O17="",X17,V17*O17+(1-V17)*X17) -> 0.10854618 | AA17: 1 | AB17: 1 | AC17: =Y17*AA17 -> 0.077842567 | AD17: =Z17*AB17 -> 0.10854618 | AE17: =1-V17 -> 0.45351474 | AF17: PL history | AI17: 7 | AJ17: FALSE | AK17: FPL Core Insights / official FPL historical feed | AL17: https://github.com/olbauday/FPL-Core-Insights/tree/main/data/2025-2026 | AO17: 0 | AP17: FALSE | AQ17: Total xG retained; low penalty contamination
A18: 17 | B18: Merino | C18: Arsenal | D18: MID | E18: Premier League | F18: Arsenal | G18: 1024 | H18: 3.36 | I18: 1.45 | J18: 0.2953125 | K18: 0.12744141 | L18: 65.6 | M18: 1.7263158 | N18: 0.17106517 | O18: 0.073822766 | P18: =IFERROR(G18/(G18+Priors!$H$3),0) -> 0.50592885 | Q18: =IF(E18="Premier League",Priors!$H$4,IF(E18="Championship",Priors!$H$5,Priors!$H$8)) -> 1 | R18: FALSE | S18: =IF(R18=TRUE,Priors!$H$6,1) -> 1 | T18: FALSE | U18: =IF(T18=TRUE,Priors!$H$7,1) -> 1 | V18: =P18*Q18*S18*U18 -> 0.50592885 | W18: =VLOOKUP(D18,Priors!$A$3:$C$6,2,FALSE) -> 0.10751786 | X18: =VLOOKUP(D18,Priors!$A$3:$C$6,3,FALSE) -> 0.090240672 | Y18: =IF(N18="",W18,V18*N18+(1-V18)*W18) -> 0.13966828 | Z18: =IF(O18="",X18,V18*O18+(1-V18)*X18) -> 0.08193438 | AA18: 1 | AB18: 1 | AC18: =Y18*AA18 -> 0.13966828 | AD18: =Z18*AB18 -> 0.08193438 | AE18: =1-V18 -> 0.49407115 | AF18: PL history | AJ18: FALSE | AK18: FPL Core Insights / official FPL historical feed | AL18: https://github.com/olbauday/FPL-Core-Insights/tree/main/data/2025-2026 | AO18: 0 | AP18: FALSE | AQ18: Total xG retained; low penalty contamination
A19: 18 | B19: Martinelli | C19: Arsenal | D19: MID | E19: Premier League | F19: Arsenal | G19: 1065 | H19: 4.12 | I19: 1.27 | J19: 0.34816901 | K19: 0.10732394 | L19: 65.6 | M19: 1.7263158 | N19: 0.20168327 | O19: 0.062169358 | P19: =IFERROR(G19/(G19+Priors!$H$3),0) -> 0.5157385 | Q19: =IF(E19="Premier League",Priors!$H$4,IF(E19="Championship",Priors!$H$5,Priors!$H$8)) -> 1 | R19: FALSE | S19: =IF(R19=TRUE,Priors!$H$6,1) -> 1 | T19: FALSE | U19: =IF(T19=TRUE,Priors!$H$7,1) -> 1 | V19: =P19*Q19*S19*U19 -> 0.5157385 | W19: =VLOOKUP(D19,Priors!$A$3:$C$6,2,FALSE) -> 0.10751786 | X19: =VLOOKUP(D19,Priors!$A$3:$C$6,3,FALSE) -> 0.090240672 | Y19: =IF(N19="",W19,V19*N19+(1-V19)*W19) -> 0.15608259 | Z19: =IF(O19="",X19,V19*O19+(1-V19)*X19) -> 0.075763214 | AA19: 1 | AB19: 1 | AC19: =Y19*AA19 -> 0.15608259 | AD19: =Z19*AB19 -> 0.075763214 | AE19: =1-V19 -> 0.4842615 | AF19: PL history | AJ19: FALSE | AK19: FPL Core Insights / official FPL historical feed | AL19: https://github.com/olbauday/FPL-Core-Insights/tree/main/data/2025-2026 | AO19: 0 | AP19: FALSE | AQ19: Total xG retained; low penalty contamination
A20: 19 | B20: Zubimendi | C20: Arsenal | D20: MID | E20: Premier League | F20: Arsenal | G20: 2991 | H20: 2.84 | I20: 2.27 | J20: 0.085456369 | K20: 0.068304915 | L20: 65.6 | M20: 1.7263158 | N20: 0.049502165 | O20: 0.039566871 | P20: =IFERROR(G20/(G20+Priors!$H$3),0) -> 0.74943623 | Q20: =IF(E20="Premier League",Priors!$H$4,IF(E20="Championship",Priors!$H$5,Priors!$H$8)) -> 1 | R20: FALSE | S20: =IF(R20=TRUE,Priors!$H$6,1) -> 1 | T20: FALSE | U20: =IF(T20=TRUE,Priors!$H$7,1) -> 1 | V20: =P20*Q20*S20*U20 -> 0.74943623 | W20: =VLOOKUP(D20,Priors!$A$3:$C$6,2,FALSE) -> 0.10751786 | X20: =VLOOKUP(D20,Priors!$A$3:$C$6,3,FALSE) -> 0.090240672 | Y20: =IF(N20="",W20,V20*N20+(1-V20)*W20) -> 0.064038796 | Z20: =IF(O20="",X20,V20*O20+(1-V20)*X20) -> 0.05226389 | AA20: 1 | AB20: 1 | AC20: =Y20*AA20 -> 0.064038796 | AD20: =Z20*AB20 -> 0.05226389 | AE20: =1-V20 -> 0.25056377 | AF20: PL history | AJ20: FALSE | AK20: FPL Core Insights / official FPL historical feed | AL20: https://github.com/olbauday/FPL-Core-Insights/tree/main/data/2025-2026 | AO20: 0 | AP20: FALSE | AQ20: Total xG retained; low penalty contamination
A21: 20 | B21: Dowman | C21: Arsenal | D21: MID | E21: Premier League | F21: Arsenal | G21: 152 | H21: 1.19 | I21: 0.3 | J21: 0.70460526 | K21: 0.17763158 | L21: 65.6 | M21: 1.7263158 | N21: 0.40815549 | O21: 0.10289634 | P21: =IFERROR(G21/(G21+Priors!$H$3),0) -> 0.13194444 | Q21: =IF(E21="Premier League",Priors!$H$4,IF(E21="Championship",Priors!$H$5,Priors!$H$8)) -> 1 | R21: FALSE | S21: =IF(R21=TRUE,Priors!$H$6,1) -> 1 | T21: FALSE | U21: =IF(T21=TRUE,Priors!$H$7,1) -> 1 | V21: =P21*Q21*S21*U21 -> 0.13194444 | W21: =VLOOKUP(D21,Priors!$A$3:$C$6,2,FALSE) -> 0.10751786 | X21: =VLOOKUP(D21,Priors!$A$3:$C$6,3,FALSE) -> 0.090240672 | Y21: =IF(N21="",W21,V21*N21+(1-V21)*W21) -> 0.14718533 | Z21: =IF(O21="",X21,V21*O21+(1-V21)*X21) -> 0.091910517 | AA21: 1 | AB21: 1 | AC21: =Y21*AA21 -> 0.14718533 | AD21: =Z21*AB21 -> 0.091910517 | AE21: =1-V21 -> 0.86805556 | AF21: PL history | AJ21: TRUE | AK21: FPL Core Insights / official FPL historical feed | AL21: https://github.com/olbauday/FPL-Core-Insights/tree/main/data/2025-2026 | AO21: 0 | AP21: FALSE | AQ21: Total xG retained; low penalty contamination
A22: 21 | B22: Nørgaard | C22: Arsenal | D22: MID | E22: Premier League | F22: Arsenal | G22: 101 | H22: 0.08 | I22: 0.04 | J22: 0.071287129 | K22: 0.035643564 | L22: 65.6 | M22: 1.7263158 | N22: 0.041294373 | O22: 0.020647187 | P22: =IFERROR(G22/(G22+Priors!$H$3),0) -> 0.091734787 | Q22: =IF(E22="Premier League",Priors!$H$4,IF(E22="Championship",Priors!$H$5,Priors!$H$8)) -> 1 | R22: FALSE | S22: =IF(R22=TRUE,Priors!$H$6,1) -> 1 | T22: FALSE | U22: =IF(T22=TRUE,Priors!$H$7,1) -> 1 | V22: =P22*Q22*S22*U22 -> 0.091734787 | W22: =VLOOKUP(D22,Priors!$A$3:$C$6,2,FALSE) -> 0.10751786 | X22: =VLOOKUP(D22,Priors!$A$3:$C$6,3,FALSE) -> 0.090240672 | Y22: =IF(N22="",W22,V22*N22+(1-V22)*W22) -> 0.10144286 | Z22: =IF(O22="",X22,V22*O22+(1-V22)*X22) -> 0.083856528 | AA22: 1 | AB22: 1 | AC22: =Y22*AA22 -> 0.10144286 | AD22: =Z22*AB22 -> 0.083856528 | AE22: =1-V22 -> 0.90826521 | AF22: PL history | AJ22: TRUE | AK22: FPL Core Insights / official FPL historical feed | AL22: https://github.com/olbauday/FPL-Core-Insights/tree/main/data/2025-2026 | AO22: 0 | AP22: FALSE | AQ22: Total xG retained; low penalty contamination
A23: 22 | B23: Nwaneri | C23: Arsenal | D23: MID | E23: Premier League | F23: Arsenal | G23: 165 | H23: 0.23 | I23: 0.08 | J23: 0.12545455 | K23: 0.043636364 | L23: 65.6 | M23: 1.7263158 | N23: 0.07267184 | O23: 0.025277162 | P23: =IFERROR(G23/(G23+Priors!$H$3),0) -> 0.1416309 | Q23: =IF(E23="Premier League",Priors!$H$4,IF(E23="Championship",Priors!$H$5,Priors!$H$8)) -> 1 | R23: FALSE | S23: =IF(R23=TRUE,Priors!$H$6,1) -> 1 | T23: FALSE | U23: =IF(T23=TRUE,Priors!$H$7,1) -> 1 | V23: =P23*Q23*S23*U23 -> 0.1416309 | W23: =VLOOKUP(D23,Priors!$A$3:$C$6,2,FALSE) -> 0.10751786 | X23: =VLOOKUP(D23,Priors!$A$3:$C$6,3,FALSE) -> 0.090240672 | Y23: =IF(N23="",W23,V23*N23+(1-V23)*W23) -> 0.10258259 | Z23: =IF(O23="",X23,V23*O23+(1-V23)*X23) -> 0.081039831 | AA23: 1 | AB23: 1 | AC23: =Y23*AA23 -> 0.10258259 | AD23: =Z23*AB23 -> 0.081039831 | AE23: =1-V23 -> 0.8583691 | AF23: PL history | AJ23: TRUE | AK23: FPL Core Insights / official FPL historical feed | AL23: https://github.com/olbauday/FPL-Core-Insights/tree/main/data/2025-2026 | AO23: 0 | AP23: FALSE | AQ23: Total xG retained; low penalty contamination
A24: 23 | B24: Fábio Vieira | C24: Arsenal | D24: MID | E24: Missing/non-PL | P24: =IFERROR(G24/(G24+Priors!$H$3),0) -> 0 | Q24: =IF(E24="Premier League",Priors!$H$4,IF(E24="Championship",Priors!$H$5,Priors!$H$8)) -> 0 | R24: FALSE | S24: =IF(R24=TRUE,Priors!$H$6,1) -> 1 | T24: FALSE | U24: =IF(T24=TRUE,Priors!$H$7,1) -> 1 | V24: =P24*Q24*S24*U24 -> 0 | W24: =VLOOKUP(D24,Priors!$A$3:$C$6,2,FALSE) -> 0.10751786 | X24: =VLOOKUP(D24,Priors!$A$3:$C$6,3,FALSE) -> 0.090240672 | Y24: =IF(N24="",W24,V24*N24+(1-V24)*W24) -> 0.10751786 | Z24: =IF(O24="",X24,V24*O24+(1-V24)*X24) -> 0.090240672 | AA24: 1 | AB24: 1 | AC24: =Y24*AA24 -> 0.10751786 | AD24: =Z24*AB24 -> 0.090240672 | AE24: =1-V24 -> 1 | AF24: Missing/non-PL | AJ24: TRUE | AK24: No reliable 25/26 history loaded | AO24: 0 | AP24: FALSE | AQ24: Total xG retained; low penalty contamination
A25: 24 | B25: Nelson | C25: Arsenal | D25: MID | E25: Premier League | F25: Brentford | G25: 118 | H25: 0.71 | I25: 0.11 | J25: 0.54152542 | K25: 0.083898305 | L25: 60.3 | M25: 1.5868421 | N25: 0.3412598 | O25: 0.052871237 | P25: =IFERROR(G25/(G25+Priors!$H$3),0) -> 0.10554562 | Q25: =IF(E25="Premier League",Priors!$H$4,IF(E25="Championship",Priors!$H$5,Priors!$H$8)) -> 1 | R25: TRUE | S25: =IF(R25=TRUE,Priors!$H$6,1) -> 0.85 | T25: FALSE | U25: =IF(T25=TRUE,Priors!$H$7,1) -> 1 | V25: =P25*Q25*S25*U25 -> 0.089713775 | W25: =VLOOKUP(D25,Priors!$A$3:$C$6,2,FALSE) -> 0.10751786 | X25: =VLOOKUP(D25,Priors!$A$3:$C$6,3,FALSE) -> 0.090240672 | Y25: =IF(N25="",W25,V25*N25+(1-V25)*W25) -> 0.12848773 | Z25: =IF(O25="",X25,V25*O25+(1-V25)*X25) -> 0.086888119 | AA25: 1 | AB25: 1 | AC25: =Y25*AA25 -> 0.12848773 | AD25: =Z25*AB25 -> 0.086888119 | AE25: =1-V25 -> 0.91028623 | AF25: PL history | AJ25: TRUE | AK25: FPL Core Insights / official FPL historical feed | AL25: https://github.com/olbauday/FPL-Core-Insights/tree/main/data/2025-2026 | AO25: 0 | AP25: FALSE | AQ25: Total xG retained; low penalty contamination
A26: 25 | B26: Gyökeres | C26: Arsenal | D26: FWD | E26: Premier League | F26: Arsenal | G26: 2217 | H26: 12.26 | I26: 1.94 | J26: 0.49769959 | K26: 0.078755074 | L26: 65.6 | M26: 1.7263158 | N26: 0.28830159 | O26: 0.045620318 | P26: =IFERROR(G26/(G26+Priors!$H$3),0) -> 0.68915138 | Q26: =IF(E26="Premier League",Priors!$H$4,IF(E26="Championship",Priors!$H$5,Priors!$H$8)) -> 1 | R26: FALSE | S26: =IF(R26=TRUE,Priors!$H$6,1) -> 1 | T26: FALSE | U26: =IF(T26=TRUE,Priors!$H$7,1) -> 1 | V26: =P26*Q26*S26*U26 -> 0.68915138 | W26: =VLOOKUP(D26,Priors!$A$3:$C$6,2,FALSE) -> 0.30461526 | X26: =VLOOKUP(D26,Priors!$A$3:$C$6,3,FALSE) -> 0.039258062 | Y26: =IF(N26="",W26,V26*N26+(1-V26)*W26) -> 0.29337267 | Z26: =IF(O26="",X26,V26*O26+(1-V26)*X26) -> 0.043642619 | AA26: 1 | AB26: 1 | AC26: =Y26*AA26 -> 0.29337267 | AD26: =Z26*AB26 -> 0.043642619 | AE26: =1-V26 -> 0.31084862 | AF26: PL history | AG26: 2 | AJ26: FALSE | AK26: FPL Core Insights / official FPL historical feed | AL26: https://github.com/olbauday/FPL-Core-Insights/tree/main/data/2025-2026 | AN26: 2 | AO26: 0 | AP26: TRUE | AQ26: Total xG retained; penalty channel not decomposed
A27: 26 | B27: Havertz | C27: Arsenal | D27: FWD | E27: Premier League | F27: Arsenal | G27: 577 | H27: 3.31 | I27: 0.64 | J27: 0.51629116 | K27: 0.09982669 | L27: 65.6 | M27: 1.7263158 | N27: 0.2990711 | O27: 0.057826436 | P27: =IFERROR(G27/(G27+Priors!$H$3),0) -> 0.36588459 | Q27: =IF(E27="Premier League",Priors!$H$4,IF(E27="Championship",Priors!$H$5,Priors!$H$8)) -> 1 | R27: FALSE | S27: =IF(R27=TRUE,Priors!$H$6,1) -> 1 | T27: FALSE | U27: =IF(T27=TRUE,Priors!$H$7,1) -> 1 | V27: =P27*Q27*S27*U27 -> 0.36588459 | W27: =VLOOKUP(D27,Priors!$A$3:$C$6,2,FALSE) -> 0.30461526 | X27: =VLOOKUP(D27,Priors!$A$3:$C$6,3,FALSE) -> 0.039258062 | Y27: =IF(N27="",W27,V27*N27+(1-V27)*W27) -> 0.30258673 | Z27: =IF(O27="",X27,V27*O27+(1-V27)*X27) -> 0.046051944 | AA27: 1 | AB27: 1 | AC27: =Y27*AA27 -> 0.30258673 | AD27: =Z27*AB27 -> 0.046051944 | AE27: =1-V27 -> 0.63411541 | AF27: PL history | AJ27: TRUE | AK27: FPL Core Insights / official FPL historical feed | AL27: https://github.com/olbauday/FPL-Core-Insights/tree/main/data/2025-2026 | AO27: 0 | AP27: FALSE | AQ27: Total xG retained; low penalty contamination
A28: 27 | B28: G.Jesus | C28: Arsenal | D28: FWD | E28: Premier League | F28: Arsenal | G28: 418 | H28: 2.71 | I28: 0.26 | J28: 0.58349282 | K28: 0.055980861 | L28: 65.6 | M28: 1.7263158 | N28: 0.33799889 | O28: 0.032427938 | P28: =IFERROR(G28/(G28+Priors!$H$3),0) -> 0.29478138 | Q28: =IF(E28="Premier League",Priors!$H$4,IF(E28="Championship",Priors!$H$5,Priors!$H$8)) -> 1 | R28: FALSE | S28: =IF(R28=TRUE,Priors!$H$6,1) -> 1 | T28: FALSE | U28: =IF(T28=TRUE,Priors!$H$7,1) -> 1 | V28: =P28*Q28*S28*U28 -> 0.29478138 | W28: =VLOOKUP(D28,Priors!$A$3:$C$6,2,FALSE) -> 0.30461526 | X28: =VLOOKUP(D28,Priors!$A$3:$C$6,3,FALSE) -> 0.039258062 | Y28: =IF(N28="",W28,V28*N28+(1-V28)*W28) -> 0.31445613 | Z28: =IF(O28="",X28,V28*O28+(1-V28)*X28) -> 0.037244668 | AA28: 1 | AB28: 1 | AC28: =Y28*AA28 -> 0.31445613 | AD28: =Z28*AB28 -> 0.037244668 | AE28: =1-V28 -> 0.70521862 | AF28: PL history | AJ28: TRUE | AK28: FPL Core Insights / official FPL historical feed | AL28: https://github.com/olbauday/FPL-Core-Insights/tree/main/data/2025-2026 | AO28: 0 | AP28: FALSE | AQ28: Total xG retained; low penalty contamination
A29: 557 | B29: Tzolis | C29: Arsenal | D29: MID | E29: Missing/non-PL | P29: =IFERROR(G29/(G29+Priors!$H$3),0) -> 0 | Q29: =IF(E29="Premier League",Priors!$H$4,IF(E29="Championship",Priors!$H$5,Priors!$H$8)) -> 0 | R29: FALSE | S29: =IF(R29=TRUE,Priors!$H$6,1) -> 1 | T29: FALSE | U29: =IF(T29=TRUE,Priors!$H$7,1) -> 1 | V29: =P29*Q29*S29*U29 -> 0 | W29: =VLOOKUP(D29,Priors!$A$3:$C$6,2,FALSE) -> 0.10751786 | X29: =VLOOKUP(D29,Priors!$A$3:$C$6,3,FALSE) -> 0.090240672 | Y29: =IF(N29="",W29,V29*N29+(1-V29)*W29) -> 0.10751786 | Z29: =IF(O29="",X29,V29*O29+(1-V29)*X29) -> 0.090240672 | AA29: 1 | AB29: 1 | AC29: =Y29*AA29 -> 0.10751786 | AD29: =Z29*AB29 -> 0.090240672 | AE29: =1-V29 -> 1 | AF29: Missing/non-PL | AJ29: TRUE | AK29: No reliable 25/26 history loaded | AO29: 0 | AP29: FALSE | AQ29: Total xG retained; low penalty contamination
A30: 28 | B30: Martinez | C30: Aston Villa | D30: GK | E30: Premier League | F30: Aston Villa | G30: 2835 | H30: 0 | I30: 0.08 | J30: 0 | K30: 0.0025396825 | L30: 48.2 | M30: 1.2684211 | N30: 0 | O30: 0.0020022393 | P30: =IFERROR(G30/(G30+Priors!$H$3),0) -> 0.73924381 | Q30: =IF(E30="Premier League",Priors!$H$4,IF(E30="Championship",Priors!$H$5,Priors!$H$8)) -> 1 | R30: FALSE | S30: =IF(R30=TRUE,Priors!$H$6,1) -> 1 | T30: FALSE | U30: =IF(T30=TRUE,Priors!$H$7,1) -> 1 | V30: =P30*Q30*S30*U30 -> 0.73924381 | W30: =VLOOKUP(D30,Priors!$A$3:$C$6,2,FALSE) -> 0.00016719535 | X30: =VLOOKUP(D30,Priors!$A$3:$C$6,3,FALSE) -> 0.0013793616 | Y30: =IF(N30="",W30,V30*N30+(1-V30)*W30) -> 4.3597223e-05 | Z30: =IF(O30="",X30,V30*O30+(1-V30)*X30) -> 0.0018398201 | AA30: 1 | AB30: 1 | AC30: =Y30*AA30 -> 4.3597223e-05 | AD30: =Z30*AB30 -> 0.0018398201 | AE30: =1-V30 -> 0.26075619 | AF30: PL history | AJ30: FALSE | AK30: FPL Core Insights / official FPL historical feed | AL30: https://github.com/olbauday/FPL-Core-Insights/tree/main/data/2025-2026 | AO30: 0 | AP30: FALSE | AQ30: Total xG retained; low penalty contamination
A31: 29 | B31: M.Bizot | C31: Aston Villa | D31: GK | E31: Premier League | F31: Aston Villa | G31: 585 | H31: 0 | I31: 0 | J31: 0 | K31: 0 | L31: 48.2 | M31: 1.2684211 | N31: 0 | O31: 0 | P31: =IFERROR(G31/(G31+Priors!$H$3),0) -> 0.36908517 | Q31: =IF(E31="Premier League",Priors!$H$4,IF(E31="Championship",Priors!$H$5,Priors!$H$8)) -> 1 | R31: FALSE | S31: =IF(R31=TRUE,Priors!$H$6,1) -> 1 | T31: FALSE | U31: =IF(T31=TRUE,Priors!$H$7,1) -> 1 | V31: =P31*Q31*S31*U31 -> 0.36908517 | W31: =VLOOKUP(D31,Priors!$A$3:$C$6,2,FALSE) -> 0.00016719535 | X31: =VLOOKUP(D31,Priors!$A$3:$C$6,3,FALSE) -> 0.0013793616 | Y31: =IF(N31="",W31,V31*N31+(1-V31)*W31) -> 0.00010548603 | Z31: =IF(O31="",X31,V31*O31+(1-V31)*X31) -> 0.00087025971 | AA31: 1 | AB31: 1 | AC31: =Y31*AA31 -> 0.00010548603 | AD31: =Z31*AB31 -> 0.00087025971 | AE31: =1-V31 -> 0.63091483 | AF31: PL history | AJ31: TRUE | AK31: FPL Core Insights / official FPL historical feed | AL31: https://github.com/olbauday/FPL-Core-Insights/tree/main/data/2025-2026 | AO31: 0 | AP31: FALSE | AQ31: Total xG retained; low penalty contamination
A32: 30 | B32: Digne | C32: Aston Villa | D32: DEF | E32: Premier League | F32: Aston Villa | G32: 1842 | H32: 0.67 | I32: 3.28 | J32: 0.032736156 | K32: 0.16026059 | L32: 48.2 | M32: 1.2684211 | N32: 0.025808588 | O32: 0.12634652 | P32: =IFERROR(G32/(G32+Priors!$H$3),0) -> 0.64813512 | Q32: =IF(E32="Premier League",Priors!$H$4,IF(E32="Championship",Priors!$H$5,Priors!$H$8)) -> 1 | R32: FALSE | S32: =IF(R32=TRUE,Priors!$H$6,1) -> 1 | T32: FALSE | U32: =IF(T32=TRUE,Priors!$H$7,1) -> 1 | V32: =P32*Q32*S32*U32 -> 0.64813512 | W32: =VLOOKUP(D32,Priors!$A$3:$C$6,2,FALSE) -> 0.041142361 | X32: =VLOOKUP(D32,Priors!$A$3:$C$6,3,FALSE) -> 0.04051308 | Y32: =IF(N32="",W32,V32*N32+(1-V32)*W32) -> 0.031204004 | Z32: =IF(O32="",X32,V32*O32+(1-V32)*X32) -> 0.096144747 | AA32: 1 | AB32: 1 | AC32: =Y32*AA32 -> 0.031204004 | AD32: =Z32*AB32 -> 0.096144747 | AE32: =1-V32 -> 0.35186488 | AF32: PL history | AI32: 4 | AJ32: FALSE | AK32: FPL Core Insights / official FPL historical feed | AL32: https://github.com/olbauday/FPL-Core-Insights/tree/main/data/2025-2026 | AO32: 0 | AP32: FALSE | AQ32: Total xG retained; low penalty contamination
A33: 31 | B33: Konsa | C33: Aston Villa | D33: DEF | E33: Premier League | F33: Aston Villa | G33: 3035 | H33: 1.27 | I33: 0.59 | J33: 0.037660626 | K33: 0.017495881 | L33: 48.2 | M33: 1.2684211 | N33: 0.02969095 | O33: 0.013793433 | P33: =IFERROR(G33/(G33+Priors!$H$3),0) -> 0.75216853 | Q33: =IF(E33="Premier League",Priors!$H$4,IF(E33="Championship",Priors!$H$5,Priors!$H$8)) -> 1 | R33: FALSE | S33: =IF(R33=TRUE,Priors!$H$6,1) -> 1 | T33: FALSE | U33: =IF(T33=TRUE,Priors!$H$7,1) -> 1 | V33: =P33*Q33*S33*U33 -> 0.75216853 | W33: =VLOOKUP(D33,Priors!$A$3:$C$6,2,FALSE) -> 0.041142361 | X33: =VLOOKUP(D33,Priors!$A$3:$C$6,3,FALSE) -> 0.04051308 | Y33: =IF(N33="",W33,V33*N33+(1-V33)*W33) -> 0.03252897 | Z33: =IF(O33="",X33,V33*O33+(1-V33)*X33) -> 0.020415403 | AA33: 1 | AB33: 1 | AC33: =Y33*AA33 -> 0.03252897 | AD33: =Z33*AB33 -> 0.020415403 | AE33: =1-V33 -> 0.24783147 | AF33: PL history | AJ33: FALSE | AK33: FPL Core Insights / official FPL historical feed | AL33: https://github.com/olbauday/FPL-Core-Insights/tree/main/data/2025-2026 | AO33: 0 | AP33: FALSE | AQ33: Total xG retained; low penalty contamination
A34: 32 | B34: Cash | C34: Aston Villa | D34: DEF | E34: Premier League | F34: Aston Villa | G34: 3016 | H34: 1.14 | I34: 2.94 | J34: 0.034018568 | K34: 0.087732095 | L34: 48.2 | M34: 1.2684211 | N34: 0.026819618 | O34: 0.069166382 | P34: =IFERROR(G34/(G34+Priors!$H$3),0) -> 0.75099602 | Q34: =IF(E34="Premier League",Priors!$H$4,IF(E34="Championship",Priors!$H$5,Priors!$H$8)) -> 1 | R34: FALSE | S34: =IF(R34=TRUE,Priors!$H$6,1) -> 1 | T34: FALSE | U34: =IF(T34=TRUE,Priors!$H$7,1) -> 1 | V34: =P34*Q34*S34*U34 -> 0.75099602 | W34: =VLOOKUP(D34,Priors!$A$3:$C$6,2,FALSE) -> 0.041142361 | X34: =VLOOKUP(D34,Priors!$A$3:$C$6,3,FALSE) -> 0.04051308 | Y34: =IF(N34="",W34,V34*N34+(1-V34)*W34) -> 0.030386038 | Z34: =IF(O34="",X34,V34*O34+(1-V34)*X34) -> 0.062031596 | AA34: 1 | AB34: 1 | AC34: =Y34*AA34 -> 0.030386038 | AD34: =Z34*AB34 -> 0.062031596 | AE34: =1-V34 -> 0.24900398 | AF34: PL history | AI34: 5 | AJ34: FALSE | AK34: FPL Core Insights / official FPL historical feed | AL34: https://github.com/olbauday/FPL-Core-Insights/tree/main/data/2025-2026 | AO34: 0 | AP34: FALSE | AQ34: Total xG retained; low penalty contamination
A35: 33 | B35: Mings | C35: Aston Villa | D35: DEF | E35: Premier League | F35: Aston Villa | G35: 1322 | H35: 1.3 | I35: 0.42 | J35: 0.088502269 | K35: 0.028593041 | L35: 48.2 | M35: 1.2684211 | N35: 0.069773573 | O35: 0.022542231 | P35: =IFERROR(G35/(G35+Priors!$H$3),0) -> 0.56933678 | Q35: =IF(E35="Premier League",Priors!$H$4,IF(E35="Championship",Priors!$H$5,Priors!$H$8)) -> 1 | R35: FALSE | S35: =IF(R35=TRUE,Priors!$H$6,1) -> 1 | T35: FALSE | U35: =IF(T35=TRUE,Priors!$H$7,1) -> 1 | V35: =P35*Q35*S35*U35 -> 0.56933678 | W35: =VLOOKUP(D35,Priors!$A$3:$C$6,2,FALSE) -> 0.041142361 | X35: =VLOOKUP(D35,Priors!$A$3:$C$6,3,FALSE) -> 0.04051308 | Y35: =IF(N35="",W35,V35*N35+(1-V35)*W35) -> 0.057443163 | Z35: =IF(O35="",X35,V35*O35+(1-V35)*X35) -> 0.030281615 | AA35: 1 | AB35: 1 | AC35: =Y35*AA35 -> 0.057443163 | AD35: =Z35*AB35 -> 0.030281615 | AE35: =1-V35 -> 0.43066322 | AF35: PL history | AJ35: FALSE | AK35: FPL Core Insights / official FPL historical feed | AL35: https://github.com/olbauday/FPL-Core-Insights/tree/main/data/2025-2026 | AO35: 0 | AP35: FALSE | AQ35: Total xG retained; low penalty contamination
A36: 34 | B36: Pau | C36: Aston Villa | D36: DEF | E36: Premier League | F36: Aston Villa | G36: 1673 | H36: 1.33 | I36: 0.39 | J36: 0.071548117 | K36: 0.020980275 | L36: 48.2 | M36: 1.2684211 | N36: 0.056407229 | O36: 0.016540466 | P36: =IFERROR(G36/(G36+Priors!$H$3),0) -> 0.62588851 | Q36: =IF(E36="Premier League",Priors!$H$4,IF(E36="Championship",Priors!$H$5,Priors!$H$8)) -> 1 | R36: FALSE | S36: =IF(R36=TRUE,Priors!$H$6,1) -> 1 | T36: FALSE | U36: =IF(T36=TRUE,Priors!$H$7,1) -> 1 | V36: =P36*Q36*S36*U36 -> 0.62588851 | W36: =VLOOKUP(D36,Priors!$A$3:$C$6,2,FALSE) -> 0.041142361 | X36: =VLOOKUP(D36,Priors!$A$3:$C$6,3,FALSE) -> 0.04051308 | Y36: =IF(N36="",W36,V36*N36+(1-V36)*W36) -> 0.050696467 | Z36: =IF(O36="",X36,V36*O36+(1-V36)*X36) -> 0.025508896 | AA36: 1 | AB36: 1 | AC36: =Y36*AA36 -> 0.050696467 | AD36: =Z36*AB36 -> 0.025508896 | AE36: =1-V36 -> 0.37411149 | AF36: PL history | AJ36: FALSE | AK36: FPL Core Insights / official FPL historical feed | AL36: https://github.com/olbauday/FPL-Core-Insights/tree/main/data/2025-2026 | AO36: 0 | AP36: FALSE | AQ36: Total xG retained; low penalty contamination
A37: 35 | B37: Bogarde | C37: Aston Villa | D37: MID | E37: Premier League | F37: Aston Villa | G37: 1042 | H37: 0 | I37: 0.2 | J37: 0 | K37: 0.017274472 | L37: 48.2 | M37: 1.2684211 | N37: 0 | O37: 0.013618878 | P37: =IFERROR(G37/(G37+Priors!$H$3),0) -> 0.51028404 | Q37: =IF(E37="Premier League",Priors!$H$4,IF(E37="Championship",Priors!$H$5,Priors!$H$8)) -> 1 | R37: FALSE | S37: =IF(R37=TRUE,Priors!$H$6,1) -> 1 | T37: FALSE | U37: =IF(T37=TRUE,Priors!$H$7,1) -> 1 | V37: =P37*Q37*S37*U37 -> 0.51028404 | W37: =VLOOKUP(D37,Priors!$A$3:$C$6,2,FALSE) -> 0.10751786 | X37: =VLOOKUP(D37,Priors!$A$3:$C$6,3,FALSE) -> 0.090240672 | Y37: =IF(N37="",W37,V37*N37+(1-V37)*W37) -> 0.052653213 | Z37: =IF(O37="",X37,V37*O37+(1-V37)*X37) -> 0.051141794 | AA37: 1 | AB37: 1 | AC37: =Y37*AA37 -> 0.052653213 | AD37: =Z37*AB37 -> 0.051141794 | AE37: =1-V37 -> 0.48971596 | AF37: PL history | AJ37: FALSE | AK37: FPL Core Insights / official FPL historical feed | AL37: https://github.com/olbauday/FPL-Core-Insights/tree/main/data/2025-2026 | AO37: 0 | AP37: FALSE | AQ37: Total xG retained; low penalty contamination
A38: 36 | B38: Maatsen | C38: Aston Villa | D38: DEF | E38: Premier League | F38: Aston Villa | G38: 1590 | H38: 1.26 | I38: 2.39 | J38: 0.071320755 | K38: 0.13528302 | L38: 48.2 | M38: 1.2684211 | N38: 0.056227981 | O38: 0.10665466 | P38: =IFERROR(G38/(G38+Priors!$H$3),0) -> 0.61389961 | Q38: =IF(E38="Premier League",Priors!$H$4,IF(E38="Championship",Priors!$H$5,Priors!$H$8)) -> 1 | R38: FALSE | S38: =IF(R38=TRUE,Priors!$H$6,1) -> 1 | T38: FALSE | U38: =IF(T38=TRUE,Priors!$H$7,1) -> 1 | V38: =P38*Q38*S38*U38 -> 0.61389961 | W38: =VLOOKUP(D38,Priors!$A$3:$C$6,2,FALSE) -> 0.041142361 | X38: =VLOOKUP(D38,Priors!$A$3:$C$6,3,FALSE) -> 0.04051308 | Y38: =IF(N38="",W38,V38*N38+(1-V38)*W38) -> 0.050403417 | Z38: =IF(O38="",X38,V38*O38+(1-V38)*X38) -> 0.081117372 | AA38: 1 | AB38: 1 | AC38: =Y38*AA38 -> 0.050403417 | AD38: =Z38*AB38 -> 0.081117372 | AE38: =1-V38 -> 0.38610039 | AF38: PL history | AJ38: FALSE | AK38: FPL Core Insights / official FPL historical feed | AL38: https://github.com/olbauday/FPL-Core-Insights/tree/main/data/2025-2026 | AO38: 0 | AP38: FALSE | AQ38: Total xG retained; low penalty contamination
A39: 37 | B39: Lindelöf | C39: Aston Villa | D39: DEF | E39: Premier League | F39: Aston Villa | G39: 942 | H39: 0.28 | I39: 0.1 | J39: 0.026751592 | K39: 0.0095541401 | L39: 48.2 | M39: 1.2684211 | N39: 0.021090467 | O39: 0.0075323096 | P39: =IFERROR(G39/(G39+Priors!$H$3),0) -> 0.48506694 | Q39: =IF(E39="Premier League",Priors!$H$4,IF(E39="Championship",Priors!$H$5,Priors!$H$8)) -> 1 | R39: FALSE | S39: =IF(R39=TRUE,Priors!$H$6,1) -> 1 | T39: FALSE | U39: =IF(T39=TRUE,Priors!$H$7,1) -> 1 | V39: =P39*Q39*S39*U39 -> 0.48506694 | W39: =VLOOKUP(D39,Priors!$A$3:$C$6,2,FALSE) -> 0.041142361 | X39: =VLOOKUP(D39,Priors!$A$3:$C$6,3,FALSE) -> 0.04051308 | Y39: =IF(N39="",W39,V39*N39+(1-V39)*W39) -> 0.03141585 | Z39: =IF(O39="",X39,V39*O39+(1-V39)*X39) -> 0.024515199 | AA39: 1 | AB39: 1 | AC39: =Y39*AA39 -> 0.03141585 | AD39: =Z39*AB39 -> 0.024515199 | AE39: =1-V39 -> 0.51493306 | AF39: PL history | AJ39: FALSE | AK39: FPL Core Insights / official FPL historical feed | AL39: https://github.com/olbauday/FPL-Core-Insights/tree/main/data/2025-2026 | AO39: 0 | AP39: FALSE | AQ39: Total xG retained; low penalty contamination
A40: 38 | B40: A.García | C40: Aston Villa | D40: DEF | E40: Premier League | F40: Aston Villa | G40: 83 | H40: 0 | I40: 0.01 | J40: 0 | K40: 0.010843373 | L40: 48.2 | M40: 1.2684211 | N40: 0 | O40: 0.0085487177 | P40: =IFERROR(G40/(G40+Priors!$H$3),0) -> 0.076638966 | Q40: =IF(E40="Premier League",Priors!$H$4,IF(E40="Championship",Priors!$H$5,Priors!$H$8)) -> 1 | R40: FALSE | S40: =IF(R40=TRUE,Priors!$H$6,1) -> 1 | T40: FALSE | U40: =IF(T40=TRUE,Priors!$H$7,1) -> 1 | V40: =P40*Q40*S40*U40 -> 0.076638966 | W40: =VLOOKUP(D40,Priors!$A$3:$C$6,2,FALSE) -> 0.041142361 | X40: =VLOOKUP(D40,Priors!$A$3:$C$6,3,FALSE) -> 0.04051308 | Y40: =IF(N40="",W40,V40*N40+(1-V40)*W40) -> 0.037989253 | Z40: =IF(O40="",X40,V40*O40+(1-V40)*X40) -> 0.038063364 | AA40: 1 | AB40: 1 | AC40: =Y40*AA40 -> 0.037989253 | AD40: =Z40*AB40 -> 0.038063364 | AE40: =1-V40 -> 0.92336103 | AF40: PL history | AJ40: TRUE | AK40: FPL Core Insights / official FPL historical feed | AL40: https://github.com/olbauday/FPL-Core-Insights/tree/main/data/2025-2026 | AQ40: No comparable 25/26 PL penalty history
A41: 39 | B41: Nedeljkovic | C41: Aston Villa | D41: DEF | E41: Missing/non-PL | P41: =IFERROR(G41/(G41+Priors!$H$3),0) -> 0 | Q41: =IF(E41="Premier League",Priors!$H$4,IF(E41="Championship",Priors!$H$5,Priors!$H$8)) -> 0 | R41: FALSE | S41: =IF(R41=TRUE,Priors!$H$6,1) -> 1 | T41: FALSE | U41: =IF(T41=TRUE,Priors!$H$7,1) -> 1 | V41: =P41*Q41*S41*U41 -> 0 | W41: =VLOOKUP(D41,Priors!$A$3:$C$6,2,FALSE) -> 0.041142361 | X41: =VLOOKUP(D41,Priors!$A$3:$C$6,3,FALSE) -> 0.04051308 | Y41: =IF(N41="",W41,V41*N41+(1-V41)*W41) -> 0.041142361 | Z41: =IF(O41="",X41,V41*O41+(1-V41)*X41) -> 0.04051308 | AA41: 1 | AB41: 1 | AC41: =Y41*AA41 -> 0.041142361 | AD41: =Z41*AB41 -> 0.04051308 | AE41: =1-V41 -> 1 | AF41: Missing/non-PL | AJ41: TRUE | AK41: No reliable 25/26 history loaded | AO41: 0 | AP41: FALSE | AQ41: Total xG retained; low penalty contamination
A42: 41 | B42: Buendía | C42: Aston Villa | D42: MID | E42: Premier League | F42: Aston Villa | G42: 1753 | H42: 3.38 | I42: 2.23 | J42: 0.17353109 | K42: 0.11448945 | L42: 48.2 | M42: 1.2684211 | N42: 0.13680874 | O42: 0.090261389 | P42: =IFERROR(G42/(G42+Priors!$H$3),0) -> 0.6367599 | Q42: =IF(E42="Premier League",Priors!$H$4,IF(E42="Championship",Priors!$H$5,Priors!$H$8)) -> 1 | R42: FALSE | S42: =IF(R42=TRUE,Priors!$H$6,1) -> 1 | T42: FALSE | U42: =IF(T42=TRUE,Priors!$H$7,1) -> 1 | V42: =P42*Q42*S42*U42 -> 0.6367599 | W42: =VLOOKUP(D42,Priors!$A$3:$C$6,2,FALSE) -> 0.10751786 | X42: =VLOOKUP(D42,Priors!$A$3:$C$6,3,FALSE) -> 0.090240672 | Y42: =IF(N42="",W42,V42*N42+(1-V42)*W42) -> 0.12616912 | Z42: =IF(O42="",X42,V42*O42+(1-V42)*X42) -> 0.090253864 | AA42: 1 | AB42: 1 | AC42: =Y42*AA42 -> 0.12616912 | AD42: =Z42*AB42 -> 0.090253864 | AE42: =1-V42 -> 0.3632401 | AF42: PL history | AG42: 1 | AH42: 1 | AJ42: FALSE | AK42: FPL Core Insights / official FPL historical feed | AL42: https://github.com/olbauday/FPL-Core-Insights/tree/main/data/2025-2026 | AN42: 2 | AO42: 0 | AP42: TRUE | AQ42: Total xG retained; penalty channel not decomposed
A43: 42 | B43: Guessand | C43: Aston Villa | D43: MID | E43: Premier League | F43: Crystal Palace | G43: 909 | H43: 1.56 | I43: 0.85 | J43: 0.15445545 | K43: 0.084158416 | L43: 58.2 | M43: 1.5315789 | N43: 0.1008472 | O43: 0.054948794 | P43: =IFERROR(G43/(G43+Priors!$H$3),0) -> 0.47616553 | Q43: =IF(E43="Premier League",Priors!$H$4,IF(E43="Championship",Priors!$H$5,Priors!$H$8)) -> 1 | R43: TRUE | S43: =IF(R43=TRUE,Priors!$H$6,1) -> 0.85 | T43: FALSE | U43: =IF(T43=TRUE,Priors!$H$7,1) -> 1 | V43: =P43*Q43*S43*U43 -> 0.4047407 | W43: =VLOOKUP(D43,Priors!$A$3:$C$6,2,FALSE) -> 0.10751786 | X43: =VLOOKUP(D43,Priors!$A$3:$C$6,3,FALSE) -> 0.090240672 | Y43: =IF(N43="",W43,V43*N43+(1-V43)*W43) -> 0.10481797 | Z43: =IF(O43="",X43,V43*O43+(1-V43)*X43) -> 0.075956612 | AA43: 1 | AB43: 1 | AC43: =Y43*AA43 -> 0.10481797 | AD43: =Z43*AB43 -> 0.075956612 | AE43: =1-V43 -> 0.5952593 | AF43: PL history | AJ43: TRUE | AK43: FPL Core Insights / official FPL historical feed | AL43: https://github.com/olbauday/FPL-Core-Insights/tree/main/data/2025-2026 | AO43: 0 | AP43: FALSE | AQ43: Total xG retained; low penalty contamination
A44: 44 | B44: Bailey | C44: Aston Villa | D44: MID | E44: Premier League | F44: Aston Villa | G44: 450 | H44: 0.5 | I44: 1.46 | J44: 0.1 | K44: 0.292 | L44: 48.2 | M44: 1.2684211 | N44: 0.078838174 | O44: 0.23020747 | P44: =IFERROR(G44/(G44+Priors!$H$3),0) -> 0.31034483 | Q44: =IF(E44="Premier League",Priors!$H$4,IF(E44="Championship",Priors!$H$5,Priors!$H$8)) -> 1 | R44: FALSE | S44: =IF(R44=TRUE,Priors!$H$6,1) -> 1 | T44: FALSE | U44: =IF(T44=TRUE,Priors!$H$7,1) -> 1 | V44: =P44*Q44*S44*U44 -> 0.31034483 | W44: =VLOOKUP(D44,Priors!$A$3:$C$6,2,FALSE) -> 0.10751786 | X44: =VLOOKUP(D44,Priors!$A$3:$C$6,3,FALSE) -> 0.090240672 | Y44: =IF(N44="",W44,V44*N44+(1-V44)*W44) -> 0.098617269 | Z44: =IF(O44="",X44,V44*O44+(1-V44)*X44) -> 0.13367864 | AA44: 1 | AB44: 1 | AC44: =Y44*AA44 -> 0.098617269 | AD44: =Z44*AB44 -> 0.13367864 | AE44: =1-V44 -> 0.68965517 | AF44: PL history | AJ44: TRUE | AK44: FPL Core Insights / official FPL historical feed | AL44: https://github.com/olbauday/FPL-Core-Insights/tree/main/data/2025-2026 | AO44: 0 | AP44: FALSE | AQ44: Total xG retained; low penalty contamination
A45: 45 | B45: McGinn | C45: Aston Villa | D45: MID | E45: Premier League | F45: Aston Villa | G45: 2136 | H45: 3 | I45: 4.11 | J45: 0.12640449 | K45: 0.17317416 | L45: 48.2 | M45: 1.2684211 | N45: 0.099654996 | O45: 0.13652734 | P45: =IFERROR(G45/(G45+Priors!$H$3),0) -> 0.68112245 | Q45: =IF(E45="Premier League",Priors!$H$4,IF(E45="Championship",Priors!$H$5,Priors!$H$8)) -> 1 | R45: FALSE | S45: =IF(R45=TRUE,Priors!$H$6,1) -> 1 | T45: FALSE | U45: =IF(T45=TRUE,Priors!$H$7,1) -> 1 | V45: =P45*Q45*S45*U45 -> 0.68112245 | W45: =VLOOKUP(D45,Priors!$A$3:$C$6,2,FALSE) -> 0.10751786 | X45: =VLOOKUP(D45,Priors!$A$3:$C$6,3,FALSE) -> 0.090240672 | Y45: =IF(N45="",W45,V45*N45+(1-V45)*W45) -> 0.10216229 | Z45: =IF(O45="",X45,V45*O45+(1-V45)*X45) -> 0.12176756 | AA45: 1 | AB45: 1 | AC45: =Y45*AA45 -> 0.10216229 | AD45: =Z45*AB45 -> 0.12176756 | AE45: =1-V45 -> 0.31887755 | AF45: PL history | AI45: 6 | AJ45: FALSE | AK45: FPL Core Insights / official FPL historical feed | AL45: https://github.com/olbauday/FPL-Core-Insights/tree/main/data/2025-2026 | AO45: 0 | AP45: FALSE | AQ45: Total xG retained; low penalty contamination
A46: 46 | B46: Barkley | C46: Aston Villa | D46: MID | E46: Premier League | F46: Aston Villa | G46: 844 | H46: 1.58 | I46: 1.26 | J46: 0.16848341 | K46: 0.13436019 | L46: 48.2 | M46: 1.2684211 | N46: 0.13282925 | O46: 0.10592712 | P46: =IFERROR(G46/(G46+Priors!$H$3),0) -> 0.45770065 | Q46: =IF(E46="Premier League",Priors!$H$4,IF(E46="Championship",Priors!$H$5,Priors!$H$8)) -> 1 | R46: FALSE | S46: =IF(R46=TRUE,Priors!$H$6,1) -> 1 | T46: FALSE | U46: =IF(T46=TRUE,Priors!$H$7,1) -> 1 | V46: =P46*Q46*S46*U46 -> 0.45770065 | W46: =VLOOKUP(D46,Priors!$A$3:$C$6,2,FALSE) -> 0.10751786 | X46: =VLOOKUP(D46,Priors!$A$3:$C$6,3,FALSE) -> 0.090240672 | Y46: =IF(N46="",W46,V46*N46+(1-V46)*W46) -> 0.1191029 | Z46: =IF(O46="",X46,V46*O46+(1-V46)*X46) -> 0.09742037 | AA46: 1 | AB46: 1 | AC46: =Y46*AA46 -> 0.1191029 | AD46: =Z46*AB46 -> 0.09742037 | AE46: =1-V46 -> 0.54229935 | AF46: PL history | AJ46: FALSE | AK46: FPL Core Insights / official FPL historical feed | AL46: https://github.com/olbauday/FPL-Core-Insights/tree/main/data/2025-2026 | AO46: 0 | AP46: FALSE | AQ46: Total xG retained; low penalty contamination
A47: 47 | B47: Kamara | C47: Aston Villa | D47: MID | E47: Premier League | F47: Aston Villa | G47: 1410 | H47: 0.53 | I47: 0.84 | J47: 0.033829787 | K47: 0.053617021 | L47: 48.2 | M47: 1.2684211 | N47: 0.026670787 | O47: 0.042270681 | P47: =IFERROR(G47/(G47+Priors!$H$3),0) -> 0.58506224 | Q47: =IF(E47="Premier League",Priors!$H$4,IF(E47="Championship",Priors!$H$5,Priors!$H$8)) -> 1 | R47: FALSE | S47: =IF(R47=TRUE,Priors!$H$6,1) -> 1 | T47: FALSE | U47: =IF(T47=TRUE,Priors!$H$7,1) -> 1 | V47: =P47*Q47*S47*U47 -> 0.58506224 | W47: =VLOOKUP(D47,Priors!$A$3:$C$6,2,FALSE) -> 0.10751786 | X47: =VLOOKUP(D47,Priors!$A$3:$C$6,3,FALSE) -> 0.090240672 | Y47: =IF(N47="",W47,V47*N47+(1-V47)*W47) -> 0.060217291 | Z47: =IF(O47="",X47,V47*O47+(1-V47)*X47) -> 0.062175241 | AA47: 1 | AB47: 1 | AC47: =Y47*AA47 -> 0.060217291 | AD47: =Z47*AB47 -> 0.062175241 | AE47: =1-V47 -> 0.41493776 | AF47: PL history | AJ47: FALSE | AK47: FPL Core Insights / official FPL historical feed | AL47: https://github.com/olbauday/FPL-Core-Insights/tree/main/data/2025-2026 | AO47: 0 | AP47: FALSE | AQ47: Total xG retained; low penalty contamination
A48: 48 | B48: Onana | C48: Aston Villa | D48: MID | E48: Premier League | F48: Aston Villa | G48: 1755 | H48: 1.68 | I48: 0.69 | J48: 0.086153846 | K48: 0.035384615 | L48: 48.2 | M48: 1.2684211 | N48: 0.067922119 | O48: 0.027896585 | P48: =IFERROR(G48/(G48+Priors!$H$3),0) -> 0.63702359 | Q48: =IF(E48="Premier League",Priors!$H$4,IF(E48="Championship",Priors!$H$5,Priors!$H$8)) -> 1 | R48: FALSE | S48: =IF(R48=TRUE,Priors!$H$6,1) -> 1 | T48: FALSE | U48: =IF(T48=TRUE,Priors!$H$7,1) -> 1 | V48: =P48*Q48*S48*U48 -> 0.63702359 | W48: =VLOOKUP(D48,Priors!$A$3:$C$6,2,FALSE) -> 0.10751786 | X48: =VLOOKUP(D48,Priors!$A$3:$C$6,3,FALSE) -> 0.090240672 | Y48: =IF(N48="",W48,V48*N48+(1-V48)*W48) -> 0.082294439 | Z48: =IF(O48="",X48,V48*O48+(1-V48)*X48) -> 0.050526017 | AA48: 1 | AB48: 1 | AC48: =Y48*AA48 -> 0.082294439 | AD48: =Z48*AB48 -> 0.050526017 | AE48: =1-V48 -> 0.36297641 | AF48: PL history | AJ48: FALSE | AK48: FPL Core Insights / official FPL historical feed | AL48: https://github.com/olbauday/FPL-Core-Insights/tree/main/data/2025-2026 | AO48: 0 | AP48: FALSE | AQ48: Total xG retained; low penalty contamination
A49: 49 | B49: Iling Jr | C49: Aston Villa | D49: MID | E49: Missing/non-PL | P49: =IFERROR(G49/(G49+Priors!$H$3),0) -> 0 | Q49: =IF(E49="Premier League",Priors!$H$4,IF(E49="Championship",Priors!$H$5,Priors!$H$8)) -> 0 | R49: FALSE | S49: =IF(R49=TRUE,Priors!$H$6,1) -> 1 | T49: FALSE | U49: =IF(T49=TRUE,Priors!$H$7,1) -> 1 | V49: =P49*Q49*S49*U49 -> 0 | W49: =VLOOKUP(D49,Priors!$A$3:$C$6,2,FALSE) -> 0.10751786 | X49: =VLOOKUP(D49,Priors!$A$3:$C$6,3,FALSE) -> 0.090240672 | Y49: =IF(N49="",W49,V49*N49+(1-V49)*W49) -> 0.10751786 | Z49: =IF(O49="",X49,V49*O49+(1-V49)*X49) -> 0.090240672 | AA49: 1 | AB49: 1 | AC49: =Y49*AA49 -> 0.10751786 | AD49: =Z49*AB49 -> 0.090240672 | AE49: =1-V49 -> 1 | AF49: Missing/non-PL | AJ49: TRUE | AK49: No reliable 25/26 history loaded | AO49: 0 | AP49: FALSE | AQ49: Total xG retained; low penalty contamination
A50: 50 | B50: Burrowes | C50: Aston Villa | D50: MID | E50: Premier League | F50: Aston Villa | G50: 16 | H50: 0 | I50: 0 | J50: 0 | K50: 0 | L50: 48.2 | M50: 1.2684211 | N50: 0 | O50: 0 | P50: =IFERROR(G50/(G50+Priors!$H$3),0) -> 0.015748031 | Q50: =IF(E50="Premier League",Priors!$H$4,IF(E50="Championship",Priors!$H$5,Priors!$H$8)) -> 1 | R50: FALSE | S50: =IF(R50=TRUE,Priors!$H$6,1) -> 1 | T50: FALSE | U50: =IF(T50=TRUE,Priors!$H$7,1) -> 1 | V50: =P50*Q50*S50*U50 -> 0.015748031 | W50: =VLOOKUP(D50,Priors!$A$3:$C$6,2,FALSE) -> 0.10751786 | X50: =VLOOKUP(D50,Priors!$A$3:$C$6,3,FALSE) -> 0.090240672 | Y50: =IF(N50="",W50,V50*N50+(1-V50)*W50) -> 0.10582467 | Z50: =IF(O50="",X50,V50*O50+(1-V50)*X50) -> 0.088819559 | AA50: 1 | AB50: 1 | AC50: =Y50*AA50 -> 0.10582467 | AD50: =Z50*AB50 -> 0.088819559 | AE50: =1-V50 -> 0.98425197 | AF50: PL history | AJ50: TRUE | AK50: FPL Core Insights / official FPL historical feed | AL50: https://github.com/olbauday/FPL-Core-Insights/tree/main/data/2025-2026 | AO50: 0 | AP50: FALSE | AQ50: Total xG retained; low penalty contamination
A51: 51 | B51: George Hemmings | C51: Aston Villa | D51: MID | E51: Premier League | F51: Aston Villa | G51: 25 | H51: 0.04 | I51: 0.01 | J51: 0.144 | K51: 0.036 | L51: 48.2 | M51: 1.2684211 | N51: 0.11352697 | O51: 0.028381743 | P51: =IFERROR(G51/(G51+Priors!$H$3),0) -> 0.024390244 | Q51: =IF(E51="Premier League",Priors!$H$4,IF(E51="Championship",Priors!$H$5,Priors!$H$8)) -> 1 | R51: FALSE | S51: =IF(R51=TRUE,Priors!$H$6,1) -> 1 | T51: FALSE | U51: =IF(T51=TRUE,Priors!$H$7,1) -> 1 | V51: =P51*Q51*S51*U51 -> 0.024390244 | W51: =VLOOKUP(D51,Priors!$A$3:$C$6,2,FALSE) -> 0.10751786 | X51: =VLOOKUP(D51,Priors!$A$3:$C$6,3,FALSE) -> 0.090240672 | Y51: =IF(N51="",W51,V51*N51+(1-V51)*W51) -> 0.10766442 | Z51: =IF(O51="",X51,V51*O51+(1-V51)*X51) -> 0.088731918 | AA51: 1 | AB51: 1 | AC51: =Y51*AA51 -> 0.10766442 | AD51: =Z51*AB51 -> 0.088731918 | AE51: =1-V51 -> 0.97560976 | AF51: PL history | AJ51: TRUE | AK51: FPL Core Insights / official FPL historical feed | AL51: https://github.com/olbauday/FPL-Core-Insights/tree/main/data/2025-2026 | AO51: 0 | AP51: FALSE | AQ51: Total xG retained; low penalty contamination
A52: 52 | B52: Alysson | C52: Aston Villa | D52: MID | E52: Premier League | F52: Aston Villa | G52: 47 | H52: 0.05 | I52: 0.05 | J52: 0.095744681 | K52: 0.095744681 | L52: 48.2 | M52: 1.2684211 | N52: 0.075483358 | O52: 0.075483358 | P52: =IFERROR(G52/(G52+Priors!$H$3),0) -> 0.044890162 | Q52: =IF(E52="Premier League",Priors!$H$4,IF(E52="Championship",Priors!$H$5,Priors!$H$8)) -> 1 | R52: FALSE | S52: =IF(R52=TRUE,Priors!$H$6,1) -> 1 | T52: FALSE | U52: =IF(T52=TRUE,Priors!$H$7,1) -> 1 | V52: =P52*Q52*S52*U52 -> 0.044890162 | W52: =VLOOKUP(D52,Priors!$A$3:$C$6,2,FALSE) -> 0.10751786 | X52: =VLOOKUP(D52,Priors!$A$3:$C$6,3,FALSE) -> 0.090240672 | Y52: =IF(N52="",W52,V52*N52+(1-V52)*W52) -> 0.10607983 | Z52: =IF(O52="",X52,V52*O52+(1-V52)*X52) -> 0.089578214 | AA52: 1 | AB52: 1 | AC52: =Y52*AA52 -> 0.10607983 | AD52: =Z52*AB52 -> 0.089578214 | AE52: =1-V52 -> 0.95510984 | AF52: PL history | AJ52: TRUE | AK52: FPL Core Insights / official FPL historical feed | AL52: https://github.com/olbauday/FPL-Core-Insights/tree/main/data/2025-2026 | AO52: 0 | AP52: FALSE | AQ52: Total xG retained; low penalty contamination
A53: 53 | B53: Manzambi | C53: Aston Villa | D53: MID | E53: Missing/non-PL | P53: =IFERROR(G53/(G53+Priors!$H$3),0) -> 0 | Q53: =IF(E53="Premier League",Priors!$H$4,IF(E53="Championship",Priors!$H$5,Priors!$H$8)) -> 0 | R53: FALSE | S53: =IF(R53=TRUE,Priors!$H$6,1) -> 1 | T53: FALSE | U53: =IF(T53=TRUE,Priors!$H$7,1) -> 1 | V53: =P53*Q53*S53*U53 -> 0 | W53: =VLOOKUP(D53,Priors!$A$3:$C$6,2,FALSE) -> 0.10751786 | X53: =VLOOKUP(D53,Priors!$A$3:$C$6,3,FALSE) -> 0.090240672 | Y53: =IF(N53="",W53,V53*N53+(1-V53)*W53) -> 0.10751786 | Z53: =IF(O53="",X53,V53*O53+(1-V53)*X53) -> 0.090240672 | AA53: 1 | AB53: 1 | AC53: =Y53*AA53 -> 0.10751786 | AD53: =Z53*AB53 -> 0.090240672 | AE53: =1-V53 -> 1 | AF53: Missing/non-PL | AJ53: TRUE | AK53: No reliable 25/26 history loaded | AO53: 0 | AP53: FALSE | AQ53: Total xG retained; low penalty contamination
A54: 54 | B54: Gomes | C54: Aston Villa | D54: MID | E54: Premier League | F54: Wolves | G54: 2829 | H54: 1.29 | I54: 2.09 | J54: 0.041039236 | K54: 0.066489926 | L54: 35.5 | M54: 0.93421053 | N54: 0.043929324 | O54: 0.071172315 | P54: =IFERROR(G54/(G54+Priors!$H$3),0) -> 0.73883521 | Q54: =IF(E54="Premier League",Priors!$H$4,IF(E54="Championship",Priors!$H$5,Priors!$H$8)) -> 1 | R54: TRUE | S54: =IF(R54=TRUE,Priors!$H$6,1) -> 0.85 | T54: FALSE | U54: =IF(T54=TRUE,Priors!$H$7,1) -> 1 | V54: =P54*Q54*S54*U54 -> 0.62800992 | W54: =VLOOKUP(D54,Priors!$A$3:$C$6,2,FALSE) -> 0.10751786 | X54: =VLOOKUP(D54,Priors!$A$3:$C$6,3,FALSE) -> 0.090240672 | Y54: =IF(N54="",W54,V54*N54+(1-V54)*W54) -> 0.067583628 | Z54: =IF(O54="",X54,V54*O54+(1-V54)*X54) -> 0.078265554 | AA54: 1 | AB54: 1 | AC54: =Y54*AA54 -> 0.067583628 | AD54: =Z54*AB54 -> 0.078265554 | AE54: =1-V54 -> 0.37199008 | AF54: PL history | AJ54: TRUE | AK54: FPL Core Insights / official FPL historical feed | AL54: https://github.com/olbauday/FPL-Core-Insights/tree/main/data/2025-2026 | AQ54: No comparable 25/26 PL penalty history
A55: 55 | B55: Watkins | C55: Aston Villa | D55: FWD | E55: Premier League | F55: Aston Villa | G55: 2833 | H55: 15.4 | I55: 1.18 | J55: 0.48923403 | K55: 0.037486763 | L55: 48.2 | M55: 1.2684211 | N55: 0.38570318 | O55: 0.02955388 | P55: =IFERROR(G55/(G55+Priors!$H$3),0) -> 0.73910775 | Q55: =IF(E55="Premier League",Priors!$H$4,IF(E55="Championship",Priors!$H$5,Priors!$H$8)) -> 1 | R55: FALSE | S55: =IF(R55=TRUE,Priors!$H$6,1) -> 1 | T55: FALSE | U55: =IF(T55=TRUE,Priors!$H$7,1) -> 1 | V55: =P55*Q55*S55*U55 -> 0.73910775 | W55: =VLOOKUP(D55,Priors!$A$3:$C$6,2,FALSE) -> 0.30461526 | X55: =VLOOKUP(D55,Priors!$A$3:$C$6,3,FALSE) -> 0.039258062 | Y55: =IF(N55="",W55,V55*N55+(1-V55)*W55) -> 0.36454797 | Z55: =IF(O55="",X55,V55*O55+(1-V55)*X55) -> 0.032085626 | AA55: 1 | AB55: 1 | AC55: =Y55*AA55 -> 0.36454797 | AD55: =Z55*AB55 -> 0.032085626 | AE55: =1-V55 -> 0.26089225 | AF55: PL history | AG55: 2 | AJ55: FALSE | AK55: FPL Core Insights / official FPL historical feed | AL55: https://github.com/olbauday/FPL-Core-Insights/tree/main/data/2025-2026 | AO55: 0 | AP55: FALSE | AQ55: Total xG retained; low penalty contamination
A56: 56 | B56: Abraham | C56: Aston Villa | D56: FWD | E56: Premier League | F56: Aston Villa | G56: 278 | H56: 2.05 | I56: 0.36 | J56: 0.66366906 | K56: 0.11654676 | L56: 48.2 | M56: 1.2684211 | N56: 0.52322457 | O56: 0.09188334 | P56: =IFERROR(G56/(G56+Priors!$H$3),0) -> 0.21752739 | Q56: =IF(E56="Premier League",Priors!$H$4,IF(E56="Championship",Priors!$H$5,Priors!$H$8)) -> 1 | R56: FALSE | S56: =IF(R56=TRUE,Priors!$H$6,1) -> 1 | T56: FALSE | U56: =IF(T56=TRUE,Priors!$H$7,1) -> 1 | V56: =P56*Q56*S56*U56 -> 0.21752739 | W56: =VLOOKUP(D56,Priors!$A$3:$C$6,2,FALSE) -> 0.30461526 | X56: =VLOOKUP(D56,Priors!$A$3:$C$6,3,FALSE) -> 0.039258062 | Y56: =IF(N56="",W56,V56*N56+(1-V56)*W56) -> 0.35216877 | Z56: =IF(O56="",X56,V56*O56+(1-V56)*X56) -> 0.050705501 | AA56: 1 | AB56: 1 | AC56: =Y56*AA56 -> 0.35216877 | AD56: =Z56*AB56 -> 0.050705501 | AE56: =1-V56 -> 0.78247261 | AF56: PL history | AJ56: TRUE | AK56: FPL Core Insights / official FPL historical feed | AL56: https://github.com/olbauday/FPL-Core-Insights/tree/main/data/2025-2026 | AN56: 3 | AO56: 0 | AP56: FALSE | AQ56: Total xG retained; low penalty contamination
A57: 160 | B57: Garnacho | C57: Aston Villa | D57: MID | E57: Premier League | F57: Chelsea | G57: 1261 | H57: 3.44 | I57: 3.68 | J57: 0.24551943 | K57: 0.26264869 | L57: 66.5 | M57: 1.75 | N57: 0.14029682 | O57: 0.15008497 | P57: =IFERROR(G57/(G57+Priors!$H$3),0) -> 0.55771782 | Q57: =IF(E57="Premier League",Priors!$H$4,IF(E57="Championship",Priors!$H$5,Priors!$H$8)) -> 1 | R57: TRUE | S57: =IF(R57=TRUE,Priors!$H$6,1) -> 0.85 | T57: FALSE | U57: =IF(T57=TRUE,Priors!$H$7,1) -> 1 | V57: =P57*Q57*S57*U57 -> 0.47406015 | W57: =VLOOKUP(D57,Priors!$A$3:$C$6,2,FALSE) -> 0.10751786 | X57: =VLOOKUP(D57,Priors!$A$3:$C$6,3,FALSE) -> 0.090240672 | Y57: =IF(N57="",W57,V57*N57+(1-V57)*W57) -> 0.12305706 | Z57: =IF(O57="",X57,V57*O57+(1-V57)*X57) -> 0.11861047 | AA57: 1 | AB57: 1 | AC57: =Y57*AA57 -> 0.12305706 | AD57: =Z57*AB57 -> 0.11861047 | AE57: =1-V57 -> 0.52593985 | AF57: PL history | AJ57: TRUE | AK57: FPL Core Insights / official FPL historical feed | AL57: https://github.com/olbauday/FPL-Core-Insights/tree/main/data/2025-2026 | AO57: 0 | AP57: FALSE | AQ57: Total xG retained; low penalty contamination
A58: 57 | B58: Petrović | C58: Bournemouth | D58: GK | E58: Premier League | F58: Bournemouth | G58: 3420 | H58: 0 | I58: 0 | J58: 0 | K58: 0 | L58: 61.9 | M58: 1.6289474 | N58: 0 | O58: 0 | P58: =IFERROR(G58/(G58+Priors!$H$3),0) -> 0.77375566 | Q58: =IF(E58="Premier League",Priors!$H$4,IF(E58="Championship",Priors!$H$5,Priors!$H$8)) -> 1 | R58: FALSE | S58: =IF(R58=TRUE,Priors!$H$6,1) -> 1 | T58: TRUE | U58: =IF(T58=TRUE,Priors!$H$7,1) -> 0.9 | V58: =P58*Q58*S58*U58 -> 0.69638009 | W58: =VLOOKUP(D58,Priors!$A$3:$C$6,2,FALSE) -> 0.00016719535 | X58: =VLOOKUP(D58,Priors!$A$3:$C$6,3,FALSE) -> 0.0013793616 | Y58: =IF(N58="",W58,V58*N58+(1-V58)*W58) -> 5.0763837e-05 | Z58: =IF(O58="",X58,V58*O58+(1-V58)*X58) -> 0.00041880165 | AA58: 1 | AB58: 1 | AC58: =Y58*AA58 -> 5.0763837e-05 | AD58: =Z58*AB58 -> 0.00041880165 | AE58: =1-V58 -> 0.30361991 | AF58: PL history | AJ58: TRUE | AK58: FPL Core Insights / official FPL historical feed | AL58: https://github.com/olbauday/FPL-Core-Insights/tree/main/data/2025-2026 | AO58: 0 | AP58: FALSE | AQ58: Total xG retained; low penalty contamination
A59: 58 | B59: Forster | C59: Bournemouth | D59: GK | E59: Missing/non-PL | P59: =IFERROR(G59/(G59+Priors!$H$3),0) -> 0 | Q59: =IF(E59="Premier League",Priors!$H$4,IF(E59="Championship",Priors!$H$5,Priors!$H$8)) -> 0 | R59: FALSE | S59: =IF(R59=TRUE,Priors!$H$6,1) -> 1 | T59: TRUE | U59: =IF(T59=TRUE,Priors!$H$7,1) -> 0.9 | V59: =P59*Q59*S59*U59 -> 0 | W59: =VLOOKUP(D59,Priors!$A$3:$C$6,2,FALSE) -> 0.00016719535 | X59: =VLOOKUP(D59,Priors!$A$3:$C$6,3,FALSE) -> 0.0013793616 | Y59: =IF(N59="",W59,V59*N59+(1-V59)*W59) -> 0.00016719535 | Z59: =IF(O59="",X59,V59*O59+(1-V59)*X59) -> 0.0013793616 | AA59: 1 | AB59: 1 | AC59: =Y59*AA59 -> 0.00016719535 | AD59: =Z59*AB59 -> 0.0013793616 | AE59: =1-V59 -> 1 | AF59: Missing/non-PL | AJ59: TRUE | AK59: No reliable 25/26 history loaded | AO59: 0 | AP59: FALSE | AQ59: Total xG retained; low penalty contamination
A60: 59 | B60: Dennis | C60: Bournemouth | D60: GK | E60: Missing/non-PL | P60: =IFERROR(G60/(G60+Priors!$H$3),0) -> 0 | Q60: =IF(E60="Premier League",Priors!$H$4,IF(E60="Championship",Priors!$H$5,Priors!$H$8)) -> 0 | R60: FALSE | S60: =IF(R60=TRUE,Priors!$H$6,1) -> 1 | T60: TRUE | U60: =IF(T60=TRUE,Priors!$H$7,1) -> 0.9 | V60: =P60*Q60*S60*U60 -> 0 | W60: =VLOOKUP(D60,Priors!$A$3:$C$6,2,FALSE) -> 0.00016719535 | X60: =VLOOKUP(D60,Priors!$A$3:$C$6,3,FALSE) -> 0.0013793616 | Y60: =IF(N60="",W60,V60*N60+(1-V60)*W60) -> 0.00016719535 | Z60: =IF(O60="",X60,V60*O60+(1-V60)*X60) -> 0.0013793616 | AA60: 1 | AB60: 1 | AC60: =Y60*AA60 -> 0.00016719535 | AD60: =Z60*AB60 -> 0.0013793616 | AE60: =1-V60 -> 1 | AF60: Missing/non-PL | AJ60: TRUE | AK60: No reliable 25/26 history loaded | AO60: 0 | AP60: FALSE | AQ60: Total xG retained; low penalty contamination
A61: 60 | B61: Hill | C61: Bournemouth | D61: DEF | E61: Premier League | F61: Bournemouth | G61: 2102 | H61: 0.89 | I61: 1.16 | J61: 0.038106565 | K61: 0.049666984 | L61: 61.9 | M61: 1.6289474 | N61: 0.023393368 | O61: 0.030490232 | P61: =IFERROR(G61/(G61+Priors!$H$3),0) -> 0.67762734 | Q61: =IF(E61="Premier League",Priors!$H$4,IF(E61="Championship",Priors!$H$5,Priors!$H$8)) -> 1 | R61: FALSE | S61: =IF(R61=TRUE,Priors!$H$6,1) -> 1 | T61: TRUE | U61: =IF(T61=TRUE,Priors!$H$7,1) -> 0.9 | V61: =P61*Q61*S61*U61 -> 0.6098646 | W61: =VLOOKUP(D61,Priors!$A$3:$C$6,2,FALSE) -> 0.041142361 | X61: =VLOOKUP(D61,Priors!$A$3:$C$6,3,FALSE) -> 0.04051308 | Y61: =IF(N61="",W61,V61*N61+(1-V61)*W61) -> 0.030317879 | Z61: =IF(O61="",X61,V61*O61+(1-V61)*X61) -> 0.0344005 | AA61: 1 | AB61: 1 | AC61: =Y61*AA61 -> 0.030317879 | AD61: =Z61*AB61 -> 0.0344005 | AE61: =1-V61 -> 0.3901354 | AF61: PL history | AJ61: TRUE | AK61: FPL Core Insights / official FPL historical feed | AL61: https://github.com/olbauday/FPL-Core-Insights/tree/main/data/2025-2026 | AO61: 0 | AP61: FALSE | AQ61: Total xG retained; low penalty contamination
A62: 61 | B62: Truffert | C62: Bournemouth | D62: DEF | E62: Premier League | F62: Bournemouth | G62: 3378 | H62: 1.35 | I62: 3.07 | J62: 0.035968028 | K62: 0.081793961 | L62: 61.9 | M62: 1.6289474 | N62: 0.022080534 | O62: 0.050212771 | P62: =IFERROR(G62/(G62+Priors!$H$3),0) -> 0.7715852 | Q62: =IF(E62="Premier League",Priors!$H$4,IF(E62="Championship",Priors!$H$5,Priors!$H$8)) -> 1 | R62: FALSE | S62: =IF(R62=TRUE,Priors!$H$6,1) -> 1 | T62: TRUE | U62: =IF(T62=TRUE,Priors!$H$7,1) -> 0.9 | V62: =P62*Q62*S62*U62 -> 0.69442668 | W62: =VLOOKUP(D62,Priors!$A$3:$C$6,2,FALSE) -> 0.041142361 | X62: =VLOOKUP(D62,Priors!$A$3:$C$6,3,FALSE) -> 0.04051308 | Y62: =IF(N62="",W62,V62*N62+(1-V62)*W62) -> 0.02790532 | Z62: =IF(O62="",X62,V62*O62+(1-V62)*X62) -> 0.047248804 | AA62: 1 | AB62: 1 | AC62: =Y62*AA62 -> 0.02790532 | AD62: =Z62*AB62 -> 0.047248804 | AE62: =1-V62 -> 0.30557332 | AF62: PL history | AJ62: TRUE | AK62: FPL Core Insights / official FPL historical feed | AL62: https://github.com/olbauday/FPL-Core-Insights/tree/main/data/2025-2026 | AO62: 0 | AP62: FALSE | AQ62: Total xG retained; low penalty contamination
A63: 62 | B63: Diakité | C63: Bournemouth | D63: DEF | E63: Premier League | F63: Bournemouth | G63: 1275 | H63: 0.02 | I63: 0.19 | J63: 0.0014117647 | K63: 0.013411765 | L63: 61.9 | M63: 1.6289474 | N63: 0.000866673 | O63: 0.0082333935 | P63: =IFERROR(G63/(G63+Priors!$H$3),0) -> 0.56043956 | Q63: =IF(E63="Premier League",Priors!$H$4,IF(E63="Championship",Priors!$H$5,Priors!$H$8)) -> 1 | R63: FALSE | S63: =IF(R63=TRUE,Priors!$H$6,1) -> 1 | T63: TRUE | U63: =IF(T63=TRUE,Priors!$H$7,1) -> 0.9 | V63: =P63*Q63*S63*U63 -> 0.5043956 | W63: =VLOOKUP(D63,Priors!$A$3:$C$6,2,FALSE) -> 0.041142361 | X63: =VLOOKUP(D63,Priors!$A$3:$C$6,3,FALSE) -> 0.04051308 | Y63: =IF(N63="",W63,V63*N63+(1-V63)*W63) -> 0.020827481 | Z63: =IF(O63="",X63,V63*O63+(1-V63)*X63) -> 0.024231348 | AA63: 1 | AB63: 1 | AC63: =Y63*AA63 -> 0.020827481 | AD63: =Z63*AB63 -> 0.024231348 | AE63: =1-V63 -> 0.4956044 | AF63: PL history | AJ63: TRUE | AK63: FPL Core Insights / official FPL historical feed | AL63: https://github.com/olbauday/FPL-Core-Insights/tree/main/data/2025-2026 | AO63: 0 | AP63: FALSE | AQ63: Total xG retained; low penalty contamination
A64: 63 | B64: Milosavljević | C64: Bournemouth | D64: DEF | E64: Premier League | F64: Bournemouth | G64: 367 | H64: 0.15 | I64: 0.19 | J64: 0.036784741 | K64: 0.046594005 | L64: 61.9 | M64: 1.6289474 | N64: 0.022581909 | O64: 0.028603751 | P64: =IFERROR(G64/(G64+Priors!$H$3),0) -> 0.2684711 | Q64: =IF(E64="Premier League",Priors!$H$4,IF(E64="Championship",Priors!$H$5,Priors!$H$8)) -> 1 | R64: FALSE | S64: =IF(R64=TRUE,Priors!$H$6,1) -> 1 | T64: TRUE | U64: =IF(T64=TRUE,Priors!$H$7,1) -> 0.9 | V64: =P64*Q64*S64*U64 -> 0.24162399 | W64: =VLOOKUP(D64,Priors!$A$3:$C$6,2,FALSE) -> 0.041142361 | X64: =VLOOKUP(D64,Priors!$A$3:$C$6,3,FALSE) -> 0.04051308 | Y64: =IF(N64="",W64,V64*N64+(1-V64)*W64) -> 0.036657711 | Z64: =IF(O64="",X64,V64*O64+(1-V64)*X64) -> 0.0376355 | AA64: 1 | AB64: 1 | AC64: =Y64*AA64 -> 0.036657711 | AD64: =Z64*AB64 -> 0.0376355 | AE64: =1-V64 -> 0.75837601 | AF64: PL history | AJ64: TRUE | AK64: FPL Core Insights / official FPL historical feed | AL64: https://github.com/olbauday/FPL-Core-Insights/tree/main/data/2025-2026 | AO64: 0 | AP64: FALSE | AQ64: Total xG retained; low penalty contamination
A65: 64 | B65: Smith | C65: Bournemouth | D65: DEF | E65: Premier League | F65: Bournemouth | G65: 1073 | H65: 0 | I65: 0.23 | J65: 0 | K65: 0.019291705 | L65: 61.9 | M65: 1.6289474 | N65: 0 | O65: 0.01184305 | P65: =IFERROR(G65/(G65+Priors!$H$3),0) -> 0.51760733 | Q65: =IF(E65="Premier League",Priors!$H$4,IF(E65="Championship",Priors!$H$5,Priors!$H$8)) -> 1 | R65: FALSE | S65: =IF(R65=TRUE,Priors!$H$6,1) -> 1 | T65: TRUE | U65: =IF(T65=TRUE,Priors!$H$7,1) -> 0.9 | V65: =P65*Q65*S65*U65 -> 0.4658466 | W65: =VLOOKUP(D65,Priors!$A$3:$C$6,2,FALSE) -> 0.041142361 | X65: =VLOOKUP(D65,Priors!$A$3:$C$6,3,FALSE) -> 0.04051308 | Y65: =IF(N65="",W65,V65*N65+(1-V65)*W65) -> 0.021976332 | Z65: =IF(O65="",X65,V65*O65+(1-V65)*X65) -> 0.027157244 | AA65: 1 | AB65: 1 | AC65: =Y65*AA65 -> 0.021976332 | AD65: =Z65*AB65 -> 0.027157244 | AE65: =1-V65 -> 0.5341534 | AF65: PL history | AJ65: TRUE | AK65: FPL Core Insights / official FPL historical feed | AL65: https://github.com/olbauday/FPL-Core-Insights/tree/main/data/2025-2026 | AO65: 0 | AP65: FALSE | AQ65: Total xG retained; low penalty contamination
A66: 65 | B66: J.Araujo | C66: Bournemouth | D66: DEF | E66: Missing/non-PL | P66: =IFERROR(G66/(G66+Priors!$H$3),0) -> 0 | Q66: =IF(E66="Premier League",Priors!$H$4,IF(E66="Championship",Priors!$H$5,Priors!$H$8)) -> 0 | R66: FALSE | S66: =IF(R66=TRUE,Priors!$H$6,1) -> 1 | T66: TRUE | U66: =IF(T66=TRUE,Priors!$H$7,1) -> 0.9 | V66: =P66*Q66*S66*U66 -> 0 | W66: =VLOOKUP(D66,Priors!$A$3:$C$6,2,FALSE) -> 0.041142361 | X66: =VLOOKUP(D66,Priors!$A$3:$C$6,3,FALSE) -> 0.04051308 | Y66: =IF(N66="",W66,V66*N66+(1-V66)*W66) -> 0.041142361 | Z66: =IF(O66="",X66,V66*O66+(1-V66)*X66) -> 0.04051308 | AA66: 1 | AB66: 1 | AC66: =Y66*AA66 -> 0.041142361 | AD66: =Z66*AB66 -> 0.04051308 | AE66: =1-V66 -> 1 | AF66: Missing/non-PL | AJ66: TRUE | AK66: No reliable 25/26 history loaded | AO66: 0 | AP66: FALSE | AQ66: Total xG retained; low penalty contamination
A67: 66 | B67: Soler | C67: Bournemouth | D67: DEF | E67: Premier League | F67: Bournemouth | G67: 34 | H67: 0 | I67: 0 | J67: 0 | K67: 0 | L67: 61.9 | M67: 1.6289474 | N67: 0 | O67: 0 | P67: =IFERROR(G67/(G67+Priors!$H$3),0) -> 0.032882012 | Q67: =IF(E67="Premier League",Priors!$H$4,IF(E67="Championship",Priors!$H$5,Priors!$H$8)) -> 1 | R67: FALSE | S67: =IF(R67=TRUE,Priors!$H$6,1) -> 1 | T67: TRUE | U67: =IF(T67=TRUE,Priors!$H$7,1) -> 0.9 | V67: =P67*Q67*S67*U67 -> 0.02959381 | W67: =VLOOKUP(D67,Priors!$A$3:$C$6,2,FALSE) -> 0.041142361 | X67: =VLOOKUP(D67,Priors!$A$3:$C$6,3,FALSE) -> 0.04051308 | Y67: =IF(N67="",W67,V67*N67+(1-V67)*W67) -> 0.039924802 | Z67: =IF(O67="",X67,V67*O67+(1-V67)*X67) -> 0.039314143 | AA67: 1 | AB67: 1 | AC67: =Y67*AA67 -> 0.039924802 | AD67: =Z67*AB67 -> 0.039314143 | AE67: =1-V67 -> 0.97040619 | AF67: PL history | AJ67: TRUE | AK67: FPL Core Insights / official FPL historical feed | AL67: https://github.com/olbauday/FPL-Core-Insights/tree/main/data/2025-2026 | AO67: 0 | AP67: FALSE | AQ67: Total xG retained; low penalty contamination
A68: 67 | B68: Rayan | C68: Bournemouth | D68: MID | E68: Premier League | F68: Bournemouth | G68: 1110 | H68: 2.67 | I68: 1.84 | J68: 0.21648649 | K68: 0.14918919 | L68: 61.9 | M68: 1.6289474 | N68: 0.13289962 | O68: 0.091586255 | P68: =IFERROR(G68/(G68+Priors!$H$3),0) -> 0.52606635 | Q68: =IF(E68="Premier League",Priors!$H$4,IF(E68="Championship",Priors!$H$5,Priors!$H$8)) -> 1 | R68: FALSE | S68: =IF(R68=TRUE,Priors!$H$6,1) -> 1 | T68: TRUE | U68: =IF(T68=TRUE,Priors!$H$7,1) -> 0.9 | V68: =P68*Q68*S68*U68 -> 0.47345972 | W68: =VLOOKUP(D68,Priors!$A$3:$C$6,2,FALSE) -> 0.10751786 | X68: =VLOOKUP(D68,Priors!$A$3:$C$6,3,FALSE) -> 0.090240672 | Y68: =IF(N68="",W68,V68*N68+(1-V68)*W68) -> 0.1195351 | Z68: =IF(O68="",X68,V68*O68+(1-V68)*X68) -> 0.090877751 | AA68: 1 | AB68: 1 | AC68: =Y68*AA68 -> 0.1195351 | AD68: =Z68*AB68 -> 0.090877751 | AE68: =1-V68 -> 0.52654028 | AF68: PL history | AJ68: TRUE | AK68: FPL Core Insights / official FPL historical feed | AL68: https://github.com/olbauday/FPL-Core-Insights/tree/main/data/2025-2026 | AO68: 0 | AP68: FALSE | AQ68: Total xG retained; low penalty contamination
A69: 68 | B69: Tavernier | C69: Bournemouth | D69: MID | E69: Premier League | F69: Bournemouth | G69: 2732 | H69: 9.06 | I69: 4.6 | J69: 0.29846266 | K69: 0.15153734 | L69: 61.9 | M69: 1.6289474 | N69: 0.18322425 | O69: 0.093027766 | P69: =IFERROR(G69/(G69+Priors!$H$3),0) -> 0.73204716 | Q69: =IF(E69="Premier League",Priors!$H$4,IF(E69="Championship",Priors!$H$5,Priors!$H$8)) -> 1 | R69: FALSE | S69: =IF(R69=TRUE,Priors!$H$6,1) -> 1 | T69: TRUE | U69: =IF(T69=TRUE,Priors!$H$7,1) -> 0.9 | V69: =P69*Q69*S69*U69 -> 0.65884244 | W69: =VLOOKUP(D69,Priors!$A$3:$C$6,2,FALSE) -> 0.10751786 | X69: =VLOOKUP(D69,Priors!$A$3:$C$6,3,FALSE) -> 0.090240672 | Y69: =IF(N69="",W69,V69*N69+(1-V69)*W69) -> 0.15739645 | Z69: =IF(O69="",X69,V69*O69+(1-V69)*X69) -> 0.092076928 | AA69: 1 | AB69: 1 | AC69: =Y69*AA69 -> 0.15739645 | AD69: =Z69*AB69 -> 0.092076928 | AE69: =1-V69 -> 0.34115756 | AF69: PL history | AG69: 3 | AH69: 1 | AI69: 6 | AJ69: TRUE | AK69: FPL Core Insights / official FPL historical feed | AL69: https://github.com/olbauday/FPL-Core-Insights/tree/main/data/2025-2026 | AN69: 4 | AO69: 0 | AP69: FALSE | AQ69: Total xG retained; low penalty contamination
A70: 69 | B70: Scott | C70: Bournemouth | D70: MID | E70: Premier League | F70: Bournemouth | G70: 2848 | H70: 3.8 | I70: 2.94 | J70: 0.12008427 | K70: 0.092907303 | L70: 61.9 | M70: 1.6289474 | N70: 0.073718938 | O70: 0.057035178 | P70: =IFERROR(G70/(G70+Priors!$H$3),0) -> 0.74012474 | Q70: =IF(E70="Premier League",Priors!$H$4,IF(E70="Championship",Priors!$H$5,Priors!$H$8)) -> 1 | R70: FALSE | S70: =IF(R70=TRUE,Priors!$H$6,1) -> 1 | T70: TRUE | U70: =IF(T70=TRUE,Priors!$H$7,1) -> 0.9 | V70: =P70*Q70*S70*U70 -> 0.66611227 | W70: =VLOOKUP(D70,Priors!$A$3:$C$6,2,FALSE) -> 0.10751786 | X70: =VLOOKUP(D70,Priors!$A$3:$C$6,3,FALSE) -> 0.090240672 | Y70: =IF(N70="",W70,V70*N70+(1-V70)*W70) -> 0.085003984 | Z70: =IF(O70="",X70,V70*O70+(1-V70)*X70) -> 0.068122085 | AA70: 1 | AB70: 1 | AC70: =Y70*AA70 -> 0.085003984 | AD70: =Z70*AB70 -> 0.068122085 | AE70: =1-V70 -> 0.33388773 | AF70: PL history | AH70: 4 | AI70: 7 | AJ70: TRUE | AK70: FPL Core Insights / official FPL historical feed | AL70: https://github.com/olbauday/FPL-Core-Insights/tree/main/data/2025-2026 | AO70: 0 | AP70: FALSE | AQ70: Total xG retained; low penalty contamination
A71: 70 | B71: Kluivert | C71: Bournemouth | D71: MID | E71: Premier League | F71: Bournemouth | G71: 945 | H71: 2.31 | I71: 1.55 | J71: 0.22 | K71: 0.14761905 | L71: 61.9 | M71: 1.6289474 | N71: 0.13505654 | O71: 0.090622356 | P71: =IFERROR(G71/(G71+Priors!$H$3),0) -> 0.48586118 | Q71: =IF(E71="Premier League",Priors!$H$4,IF(E71="Championship",Priors!$H$5,Priors!$H$8)) -> 1 | R71: FALSE | S71: =IF(R71=TRUE,Priors!$H$6,1) -> 1 | T71: TRUE | U71: =IF(T71=TRUE,Priors!$H$7,1) -> 0.9 | V71: =P71*Q71*S71*U71 -> 0.43727506 | W71: =VLOOKUP(D71,Priors!$A$3:$C$6,2,FALSE) -> 0.10751786 | X71: =VLOOKUP(D71,Priors!$A$3:$C$6,3,FALSE) -> 0.090240672 | Y71: =IF(N71="",W71,V71*N71+(1-V71)*W71) -> 0.11955984 | Z71: =IF(O71="",X71,V71*O71+(1-V71)*X71) -> 0.090407573 | AA71: 1 | AB71: 1 | AC71: =Y71*AA71 -> 0.11955984 | AD71: =Z71*AB71 -> 0.090407573 | AE71: =1-V71 -> 0.56272494 | AF71: PL history | AG71: 2 | AH71: 2 | AJ71: TRUE | AK71: FPL Core Insights / official FPL historical feed | AL71: https://github.com/olbauday/FPL-Core-Insights/tree/main/data/2025-2026 | AN71: 1 | AO71: 0 | AP71: TRUE | AQ71: Total xG retained; penalty channel not decomposed
A72: 71 | B72: Cook | C72: Bournemouth | D72: MID | E72: Premier League | F72: Bournemouth | G72: 872 | H72: 0.07 | I72: 0.52 | J72: 0.0072247706 | K72: 0.053669725 | L72: 61.9 | M72: 1.6289474 | N72: 0.0044352388 | O72: 0.032947489 | P72: =IFERROR(G72/(G72+Priors!$H$3),0) -> 0.46581197 | Q72: =IF(E72="Premier League",Priors!$H$4,IF(E72="Championship",Priors!$H$5,Priors!$H$8)) -> 1 | R72: FALSE | S72: =IF(R72=TRUE,Priors!$H$6,1) -> 1 | T72: TRUE | U72: =IF(T72=TRUE,Priors!$H$7,1) -> 0.9 | V72: =P72*Q72*S72*U72 -> 0.41923077 | W72: =VLOOKUP(D72,Priors!$A$3:$C$6,2,FALSE) -> 0.10751786 | X72: =VLOOKUP(D72,Priors!$A$3:$C$6,3,FALSE) -> 0.090240672 | Y72: =IF(N72="",W72,V72*N72+(1-V72)*W72) -> 0.064302454 | Z72: =IF(O72="",X72,V72*O72+(1-V72)*X72) -> 0.066221607 | AA72: 1 | AB72: 1 | AC72: =Y72*AA72 -> 0.064302454 | AD72: =Z72*AB72 -> 0.066221607 | AE72: =1-V72 -> 0.58076923 | AF72: PL history | AI72: 8 | AJ72: TRUE | AK72: FPL Core Insights / official FPL historical feed | AL72: https://github.com/olbauday/FPL-Core-Insights/tree/main/data/2025-2026 | AO72: 0 | AP72: FALSE | AQ72: Total xG retained; low penalty contamination
A73: 72 | B73: Gannon-Doak | C73: Bournemouth | D73: MID | E73: Premier League | F73: Bournemouth | G73: 105 | H73: 0.26 | I73: 0.13 | J73: 0.22285714 | K73: 0.11142857 | L73: 61.9 | M73: 1.6289474 | N73: 0.13681052 | O73: 0.068405262 | P73: =IFERROR(G73/(G73+Priors!$H$3),0) -> 0.095022624 | Q73: =IF(E73="Premier League",Priors!$H$4,IF(E73="Championship",Priors!$H$5,Priors!$H$8)) -> 1 | R73: FALSE | S73: =IF(R73=TRUE,Priors!$H$6,1) -> 1 | T73: TRUE | U73: =IF(T73=TRUE,Priors!$H$7,1) -> 0.9 | V73: =P73*Q73*S73*U73 -> 0.085520362 | W73: =VLOOKUP(D73,Priors!$A$3:$C$6,2,FALSE) -> 0.10751786 | X73: =VLOOKUP(D73,Priors!$A$3:$C$6,3,FALSE) -> 0.090240672 | Y73: =IF(N73="",W73,V73*N73+(1-V73)*W73) -> 0.11002298 | Z73: =IF(O73="",X73,V73*O73+(1-V73)*X73) -> 0.0883733 | AA73: 1 | AB73: 1 | AC73: =Y73*AA73 -> 0.11002298 | AD73: =Z73*AB73 -> 0.0883733 | AE73: =1-V73 -> 0.91447964 | AF73: PL history | AJ73: TRUE | AK73: FPL Core Insights / official FPL historical feed | AL73: https://github.com/olbauday/FPL-Core-Insights/tree/main/data/2025-2026 | AO73: 0 | AP73: FALSE | AQ73: Total xG retained; low penalty contamination
A74: 73 | B74: Adams | C74: Bournemouth | D74: MID | E74: Premier League | F74: Bournemouth | G74: 1769 | H74: 0.63 | I74: 0.63 | J74: 0.032052007 | K74: 0.032052007 | L74: 61.9 | M74: 1.6289474 | N74: 0.019676515 | O74: 0.019676515 | P74: =IFERROR(G74/(G74+Priors!$H$3),0) -> 0.63885879 | Q74: =IF(E74="Premier League",Priors!$H$4,IF(E74="Championship",Priors!$H$5,Priors!$H$8)) -> 1 | R74: FALSE | S74: =IF(R74=TRUE,Priors!$H$6,1) -> 1 | T74: TRUE | U74: =IF(T74=TRUE,Priors!$H$7,1) -> 0.9 | V74: =P74*Q74*S74*U74 -> 0.57497291 | W74: =VLOOKUP(D74,Priors!$A$3:$C$6,2,FALSE) -> 0.10751786 | X74: =VLOOKUP(D74,Priors!$A$3:$C$6,3,FALSE) -> 0.090240672 | Y74: =IF(N74="",W74,V74*N74+(1-V74)*W74) -> 0.057011466 | Z74: =IF(O74="",X74,V74*O74+(1-V74)*X74) -> 0.049668193 | AA74: 1 | AB74: 1 | AC74: =Y74*AA74 -> 0.057011466 | AD74: =Z74*AB74 -> 0.049668193 | AE74: =1-V74 -> 0.42502709 | AF74: PL history | AJ74: TRUE | AK74: FPL Core Insights / official FPL historical feed | AL74: https://github.com/olbauday/FPL-Core-Insights/tree/main/data/2025-2026 | AO74: 0 | AP74: FALSE | AQ74: Total xG retained; low penalty contamination
A75: 74 | B75: Brooks | C75: Bournemouth | D75: MID | E75: Premier League | F75: Bournemouth | G75: 1188 | H75: 5.81 | I75: 3.4 | J75: 0.44015152 | K75: 0.25757576 | L75: 61.9 | M75: 1.6289474 | N75: 0.2702061 | O75: 0.15812405 | P75: =IFERROR(G75/(G75+Priors!$H$3),0) -> 0.54296161 | Q75: =IF(E75="Premier League",Priors!$H$4,IF(E75="Championship",Priors!$H$5,Priors!$H$8)) -> 1 | R75: FALSE | S75: =IF(R75=TRUE,Priors!$H$6,1) -> 1 | T75: TRUE | U75: =IF(T75=TRUE,Priors!$H$7,1) -> 0.9 | V75: =P75*Q75*S75*U75 -> 0.48866545 | W75: =VLOOKUP(D75,Priors!$A$3:$C$6,2,FALSE) -> 0.10751786 | X75: =VLOOKUP(D75,Priors!$A$3:$C$6,3,FALSE) -> 0.090240672 | Y75: =IF(N75="",W75,V75*N75+(1-V75)*W75) -> 0.18701798 | Z75: =IF(O75="",X75,V75*O75+(1-V75)*X75) -> 0.12341293 | AA75: 1 | AB75: 1 | AC75: =Y75*AA75 -> 0.18701798 | AD75: =Z75*AB75 -> 0.12341293 | AE75: =1-V75 -> 0.51133455 | AF75: PL history | AH75: 3 | AI75: 9 | AJ75: TRUE | AK75: FPL Core Insights / official FPL historical feed | AL75: https://github.com/olbauday/FPL-Core-Insights/tree/main/data/2025-2026 | AO75: 0 | AP75: FALSE | AQ75: Total xG retained; low penalty contamination
A76: 75 | B76: Christie | C76: Bournemouth | D76: MID | E76: Premier League | F76: Bournemouth | G76: 978 | H76: 1.81 | I76: 0.79 | J76: 0.16656442 | K76: 0.072699387 | L76: 61.9 | M76: 1.6289474 | N76: 0.10225279 | O76: 0.044629672 | P76: =IFERROR(G76/(G76+Priors!$H$3),0) -> 0.49443883 | Q76: =IF(E76="Premier League",Priors!$H$4,IF(E76="Championship",Priors!$H$5,Priors!$H$8)) -> 1 | R76: FALSE | S76: =IF(R76=TRUE,Priors!$H$6,1) -> 1 | T76: TRUE | U76: =IF(T76=TRUE,Priors!$H$7,1) -> 0.9 | V76: =P76*Q76*S76*U76 -> 0.44499494 | W76: =VLOOKUP(D76,Priors!$A$3:$C$6,2,FALSE) -> 0.10751786 | X76: =VLOOKUP(D76,Priors!$A$3:$C$6,3,FALSE) -> 0.090240672 | Y76: =IF(N76="",W76,V76*N76+(1-V76)*W76) -> 0.10517493 | Z76: =IF(O76="",X76,V76*O76+(1-V76)*X76) -> 0.069944008 | AA76: 1 | AB76: 1 | AC76: =Y76*AA76 -> 0.10517493 | AD76: =Z76*AB76 -> 0.069944008 | AE76: =1-V76 -> 0.55500506 | AF76: PL history | AI76: 10 | AJ76: TRUE | AK76: FPL Core Insights / official FPL historical feed | AL76: https://github.com/olbauday/FPL-Core-Insights/tree/main/data/2025-2026 | AO76: 0 | AP76: FALSE | AQ76: Total xG retained; low penalty contamination
A77: 76 | B77: Tóth.A | C77: Bournemouth | D77: MID | E77: Premier League | F77: Bournemouth | G77: 135 | H77: 0.11 | I77: 0.33 | J77: 0.073333333 | K77: 0.22 | L77: 61.9 | M77: 1.6289474 | N77: 0.045018848 | O77: 0.13505654 | P77: =IFERROR(G77/(G77+Priors!$H$3),0) -> 0.11894273 | Q77: =IF(E77="Premier League",Priors!$H$4,IF(E77="Championship",Priors!$H$5,Priors!$H$8)) -> 1 | R77: FALSE | S77: =IF(R77=TRUE,Priors!$H$6,1) -> 1 | T77: TRUE | U77: =IF(T77=TRUE,Priors!$H$7,1) -> 0.9 | V77: =P77*Q77*S77*U77 -> 0.10704846 | W77: =VLOOKUP(D77,Priors!$A$3:$C$6,2,FALSE) -> 0.10751786 | X77: =VLOOKUP(D77,Priors!$A$3:$C$6,3,FALSE) -> 0.090240672 | Y77: =IF(N77="",W77,V77*N77+(1-V77)*W77) -> 0.10082744 | Z77: =IF(O77="",X77,V77*O77+(1-V77)*X77) -> 0.095038142 | AA77: 1 | AB77: 1 | AC77: =Y77*AA77 -> 0.10082744 | AD77: =Z77*AB77 -> 0.095038142 | AE77: =1-V77 -> 0.89295154 | AF77: PL history | AJ77: TRUE | AK77: FPL Core Insights / official FPL historical feed | AL77: https://github.com/olbauday/FPL-Core-Insights/tree/main/data/2025-2026 | AO77: 0 | AP77: FALSE | AQ77: Total xG retained; low penalty contamination
A78: 77 | B78: Adli | C78: Bournemouth | D78: MID | E78: Premier League | F78: Bournemouth | G78: 1074 | H78: 2.6 | I78: 1.62 | J78: 0.21787709 | K78: 0.13575419 | L78: 61.9 | M78: 1.6289474 | N78: 0.13375331 | O78: 0.083338598 | P78: =IFERROR(G78/(G78+Priors!$H$3),0) -> 0.51783992 | Q78: =IF(E78="Premier League",Priors!$H$4,IF(E78="Championship",Priors!$H$5,Priors!$H$8)) -> 1 | R78: FALSE | S78: =IF(R78=TRUE,Priors!$H$6,1) -> 1 | T78: TRUE | U78: =IF(T78=TRUE,Priors!$H$7,1) -> 0.9 | V78: =P78*Q78*S78*U78 -> 0.46605593 | W78: =VLOOKUP(D78,Priors!$A$3:$C$6,2,FALSE) -> 0.10751786 | X78: =VLOOKUP(D78,Priors!$A$3:$C$6,3,FALSE) -> 0.090240672 | Y78: =IF(N78="",W78,V78*N78+(1-V78)*W78) -> 0.11974505 | Z78: =IF(O78="",X78,V78*O78+(1-V78)*X78) -> 0.087023919 | AA78: 1 | AB78: 1 | AC78: =Y78*AA78 -> 0.11974505 | AD78: =Z78*AB78 -> 0.087023919 | AE78: =1-V78 -> 0.53394407 | AF78: PL history | AJ78: TRUE | AK78: FPL Core Insights / official FPL historical feed | AL78: https://github.com/olbauday/FPL-Core-Insights/tree/main/data/2025-2026 | AO78: 0 | AP78: FALSE | AQ78: Total xG retained; low penalty contamination
A79: 78 | B79: Kroupi.Jr | C79: Bournemouth | D79: MID | E79: Premier League | F79: Bournemouth | G79: 1663 | H79: 8.31 | I79: 1.51 | J79: 0.4497294 | K79: 0.081719784 | L79: 61.9 | M79: 1.6289474 | N79: 0.2760859 | O79: 0.050167234 | P79: =IFERROR(G79/(G79+Priors!$H$3),0) -> 0.62448367 | Q79: =IF(E79="Premier League",Priors!$H$4,IF(E79="Championship",Priors!$H$5,Priors!$H$8)) -> 1 | R79: FALSE | S79: =IF(R79=TRUE,Priors!$H$6,1) -> 1 | T79: TRUE | U79: =IF(T79=TRUE,Priors!$H$7,1) -> 0.9 | V79: =P79*Q79*S79*U79 -> 0.5620353 | W79: =VLOOKUP(D79,Priors!$A$3:$C$6,2,FALSE) -> 0.10751786 | X79: =VLOOKUP(D79,Priors!$A$3:$C$6,3,FALSE) -> 0.090240672 | Y79: =IF(N79="",W79,V79*N79+(1-V79)*W79) -> 0.20225905 | Z79: =IF(O79="",X79,V79*O79+(1-V79)*X79) -> 0.067717985 | AA79: 1 | AB79: 1 | AC79: =Y79*AA79 -> 0.20225905 | AD79: =Z79*AB79 -> 0.067717985 | AE79: =1-V79 -> 0.4379647 | AF79: PL history | AG79: 1 | AJ79: TRUE | AK79: FPL Core Insights / official FPL historical feed | AL79: https://github.com/olbauday/FPL-Core-Insights/tree/main/data/2025-2026 | AN79: 2 | AO79: 0 | AP79: TRUE | AQ79: Total xG retained; penalty channel not decomposed
A80: 79 | B80: Evanilson | C80: Bournemouth | D80: FWD | E80: Premier League | F80: Bournemouth | G80: 2741 | H80: 10.64 | I80: 1.48 | J80: 0.34936155 | K80: 0.048595403 | L80: 61.9 | M80: 1.6289474 | N80: 0.21447074 | O80: 0.029832396 | P80: =IFERROR(G80/(G80+Priors!$H$3),0) -> 0.73269179 | Q80: =IF(E80="Premier League",Priors!$H$4,IF(E80="Championship",Priors!$H$5,Priors!$H$8)) -> 1 | R80: FALSE | S80: =IF(R80=TRUE,Priors!$H$6,1) -> 1 | T80: TRUE | U80: =IF(T80=TRUE,Priors!$H$7,1) -> 0.9 | V80: =P80*Q80*S80*U80 -> 0.65942261 | W80: =VLOOKUP(D80,Priors!$A$3:$C$6,2,FALSE) -> 0.30461526 | X80: =VLOOKUP(D80,Priors!$A$3:$C$6,3,FALSE) -> 0.039258062 | Y80: =IF(N80="",W80,V80*N80+(1-V80)*W80) -> 0.24517192 | Z80: =IF(O80="",X80,V80*O80+(1-V80)*X80) -> 0.033042565 | AA80: 1 | AB80: 1 | AC80: =Y80*AA80 -> 0.24517192 | AD80: =Z80*AB80 -> 0.033042565 | AE80: =1-V80 -> 0.34057739 | AF80: PL history | AJ80: TRUE | AK80: FPL Core Insights / official FPL historical feed | AL80: https://github.com/olbauday/FPL-Core-Insights/tree/main/data/2025-2026 | AO80: 0 | AP80: FALSE | AQ80: Total xG retained; low penalty contamination
A81: 80 | B81: Enes Ünal | C81: Bournemouth | D81: FWD | E81: Premier League | F81: Bournemouth | G81: 214 | H81: 2 | I81: 0.07 | J81: 0.8411215 | K81: 0.029439252 | L81: 61.9 | M81: 1.6289474 | N81: 0.51635891 | O81: 0.018072562 | P81: =IFERROR(G81/(G81+Priors!$H$3),0) -> 0.17627677 | Q81: =IF(E81="Premier League",Priors!$H$4,IF(E81="Championship",Priors!$H$5,Priors!$H$8)) -> 1 | R81: FALSE | S81: =IF(R81=TRUE,Priors!$H$6,1) -> 1 | T81: TRUE | U81: =IF(T81=TRUE,Priors!$H$7,1) -> 0.9 | V81: =P81*Q81*S81*U81 -> 0.15864909 | W81: =VLOOKUP(D81,Priors!$A$3:$C$6,2,FALSE) -> 0.30461526 | X81: =VLOOKUP(D81,Priors!$A$3:$C$6,3,FALSE) -> 0.039258062 | Y81: =IF(N81="",W81,V81*N81+(1-V81)*W81) -> 0.33820819 | Z81: =IF(O81="",X81,V81*O81+(1-V81)*X81) -> 0.035897001 | AA81: 1 | AB81: 1 | AC81: =Y81*AA81 -> 0.33820819 | AD81: =Z81*AB81 -> 0.035897001 | AE81: =1-V81 -> 0.84135091 | AF81: PL history | AH81: 5 | AJ81: TRUE | AK81: FPL Core Insights / official FPL historical feed | AL81: https://github.com/olbauday/FPL-Core-Insights/tree/main/data/2025-2026 | AO81: 0 | AP81: FALSE | AQ81: Total xG retained; low penalty contamination
A82: 81 | B82: Rodríguez | C82: Bournemouth | D82: FWD | E82: Missing/non-PL | P82: =IFERROR(G82/(G82+Priors!$H$3),0) -> 0 | Q82: =IF(E82="Premier League",Priors!$H$4,IF(E82="Championship",Priors!$H$5,Priors!$H$8)) -> 0 | R82: FALSE | S82: =IF(R82=TRUE,Priors!$H$6,1) -> 1 | T82: TRUE | U82: =IF(T82=TRUE,Priors!$H$7,1) -> 0.9 | V82: =P82*Q82*S82*U82 -> 0 | W82: =VLOOKUP(D82,Priors!$A$3:$C$6,2,FALSE) -> 0.30461526 | X82: =VLOOKUP(D82,Priors!$A$3:$C$6,3,FALSE) -> 0.039258062 | Y82: =IF(N82="",W82,V82*N82+(1-V82)*W82) -> 0.30461526 | Z82: =IF(O82="",X82,V82*O82+(1-V82)*X82) -> 0.039258062 | AA82: 1 | AB82: 1 | AC82: =Y82*AA82 -> 0.30461526 | AD82: =Z82*AB82 -> 0.039258062 | AE82: =1-V82 -> 1 | AF82: Missing/non-PL | AJ82: TRUE | AK82: No reliable 25/26 history loaded | AQ82: No comparable 25/26 PL penalty history
A83: 566 | B83: Silva | C83: Bournemouth | D83: DEF | E83: Missing/non-PL | P83: =IFERROR(G83/(G83+Priors!$H$3),0) -> 0 | Q83: =IF(E83="Premier League",Priors!$H$4,IF(E83="Championship",Priors!$H$5,Priors!$H$8)) -> 0 | R83: FALSE | S83: =IF(R83=TRUE,Priors!$H$6,1) -> 1 | T83: TRUE | U83: =IF(T83=TRUE,Priors!$H$7,1) -> 0.9 | V83: =P83*Q83*S83*U83 -> 0 | W83: =VLOOKUP(D83,Priors!$A$3:$C$6,2,FALSE) -> 0.041142361 | X83: =VLOOKUP(D83,Priors!$A$3:$C$6,3,FALSE) -> 0.04051308 | Y83: =IF(N83="",W83,V83*N83+(1-V83)*W83) -> 0.041142361 | Z83: =IF(O83="",X83,V83*O83+(1-V83)*X83) -> 0.04051308 | AA83: 1 | AB83: 1 | AC83: =Y83*AA83 -> 0.041142361 | AD83: =Z83*AB83 -> 0.04051308 | AE83: =1-V83 -> 1 | AF83: Missing/non-PL | AJ83: TRUE | AK83: No reliable 25/26 history loaded | AO83: 0 | AP83: FALSE | AQ83: Total xG retained; low penalty contamination
A84: 82 | B84: Kelleher | C84: Brentford | D84: GK | E84: Premier League | F84: Brentford | G84: 3330 | H84: 0 | I84: 0.22 | J84: 0 | K84: 0.0059459459 | L84: 60.3 | M84: 1.5868421 | N84: 0 | O84: 0.0037470306 | P84: =IFERROR(G84/(G84+Priors!$H$3),0) -> 0.76905312 | Q84: =IF(E84="Premier League",Priors!$H$4,IF(E84="Championship",Priors!$H$5,Priors!$H$8)) -> 1 | R84: FALSE | S84: =IF(R84=TRUE,Priors!$H$6,1) -> 1 | T84: FALSE | U84: =IF(T84=TRUE,Priors!$H$7,1) -> 1 | V84: =P84*Q84*S84*U84 -> 0.76905312 | W84: =VLOOKUP(D84,Priors!$A$3:$C$6,2,FALSE) -> 0.00016719535 | X84: =VLOOKUP(D84,Priors!$A$3:$C$6,3,FALSE) -> 0.0013793616 | Y84: =IF(N84="",W84,V84*N84+(1-V84)*W84) -> 3.8613245e-05 | Z84: =IF(O84="",X84,V84*O84+(1-V84)*X84) -> 0.0032002248 | AA84: 1 | AB84: 1 | AC84: =Y84*AA84 -> 3.8613245e-05 | AD84: =Z84*AB84 -> 0.0032002248 | AE84: =1-V84 -> 0.23094688 | AF84: PL history | AJ84: FALSE | AK84: FPL Core Insights / official FPL historical feed | AL84: https://github.com/olbauday/FPL-Core-Insights/tree/main/data/2025-2026 | AO84: 0 | AP84: FALSE | AQ84: Total xG retained; low penalty contamination
A85: 83 | B85: Valdimarsson | C85: Brentford | D85: GK | E85: Premier League | F85: Brentford | G85: 90 | H85: 0 | I85: 0 | J85: 0 | K85: 0 | L85: 60.3 | M85: 1.5868421 | N85: 0 | O85: 0 | P85: =IFERROR(G85/(G85+Priors!$H$3),0) -> 0.082568807 | Q85: =IF(E85="Premier League",Priors!$H$4,IF(E85="Championship",Priors!$H$5,Priors!$H$8)) -> 1 | R85: FALSE | S85: =IF(R85=TRUE,Priors!$H$6,1) -> 1 | T85: FALSE | U85: =IF(T85=TRUE,Priors!$H$7,1) -> 1 | V85: =P85*Q85*S85*U85 -> 0.082568807 | W85: =VLOOKUP(D85,Priors!$A$3:$C$6,2,FALSE) -> 0.00016719535 | X85: =VLOOKUP(D85,Priors!$A$3:$C$6,3,FALSE) -> 0.0013793616 | Y85: =IF(N85="",W85,V85*N85+(1-V85)*W85) -> 0.00015339023 | Z85: =IF(O85="",X85,V85*O85+(1-V85)*X85) -> 0.0012654694 | AA85: 1 | AB85: 1 | AC85: =Y85*AA85 -> 0.00015339023 | AD85: =Z85*AB85 -> 0.0012654694 | AE85: =1-V85 -> 0.91743119 | AF85: PL history | AJ85: TRUE | AK85: FPL Core Insights / official FPL historical feed | AL85: https://github.com/olbauday/FPL-Core-Insights/tree/main/data/2025-2026 | AO85: 0 | AP85: FALSE | AQ85: Total xG retained; low penalty contamination
A86: 84 | B86: Collins | C86: Brentford | D86: DEF | E86: Premier League | F86: Brentford | G86: 2971 | H86: 2.24 | I86: 1.71 | J86: 0.067855941 | K86: 0.05180074 | L86: 60.3 | M86: 1.5868421 | N86: 0.042761621 | O86: 0.032643916 | P86: =IFERROR(G86/(G86+Priors!$H$3),0) -> 0.74817426 | Q86: =IF(E86="Premier League",Priors!$H$4,IF(E86="Championship",Priors!$H$5,Priors!$H$8)) -> 1 | R86: FALSE | S86: =IF(R86=TRUE,Priors!$H$6,1) -> 1 | T86: FALSE | U86: =IF(T86=TRUE,Priors!$H$7,1) -> 1 | V86: =P86*Q86*S86*U86 -> 0.74817426 | W86: =VLOOKUP(D86,Priors!$A$3:$C$6,2,FALSE) -> 0.041142361 | X86: =VLOOKUP(D86,Priors!$A$3:$C$6,3,FALSE) -> 0.04051308 | Y86: =IF(N86="",W86,V86*N86+(1-V86)*W86) -> 0.04235385 | Z86: =IF(O86="",X86,V86*O86+(1-V86)*X86) -> 0.034625574 | AA86: 1 | AB86: 1 | AC86: =Y86*AA86 -> 0.04235385 | AD86: =Z86*AB86 -> 0.034625574 | AE86: =1-V86 -> 0.25182574 | AF86: PL history | AJ86: FALSE | AK86: FPL Core Insights / official FPL historical feed | AL86: https://github.com/olbauday/FPL-Core-Insights/tree/main/data/2025-2026 | AO86: 0 | AP86: FALSE | AQ86: Total xG retained; low penalty contamination
A87: 85 | B87: Van den Berg | C87: Brentford | D87: DEF | E87: Premier League | F87: Brentford | G87: 2761 | H87: 3.36 | I87: 1.45 | J87: 0.10952553 | K87: 0.047265484 | L87: 60.3 | M87: 1.5868421 | N87: 0.069021066 | O87: 0.029785877 | P87: =IFERROR(G87/(G87+Priors!$H$3),0) -> 0.73411327 | Q87: =IF(E87="Premier League",Priors!$H$4,IF(E87="Championship",Priors!$H$5,Priors!$H$8)) -> 1 | R87: FALSE | S87: =IF(R87=TRUE,Priors!$H$6,1) -> 1 | T87: FALSE | U87: =IF(T87=TRUE,Priors!$H$7,1) -> 1 | V87: =P87*Q87*S87*U87 -> 0.73411327 | W87: =VLOOKUP(D87,Priors!$A$3:$C$6,2,FALSE) -> 0.041142361 | X87: =VLOOKUP(D87,Priors!$A$3:$C$6,3,FALSE) -> 0.04051308 | Y87: =IF(N87="",W87,V87*N87+(1-V87)*W87) -> 0.061608489 | Z87: =IF(O87="",X87,V87*O87+(1-V87)*X87) -> 0.032638098 | AA87: 1 | AB87: 1 | AC87: =Y87*AA87 -> 0.061608489 | AD87: =Z87*AB87 -> 0.032638098 | AE87: =1-V87 -> 0.26588673 | AF87: PL history | AJ87: FALSE | AK87: FPL Core Insights / official FPL historical feed | AL87: https://github.com/olbauday/FPL-Core-Insights/tree/main/data/2025-2026 | AO87: 0 | AP87: FALSE | AQ87: Total xG retained; low penalty contamination
A88: 86 | B88: Lewis-Potter | C88: Brentford | D88: MID | E88: Premier League | F88: Brentford | G88: 1960 | H88: 3.01 | I88: 2.51 | J88: 0.13821429 | K88: 0.1152551 | L88: 60.3 | M88: 1.5868421 | N88: 0.087100213 | O88: 0.072631739 | P88: =IFERROR(G88/(G88+Priors!$H$3),0) -> 0.66216216 | Q88: =IF(E88="Premier League",Priors!$H$4,IF(E88="Championship",Priors!$H$5,Priors!$H$8)) -> 1 | R88: FALSE | S88: =IF(R88=TRUE,Priors!$H$6,1) -> 1 | T88: FALSE | U88: =IF(T88=TRUE,Priors!$H$7,1) -> 1 | V88: =P88*Q88*S88*U88 -> 0.66216216 | W88: =VLOOKUP(D88,Priors!$A$3:$C$6,2,FALSE) -> 0.10751786 | X88: =VLOOKUP(D88,Priors!$A$3:$C$6,3,FALSE) -> 0.090240672 | Y88: =IF(N88="",W88,V88*N88+(1-V88)*W88) -> 0.093998067 | Z88: =IF(O88="",X88,V88*O88+(1-V88)*X88) -> 0.078580703 | AA88: 1 | AB88: 1 | AC88: =Y88*AA88 -> 0.093998067 | AD88: =Z88*AB88 -> 0.078580703 | AE88: =1-V88 -> 0.33783784 | AF88: PL history | AH88: 1 | AJ88: FALSE | AK88: FPL Core Insights / official FPL historical feed | AL88: https://github.com/olbauday/FPL-Core-Insights/tree/main/data/2025-2026 | AO88: 0 | AP88: FALSE | AQ88: Total xG retained; low penalty contamination
A89: 87 | B89: Ajer | C89: Brentford | D89: DEF | E89: Premier League | F89: Brentford | G89: 1805 | H89: 0.69 | I89: 0.73 | J89: 0.034404432 | K89: 0.036398892 | L89: 60.3 | M89: 1.5868421 | N89: 0.021681068 | O89: 0.022937942 | P89: =IFERROR(G89/(G89+Priors!$H$3),0) -> 0.64349376 | Q89: =IF(E89="Premier League",Priors!$H$4,IF(E89="Championship",Priors!$H$5,Priors!$H$8)) -> 1 | R89: FALSE | S89: =IF(R89=TRUE,Priors!$H$6,1) -> 1 | T89: FALSE | U89: =IF(T89=TRUE,Priors!$H$7,1) -> 1 | V89: =P89*Q89*S89*U89 -> 0.64349376 | W89: =VLOOKUP(D89,Priors!$A$3:$C$6,2,FALSE) -> 0.041142361 | X89: =VLOOKUP(D89,Priors!$A$3:$C$6,3,FALSE) -> 0.04051308 | Y89: =IF(N89="",W89,V89*N89+(1-V89)*W89) -> 0.028619141 | Z89: =IF(O89="",X89,V89*O89+(1-V89)*X89) -> 0.029203588 | AA89: 1 | AB89: 1 | AC89: =Y89*AA89 -> 0.028619141 | AD89: =Z89*AB89 -> 0.029203588 | AE89: =1-V89 -> 0.35650624 | AF89: PL history | AJ89: FALSE | AK89: FPL Core Insights / official FPL historical feed | AL89: https://github.com/olbauday/FPL-Core-Insights/tree/main/data/2025-2026 | AO89: 0 | AP89: FALSE | AQ89: Total xG retained; low penalty contamination
A90: 88 | B90: Kayode | C90: Brentford | D90: DEF | E90: Premier League | F90: Brentford | G90: 3258 | H90: 1.28 | I90: 2.89 | J90: 0.035359116 | K90: 0.079834254 | L90: 60.3 | M90: 1.5868421 | N90: 0.022282693 | O90: 0.050310144 | P90: =IFERROR(G90/(G90+Priors!$H$3),0) -> 0.76514796 | Q90: =IF(E90="Premier League",Priors!$H$4,IF(E90="Championship",Priors!$H$5,Priors!$H$8)) -> 1 | R90: FALSE | S90: =IF(R90=TRUE,Priors!$H$6,1) -> 1 | T90: FALSE | U90: =IF(T90=TRUE,Priors!$H$7,1) -> 1 | V90: =P90*Q90*S90*U90 -> 0.76514796 | W90: =VLOOKUP(D90,Priors!$A$3:$C$6,2,FALSE) -> 0.041142361 | X90: =VLOOKUP(D90,Priors!$A$3:$C$6,3,FALSE) -> 0.04051308 | Y90: =IF(N90="",W90,V90*N90+(1-V90)*W90) -> 0.026711925 | Z90: =IF(O90="",X90,V90*O90+(1-V90)*X90) -> 0.048009283 | AA90: 1 | AB90: 1 | AC90: =Y90*AA90 -> 0.026711925 | AD90: =Z90*AB90 -> 0.048009283 | AE90: =1-V90 -> 0.23485204 | AF90: PL history | AJ90: FALSE | AK90: FPL Core Insights / official FPL historical feed | AL90: https://github.com/olbauday/FPL-Core-Insights/tree/main/data/2025-2026 | AO90: 0 | AP90: FALSE | AQ90: Total xG retained; low penalty contamination
A91: 89 | B91: Henry | C91: Brentford | D91: DEF | E91: Premier League | F91: Brentford | G91: 1322 | H91: 0.18 | I91: 0.54 | J91: 0.01225416 | K91: 0.036762481 | L91: 60.3 | M91: 1.5868421 | N91: 0.0077223564 | O91: 0.023167069 | P91: =IFERROR(G91/(G91+Priors!$H$3),0) -> 0.56933678 | Q91: =IF(E91="Premier League",Priors!$H$4,IF(E91="Championship",Priors!$H$5,Priors!$H$8)) -> 1 | R91: FALSE | S91: =IF(R91=TRUE,Priors!$H$6,1) -> 1 | T91: FALSE | U91: =IF(T91=TRUE,Priors!$H$7,1) -> 1 | V91: =P91*Q91*S91*U91 -> 0.56933678 | W91: =VLOOKUP(D91,Priors!$A$3:$C$6,2,FALSE) -> 0.041142361 | X91: =VLOOKUP(D91,Priors!$A$3:$C$6,3,FALSE) -> 0.04051308 | Y91: =IF(N91="",W91,V91*N91+(1-V91)*W91) -> 0.022115123 | Z91: =IF(O91="",X91,V91*O91+(1-V91)*X91) -> 0.030637358 | AA91: 1 | AB91: 1 | AC91: =Y91*AA91 -> 0.022115123 | AD91: =Z91*AB91 -> 0.030637358 | AE91: =1-V91 -> 0.43066322 | AF91: PL history | AJ91: FALSE | AK91: FPL Core Insights / official FPL historical feed | AL91: https://github.com/olbauday/FPL-Core-Insights/tree/main/data/2025-2026 | AO91: 0 | AP91: FALSE | AQ91: Total xG retained; low penalty contamination
A92: 90 | B92: Hickey | C92: Brentford | D92: DEF | E92: Premier League | F92: Brentford | G92: 679 | H92: 0.44 | I92: 0.17 | J92: 0.05832106 | K92: 0.022533137 | L92: 60.3 | M92: 1.5868421 | N92: 0.036752907 | O92: 0.014199987 | P92: =IFERROR(G92/(G92+Priors!$H$3),0) -> 0.40440739 | Q92: =IF(E92="Premier League",Priors!$H$4,IF(E92="Championship",Priors!$H$5,Priors!$H$8)) -> 1 | R92: FALSE | S92: =IF(R92=TRUE,Priors!$H$6,1) -> 1 | T92: FALSE | U92: =IF(T92=TRUE,Priors!$H$7,1) -> 1 | V92: =P92*Q92*S92*U92 -> 0.40440739 | W92: =VLOOKUP(D92,Priors!$A$3:$C$6,2,FALSE) -> 0.041142361 | X92: =VLOOKUP(D92,Priors!$A$3:$C$6,3,FALSE) -> 0.04051308 | Y92: =IF(N92="",W92,V92*N92+(1-V92)*W92) -> 0.039367234 | Z92: =IF(O92="",X92,V92*O92+(1-V92)*X92) -> 0.029871871 | AA92: 1 | AB92: 1 | AC92: =Y92*AA92 -> 0.039367234 | AD92: =Z92*AB92 -> 0.029871871 | AE92: =1-V92 -> 0.59559261 | AF92: PL history | AJ92: TRUE | AK92: FPL Core Insights / official FPL historical feed | AL92: https://github.com/olbauday/FPL-Core-Insights/tree/main/data/2025-2026 | AO92: 0 | AP92: FALSE | AQ92: Total xG retained; low penalty contamination
A93: 91 | B93: Pinnock | C93: Brentford | D93: DEF | E93: Premier League | F93: Brentford | G93: 318 | H93: 0.01 | I93: 0.06 | J93: 0.0028301887 | K93: 0.016981132 | L93: 60.3 | M93: 1.5868421 | N93: 0.0017835352 | O93: 0.010701211 | P93: =IFERROR(G93/(G93+Priors!$H$3),0) -> 0.24127466 | Q93: =IF(E93="Premier League",Priors!$H$4,IF(E93="Championship",Priors!$H$5,Priors!$H$8)) -> 1 | R93: FALSE | S93: =IF(R93=TRUE,Priors!$H$6,1) -> 1 | T93: FALSE | U93: =IF(T93=TRUE,Priors!$H$7,1) -> 1 | V93: =P93*Q93*S93*U93 -> 0.24127466 | W93: =VLOOKUP(D93,Priors!$A$3:$C$6,2,FALSE) -> 0.041142361 | X93: =VLOOKUP(D93,Priors!$A$3:$C$6,3,FALSE) -> 0.04051308 | Y93: =IF(N93="",W93,V93*N93+(1-V93)*W93) -> 0.031646074 | Z93: =IF(O93="",X93,V93*O93+(1-V93)*X93) -> 0.033320231 | AA93: 1 | AB93: 1 | AC93: =Y93*AA93 -> 0.031646074 | AD93: =Z93*AB93 -> 0.033320231 | AE93: =1-V93 -> 0.75872534 | AF93: PL history | AJ93: TRUE | AK93: FPL Core Insights / official FPL historical feed | AL93: https://github.com/olbauday/FPL-Core-Insights/tree/main/data/2025-2026 | AO93: 0 | AP93: FALSE | AQ93: Total xG retained; low penalty contamination
A94: 92 | B94: Ji-soo | C94: Brentford | D94: DEF | E94: Missing/non-PL | P94: =IFERROR(G94/(G94+Priors!$H$3),0) -> 0 | Q94: =IF(E94="Premier League",Priors!$H$4,IF(E94="Championship",Priors!$H$5,Priors!$H$8)) -> 0 | R94: FALSE | S94: =IF(R94=TRUE,Priors!$H$6,1) -> 1 | T94: FALSE | U94: =IF(T94=TRUE,Priors!$H$7,1) -> 1 | V94: =P94*Q94*S94*U94 -> 0 | W94: =VLOOKUP(D94,Priors!$A$3:$C$6,2,FALSE) -> 0.041142361 | X94: =VLOOKUP(D94,Priors!$A$3:$C$6,3,FALSE) -> 0.04051308 | Y94: =IF(N94="",W94,V94*N94+(1-V94)*W94) -> 0.041142361 | Z94: =IF(O94="",X94,V94*O94+(1-V94)*X94) -> 0.04051308 | AA94: 1 | AB94: 1 | AC94: =Y94*AA94 -> 0.041142361 | AD94: =Z94*AB94 -> 0.04051308 | AE94: =1-V94 -> 1 | AF94: Missing/non-PL | AJ94: TRUE | AK94: No reliable 25/26 history loaded | AQ94: No comparable 25/26 PL penalty history
A95: 93 | B95: Schuster | C95: Brentford | D95: DEF | E95: Missing/non-PL | P95: =IFERROR(G95/(G95+Priors!$H$3),0) -> 0 | Q95: =IF(E95="Premier League",Priors!$H$4,IF(E95="Championship",Priors!$H$5,Priors!$H$8)) -> 0 | R95: FALSE | S95: =IF(R95=TRUE,Priors!$H$6,1) -> 1 | T95: FALSE | U95: =IF(T95=TRUE,Priors!$H$7,1) -> 1 | V95: =P95*Q95*S95*U95 -> 0 | W95: =VLOOKUP(D95,Priors!$A$3:$C$6,2,FALSE) -> 0.041142361 | X95: =VLOOKUP(D95,Priors!$A$3:$C$6,3,FALSE) -> 0.04051308 | Y95: =IF(N95="",W95,V95*N95+(1-V95)*W95) -> 0.041142361 | Z95: =IF(O95="",X95,V95*O95+(1-V95)*X95) -> 0.04051308 | AA95: 1 | AB95: 1 | AC95: =Y95*AA95 -> 0.041142361 | AD95: =Z95*AB95 -> 0.04051308 | AE95: =1-V95 -> 1 | AF95: Missing/non-PL | AJ95: TRUE | AK95: No reliable 25/26 history loaded | AN95: 3 | AO95: 1 | AP95: TRUE | AQ95: Total xG retained; penalty channel not decomposed
A96: 94 | B96: Schade | C96: Brentford | D96: MID | E96: Premier League | F96: Brentford | G96: 2744 | H96: 12.08 | I96: 2.05 | J96: 0.39620991 | K96: 0.067237609 | L96: 60.3 | M96: 1.5868421 | N96: 0.24968452 | O96: 0.042371959 | P96: =IFERROR(G96/(G96+Priors!$H$3),0) -> 0.73290598 | Q96: =IF(E96="Premier League",Priors!$H$4,IF(E96="Championship",Priors!$H$5,Priors!$H$8)) -> 1 | R96: FALSE | S96: =IF(R96=TRUE,Priors!$H$6,1) -> 1 | T96: FALSE | U96: =IF(T96=TRUE,Priors!$H$7,1) -> 1 | V96: =P96*Q96*S96*U96 -> 0.73290598 | W96: =VLOOKUP(D96,Priors!$A$3:$C$6,2,FALSE) -> 0.10751786 | X96: =VLOOKUP(D96,Priors!$A$3:$C$6,3,FALSE) -> 0.090240672 | Y96: =IF(N96="",W96,V96*N96+(1-V96)*W96) -> 0.21171266 | Z96: =IF(O96="",X96,V96*O96+(1-V96)*X96) -> 0.055157406 | AA96: 1 | AB96: 1 | AC96: =Y96*AA96 -> 0.21171266 | AD96: =Z96*AB96 -> 0.055157406 | AE96: =1-V96 -> 0.26709402 | AF96: PL history | AG96: 2 | AJ96: FALSE | AK96: FPL Core Insights / official FPL historical feed | AL96: https://github.com/olbauday/FPL-Core-Insights/tree/main/data/2025-2026 | AO96: 0 | AP96: FALSE | AQ96: Total xG retained; low penalty contamination
A97: 95 | B97: O.Dango | C97: Brentford | D97: MID | E97: Premier League | F97: Brentford | G97: 2271 | H97: 7.94 | I97: 4.12 | J97: 0.31466314 | K97: 0.16327609 | L97: 60.3 | M97: 1.5868421 | N97: 0.19829518 | O97: 0.10289372 | P97: =IFERROR(G97/(G97+Priors!$H$3),0) -> 0.69428309 | Q97: =IF(E97="Premier League",Priors!$H$4,IF(E97="Championship",Priors!$H$5,Priors!$H$8)) -> 1 | R97: FALSE | S97: =IF(R97=TRUE,Priors!$H$6,1) -> 1 | T97: FALSE | U97: =IF(T97=TRUE,Priors!$H$7,1) -> 1 | V97: =P97*Q97*S97*U97 -> 0.69428309 | W97: =VLOOKUP(D97,Priors!$A$3:$C$6,2,FALSE) -> 0.10751786 | X97: =VLOOKUP(D97,Priors!$A$3:$C$6,3,FALSE) -> 0.090240672 | Y97: =IF(N97="",W97,V97*N97+(1-V97)*W97) -> 0.17054302 | Z97: =IF(O97="",X97,V97*O97+(1-V97)*X97) -> 0.09902547 | AA97: 1 | AB97: 1 | AC97: =Y97*AA97 -> 0.17054302 | AD97: =Z97*AB97 -> 0.09902547 | AE97: =1-V97 -> 0.30571691 | AF97: PL history | AI97: 8 | AJ97: FALSE | AK97: FPL Core Insights / official FPL historical feed | AL97: https://github.com/olbauday/FPL-Core-Insights/tree/main/data/2025-2026 | AO97: 0 | AP97: FALSE | AQ97: Total xG retained; low penalty contamination
A98: 96 | B98: Damsgaard | C98: Brentford | D98: MID | E98: Premier League | F98: Brentford | G98: 2046 | H98: 2.61 | I98: 5.43 | J98: 0.11480938 | K98: 0.2388563 | L98: 60.3 | M98: 1.5868421 | N98: 0.072350856 | O98: 0.15052304 | P98: =IFERROR(G98/(G98+Priors!$H$3),0) -> 0.67170059 | Q98: =IF(E98="Premier League",Priors!$H$4,IF(E98="Championship",Priors!$H$5,Priors!$H$8)) -> 1 | R98: FALSE | S98: =IF(R98=TRUE,Priors!$H$6,1) -> 1 | T98: FALSE | U98: =IF(T98=TRUE,Priors!$H$7,1) -> 1 | V98: =P98*Q98*S98*U98 -> 0.67170059 | W98: =VLOOKUP(D98,Priors!$A$3:$C$6,2,FALSE) -> 0.10751786 | X98: =VLOOKUP(D98,Priors!$A$3:$C$6,3,FALSE) -> 0.090240672 | Y98: =IF(N98="",W98,V98*N98+(1-V98)*W98) -> 0.083896163 | Z98: =IF(O98="",X98,V98*O98+(1-V98)*X98) -> 0.13073238 | AA98: 1 | AB98: 1 | AC98: =Y98*AA98 -> 0.083896163 | AD98: =Z98*AB98 -> 0.13073238 | AE98: =1-V98 -> 0.32829941 | AF98: PL history | AH98: 3 | AI98: 6 | AJ98: FALSE | AK98: FPL Core Insights / official FPL historical feed | AL98: https://github.com/olbauday/FPL-Core-Insights/tree/main/data/2025-2026 | AN98: 5 | AO98: 0 | AP98: FALSE | AQ98: Total xG retained; low penalty contamination
A99: 97 | B99: Jensen | C99: Brentford | D99: MID | E99: Premier League | F99: Brentford | G99: 2239 | H99: 2.21 | I99: 6.06 | J99: 0.088834301 | K99: 0.24359089 | L99: 60.3 | M99: 1.5868421 | N99: 0.055981815 | O99: 0.1535067 | P99: =IFERROR(G99/(G99+Priors!$H$3),0) -> 0.69126274 | Q99: =IF(E99="Premier League",Priors!$H$4,IF(E99="Championship",Priors!$H$5,Priors!$H$8)) -> 1 | R99: FALSE | S99: =IF(R99=TRUE,Priors!$H$6,1) -> 1 | T99: FALSE | U99: =IF(T99=TRUE,Priors!$H$7,1) -> 1 | V99: =P99*Q99*S99*U99 -> 0.69126274 | W99: =VLOOKUP(D99,Priors!$A$3:$C$6,2,FALSE) -> 0.10751786 | X99: =VLOOKUP(D99,Priors!$A$3:$C$6,3,FALSE) -> 0.090240672 | Y99: =IF(N99="",W99,V99*N99+(1-V99)*W99) -> 0.071892913 | Z99: =IF(O99="",X99,V99*O99+(1-V99)*X99) -> 0.13397412 | AA99: 1 | AB99: 1 | AC99: =Y99*AA99 -> 0.071892913 | AD99: =Z99*AB99 -> 0.13397412 | AE99: =1-V99 -> 0.30873726 | AF99: PL history | AG99: 3 | AH99: 2 | AI99: 5 | AJ99: FALSE | AK99: FPL Core Insights / official FPL historical feed | AL99: https://github.com/olbauday/FPL-Core-Insights/tree/main/data/2025-2026 | AO99: 0 | AP99: FALSE | AQ99: Total xG retained; low penalty contamination
A100: 98 | B100: Janelt | C100: Brentford | D100: MID | E100: Premier League | F100: Brentford | G100: 1434 | H100: 0.82 | I100: 2.27 | J100: 0.051464435 | K100: 0.14246862 | L100: 60.3 | M100: 1.5868421 | N100: 0.032431982 | O100: 0.089781219 | P100: =IFERROR(G100/(G100+Priors!$H$3),0) -> 0.58915366 | Q100: =IF(E100="Premier League",Priors!$H$4,IF(E100="Championship",Priors!$H$5,Priors!$H$8)) -> 1 | R100: FALSE | S100: =IF(R100=TRUE,Priors!$H$6,1) -> 1 | T100: FALSE | U100: =IF(T100=TRUE,Priors!$H$7,1) -> 1 | V100: =P100*Q100*S100*U100 -> 0.58915366 | W100: =VLOOKUP(D100,Priors!$A$3:$C$6,2,FALSE) -> 0.10751786 | X100: =VLOOKUP(D100,Priors!$A$3:$C$6,3,FALSE) -> 0.090240672 | Y100: =IF(N100="",W100,V100*N100+(1-V100)*W100) -> 0.063280741 | Z100: =IF(O100="",X100,V100*O100+(1-V100)*X100) -> 0.089969984 | AA100: 1 | AB100: 1 | AC100: =Y100*AA100 -> 0.063280741 | AD100: =Z100*AB100 -> 0.089969984 | AE100: =1-V100 -> 0.41084634 | AF100: PL history | AI100: 7 | AJ100: FALSE | AK100: FPL Core Insights / official FPL historical feed | AL100: https://github.com/olbauday/FPL-Core-Insights/tree/main/data/2025-2026 | AO100: 0 | AP100: FALSE | AQ100: Total xG retained; low penalty contamination
...

Sheet Team_Attack
A1: Hist Team | B1: Hist League | C1: Matches 25/26 | D1: Team xG 25/26 | E1: Team xG / Match | F1: Current PL Team? | G1: Promoted 26/27? | H1: Current Manager | I1: Manager Start | J1: New Manager Summer? | K1: 26/27 Baseline Team xG/Match | L1: Notes | M1: Source URL
A2: Man City | B2: Premier League | C2: 38 | D2: 71.6 | E2: 1.8842105 | F2: TRUE | G2: FALSE | H2: Enzo Maresca | I2: 2026-06-29 | J2: TRUE | L2: 26/27 baseline intentionally blank until team-attack model. | M2: https://www.fotmob.com/leagues/47/stats/season/27110/teams/expected_goals_team/premier-league-teams
A3: Chelsea | B3: Premier League | C3: 38 | D3: 66.5 | E3: 1.75 | F3: TRUE | G3: FALSE | H3: Xabi Alonso | I3: 2026-07-01 | J3: TRUE | L3: 26/27 baseline intentionally blank until team-attack model. | M3: https://www.fotmob.com/leagues/47/stats/season/27110/teams/expected_goals_team/premier-league-teams
A4: Arsenal | B4: Premier League | C4: 38 | D4: 65.6 | E4: 1.7263158 | F4: TRUE | G4: FALSE | H4: Mikel Arteta | I4: 2019-12-22 | J4: FALSE | L4: 26/27 baseline intentionally blank until team-attack model. | M4: https://www.fotmob.com/leagues/47/stats/season/27110/teams/expected_goals_team/premier-league-teams
A5: Man Utd | B5: Premier League | C5: 38 | D5: 65.3 | E5: 1.7184211 | F5: TRUE | G5: FALSE | H5: Michael Carrick | I5: 2026-01-13 | J5: FALSE | L5: 26/27 baseline intentionally blank until team-attack model. | M5: https://www.fotmob.com/leagues/47/stats/season/27110/teams/expected_goals_team/premier-league-teams
A6: Bournemouth | B6: Premier League | C6: 38 | D6: 61.9 | E6: 1.6289474 | F6: TRUE | G6: FALSE | H6: Marco Rose | I6: 2026-06-01 | J6: TRUE | L6: 26/27 baseline intentionally blank until team-attack model. | M6: https://www.fotmob.com/leagues/47/stats/season/27110/teams/expected_goals_team/premier-league-teams
A7: Liverpool | B7: Premier League | C7: 38 | D7: 61.3 | E7: 1.6131579 | F7: TRUE | G7: FALSE | H7: Andoni Iraola | I7: 2026-06-04 | J7: TRUE | L7: 26/27 baseline intentionally blank until team-attack model. | M7: https://www.fotmob.com/leagues/47/stats/season/27110/teams/expected_goals_team/premier-league-teams
A8: Brentford | B8: Premier League | C8: 38 | D8: 60.3 | E8: 1.5868421 | F8: TRUE | G8: FALSE | H8: Keith Andrews | I8: 2025-06-27 | J8: FALSE | L8: 26/27 baseline intentionally blank until team-attack model. | M8: https://www.fotmob.com/leagues/47/stats/season/27110/teams/expected_goals_team/premier-league-teams
A9: Crystal Palace | B9: Premier League | C9: 38 | D9: 58.2 | E9: 1.5315789 | F9: TRUE | G9: FALSE | H9: Pierre Sage | I9: 2026-06-15 | J9: TRUE | L9: 26/27 baseline intentionally blank until team-attack model. | M9: https://www.fotmob.com/leagues/47/stats/season/27110/teams/expected_goals_team/premier-league-teams
A10: Brighton | B10: Premier League | C10: 38 | D10: 57.9 | E10: 1.5236842 | F10: TRUE | G10: FALSE | H10: Fabian Hurzeler | I10: 2024-06-15 | J10: FALSE | L10: 26/27 baseline intentionally blank until team-attack model. | M10: https://www.fotmob.com/leagues/47/stats/season/27110/teams/expected_goals_team/premier-league-teams
A11: Newcastle | B11: Premier League | C11: 38 | D11: 57.1 | E11: 1.5026316 | F11: TRUE | G11: FALSE | H11: Matthias Jaissle | I11: 2026-08-05 | J11: TRUE | L11: 26/27 baseline intentionally blank until team-attack model. | M11: https://www.fotmob.com/leagues/47/stats/season/27110/teams/expected_goals_team/premier-league-teams
A12: Leeds | B12: Premier League | C12: 38 | D12: 54.2 | E12: 1.4263158 | F12: TRUE | G12: FALSE | H12: Daniel Farke | I12: 2023-07-04 | J12: FALSE | L12: 26/27 baseline intentionally blank until team-attack model. | M12: https://www.fotmob.com/leagues/47/stats/season/27110/teams/expected_goals_team/premier-league-teams
A13: Fulham | B13: Premier League | C13: 38 | D13: 48.4 | E13: 1.2736842 | F13: TRUE | G13: FALSE | H13: Alvaro Arbeloa | I13: 2026-07-07 | J13: TRUE | L13: 26/27 baseline intentionally blank until team-attack model. | M13: https://www.fotmob.com/leagues/47/stats/season/27110/teams/expected_goals_team/premier-league-teams
... A15: Everton | B15: Premier League | C15: 38 | D15: 46.7 | E15: 1.2289474 | F15: TRUE | G15: FALSE | H15: David Moyes | I15: 2025-01-11 | J15: FALSE | L15: 26/27 baseline intentionally blank until team-attack model. | M15: https://www.fotmob.com/leagues/47/stats/season/27110/teams/expected_goals_team/premier-league-teams
A16: West Ham | B16: Premier League | C16: 38 | D16: 46.1 | E16: 1.2131579 | F16: FALSE | G16: FALSE | J16: FALSE | L16: 26/27 baseline intentionally blank until team-attack model. | M16: https://www.fotmob.com/leagues/47/stats/season/27110/teams/expected_goals_team/premier-league-teams
A17: Nott'm Forest | B17: Premier League | C17: 38 | D17: 46 | E17: 1.2105263 | F17: TRUE | G17: FALSE | H17: Oliver Glasner | I17: 2026-07-06 | J17: TRUE | L17: 26/27 baseline intentionally blank until team-attack model. | M17: https://www.fotmob.com/leagues/47/stats/season/27110/teams/expected_goals_team/premier-league-teams
A18: Spurs | B18: Premier League | C18: 38 | D18: 40 | E18: 1.0526316 | F18: TRUE | G18: FALSE | H18: Roberto De Zerbi | I18: 2026-03-31 | J18: FALSE | L18: 26/27 baseline intentionally blank until team-attack model. | M18: https://www.fotmob.com/leagues/47/stats/season/27110/teams/expected_goals_team/premier-league-teams
A19: Sunderland | B19: Premier League | C19: 38 | D19: 38.9 | E19: 1.0236842 | F19: TRUE | G19: FALSE | H19: Regis Le Bris | I19: 2024-07-01 | J19: FALSE | L19: 26/27 baseline intentionally blank until team-attack model. | M19: https://www.fotmob.com/leagues/47/stats/season/27110/teams/expected_goals_team/premier-league-teams
A20: Wolves | B20: Premier League | C20: 38 | D20: 35.5 | E20: 0.93421053 | F20: FALSE | G20: FALSE | J20: FALSE | L20: 26/27 baseline intentionally blank until team-attack model. | M20: https://www.fotmob.com/leagues/47/stats/season/27110/teams/expected_goals_team/premier-league-teams
A21: Burnley | B21: Premier League | C21: 38 | D21: 32.5 | E21: 0.85526316 | F21: FALSE | G21: FALSE | J21: FALSE | L21: 26/27 baseline intentionally blank until team-attack model. | M21: https://www.fotmob.com/leagues/47/stats/season/27110/teams/expected_goals_team/premier-league-teams
A22: Coventry City | B22: Championship | C22: 46 | D22: 87.3 | E22: 1.8978261 | F22: TRUE | G22: TRUE | H22: Frank Lampard | I22: 2024-11-28 | J22: FALSE | L22: 26/27 baseline intentionally blank until team-attack model. | M22: https://www.fotmob.com/leagues/48/stats/season/27195/teams/expected_goals_team/championship-teams
A23: Ipswich Town | B23: Championship | C23: 46 | D23: 79.2 | E23: 1.7217391 | F23: TRUE | G23: TRUE | H23: Gary O'Neil | I23: 2026-06-23 | J23: TRUE | L23: 26/27 baseline intentionally blank until team-attack model. | M23: https://www.fotmob.com/leagues/48/stats/season/27195/teams/expected_goals_team/championship-teams
A24: Hull City | B24: Championship | C24: 46 | D24: 59.7 | E24: 1.2978261 | F24: TRUE | G24: TRUE | H24: Sergej Jakirovic | I24: 2025-06-11 | J24: FALSE | L24: 26/27 baseline intentionally blank until team-attack model. | M24: https://www.fotmob.com/leagues/48/stats/season/27195/teams/expected_goals_team/championship-teams

Sheet Priors
A1: POSITION SHARE PRIORS | G1: SHRINKAGE / RELIABILITY | J1: PHILOSOPHY / CAVEATS
A2: Position | B2: xG Share Prior | C2: xA Share Prior | D2: PL Players | E2: Hist Minutes | G2: Assumption | H2: Value | J2: PHILOSOPHY / CAVEATS
A3: GK | B3: 0.00016719535 | C3: 0.0013793616 | D3: 31 | E3: 59967 | G3: Minutes shrinkage k | H3: 1000 | J3: Attack remains team-xG-share based; v0.4 adds defensive player priors separately.
A4: DEF | B4: 0.041142361 | C4: 0.04051308 | D4: 135 | E4: 223882 | G4: PL history reliability | H4: 1 | J4: npxG is preferred conceptually, but total xG is retained until a consistent penalty-xG source exists.
A5: MID | B5: 0.10751786 | C5: 0.090240672 | D5: 190 | E5: 268280 | G5: Championship history reliability | H5: 0.8 | J5: Penalty-contaminated historical attacking priors are explicitly flagged on Attack_Priors.
A6: FWD | B6: 0.30461526 | C6: 0.039258062 | D6: 48 | E6: 57305 | G6: Changed-team transport reliability | H6: 0.85 | J6: DefCon prior = shrunk historical DC90; current workload adjustment is separate and editable.
G7: Summer new-manager reliability | H7: 0.9 | J7: DefCon points are threshold events (10 DEF / 12 MID-FWD), so DC90 is NOT directly converted to FPL points yet.
G8: Missing history reliability | H8: 0 | J8: GK save-rate proxy is shrunk separately from save volume.
J9: Save volume should later come from expected shots on target faced, not historical saves90 alone.
J10: Historical team xGA is environment evidence, not a 26/27 clean-sheet forecast.
J11: Promoted-team Championship xGA is shown league-relative and not treated as directly PL-comparable.
J12: Clean-sheet probability, save points and final xPts are deferred to the fixture engine.
J13: Role/lineup interactions remain future Python/UI work rather than hand-coded noise.
A16: DEFENSIVE PRIORS | G16: DEFENCE ASSUMPTIONS | J16: GOALKEEPER PRIORS
A17: Position | B17: DC90 Prior | C17: Players w/ PL hist | D17: Hist Minutes | E17: DC Threshold | G17: Assumption | H17: Value | J17: Metric | K17: Value
A18: GK | B18: =IFERROR(SUMIFS(Def_Priors!$H$2:$H$568,Def_Priors!$D$2:$D$568,A18,Def_Priors!$E$2:$E$568,"Premier League")*90/SUMIFS(Def_Priors!$G$2:$G$568,Def_Priors!$D$2:$D$568,A18,Def_Priors!$E$2:$E$568,"Premier League"),0) -> 2.6414528 | C18: =COUNTIFS(Def_Priors!$D$2:$D$568,A18,Def_Priors!$E$2:$E$568,"Premier League",Def_Priors!$G$2:$G$568,">0") -> 31 | D18: =SUMIFS(Def_Priors!$G$2:$G$568,Def_Priors!$D$2:$D$568,A18,Def_Priors!$E$2:$E$568,"Premier League") -> 59967 | G18: DefCon shrinkage minutes k | H18: 1000 | J18: PL GK Saves90 | K18: =IFERROR(SUMIFS(Def_Priors!$J$2:$J$568,Def_Priors!$D$2:$D$568,"GK",Def_Priors!$E$2:$E$568,"Premier League")*90/SUMIFS(Def_Priors!$G$2:$G$568,Def_Priors!$D$2:$D$568,"GK",Def_Priors!$E$2:$E$568,"Premier League"),0) -> 2.7435089
A19: DEF | B19: =IFERROR(SUMIFS(Def_Priors!$H$2:$H$568,Def_Priors!$D$2:$D$568,A19,Def_Priors!$E$2:$E$568,"Premier League")*90/SUMIFS(Def_Priors!$G$2:$G$568,Def_Priors!$D$2:$D$568,A19,Def_Priors!$E$2:$E$568,"Premier League"),0) -> 8.7398272 | C19: =COUNTIFS(Def_Priors!$D$2:$D$568,A19,Def_Priors!$E$2:$E$568,"Premier League",Def_Priors!$G$2:$G$568,">0") -> 135 | D19: =SUMIFS(Def_Priors!$G$2:$G$568,Def_Priors!$D$2:$D$568,A19,Def_Priors!$E$2:$E$568,"Premier League") -> 223882 | E19: 10 | G19: PL defensive-history reliability | H19: 1 | J19: PL GK Save% Proxy | K19: =IFERROR(SUMIFS(Def_Priors!$J$2:$J$568,Def_Priors!$D$2:$D$568,"GK",Def_Priors!$E$2:$E$568,"Premier League")/(SUMIFS(Def_Priors!$J$2:$J$568,Def_Priors!$D$2:$D$568,"GK",Def_Priors!$E$2:$E$568,"Premier League")+SUMIFS(Def_Priors!$L$2:$L$568,Def_Priors!$D$2:$D$568,"GK",Def_Priors!$E$2:$E$568,"Premier League")),0) -> 0.67280088
A20: MID | B20: =IFERROR(SUMIFS(Def_Priors!$H$2:$H$568,Def_Priors!$D$2:$D$568,A20,Def_Priors!$E$2:$E$568,"Premier League")*90/SUMIFS(Def_Priors!$G$2:$G$568,Def_Priors!$D$2:$D$568,A20,Def_Priors!$E$2:$E$568,"Premier League"),0) -> 8.4555315 | C20: =COUNTIFS(Def_Priors!$D$2:$D$568,A20,Def_Priors!$E$2:$E$568,"Premier League",Def_Priors!$G$2:$G$568,">0") -> 190 | D20: =SUMIFS(Def_Priors!$G$2:$G$568,Def_Priors!$D$2:$D$568,A20,Def_Priors!$E$2:$E$568,"Premier League") -> 268280 | E20: 12 | G20: Changed-team reliability | H20: 0.85 | J20: Save points conversion | K20: Deferred to fixture engine
A21: FWD | B21: =IFERROR(SUMIFS(Def_Priors!$H$2:$H$568,Def_Priors!$D$2:$D$568,A21,Def_Priors!$E$2:$E$568,"Premier League")*90/SUMIFS(Def_Priors!$G$2:$G$568,Def_Priors!$D$2:$D$568,A21,Def_Priors!$E$2:$E$568,"Premier League"),0) -> 4.5137423 | C21: =COUNTIFS(Def_Priors!$D$2:$D$568,A21,Def_Priors!$E$2:$E$568,"Premier League",Def_Priors!$G$2:$G$568,">0") -> 48 | D21: =SUMIFS(Def_Priors!$G$2:$G$568,Def_Priors!$D$2:$D$568,A21,Def_Priors!$E$2:$E$568,"Premier League") -> 57305 | E21: 12 | G21: New-manager reliability | H21: 0.9
G22: GK save-rate note | H22: Proxy only until shot-on-target model
G25: FIXTURE / TEAM ENGINE | J25: STRUCTURAL MODEL NOTES
G26: Assumption | H26: Value | J26: Channel | K26: Treatment
G27: PL baseline xG / team / match | H27: 1.3976316 | J27: Bookmaker market | K27: Primary near-term anchor; normalized to fair 1X2 first.
G28: Home scoring multiplier | H28: 1.1 | J28: History | K28: Parallel structural estimate and long-horizon fallback.
G29: Away scoring multiplier | H29: 0.9 | J29: Squad changes | K29: Editable team attack/defence multipliers; default 1.00.
G30: Default market weight when available | H30: 1 | J30: Manager changes | K30: Editable team attack/defence multipliers; default 1.00.
G31: Market method | H31: De-vigged 1X2 -> independent Poisson lambdas | J31: User view | K31: Override final team xG directly when desired; model value remains visible.
J32: Backsolve | K32: Future Python layer will compare forecast errors by channel.

Sheet Fixtures
A1: GW | B1: Fixture ID | C1: Kickoff UTC | D1: Team | E1: Opponent | F1: H/A | G1: Official FDR | H1: Market Team xG | I1: Market Opp xG | J1: CS Prob | K1: Attack Fixture Adj | L1: Def Fixture Adj | M1: Notes | N1: Source URL
A2: 1 | B2: 1 | C2: 46255.792 | D2: Coventry City | E2: Arsenal | F2: A | G2: 5 | J2: =IF(I2="","",EXP(-I2)) | K2: 1 | L2: 1 | N2: https://fantasy.premierleague.com/
A3: 1 | B3: 1 | C3: 46255.792 | D3: Arsenal | E3: Coventry City | F3: H | G3: 2 | J3: =IF(I3="","",EXP(-I3)) | K3: 1 | L3: 1 | N3: https://fantasy.premierleague.com/
A4: 1 | B4: 2 | C4: 46256.688 | D4: Spurs | E4: Brentford | F4: A | G4: 3 | J4: =IF(I4="","",EXP(-I4)) | K4: 1 | L4: 1 | N4: https://fantasy.premierleague.com/
A5: 1 | B5: 2 | C5: 46256.688 | D5: Brentford | E5: Spurs | F5: H | G5: 3 | J5: =IF(I5="","",EXP(-I5)) | K5: 1 | L5: 1 | N5: https://fantasy.premierleague.com/
A6: 1 | B6: 3 | C6: 46256.583 | D6: Crystal Palace | E6: Everton | F6: A | G6: 3 | J6: =IF(I6="","",EXP(-I6)) | K6: 1 | L6: 1 | N6: https://fantasy.premierleague.com/
A7: 1 | B7: 3 | C7: 46256.583 | D7: Everton | E7: Crystal Palace | F7: H | G7: 3 | J7: =IF(I7="","",EXP(-I7)) | K7: 1 | L7: 1 | N7: https://fantasy.premierleague.com/
A8: 1 | B8: 4 | C8: 46256.479 | D8: Man Utd | E8: Hull City | F8: A | G8: 2 | J8: =IF(I8="","",EXP(-I8)) | K8: 1 | L8: 1 | N8: https://fantasy.premierleague.com/
A9: 1 | B9: 4 | C9: 46256.479 | D9: Hull City | E9: Man Utd | F9: H | G9: 4 | J9: =IF(I9="","",EXP(-I9)) | K9: 1 | L9: 1 | N9: https://fantasy.premierleague.com/
A10: 1 | B10: 5 | C10: 46256.583 | D10: Sunderland | E10: Ipswich Town | F10: A | G10: 2 | J10: =IF(I10="","",EXP(-I10)) | K10: 1 | L10: 1 | N10: https://fantasy.premierleague.com/
A11: 1 | B11: 5 | C11: 46256.583 | D11: Ipswich Town | E11: Sunderland | F11: H | G11: 2 | J11: =IF(I11="","",EXP(-I11)) | K11: 1 | L11: 1 | N11: https://fantasy.premierleague.com/
A12: 1 | B12: 6 | C12: 46256.583 | D12: Leeds | E12: Nott'm Forest | F12: A | G12: 3 | J12: =IF(I12="","",EXP(-I12)) | K12: 1 | L12: 1 | N12: https://fantasy.premierleague.com/
A13: 1 | B13: 6 | C13: 46256.583 | D13: Nott'm Forest | E13: Leeds | F13: H | G13: 2 | J13: =IF(I13="","",EXP(-I13)) | K13: 1 | L13: 1 | N13: https://fantasy.premierleague.com/
... A761: 38 | B761: 380 | C761: 46537.625 | D761: Sunderland | E761: Man City | F761: H | G761: 4 | J761: =IF(I761="","",EXP(-I761)) | K761: 1 | L761: 1 | N761: https://fantasy.premierleague.com/

Sheet Projections
A1: GW | B1: Player ID | C1: Player | D1: Team | E1: Expected Mins | F1: Team xG | G1: xG Share | H1: xA Share | I1: Expected xG | J1: Expected xA | K1: Attacking xPts | L1: Total xPts
A3: Deferred: v0.3 deliberately stops at attacking priors; fixture/minutes/xPts comes later.

Sheet Squad
A1: Player | B1: Team | C1: FPL Pos | D1: Current £m | E1: Starter? | F1: Captain? | G1: 6GW xPts | H1: VORP | I1: Marginal £ Value | J1: Notes

Sheet Lists
A1: Teams | B1: Positions | C1: Role Change
A2: Arsenal | B2: GK | C2: None
A3: Aston Villa | B3: DEF | C3: More goal-focused
A4: Bournemouth | B4: MID | C4: More creative
A5: Brentford | B5: FWD | C5: Deeper
A6: Brighton | C6: Rotation/unclear
A7: Chelsea
A8: Coventry City
A9: Crystal Palace
A10: Everton
A11: Fulham
A12: Hull City
A13: Ipswich Town
A14: Leeds
A15: Liverpool
A16: Man City
A17: Man Utd
A18: Newcastle
... A21: Sunderland

Sheet Team_Defence
A1: Hist Team | B1: Hist League | C1: Matches 25/26 | D1: xGA 25/26 | E1: xGA / Match | F1: League Avg xGA / Match | G1: League-Relative Defence | H1: Current PL Team? | I1: Promoted 26/27? | J1: Current Manager | K1: New Manager Summer? | L1: 26/27 Baseline xGA / Match | M1: Notes | N1: Source URL
A2: Ipswich Town | B2: Championship | C2: 46 | D2: 46.6 | E2: 1.0130435 | F2: 1.3019022 | G2: 1.2851395 | H2: TRUE | I2: TRUE | J2: Gary O'Neil | K2: TRUE | M2: Championship relative strength is NOT treated as directly PL-comparable. | N2: https://www.fotmob.com/leagues/48/stats/season/27195/teams/expected_goals_conceded_team/championship-teams
A3: Coventry City | B3: Championship | C3: 46 | D3: 50.2 | E3: 1.0913043 | F3: 1.3019022 | G3: 1.1929781 | H3: TRUE | I3: TRUE | J3: Frank Lampard | K3: FALSE | M3: Championship relative strength is NOT treated as directly PL-comparable. | N3: https://www.fotmob.com/leagues/48/stats/season/27195/teams/expected_goals_conceded_team/championship-teams
A4: Hull City | B4: Championship | C4: 46 | D4: 80.1 | E4: 1.7413043 | F4: 1.3019022 | G4: 0.74765918 | H4: TRUE | I4: TRUE | J4: Sergej Jakirovic | K4: FALSE | M4: Championship relative strength is NOT treated as directly PL-comparable. | N4: https://www.fotmob.com/leagues/48/stats/season/27195/teams/expected_goals_conceded_team/championship-teams
A5: Arsenal | B5: Premier League | C5: 38 | D5: 28.3 | E5: 0.74473684 | F5: 1.3977632 | G5: 1.8768551 | H5: TRUE | I5: FALSE | J5: Mikel Arteta | K5: FALSE | M5: Historical defensive environment only; 26/27 baseline intentionally blank. | N5: https://www.fotmob.com/leagues/47/stats/season/27110/teams/expected_goals_conceded_team/premier-league-teams
A6: Man City | B6: Premier League | C6: 38 | D6: 44.2 | E6: 1.1631579 | F6: 1.3977632 | G6: 1.2016968 | H6: TRUE | I6: FALSE | J6: Enzo Maresca | K6: TRUE | M6: Historical defensive environment only; 26/27 baseline intentionally blank. | N6: https://www.fotmob.com/leagues/47/stats/season/27110/teams/expected_goals_conceded_team/premier-league-teams
A7: Liverpool | B7: Premier League | C7: 38 | D7: 47.4 | E7: 1.2473684 | F7: 1.3977632 | G7: 1.1205696 | H7: TRUE | I7: FALSE | J7: Andoni Iraola | K7: TRUE | M7: Historical defensive environment only; 26/27 baseline intentionally blank. | N7: https://www.fotmob.com/leagues/47/stats/season/27110/teams/expected_goals_conceded_team/premier-league-teams
A8: Man Utd | B8: Premier League | C8: 38 | D8: 48.6 | E8: 1.2789474 | F8: 1.3977632 | G8: 1.0929012 | H8: TRUE | I8: FALSE | J8: Michael Carrick | K8: FALSE | M8: Historical defensive environment only; 26/27 baseline intentionally blank. | N8: https://www.fotmob.com/leagues/47/stats/season/27110/teams/expected_goals_conceded_team/premier-league-teams
A9: Brighton | B9: Premier League | C9: 38 | D9: 49.1 | E9: 1.2921053 | F9: 1.3977632 | G9: 1.0817719 | H9: TRUE | I9: FALSE | J9: Fabian Hurzeler | K9: FALSE | M9: Historical defensive environment only; 26/27 baseline intentionally blank. | N9: https://www.fotmob.com/leagues/47/stats/season/27110/teams/expected_goals_conceded_team/premier-league-teams
A10: Newcastle | B10: Premier League | C10: 38 | D10: 51.3 | E10: 1.35 | F10: 1.3977632 | G10: 1.0353801 | H10: TRUE | I10: FALSE | J10: Matthias Jaissle | K10: TRUE | M10: Historical defensive environment only; 26/27 baseline intentionally blank. | N10: https://www.fotmob.com/leagues/47/stats/season/27110/teams/expected_goals_conceded_team/premier-league-teams
A11: Crystal Palace | B11: Premier League | C11: 38 | D11: 51.9 | E11: 1.3657895 | F11: 1.3977632 | G11: 1.0234104 | H11: TRUE | I11: FALSE | J11: Pierre Sage | K11: TRUE | M11: Historical defensive environment only; 26/27 baseline intentionally blank. | N11: https://www.fotmob.com/leagues/47/stats/season/27110/teams/expected_goals_conceded_team/premier-league-teams
A12: Chelsea | B12: Premier League | C12: 38 | D12: 52.3 | E12: 1.3763158 | F12: 1.3977632 | G12: 1.0155832 | H12: TRUE | I12: FALSE | J12: Xabi Alonso | K12: TRUE | M12: Historical defensive environment only; 26/27 baseline intentionally blank. | N12: https://www.fotmob.com/leagues/47/stats/season/27110/teams/expected_goals_conceded_team/premier-league-teams
A13: Spurs | B13: Premier League | C13: 38 | D13: 52.3 | E13: 1.3763158 | F13: 1.3977632 | G13: 1.0155832 | H13: TRUE | I13: FALSE | J13: Roberto De Zerbi | K13: FALSE | M13: Historical defensive environment only; 26/27 baseline intentionally blank. | N13: https://www.fotmob.com/leagues/47/stats/season/27110/teams/expected_goals_conceded_team/premier-league-teams
... A21: Nott'm Forest | B21: Premier League | C21: 38 | D21: 57.3 | E21: 1.5078947 | F21: 1.3977632 | G21: 0.92696335 | H21: TRUE | I21: FALSE | J21: Oliver Glasner | K21: TRUE | M21: Historical defensive environment only; 26/27 baseline intentionally blank. | N21: https://www.fotmob.com/leagues/47/stats/season/27110/teams/expected_goals_conceded_team/premier-league-teams
A22: Wolves | B22: Premier League | C22: 38 | D22: 59.5 | E22: 1.5657895 | F22: 1.3977632 | G22: 0.89268908 | H22: FALSE | I22: FALSE | K22: FALSE | M22: Historical defensive environment only; 26/27 baseline intentionally blank. | N22: https://www.fotmob.com/leagues/47/stats/season/27110/teams/expected_goals_conceded_team/premier-league-teams
A23: West Ham | B23: Premier League | C23: 38 | D23: 59.6 | E23: 1.5684211 | F23: 1.3977632 | G23: 0.89119128 | H23: FALSE | I23: FALSE | K23: FALSE | M23: Historical defensive environment only; 26/27 baseline intentionally blank. | N23: https://www.fotmob.com/leagues/47/stats/season/27110/teams/expected_goals_conceded_team/premier-league-teams
A24: Burnley | B24: Premier League | C24: 38 | D24: 75.4 | E24: 1.9842105 | F24: 1.3977632 | G24: 0.70444297 | H24: FALSE | I24: FALSE | K24: FALSE | M24: Historical defensive environment only; 26/27 baseline intentionally blank. | N24: https://www.fotmob.com/leagues/47/stats/season/27110/teams/expected_goals_conceded_team/premier-league-teams

Sheet Def_Priors
A1: Player ID | B1: Player | C1: Team | D1: FPL Pos | E1: Hist League | F1: Hist Team | G1: Hist Mins | H1: Hist DC Total | I1: Hist DC90 | J1: Hist Saves | K1: Hist Saves90 | L1: Hist Goals Conceded | M1: Hist Clean Sheets | N1: Hist Save % Proxy | O1: Hist Bonus | P1: Hist BPS | Q1: Hist BPS90 | R1: Base Min Weight | S1: League Reliability | T1: Team Changed? | U1: Transport Reliability | V1: New Manager Summer? | W1: Manager Reliability | X1: Effective Weight | Y1: Pos DC90 Prior | Z1: DC90 Prior | AA1: Def Workload Adj | AB1: Current DC90 Prior | AC1: GK Saves90 Pos Prior | AD1: GK Saves90 Prior | AE1: GK Save% Pos Prior | AF1: GK Save% Prior | AG1: Uncertainty | AH1: History Quality | AI1: DC Threshold | AJ1: DC Threshold Margin | AK1: Manual Review? | AL1: History Source | AM1: Source URL | AN1: Notes
A2: 1 | B2: Raya | C2: Arsenal | D2: GK | E2: Premier League | F2: Arsenal | G2: 3330 | H2: 94 | I2: 0 | J2: 60 | K2: 1.62 | L2: 26 | M2: 19 | N2: 0.69767442 | O2: 11 | P2: 633 | Q2: 17.108108 | R2: =IFERROR(G2/(G2+Priors!$H$18),0) -> 0.76905312 | S2: 1 | T2: FALSE | U2: 1 | V2: FALSE | W2: 1 | X2: =R2*S2*U2*W2 -> 0.76905312 | Y2: =VLOOKUP(D2,Priors!$A$18:$B$21,2,FALSE) -> 2.6414528 | Z2: =IF(OR(H2="",G2=0),Y2,X2*I2+(1-X2)*Y2) -> 0.61003529 | AA2: 1 | AB2: =Z2*AA2 -> 0.61003529 | AC2: =Priors!$K$18 -> 2.7435089 | AD2: =IF(D2<>"GK","",IF(OR(K2="",G2=0),AC2,X2*K2+(1-X2)*AC2)) -> 1.8794709 | AE2: =Priors!$K$19 -> 0.67280088 | AF2: =IF(D2<>"GK","",IF(OR(N2="",G2=0),AE2,X2*N2+(1-X2)*AE2)) -> 0.69192995 | AG2: =1-X2 -> 0.23094688 | AH2: PL history | AJ2: =IF(OR(AI2="",AI2=0),"",AB2/AI2) | AK2: =OR(AG2>=0.5,E2<>"Premier League",T2=TRUE,V2=TRUE) -> FALSE | AL2: FPL Core Insights / official FPL historical feed | AM2: https://github.com/olbauday/FPL-Core-Insights/tree/main/data/2025-2026 | AN2: GK save % is a proxy = saves/(saves+goals conceded); save volume remains a later team/fixture input.
A3: 2 | B3: Arrizabalaga | C3: Arsenal | D3: GK | E3: Premier League | F3: Arsenal | G3: 90 | H3: 0 | I3: 0 | J3: 2 | K3: 2 | L3: 1 | M3: 0 | N3: 0.66666667 | O3: 0 | P3: 11 | Q3: 11 | R3: =IFERROR(G3/(G3+Priors!$H$18),0) -> 0.082568807 | S3: 1 | T3: FALSE | U3: 1 | V3: FALSE | W3: 1 | X3: =R3*S3*U3*W3 -> 0.082568807 | Y3: =VLOOKUP(D3,Priors!$A$18:$B$21,2,FALSE) -> 2.6414528 | Z3: =IF(OR(H3="",G3=0),Y3,X3*I3+(1-X3)*Y3) -> 2.4233512 | AA3: 1 | AB3: =Z3*AA3 -> 2.4233512 | AC3: =Priors!$K$18 -> 2.7435089 | AD3: =IF(D3<>"GK","",IF(OR(K3="",G3=0),AC3,X3*K3+(1-X3)*AC3)) -> 2.6821183 | AE3: =Priors!$K$19 -> 0.67280088 | AF3: =IF(D3<>"GK","",IF(OR(N3="",G3=0),AE3,X3*N3+(1-X3)*AE3)) -> 0.67229439 | AG3: =1-X3 -> 0.91743119 | AH3: PL history | AJ3: =IF(OR(AI3="",AI3=0),"",AB3/AI3) | AK3: =OR(AG3>=0.5,E3<>"Premier League",T3=TRUE,V3=TRUE) -> TRUE | AL3: FPL Core Insights / official FPL historical feed | AM3: https://github.com/olbauday/FPL-Core-Insights/tree/main/data/2025-2026 | AN3: GK save % is a proxy = saves/(saves+goals conceded); save volume remains a later team/fixture input.
A4: 3 | B4: Meslier | C4: Arsenal | D4: GK | E4: Premier League | F4: Leeds | G4: 0 | H4: 0 | I4: 0 | J4: 0 | K4: 0 | L4: 0 | M4: 0 | O4: 0 | P4: 0 | Q4: 0 | R4: =IFERROR(G4/(G4+Priors!$H$18),0) -> 0 | S4: 1 | T4: TRUE | U4: 0.85 | V4: FALSE | W4: 1 | X4: =R4*S4*U4*W4 -> 0 | Y4: =VLOOKUP(D4,Priors!$A$18:$B$21,2,FALSE) -> 2.6414528 | Z4: =IF(OR(H4="",G4=0),Y4,X4*I4+(1-X4)*Y4) -> 2.6414528 | AA4: 1 | AB4: =Z4*AA4 -> 2.6414528 | AC4: =Priors!$K$18 -> 2.7435089 | AD4: =IF(D4<>"GK","",IF(OR(K4="",G4=0),AC4,X4*K4+(1-X4)*AC4)) -> 2.7435089 | AE4: =Priors!$K$19 -> 0.67280088 | AF4: =IF(D4<>"GK","",IF(OR(N4="",G4=0),AE4,X4*N4+(1-X4)*AE4)) -> 0.67280088 | AG4: =1-X4 -> 1 | AH4: PL history | AJ4: =IF(OR(AI4="",AI4=0),"",AB4/AI4) | AK4: =OR(AG4>=0.5,E4<>"Premier League",T4=TRUE,V4=TRUE) -> TRUE | AL4: FPL Core Insights / official FPL historical feed | AM4: https://github.com/olbauday/FPL-Core-Insights/tree/main/data/2025-2026 | AN4: GK save % is a proxy = saves/(saves+goals conceded); save volume remains a later team/fixture input.
A5: 4 | B5: Gabriel | C5: Arsenal | D5: DEF | E5: Premier League | F5: Arsenal | G5: 2750 | H5: 292 | I5: 9.07 | J5: 0 | K5: 0 | L5: 20 | M5: 18 | O5: 30 | P5: 724 | Q5: 23.694545 | R5: =IFERROR(G5/(G5+Priors!$H$18),0) -> 0.73333333 | S5: 1 | T5: FALSE | U5: 1 | V5: FALSE | W5: 1 | X5: =R5*S5*U5*W5 -> 0.73333333 | Y5: =VLOOKUP(D5,Priors!$A$18:$B$21,2,FALSE) -> 8.7398272 | Z5: =IF(OR(H5="",G5=0),Y5,X5*I5+(1-X5)*Y5) -> 8.9819539 | AA5: 1 | AB5: =Z5*AA5 -> 8.9819539 | AC5: =Priors!$K$18 -> 2.7435089 | AD5: =IF(D5<>"GK","",IF(OR(K5="",G5=0),AC5,X5*K5+(1-X5)*AC5)) | AE5: =Priors!$K$19 -> 0.67280088 | AF5: =IF(D5<>"GK","",IF(OR(N5="",G5=0),AE5,X5*N5+(1-X5)*AE5)) | AG5: =1-X5 -> 0.26666667 | AH5: PL history | AI5: 10 | AJ5: =IF(OR(AI5="",AI5=0),"",AB5/AI5) -> 0.89819539 | AK5: =OR(AG5>=0.5,E5<>"Premier League",T5=TRUE,V5=TRUE) -> FALSE | AL5: FPL Core Insights / official FPL historical feed | AM5: https://github.com/olbauday/FPL-Core-Insights/tree/main/data/2025-2026 | AN5: GK save % is a proxy = saves/(saves+goals conceded); save volume remains a later team/fixture input.
A6: 5 | B6: J.Timber | C6: Arsenal | D6: DEF | E6: Premier League | F6: Arsenal | G6: 2452 | H6: 178 | I6: 5.43 | J6: 0 | K6: 0 | L6: 20 | M6: 13 | O6: 9 | P6: 532 | Q6: 19.526917 | R6: =IFERROR(G6/(G6+Priors!$H$18),0) -> 0.71031286 | S6: 1 | T6: FALSE | U6: 1 | V6: FALSE | W6: 1 | X6: =R6*S6*U6*W6 -> 0.71031286 | Y6: =VLOOKUP(D6,Priors!$A$18:$B$21,2,FALSE) -> 8.7398272 | Z6: =IF(OR(H6="",G6=0),Y6,X6*I6+(1-X6)*Y6) -> 6.3888144 | AA6: 1 | AB6: =Z6*AA6 -> 6.3888144 | AC6: =Priors!$K$18 -> 2.7435089 | AD6: =IF(D6<>"GK","",IF(OR(K6="",G6=0),AC6,X6*K6+(1-X6)*AC6)) | AE6: =Priors!$K$19 -> 0.67280088 | AF6: =IF(D6<>"GK","",IF(OR(N6="",G6=0),AE6,X6*N6+(1-X6)*AE6)) | AG6: =1-X6 -> 0.28968714 | AH6: PL history | AI6: 10 | AJ6: =IF(OR(AI6="",AI6=0),"",AB6/AI6) -> 0.63888144 | AK6: =OR(AG6>=0.5,E6<>"Premier League",T6=TRUE,V6=TRUE) -> FALSE | AL6: FPL Core Insights / official FPL historical feed | AM6: https://github.com/olbauday/FPL-Core-Insights/tree/main/data/2025-2026 | AN6: GK save % is a proxy = saves/(saves+goals conceded); save volume remains a later team/fixture input.
A7: 6 | B7: Saliba | C7: Arsenal | D7: DEF | E7: Premier League | F7: Arsenal | G7: 2614 | H7: 224 | I7: 6.64 | J7: 0 | K7: 0 | L7: 20 | M7: 15 | O7: 12 | P7: 581 | Q7: 20.003826 | R7: =IFERROR(G7/(G7+Priors!$H$18),0) -> 0.72329828 | S7: 1 | T7: FALSE | U7: 1 | V7: FALSE | W7: 1 | X7: =R7*S7*U7*W7 -> 0.72329828 | Y7: =VLOOKUP(D7,Priors!$A$18:$B$21,2,FALSE) -> 8.7398272 | Z7: =IF(OR(H7="",G7=0),Y7,X7*I7+(1-X7)*Y7) -> 7.2210258 | AA7: 1 | AB7: =Z7*AA7 -> 7.2210258 | AC7: =Priors!$K$18 -> 2.7435089 | AD7: =IF(D7<>"GK","",IF(OR(K7="",G7=0),AC7,X7*K7+(1-X7)*AC7)) | AE7: =Priors!$K$19 -> 0.67280088 | AF7: =IF(D7<>"GK","",IF(OR(N7="",G7=0),AE7,X7*N7+(1-X7)*AE7)) | AG7: =1-X7 -> 0.27670172 | AH7: PL history | AI7: 10 | AJ7: =IF(OR(AI7="",AI7=0),"",AB7/AI7) -> 0.72210258 | AK7: =OR(AG7>=0.5,E7<>"Premier League",T7=TRUE,V7=TRUE) -> FALSE | AL7: FPL Core Insights / official FPL historical feed | AM7: https://github.com/olbauday/FPL-Core-Insights/tree/main/data/2025-2026 | AN7: GK save % is a proxy = saves/(saves+goals conceded); save volume remains a later team/fixture input.
A8: 7 | B8: Lewis-Skelly | C8: Arsenal | D8: MID | E8: Premier League | F8: Arsenal | G8: 697 | H8: 32 | I8: 3.23 | J8: 0 | K8: 0 | L8: 8 | M8: 2 | O8: 0 | P8: 110 | Q8: 14.20373 | R8: =IFERROR(G8/(G8+Priors!$H$18),0) -> 0.41072481 | S8: 1 | T8: FALSE | U8: 1 | V8: FALSE | W8: 1 | X8: =R8*S8*U8*W8 -> 0.41072481 | Y8: =VLOOKUP(D8,Priors!$A$18:$B$21,2,FALSE) -> 8.4555315 | Z8: =IF(OR(H8="",G8=0),Y8,X8*I8+(1-X8)*Y8) -> 6.3092761 | AA8: 1 | AB8: =Z8*AA8 -> 6.3092761 | AC8: =Priors!$K$18 -> 2.7435089 | AD8: =IF(D8<>"GK","",IF(OR(K8="",G8=0),AC8,X8*K8+(1-X8)*AC8)) | AE8: =Priors!$K$19 -> 0.67280088 | AF8: =IF(D8<>"GK","",IF(OR(N8="",G8=0),AE8,X8*N8+(1-X8)*AE8)) | AG8: =1-X8 -> 0.58927519 | AH8: PL history | AI8: 12 | AJ8: =IF(OR(AI8="",AI8=0),"",AB8/AI8) -> 0.52577301 | AK8: =OR(AG8>=0.5,E8<>"Premier League",T8=TRUE,V8=TRUE) -> TRUE | AL8: FPL Core Insights / official FPL historical feed | AM8: https://github.com/olbauday/FPL-Core-Insights/tree/main/data/2025-2026 | AN8: GK save % is a proxy = saves/(saves+goals conceded); save volume remains a later team/fixture input.
A9: 8 | B9: Calafiori | C9: Arsenal | D9: DEF | E9: Premier League | F9: Arsenal | G9: 1697 | H9: 141 | I9: 5.41 | J9: 0 | K9: 0 | L9: 8 | M9: 13 | O9: 6 | P9: 389 | Q9: 20.630524 | R9: =IFERROR(G9/(G9+Priors!$H$18),0) -> 0.62921765 | S9: 1 | T9: FALSE | U9: 1 | V9: FALSE | W9: 1 | X9: =R9*S9*U9*W9 -> 0.62921765 | Y9: =VLOOKUP(D9,Priors!$A$18:$B$21,2,FALSE) -> 8.7398272 | Z9: =IF(OR(H9="",G9=0),Y9,X9*I9+(1-X9)*Y9) -> 6.6446412 | AA9: 1 | AB9: =Z9*AA9 -> 6.6446412 | AC9: =Priors!$K$18 -> 2.7435089 | AD9: =IF(D9<>"GK","",IF(OR(K9="",G9=0),AC9,X9*K9+(1-X9)*AC9)) | AE9: =Priors!$K$19 -> 0.67280088 | AF9: =IF(D9<>"GK","",IF(OR(N9="",G9=0),AE9,X9*N9+(1-X9)*AE9)) | AG9: =1-X9 -> 0.37078235 | AH9: PL history | AI9: 10 | AJ9: =IF(OR(AI9="",AI9=0),"",AB9/AI9) -> 0.66446412 | AK9: =OR(AG9>=0.5,E9<>"Premier League",T9=TRUE,V9=TRUE) -> FALSE | AL9: FPL Core Insights / official FPL historical feed | AM9: https://github.com/olbauday/FPL-Core-Insights/tree/main/data/2025-2026 | AN9: GK save % is a proxy = saves/(saves+goals conceded); save volume remains a later team/fixture input.
A10: 9 | B10: Hincapie | C10: Arsenal | D10: DEF | E10: Premier League | F10: Arsenal | G10: 1787 | H10: 171 | I10: 8.61 | J10: 0 | K10: 0 | L10: 19 | M10: 5 | O10: 7 | P10: 335 | Q10: 16.871852 | R10: =IFERROR(G10/(G10+Priors!$H$18),0) -> 0.64119125 | S10: 1 | T10: FALSE | U10: 1 | V10: FALSE | W10: 1 | X10: =R10*S10*U10*W10 -> 0.64119125 | Y10: =VLOOKUP(D10,Priors!$A$18:$B$21,2,FALSE) -> 8.7398272 | Z10: =IF(OR(H10="",G10=0),Y10,X10*I10+(1-X10)*Y10) -> 8.6565831 | AA10: 1 | AB10: =Z10*AA10 -> 8.6565831 | AC10: =Priors!$K$18 -> 2.7435089 | AD10: =IF(D10<>"GK","",IF(OR(K10="",G10=0),AC10,X10*K10+(1-X10)*AC10)) | AE10: =Priors!$K$19 -> 0.67280088 | AF10: =IF(D10<>"GK","",IF(OR(N10="",G10=0),AE10,X10*N10+(1-X10)*AE10)) | AG10: =1-X10 -> 0.35880875 | AH10: PL history | AI10: 10 | AJ10: =IF(OR(AI10="",AI10=0),"",AB10/AI10) -> 0.86565831 | AK10: =OR(AG10>=0.5,E10<>"Premier League",T10=TRUE,V10=TRUE) -> FALSE | AL10: FPL Core Insights / official FPL historical feed | AM10: https://github.com/olbauday/FPL-Core-Insights/tree/main/data/2025-2026 | AN10: GK save % is a proxy = saves/(saves+goals conceded); save volume remains a later team/fixture input.
A11: 10 | B11: White | C11: Arsenal | D11: DEF | E11: Premier League | F11: Arsenal | G11: 699 | H11: 57 | I11: 6.82 | J11: 0 | K11: 0 | L11: 6 | M11: 5 | O11: 3 | P11: 181 | Q11: 23.304721 | R11: =IFERROR(G11/(G11+Priors!$H$18),0) -> 0.41141848 | S11: 1 | T11: FALSE | U11: 1 | V11: FALSE | W11: 1 | X11: =R11*S11*U11*W11 -> 0.41141848 | Y11: =VLOOKUP(D11,Priors!$A$18:$B$21,2,FALSE) -> 8.7398272 | Z11: =IF(OR(H11="",G11=0),Y11,X11*I11+(1-X11)*Y11) -> 7.9499748 | AA11: 1 | AB11: =Z11*AA11 -> 7.9499748 | AC11: =Priors!$K$18 -> 2.7435089 | AD11: =IF(D11<>"GK","",IF(OR(K11="",G11=0),AC11,X11*K11+(1-X11)*AC11)) | AE11: =Priors!$K$19 -> 0.67280088 | AF11: =IF(D11<>"GK","",IF(OR(N11="",G11=0),AE11,X11*N11+(1-X11)*AE11)) | AG11: =1-X11 -> 0.58858152 | AH11: PL history | AI11: 10 | AJ11: =IF(OR(AI11="",AI11=0),"",AB11/AI11) -> 0.79499748 | AK11: =OR(AG11>=0.5,E11<>"Premier League",T11=TRUE,V11=TRUE) -> TRUE | AL11: FPL Core Insights / official FPL historical feed | AM11: https://github.com/olbauday/FPL-Core-Insights/tree/main/data/2025-2026 | AN11: GK save % is a proxy = saves/(saves+goals conceded); save volume remains a later team/fixture input.
A12: 11 | B12: Mosquera | C12: Arsenal | D12: DEF | E12: Premier League | F12: Arsenal | G12: 986 | H12: 108 | I12: 8.67 | J12: 0 | K12: 0 | L12: 8 | M12: 3 | O12: 1 | P12: 195 | Q12: 17.799189 | R12: =IFERROR(G12/(G12+Priors!$H$18),0) -> 0.49647533 | S12: 1 | T12: FALSE | U12: 1 | V12: FALSE | W12: 1 | X12: =R12*S12*U12*W12 -> 0.49647533 | Y12: =VLOOKUP(D12,Priors!$A$18:$B$21,2,FALSE) -> 8.7398272 | Z12: =IF(OR(H12="",G12=0),Y12,X12*I12+(1-X12)*Y12) -> 8.7051597 | AA12: 1 | AB12: =Z12*AA12 -> 8.7051597 | AC12: =Priors!$K$18 -> 2.7435089 | AD12: =IF(D12<>"GK","",IF(OR(K12="",G12=0),AC12,X12*K12+(1-X12)*AC12)) | AE12: =Priors!$K$19 -> 0.67280088 | AF12: =IF(D12<>"GK","",IF(OR(N12="",G12=0),AE12,X12*N12+(1-X12)*AE12)) | AG12: =1-X12 -> 0.50352467 | AH12: PL history | AI12: 10 | AJ12: =IF(OR(AI12="",AI12=0),"",AB12/AI12) -> 0.87051597 | AK12: =OR(AG12>=0.5,E12<>"Premier League",T12=TRUE,V12=TRUE) -> TRUE | AL12: FPL Core Insights / official FPL historical feed | AM12: https://github.com/olbauday/FPL-Core-Insights/tree/main/data/2025-2026 | AN12: GK save % is a proxy = saves/(saves+goals conceded); save volume remains a later team/fixture input.
A13: 12 | B13: Saka | C13: Arsenal | D13: MID | E13: Premier League | F13: Arsenal | G13: 2218 | H13: 184 | I13: 7.47 | J13: 0 | K13: 0 | L13: 16 | M13: 12 | O13: 18 | P13: 570 | Q13: 23.128945 | R13: =IFERROR(G13/(G13+Priors!$H$18),0) -> 0.68924798 | S13: 1 | T13: FALSE | U13: 1 | V13: FALSE | W13: 1 | X13: =R13*S13*U13*W13 -> 0.68924798 | Y13: =VLOOKUP(D13,Priors!$A$18:$B$21,2,FALSE) -> 8.4555315 | Z13: =IF(OR(H13="",G13=0),Y13,X13*I13+(1-X13)*Y13) -> 7.7762559 | AA13: 1 | AB13: =Z13*AA13 -> 7.7762559 | AC13: =Priors!$K$18 -> 2.7435089 | AD13: =IF(D13<>"GK","",IF(OR(K13="",G13=0),AC13,X13*K13+(1-X13)*AC13)) | AE13: =Priors!$K$19 -> 0.67280088 | AF13: =IF(D13<>"GK","",IF(OR(N13="",G13=0),AE13,X13*N13+(1-X13)*AE13)) | AG13: =1-X13 -> 0.31075202 | AH13: PL history | AI13: 12 | AJ13: =IF(OR(AI13="",AI13=0),"",AB13/AI13) -> 0.64802133 | AK13: =OR(AG13>=0.5,E13<>"Premier League",T13=TRUE,V13=TRUE) -> FALSE | AL13: FPL Core Insights / official FPL historical feed | AM13: https://github.com/olbauday/FPL-Core-Insights/tree/main/data/2025-2026 | AN13: GK save % is a proxy = saves/(saves+goals conceded); save volume remains a later team/fixture input.
A14: 13 | B14: Rice | C14: Arsenal | D14: MID | E14: Premier League | F14: Arsenal | G14: 3093 | H14: 376 | I14: 10.94 | J14: 0 | K14: 0 | L14: 25 | M14: 18 | O14: 23 | P14: 790 | Q14: 22.987391 | R14: =IFERROR(G14/(G14+Priors!$H$18),0) -> 0.75568043 | S14: 1 | T14: FALSE | U14: 1 | V14: FALSE | W14: 1 | X14: =R14*S14*U14*W14 -> 0.75568043 | Y14: =VLOOKUP(D14,Priors!$A$18:$B$21,2,FALSE) -> 8.4555315 | Z14: =IF(OR(H14="",G14=0),Y14,X14*I14+(1-X14)*Y14) -> 10.332996 | AA14: 1 | AB14: =Z14*AA14 -> 10.332996 | AC14: =Priors!$K$18 -> 2.7435089 | AD14: =IF(D14<>"GK","",IF(OR(K14="",G14=0),AC14,X14*K14+(1-X14)*AC14)) | AE14: =Priors!$K$19 -> 0.67280088 | AF14: =IF(D14<>"GK","",IF(OR(N14="",G14=0),AE14,X14*N14+(1-X14)*AE14)) | AG14: =1-X14 -> 0.24431957 | AH14: PL history | AI14: 12 | AJ14: =IF(OR(AI14="",AI14=0),"",AB14/AI14) -> 0.86108298 | AK14: =OR(AG14>=0.5,E14<>"Premier League",T14=TRUE,V14=TRUE) -> FALSE | AL14: FPL Core Insights / official FPL historical feed | AM14: https://github.com/olbauday/FPL-Core-Insights/tree/main/data/2025-2026 | AN14: GK save % is a proxy = saves/(saves+goals conceded); save volume remains a later team/fixture input.
A15: 14 | B15: Eze | C15: Arsenal | D15: MID | E15: Premier League | F15: Arsenal | G15: 1885 | H15: 120 | I15: 5.73 | J15: 0 | K15: 0 | L15: 14 | M15: 11 | O15: 8 | P15: 439 | Q15: 20.960212 | R15: =IFERROR(G15/(G15+Priors!$H$18),0) -> 0.65337955 | S15: 1 | T15: FALSE | U15: 1 | V15: FALSE | W15: 1 | X15: =R15*S15*U15*W15 -> 0.65337955 | Y15: =VLOOKUP(D15,Priors!$A$18:$B$21,2,FALSE) -> 8.4555315 | Z15: =IF(OR(H15="",G15=0),Y15,X15*I15+(1-X15)*Y15) -> 6.674725 | AA15: 1 | AB15: =Z15*AA15 -> 6.674725 | AC15: =Priors!$K$18 -> 2.7435089 | AD15: =IF(D15<>"GK","",IF(OR(K15="",G15=0),AC15,X15*K15+(1-X15)*AC15)) | AE15: =Priors!$K$19 -> 0.67280088 | AF15: =IF(D15<>"GK","",IF(OR(N15="",G15=0),AE15,X15*N15+(1-X15)*AE15)) | AG15: =1-X15 -> 0.34662045 | AH15: PL history | AI15: 12 | AJ15: =IF(OR(AI15="",AI15=0),"",AB15/AI15) -> 0.55622708 | AK15: =OR(AG15>=0.5,E15<>"Premier League",T15=TRUE,V15=TRUE) -> FALSE | AL15: FPL Core Insights / official FPL historical feed | AM15: https://github.com/olbauday/FPL-Core-Insights/tree/main/data/2025-2026 | AN15: GK save % is a proxy = saves/(saves+goals conceded); save volume remains a later team/fixture input.
A16: 15 | B16: Ødegaard | C16: Arsenal | D16: MID | E16: Premier League | F16: Arsenal | G16: 1363 | H16: 102 | I16: 6.74 | J16: 0 | K16: 0 | L16: 13 | M16: 6 | O16: 5 | P16: 306 | Q16: 20.205429 | R16: =IFERROR(G16/(G16+Priors!$H$18),0) -> 0.57680914 | S16: 1 | T16: FALSE | U16: 1 | V16: FALSE | W16: 1 | X16: =R16*S16*U16*W16 -> 0.57680914 | Y16: =VLOOKUP(D16,Priors!$A$18:$B$21,2,FALSE) -> 8.4555315 | Z16: =IF(OR(H16="",G16=0),Y16,X16*I16+(1-X16)*Y16) -> 7.4659973 | AA16: 1 | AB16: =Z16*AA16 -> 7.4659973 | AC16: =Priors!$K$18 -> 2.7435089 | AD16: =IF(D16<>"GK","",IF(OR(K16="",G16=0),AC16,X16*K16+(1-X16)*AC16)) | AE16: =Priors!$K$19 -> 0.67280088 | AF16: =IF(D16<>"GK","",IF(OR(N16="",G16=0),AE16,X16*N16+(1-X16)*AE16)) | AG16: =1-X16 -> 0.42319086 | AH16: PL history | AI16: 12 | AJ16: =IF(OR(AI16="",AI16=0),"",AB16/AI16) -> 0.62216644 | AK16: =OR(AG16>=0.5,E16<>"Premier League",T16=TRUE,V16=TRUE) -> FALSE | AL16: FPL Core Insights / official FPL historical feed | AM16: https://github.com/olbauday/FPL-Core-Insights/tree/main/data/2025-2026 | AN16: GK save % is a proxy = saves/(saves+goals conceded); save volume remains a later team/fixture input.
... A28: 27 | B28: G.Jesus | C28: Arsenal | D28: FWD | E28: Premier League | F28: Arsenal | G28: 418 | H28: 30 | I28: 6.46 | J28: 0 | K28: 0 | L28: 6 | M28: 1 | O28: 0 | P28: 92 | Q28: 19.808612 | R28: =IFERROR(G28/(G28+Priors!$H$18),0) -> 0.29478138 | S28: 1 | T28: FALSE | U28: 1 | V28: FALSE | W28: 1 | X28: =R28*S28*U28*W28 -> 0.29478138 | Y28: =VLOOKUP(D28,Priors!$A$18:$B$21,2,FALSE) -> 4.5137423 | Z28: =IF(OR(H28="",G28=0),Y28,X28*I28+(1-X28)*Y28) -> 5.0874628 | AA28: 1 | AB28: =Z28*AA28 -> 5.0874628 | AC28: =Priors!$K$18 -> 2.7435089 | AD28: =IF(D28<>"GK","",IF(OR(K28="",G28=0),AC28,X28*K28+(1-X28)*AC28)) | AE28: =Priors!$K$19 -> 0.67280088 | AF28: =IF(D28<>"GK","",IF(OR(N28="",G28=0),AE28,X28*N28+(1-X28)*AE28)) | AG28: =1-X28 -> 0.70521862 | AH28: PL history | AI28: 12 | AJ28: =IF(OR(AI28="",AI28=0),"",AB28/AI28) -> 0.42395523 | AK28: =OR(AG28>=0.5,E28<>"Premier League",T28=TRUE,V28=TRUE) -> TRUE | AL28: FPL Core Insights / official FPL historical feed | AM28: https://github.com/olbauday/FPL-Core-Insights/tree/main/data/2025-2026 | AN28: GK save % is a proxy = saves/(saves+goals conceded); save volume remains a later team/fixture input.
A29: 28 | B29: Martinez | C29: Aston Villa | D29: GK | E29: Premier League | F29: Aston Villa | G29: 2835 | H29: 78 | I29: 0 | J29: 95 | K29: 3.02 | L29: 39 | M29: 7 | N29: 0.70895522 | O29: 11 | P29: 530 | Q29: 16.825397 | R29: =IFERROR(G29/(G29+Priors!$H$18),0) -> 0.73924381 | S29: 1 | T29: FALSE | U29: 1 | V29: FALSE | W29: 1 | X29: =R29*S29*U29*W29 -> 0.73924381 | Y29: =VLOOKUP(D29,Priors!$A$18:$B$21,2,FALSE) -> 2.6414528 | Z29: =IF(OR(H29="",G29=0),Y29,X29*I29+(1-X29)*Y29) -> 0.68877518 | AA29: 1 | AB29: =Z29*AA29 -> 0.68877518 | AC29: =Priors!$K$18 -> 2.7435089 | AD29: =IF(D29<>"GK","",IF(OR(K29="",G29=0),AC29,X29*K29+(1-X29)*AC29)) -> 2.9479032 | AE29: =Priors!$K$19 -> 0.67280088 | AF29: =IF(D29<>"GK","",IF(OR(N29="",G29=0),AE29,X29*N29+(1-X29)*AE29)) -> 0.69952776 | AG29: =1-X29 -> 0.26075619 | AH29: PL history | AJ29: =IF(OR(AI29="",AI29=0),"",AB29/AI29) | AK29: =OR(AG29>=0.5,E29<>"Premier League",T29=TRUE,V29=TRUE) -> FALSE | AL29: FPL Core Insights / official FPL historical feed | AM29: https://github.com/olbauday/FPL-Core-Insights/tree/main/data/2025-2026 | AN29: GK save % is a proxy = saves/(saves+goals conceded); save volume remains a later team/fixture input.
A30: 29 | B30: M.Bizot | C30: Aston Villa | D30: GK | E30: Premier League | F30: Aston Villa | G30: 585 | H30: 23 | I30: 0 | J30: 19 | K30: 2.92 | L30: 10 | M30: 1 | N30: 0.65517241 | O30: 0 | P30: 75 | Q30: 11.538462 | R30: =IFERROR(G30/(G30+Priors!$H$18),0) -> 0.36908517 | S30: 1 | T30: FALSE | U30: 1 | V30: FALSE | W30: 1 | X30: =R30*S30*U30*W30 -> 0.36908517 | Y30: =VLOOKUP(D30,Priors!$A$18:$B$21,2,FALSE) -> 2.6414528 | Z30: =IF(OR(H30="",G30=0),Y30,X30*I30+(1-X30)*Y30) -> 1.6665317 | AA30: 1 | AB30: =Z30*AA30 -> 1.6665317 | AC30: =Priors!$K$18 -> 2.7435089 | AD30: =IF(D30<>"GK","",IF(OR(K30="",G30=0),AC30,X30*K30+(1-X30)*AC30)) -> 2.8086492 | AE30: =Priors!$K$19 -> 0.67280088 | AF30: =IF(D30<>"GK","",IF(OR(N30="",G30=0),AE30,X30*N30+(1-X30)*AE30)) -> 0.66629448 | AG30: =1-X30 -> 0.63091483 | AH30: PL history | AJ30: =IF(OR(AI30="",AI30=0),"",AB30/AI30) | AK30: =OR(AG30>=0.5,E30<>"Premier League",T30=TRUE,V30=TRUE) -> TRUE | AL30: FPL Core Insights / official FPL historical feed | AM30: https://github.com/olbauday/FPL-Core-Insights/tree/main/data/2025-2026 | AN30: GK save % is a proxy = saves/(saves+goals conceded); save volume remains a later team/fixture input.
A31: 30 | B31: Digne | C31: Aston Villa | D31: DEF | E31: Premier League | F31: Aston Villa | G31: 1842 | H31: 137 | I31: 5.52 | J31: 0 | K31: 0 | L31: 23 | M31: 7 | O31: 5 | P31: 381 | Q31: 18.615635 | R31: =IFERROR(G31/(G31+Priors!$H$18),0) -> 0.64813512 | S31: 1 | T31: FALSE | U31: 1 | V31: FALSE | W31: 1 | X31: =R31*S31*U31*W31 -> 0.64813512 | Y31: =VLOOKUP(D31,Priors!$A$18:$B$21,2,FALSE) -> 8.7398272 | Z31: =IF(OR(H31="",G31=0),Y31,X31*I31+(1-X31)*Y31) -> 6.6529441 | AA31: 1 | AB31: =Z31*AA31 -> 6.6529441 | AC31: =Priors!$K$18 -> 2.7435089 | AD31: =IF(D31<>"GK","",IF(OR(K31="",G31=0),AC31,X31*K31+(1-X31)*AC31)) | AE31: =Priors!$K$19 -> 0.67280088 | AF31: =IF(D31<>"GK","",IF(OR(N31="",G31=0),AE31,X31*N31+(1-X31)*AE31)) | AG31: =1-X31 -> 0.35186488 | AH31: PL history | AI31: 10 | AJ31: =IF(OR(AI31="",AI31=0),"",AB31/AI31) -> 0.66529441 | AK31: =OR(AG31>=0.5,E31<>"Premier League",T31=TRUE,V31=TRUE) -> FALSE | AL31: FPL Core Insights / official FPL historical feed | AM31: https://github.com/olbauday/FPL-Core-Insights/tree/main/data/2025-2026 | AN31: GK save % is a proxy = saves/(saves+goals conceded); save volume remains a later team/fixture input.
A32: 31 | B32: Konsa | C32: Aston Villa | D32: DEF | E32: Premier League | F32: Aston Villa | G32: 3035 | H32: 223 | I32: 5.81 | J32: 0 | K32: 0 | L32: 44 | M32: 9 | O32: 3 | P32: 497 | Q32: 14.738056 | R32: =IFERROR(G32/(G32+Priors!$H$18),0) -> 0.75216853 | S32: 1 | T32: FALSE | U32: 1 | V32: FALSE | W32: 1 | X32: =R32*S32*U32*W32 -> 0.75216853 | Y32: =VLOOKUP(D32,Priors!$A$18:$B$21,2,FALSE) -> 8.7398272 | Z32: =IF(OR(H32="",G32=0),Y32,X32*I32+(1-X32)*Y32) -> 6.5361034 | AA32: 1 | AB32: =Z32*AA32 -> 6.5361034 | AC32: =Priors!$K$18 -> 2.7435089 | AD32: =IF(D32<>"GK","",IF(OR(K32="",G32=0),AC32,X32*K32+(1-X32)*AC32)) | AE32: =Priors!$K$19 -> 0.67280088 | AF32: =IF(D32<>"GK","",IF(OR(N32="",G32=0),AE32,X32*N32+(1-X32)*AE32)) | AG32: =1-X32 -> 0.24783147 | AH32: PL history | AI32: 10 | AJ32: =IF(OR(AI32="",AI32=0),"",AB32/AI32) -> 0.65361034 | AK32: =OR(AG32>=0.5,E32<>"Premier League",T32=TRUE,V32=TRUE) -> FALSE | AL32: FPL Core Insights / official FPL historical feed | AM32: https://github.com/olbauday/FPL-Core-Insights/tree/main/data/2025-2026 | AN32: GK save % is a proxy = saves/(saves+goals conceded); save volume remains a later team/fixture input.
A33: 32 | B33: Cash | C33: Aston Villa | D33: DEF | E33: Premier League | F33: Aston Villa | G33: 3016 | H33: 209 | I33: 5.55 | J33: 0 | K33: 0 | L33: 38 | M33: 8 | O33: 7 | P33: 450 | Q33: 13.428382 | R33: =IFERROR(G33/(G33+Priors!$H$18),0) -> 0.75099602 | S33: 1 | T33: FALSE | U33: 1 | V33: FALSE | W33: 1 | X33: =R33*S33*U33*W33 -> 0.75099602 | Y33: =VLOOKUP(D33,Priors!$A$18:$B$21,2,FALSE) -> 8.7398272 | Z33: =IF(OR(H33="",G33=0),Y33,X33*I33+(1-X33)*Y33) -> 6.3442797 | AA33: 1 | AB33: =Z33*AA33 -> 6.3442797 | AC33: =Priors!$K$18 -> 2.7435089 | AD33: =IF(D33<>"GK","",IF(OR(K33="",G33=0),AC33,X33*K33+(1-X33)*AC33)) | AE33: =Priors!$K$19 -> 0.67280088 | AF33: =IF(D33<>"GK","",IF(OR(N33="",G33=0),AE33,X33*N33+(1-X33)*AE33)) | AG33: =1-X33 -> 0.24900398 | AH33: PL history | AI33: 10 | AJ33: =IF(OR(AI33="",AI33=0),"",AB33/AI33) -> 0.63442797 | AK33: =OR(AG33>=0.5,E33<>"Premier League",T33=TRUE,V33=TRUE) -> FALSE | AL33: FPL Core Insights / official FPL historical feed | AM33: https://github.com/olbauday/FPL-Core-Insights/tree/main/data/2025-2026 | AN33: GK save % is a proxy = saves/(saves+goals conceded); save volume remains a later team/fixture input.
A34: 33 | B34: Mings | C34: Aston Villa | D34: DEF | E34: Premier League | F34: Aston Villa | G34: 1322 | H34: 123 | I34: 7.28 | J34: 0 | K34: 0 | L34: 23 | M34: 3 | O34: 4 | P34: 169 | Q34: 11.505295 | R34: =IFERROR(G34/(G34+Priors!$H$18),0) -> 0.56933678 | S34: 1 | T34: FALSE | U34: 1 | V34: FALSE | W34: 1 | X34: =R34*S34*U34*W34 -> 0.56933678 | Y34: =VLOOKUP(D34,Priors!$A$18:$B$21,2,FALSE) -> 8.7398272 | Z34: =IF(OR(H34="",G34=0),Y34,X34*I34+(1-X34)*Y34) -> 7.9086939 | AA34: 1 | AB34: =Z34*AA34 -> 7.9086939 | AC34: =Priors!$K$18 -> 2.7435089 | AD34: =IF(D34<>"GK","",IF(OR(K34="",G34=0),AC34,X34*K34+(1-X34)*AC34)) | AE34: =Priors!$K$19 -> 0.67280088 | AF34: =IF(D34<>"GK","",IF(OR(N34="",G34=0),AE34,X34*N34+(1-X34)*AE34)) | AG34: =1-X34 -> 0.43066322 | AH34: PL history | AI34: 10 | AJ34: =IF(OR(AI34="",AI34=0),"",AB34/AI34) -> 0.79086939 | AK34: =OR(AG34>=0.5,E34<>"Premier League",T34=TRUE,V34=TRUE) -> FALSE | AL34: FPL Core Insights / official FPL historical feed | AM34: https://github.com/olbauday/FPL-Core-Insights/tree/main/data/2025-2026 | AN34: GK save % is a proxy = saves/(saves+goals conceded); save volume remains a later team/fixture input.
A35: 34 | B35: Pau | C35: Aston Villa | D35: DEF | E35: Premier League | F35: Aston Villa | G35: 1673 | H35: 139 | I35: 6.03 | J35: 0 | K35: 0 | L35: 19 | M35: 5 | O35: 2 | P35: 280 | Q35: 15.062762 | R35: =IFERROR(G35/(G35+Priors!$H$18),0) -> 0.62588851 | S35: 1 | T35: FALSE | U35: 1 | V35: FALSE | W35: 1 | X35: =R35*S35*U35*W35 -> 0.62588851 | Y35: =VLOOKUP(D35,Priors!$A$18:$B$21,2,FALSE) -> 8.7398272 | Z35: =IF(OR(H35="",G35=0),Y35,X35*I35+(1-X35)*Y35) -> 7.0437775 | AA35: 1 | AB35: =Z35*AA35 -> 7.0437775 | AC35: =Priors!$K$18 -> 2.7435089 | AD35: =IF(D35<>"GK","",IF(OR(K35="",G35=0),AC35,X35*K35+(1-X35)*AC35)) | AE35: =Priors!$K$19 -> 0.67280088 | AF35: =IF(D35<>"GK","",IF(OR(N35="",G35=0),AE35,X35*N35+(1-X35)*AE35)) | AG35: =1-X35 -> 0.37411149 | AH35: PL history | AI35: 10 | AJ35: =IF(OR(AI35="",AI35=0),"",AB35/AI35) -> 0.70437775 | AK35: =OR(AG35>=0.5,E35<>"Premier League",T35=TRUE,V35=TRUE) -> FALSE | AL35: FPL Core Insights / official FPL historical feed | AM35: https://github.com/olbauday/FPL-Core-Insights/tree/main/data/2025-2026 | AN35: GK save % is a proxy = saves/(saves+goals conceded); save volume remains a later team/fixture input.
A36: 35 | B36: Bogarde | C36: Aston Villa | D36: MID | E36: Premier League | F36: Aston Villa | G36: 1042 | H36: 69 | I36: 5.18 | J36: 0 | K36: 0 | L36: 17 | M36: 2 | O36: 4 | P36: 121 | Q36: 10.451056 | R36: =IFERROR(G36/(G36+Priors!$H$18),0) -> 0.51028404 | S36: 1 | T36: FALSE | U36: 1 | V36: FALSE | W36: 1 | X36: =R36*S36*U36*W36 -> 0.51028404 | Y36: =VLOOKUP(D36,Priors!$A$18:$B$21,2,FALSE) -> 8.4555315 | Z36: =IF(OR(H36="",G36=0),Y36,X36*I36+(1-X36)*Y36) -> 6.7840801 | AA36: 1 | AB36: =Z36*AA36 -> 6.7840801 | AC36: =Priors!$K$18 -> 2.7435089 | AD36: =IF(D36<>"GK","",IF(OR(K36="",G36=0),AC36,X36*K36+(1-X36)*AC36)) | AE36: =Priors!$K$19 -> 0.67280088 | AF36: =IF(D36<>"GK","",IF(OR(N36="",G36=0),AE36,X36*N36+(1-X36)*AE36)) | AG36: =1-X36 -> 0.48971596 | AH36: PL history | AI36: 12 | AJ36: =IF(OR(AI36="",AI36=0),"",AB36/AI36) -> 0.56534001 | AK36: =OR(AG36>=0.5,E36<>"Premier League",T36=TRUE,V36=TRUE) -> FALSE | AL36: FPL Core Insights / official FPL historical feed | AM36: https://github.com/olbauday/FPL-Core-Insights/tree/main/data/2025-2026 | AN36: GK save % is a proxy = saves/(saves+goals conceded); save volume remains a later team/fixture input.
A37: 36 | B37: Maatsen | C37: Aston Villa | D37: DEF | E37: Premier League | F37: Aston Villa | G37: 1590 | H37: 140 | I37: 7.25 | J37: 0 | K37: 0 | L37: 27 | M37: 2 | O37: 1 | P37: 242 | Q37: 13.698113 | R37: =IFERROR(G37/(G37+Priors!$H$18),0) -> 0.61389961 | S37: 1 | T37: FALSE | U37: 1 | V37: FALSE | W37: 1 | X37: =R37*S37*U37*W37 -> 0.61389961 | Y37: =VLOOKUP(D37,Priors!$A$18:$B$21,2,FALSE) -> 8.7398272 | Z37: =IF(OR(H37="",G37=0),Y37,X37*I37+(1-X37)*Y37) -> 7.8252229 | AA37: 1 | AB37: =Z37*AA37 -> 7.8252229 | AC37: =Priors!$K$18 -> 2.7435089 | AD37: =IF(D37<>"GK","",IF(OR(K37="",G37=0),AC37,X37*K37+(1-X37)*AC37)) | AE37: =Priors!$K$19 -> 0.67280088 | AF37: =IF(D37<>"GK","",IF(OR(N37="",G37=0),AE37,X37*N37+(1-X37)*AE37)) | AG37: =1-X37 -> 0.38610039 | AH37: PL history | AI37: 10 | AJ37: =IF(OR(AI37="",AI37=0),"",AB37/AI37) -> 0.78252229 | AK37: =OR(AG37>=0.5,E37<>"Premier League",T37=TRUE,V37=TRUE) -> FALSE | AL37: FPL Core Insights / official FPL historical feed | AM37: https://github.com/olbauday/FPL-Core-Insights/tree/main/data/2025-2026 | AN37: GK save % is a proxy = saves/(saves+goals conceded); save volume remains a later team/fixture input.
A38: 37 | B38: Lindelöf | C38: Aston Villa | D38: DEF | E38: Premier League | F38: Aston Villa | G38: 942 | H38: 54 | I38: 5.16 | J38: 0 | K38: 0 | L38: 15 | M38: 1 | O38: 0 | P38: 124 | Q38: 11.847134 | R38: =IFERROR(G38/(G38+Priors!$H$18),0) -> 0.48506694 | S38: 1 | T38: FALSE | U38: 1 | V38: FALSE | W38: 1 | X38: =R38*S38*U38*W38 -> 0.48506694 | Y38: =VLOOKUP(D38,Priors!$A$18:$B$21,2,FALSE) -> 8.7398272 | Z38: =IF(OR(H38="",G38=0),Y38,X38*I38+(1-X38)*Y38) -> 7.0033714 | AA38: 1 | AB38: =Z38*AA38 -> 7.0033714 | AC38: =Priors!$K$18 -> 2.7435089 | AD38: =IF(D38<>"GK","",IF(OR(K38="",G38=0),AC38,X38*K38+(1-X38)*AC38)) | AE38: =Priors!$K$19 -> 0.67280088 | AF38: =IF(D38<>"GK","",IF(OR(N38="",G38=0),AE38,X38*N38+(1-X38)*AE38)) | AG38: =1-X38 -> 0.51493306 | AH38: PL history | AI38: 10 | AJ38: =IF(OR(AI38="",AI38=0),"",AB38/AI38) -> 0.70033714 | AK38: =OR(AG38>=0.5,E38<>"Premier League",T38=TRUE,V38=TRUE) -> TRUE | AL38: FPL Core Insights / official FPL historical feed | AM38: https://github.com/olbauday/FPL-Core-Insights/tree/main/data/2025-2026 | AN38: GK save % is a proxy = saves/(saves+goals conceded); save volume remains a later team/fixture input.
A39: 38 | B39: A.García | C39: Aston Villa | D39: DEF | E39: Premier League | F39: Aston Villa | G39: 83 | H39: 10 | I39: 10.84 | J39: 0 | K39: 0 | L39: 3 | M39: 0 | O39: 0 | P39: 12 | Q39: 13.012048 | R39: =IFERROR(G39/(G39+Priors!$H$18),0) -> 0.076638966 | S39: 1 | T39: FALSE | U39: 1 | V39: FALSE | W39: 1 | X39: =R39*S39*U39*W39 -> 0.076638966 | Y39: =VLOOKUP(D39,Priors!$A$18:$B$21,2,FALSE) -> 8.7398272 | Z39: =IF(OR(H39="",G39=0),Y39,X39*I39+(1-X39)*Y39) -> 8.9007823 | AA39: 1 | AB39: =Z39*AA39 -> 8.9007823 | AC39: =Priors!$K$18 -> 2.7435089 | AD39: =IF(D39<>"GK","",IF(OR(K39="",G39=0),AC39,X39*K39+(1-X39)*AC39)) | AE39: =Priors!$K$19 -> 0.67280088 | AF39: =IF(D39<>"GK","",IF(OR(N39="",G39=0),AE39,X39*N39+(1-X39)*AE39)) | AG39: =1-X39 -> 0.92336103 | AH39: PL history | AI39: 10 | AJ39: =IF(OR(AI39="",AI39=0),"",AB39/AI39) -> 0.89007823 | AK39: =OR(AG39>=0.5,E39<>"Premier League",T39=TRUE,V39=TRUE) -> TRUE | AL39: FPL Core Insights / official FPL historical feed | AM39: https://github.com/olbauday/FPL-Core-Insights/tree/main/data/2025-2026 | AN39: GK save % is a proxy = saves/(saves+goals conceded); save volume remains a later team/fixture input.
